Workbook
Name B_SEULS_NOVIEUX: #REF!
Name B_SEULS_NOVIEUX: #REF!
Name B_SEULS_NOVIEUX: #REF!
Name B_SEULS_NOVIEUX: #REF!
Name column_head: #REF!
Name column_head: #REF!
Name column_head: #REF!
Name column_head: #REF!
Name column_headings: #REF!
Name column_headings: #REF!
Name column_headings: #REF!
Name column_headings: #REF!
Name column_headings: #REF!
Name column_numbers: #REF!
Name column_numbers: #REF!
Name column_numbers: #REF!
Name column_numbers: #REF!
Name column_numbers: #REF!
Name d: #REF!
Name data: #REF!
Name data: #REF!
Name data: #REF!
Name data: #REF!
Name data: #REF!
Name data2: #REF!
Name data2: #REF!
Name data2: #REF!
Name data2: #REF!
Name e: #REF!
Name ea_flux: #REF!
Name ea_flux: #REF!
Name ea_flux: #REF!
Name ea_flux: #REF!
Name ea_flux: #REF!
Name Equilibre: #REF!
Name Equilibre: #REF!
Name Equilibre: #REF!
Name Equilibre: #REF!
Name Equilibre: #REF!
Name f: #REF!
Name fig4b: #REF!
Name fig4b: #REF!
Name fig4b: #REF!
Name fig4b: #REF!
Name footnotes: #REF!
Name footnotes: #REF!
Name footnotes: #REF!
Name footnotes: #REF!
Name footnotes: #REF!
Name footnotes2: #REF!
Name footnotes2: #REF!
Name footnotes2: #REF!
Name footnotes2: #REF!
Name gg: #REF!
Name head: #REF!
Name name: #REF!
Name name2: #REF!
Name name3: #REF!
Name name4: #REF!
Name nb: #REF!

Sheet Data-Fig1
B2: Securities in custody in Swiss banks | C2: Of which: foreign securities belonging to foreigners | D2: Of which: Swiss securities belonging to foreigners, undeclared | E2: Of which: foreign securities wrongly attributed to Switzerland | F2: Fraction of securities in custody in Switzerland held offshore by foreigners | G2: Fiduciary deposits | H2: Total offshore wealth in Switzerland | I2: Share belonging to Europeans | J2: European fortunes in Switzerland | K2: Fraction of Europe's financial wealth held in Switzerland | L2: Europe's wealth in all tax havens | M2: Memo: Europe national income | N2: (Memo: UK + France + Germany national income) | O2: Memo: Europe net financial wealth/national income | P2: Memo: Europe's net financial wealth
A3: 1910 | B3: 0.98433483 | F3: 0.5 | G3: 0 | H3: =G3+F3*B3 -> 0.49216742 | I3: 1 | J3: =I3*H3 -> 0.49216742 | K3: =J3/(P3+J3) -> 0.0040371224 | L3: =K3 -> 0.0040371224 | M3: =M4*N3/N4 -> 68.743347 | N3: 37.320339 | O3: 1.7662551 | P3: =M3*O3 -> 121.41829
A4: 1920 | B4: 2.6424385 | F4: 0.5 | G4: 0 | H4: =G4+F4*B4 -> 1.3212192 | I4: 0.95 | J4: =I4*H4 -> 1.2551583 | K4: =J4/(P4+J4) -> 0.013715282 | L4: =K4 -> 0.013715282 | M4: =M5*N4/N5 -> 79.308659 | N4: 43.056182 | O4: 1.1380869 | P4: =M4*O4 -> 90.260149
A5: 1930 | B5: 5.4221974 | F5: 0.6 | G5: 0 | H5: =G5+F5*B5 -> 3.2533184 | I5: 0.95 | J5: =I5*H5 -> 3.0906525 | K5: =J5/(P5+J5) -> 0.021873087 | L5: =K5 -> 0.021873087 | M5: =M6*N5/N6 -> 109.70096 | N5: 59.555977 | O5: 1.2598675 | P5: =M5*O5 -> 138.20867
A6: 1940 | B6: 5.3914571 | F6: 0.6 | G6: 0 | H6: =G6+F6*B6 -> 3.2348742 | I6: 0.95 | J6: =I6*H6 -> 3.0731305 | K6: =J6/(P6+J6) -> 0.016456326 | L6: =K6 -> 0.016456326 | M6: =M7*N6/N7 -> 168.09424 | N6: 91.257325 | O6: 1.0926698 | P6: =M6*O6 -> 183.6715
A7: 1950 | B7: 10.153801 | F7: =F$14 -> 0.39527154 | G7: 0.067139495 | H7: =G7+F7*B7 -> 4.0806479 | I7: 0.95 | J7: =I7*H7 -> 3.8766155 | K7: =J7/(P7+J7) -> 0.019907963 | L7: =K7 -> 0.019907963 | M7: =M8*N7/N8 -> 248.79232 | N7: 135.06781 | O7: 0.76710677 | P7: =M7*O7 -> 190.85027
A8: 1960 | B8: 35.747344 | F8: =F$14 -> 0.39527154 | G8: 2.0409204 | H8: =G8+F8*B8 -> 16.170828 | I8: 0.9 | J8: =I8*H8 -> 14.553745 | K8: =J8/(P8+J8) -> 0.031770214 | L8: =K8 -> 0.031770214 | M8: =M9*N8/N9 -> 512.33676 | N8: 278.14447 | O8: 0.8657202 | P8: =M8*O8 -> 443.54028
A9: 1970 | B9: 172.92128 | F9: =F$14 -> 0.39527154 | G9: 25.359544 | H9: =G9+F9*B9 -> 93.710406 | I9: 0.75 | J9: =I9*H9 -> 70.282805 | K9: =J9/(P9+J9) -> 0.045471193 | L9: =K9 -> 0.045471193 | M9: =M10*N9/N10 -> 1608.728 | N9: 873.36849 | O9: 0.91710523 | P9: =M9*O9 -> 1475.3728
A10: 1980 | B10: 575.09997 | F10: =F$14 -> 0.39527154 | G10: 134.26863 | H10: =G10+F10*B10 -> 361.58929 | I10: 0.6 | J10: =I10*H10 -> 216.95357 | K10: =J10/(P10+J10) -> 0.055363674 | L10: =L9+(L$14-L$9)/5 -> 0.056119979 | M10: 3500.2016 | N10: 1900.2379 | O10: 1.0575806 | P10: =M10*O10 -> 3701.7454
A11: 1990 | B11: 1488.6753 | F11: 0.44 | G11: 288.50349 | H11: =G11+F11*B11 -> 943.52063 | I11: 0.6 | J11: =I11*H11 -> 566.11238 | K11: =J11/(P11+J11) -> 0.054864763 | L11: =L10+(L$14-L$9)/5 -> 0.066768765 | M11: 7242.2766 | N11: 4074.2314 | O11: 1.3465671 | P11: =M11*O11 -> 9752.2112
A12: 2000 | B12: 3258.902 | C12: 1305.773 | D12: 124.31399 | E12: 0 | F12: =(C12+D12+E12)/B12 -> 0.43882479 | G12: 407.11989 | H12: =G12+F12*B12 -> 1837.2069 | I12: 0.6 | J12: =I12*H12 -> 1102.3241 | K12: =J12/(P12+J12) -> 0.058807266 | L12: =L11+(L$14-L$9)/5 -> 0.077417552 | M12: 11305.141 | N12: 6006.3561 | O12: 1.5605615 | P12: =M12*O12 -> 17642.368
A13: 2010 | B13: 4768.6797 | C13: 1765.1029 | D13: 77 | E13: 100 | F13: =(C13+D13+E13)/B13 -> 0.40726219 | G13: 269.08862 | H13: =G13+F13*B13 -> 2211.1916 | I13: 0.6 | J13: =I13*H13 -> 1326.7149 | K13: =J13/(P13+J13) -> 0.056981403 | L13: =L12+(L$14-L$9)/5 -> 0.088066338 | M13: 14364.581 | N13: 7123.7848 | O13: 1.5285222 | P13: =M13*O13 -> 21956.582
A14: 2013 | B14: 5245.6449 | C14: 1896.4541 | D14: 77 | E14: 100 | F14: =(C14+D14+E14)/B14 -> 0.39527154 | G14: 213.06184 | H14: =G14+E14+D14+C14 -> 2286.516 | I14: 0.6 | J14: =I14*H14 -> 1371.9096 | K14: =J14/(P14+J14) -> 0.060299856 | L14: ='Tab1'!C5 -> 0.098715125 | M14: 14311.368 | O14: 1.4938857 | P14: =M14*O14 -> 21379.548
A15: 2013 (euros) | B15: =B14/1.3 -> 4035.1115 | C15: =C14/1.3 -> 1458.8109 | D15: =D14/1.3 -> 59.230769 | E15: =E14/1.3 -> 76.923077 | G15: =G14/1.3 -> 163.89373 | H15: =H14/1.3 -> 1758.8585 | J15: =J14/1.3 -> 1055.3151 | M15: =M14/1.3 -> 11008.745 | P15: =P14/1.3 -> 16445.806
A17: Notes: All figures in current billion US$. 1910 is the average of 1910-1919, 1920 the average of 1920-1929... and 2012 the average of 2012-12. Swiss data for 2013 are as at the end of May, and based on the July 2013 Monthly bulletin of economic statistic. Sources: Securities in custody in Swiss banks and fiduciary deposits: See detailed computations & explanations in "SwissBanks20c.xlsx" and the Appendix of the book. Europe net financial wealth / national income 1910: 30% of the average 1910-1919 private wealth-national income ratio of the UK, Germany and France, as reported in Piketty-Zucman (2014, Table A5). 1920-1980: 40% of the European private wealth-income ratio in Piketty-Zucman (2014, Table A8) . 1990-2013: Eurostat (EU 27 data. Series start in 1995 and I assume the same yearly growth rate over 1990-1995 as in 1995-1996, consistent with UK, French and German data). Europe's national income 1980-2012: Eurostat data (EU27. Convereted to US$ using year-average exchange rates); 2013: 2012 national income in euros times 1.3 (memo: euro/dollar exchange rate as of May 2013: 1.304); 1910-1970: based on the evolution of French, UK and German national incomes in current US dollars, as reported in Piketty-Zucman (2014, Table A153)

Sheet Fig2
C2: Swiss bank accounts (2015)
C6: In 2015 banks domiciled in Switzerland manage 2.3 trillion dollars belonging to non-residents. Within this total, 1.3 trillion belong to Europeans. 40% of the wealth managed in Switzerland is placed in mutual funds, principally in Luxembourg.
C11: Who owns Swiss accounts | G11: Investments
C13: Europe: $1,300bn. Of which: Germany: $260bn France: $240bn Italy: $140bn UK: $140bn Spain: $110bn Greece: $80bn Belgium: $70bn Portugal: $40bn Other: $220bn | G13: Luxembourg mutual funds: $750bn
J14: =600/1800*2300 -> 766.66667
E17: Total offshore wealth in Switzerland: $2,300bn
G24: Irish mutual funds: $200bn | J24: =150/1800*2300 -> 191.66667
G27: Global equities (US, etc.) : $500bn
J28: =400/1800*2300 -> 511.11111
C29: Gulf countries: $230bn
C32: Asia: $230bn
G34: Global bonds: $600bn
C35: Latin America: $220bn | J35: =450/1800*2300 -> 575
C38: Africa: $150bn
C40: USA ($80bn) and Canda ($40bn) | G40: Deposits, other: $250bn | J40: =200/1800*2300 -> 255.55556
C42: Russia: $70bn
C47: =70+80+40+150+220+230+230+1300 -> 2320 | G47: =250+600+500+200+750 -> 2300

Sheet DataFig2
H2: Fiduciary deposits official SNB data "Banks in Switzerland" 2013
B3: US$ billion | C3: % of total | D3: Tax revenue losses | H3: 2008-2013 | I3: 2013 | J3: 2012 | K3: 2011 | L3: 2010 | M3: 2009 | N3: 2008
A4: Europe | B4: =ROUND(C4*B$24,-2) -> 1300 | C4: 0.56 | D4: =SUM(D5:D16) -> 38.443665 | H4: =AVERAGE(I4:N4) -> 17427.221 | I4: 8980.0675 | J4: 8933.883 | K4: 14220.774 | L4: 15565.085 | M4: 19608.091 | N4: 37255.425
A5: Germany | B5: =ROUND(B$4*H5/H$4,-1) -> 260 | C5: =B5/B$24 -> 0.11304348 | D5: ='Data-Fig4_Tab1'!B6*(1-'Data-Fig4_Tab1'!H6)*('Data-Fig4_Tab1'!O$3*'Data-Fig4_Tab1'!J6+'Data-Fig4_Tab1'!P$3*'Data-Fig4_Tab1'!K6+'Data-Fig4_Tab1'!L6) -> 6.26496 | H5: =AVERAGE(I5:N5) -> 3421.8635 | I5: 1514.205 | J5: 1733.569 | K5: 2663.028 | L5: 2624.386 | M5: 4133.239 | N5: 7862.754
A6: France | B6: =ROUND(B$4*H6/H$4,-1) -> 240 | C6: =B6/B$24 -> 0.10434783 | D6: ='Data-Fig4_Tab1'!B7*(1-'Data-Fig4_Tab1'!H7)*('Data-Fig4_Tab1'!O$3*'Data-Fig4_Tab1'!J7+'Data-Fig4_Tab1'!P$3*'Data-Fig4_Tab1'!K7+'Data-Fig4_Tab1'!L7) -> 12.2304 | H6: =AVERAGE(I6:N6) -> 3188.6757 | I6: 1641.261 | J6: 1659.261 | K6: 2573.71 | L6: 2868.622 | M6: 3794.505 | N6: 6594.695
A7: Italy | B7: =ROUND(B$4*H7/H$4,-1) -> 140 | C7: =B7/B$24 -> 0.060869565 | D7: ='Data-Fig4_Tab1'!B8*(1-'Data-Fig4_Tab1'!H8)*('Data-Fig4_Tab1'!O$3*'Data-Fig4_Tab1'!J8+'Data-Fig4_Tab1'!P$3*'Data-Fig4_Tab1'!K8+'Data-Fig4_Tab1'!L8) -> 1.9264 | H7: =AVERAGE(I7:N7) -> 1920.62 | I7: 452.882 | J7: 575.783 | K7: 1148.678 | L7: 1275.503 | M7: 2004.648 | N7: 6066.226
A8: UK | B8: =ROUND(B$4*H8/H$4,-1) -> 140 | C8: =B8/B$24 -> 0.060869565 | D8: ='Data-Fig4_Tab1'!B9*(1-'Data-Fig4_Tab1'!H9)*('Data-Fig4_Tab1'!O$3*'Data-Fig4_Tab1'!J9+'Data-Fig4_Tab1'!P$3*'Data-Fig4_Tab1'!K9+'Data-Fig4_Tab1'!L9) -> 4.08576 | H8: =AVERAGE(I8:N8) -> 1886.997 | I8: 962.3365 | J8: 1010.675 | K8: 1527.744 | L8: 1884.5928 | M8: 2272.2328 | N8: 3664.401
A9: Spain | B9: =ROUND(B$4*H9/H$4,-1) -> 110 | C9: =B9/B$24 -> 0.047826087 | D9: ='Data-Fig4_Tab1'!B10*(1-'Data-Fig4_Tab1'!H10)*('Data-Fig4_Tab1'!O$3*'Data-Fig4_Tab1'!J10+'Data-Fig4_Tab1'!P$3*'Data-Fig4_Tab1'!K10+'Data-Fig4_Tab1'!L10) -> 4.9984 | H9: =AVERAGE(I9:N9) -> 1437.3898 | I9: 666.732 | J9: 758.642 | K9: 1227.543 | L9: 1202.054 | M9: 1604.115 | N9: 3165.253
A10: Greece | B10: =ROUND(B$4*H10/H$4,-1) -> 80 | C10: =B10/B$24 -> 0.034782609 | D10: ='Data-Fig4_Tab1'!B11*(1-'Data-Fig4_Tab1'!H11)*('Data-Fig4_Tab1'!O$3*'Data-Fig4_Tab1'!J11+'Data-Fig4_Tab1'!P$3*'Data-Fig4_Tab1'!K11+'Data-Fig4_Tab1'!L11) -> 0.896 | H10: =AVERAGE(I10:N10) -> 1046.0657 | I10: 658.205 | J10: 859.097 | K10: 1158.381 | L10: 1308.538 | M10: 934.844 | N10: 1357.329
A11: Belgium | B11: =ROUND(B$4*H11/H$4,-1) -> 70 | C11: =B11/B$24 -> 0.030434783 | D11: ='Data-Fig4_Tab1'!B12*(1-'Data-Fig4_Tab1'!H12)*('Data-Fig4_Tab1'!O$3*'Data-Fig4_Tab1'!J12+'Data-Fig4_Tab1'!P$3*'Data-Fig4_Tab1'!K12+'Data-Fig4_Tab1'!L12) -> 1.624 | H11: =AVERAGE(I11:N11) -> 940.79683 | I11: 298.885 | J11: 420.985 | K11: 624.186 | L11: 692.988 | M11: 1197.333 | N11: 2410.404
A12: Portugal | B12: =ROUND(B$4*H12/H$4,-1) -> 40 | C12: =B12/B$24 -> 0.017391304 | D12: ='Data-Fig4_Tab1'!B13*(1-'Data-Fig4_Tab1'!H13)*('Data-Fig4_Tab1'!O$3*'Data-Fig4_Tab1'!J13+'Data-Fig4_Tab1'!P$3*'Data-Fig4_Tab1'!K13+'Data-Fig4_Tab1'!L13) -> 0.7168 | H12: =AVERAGE(I12:N12) -> 589.43333 | I12: 1065.29 | J12: 299.055 | K12: 485.327 | L12: 343.271 | M12: 436.653 | N12: 907.004
A13: Poland | B13: =ROUND(B$4*H13/H$4,-1) -> 20 | C13: =B13/B$24 -> 0.0086956522 | D13: ='Data-Fig4_Tab1'!B14*(1-'Data-Fig4_Tab1'!H14)*('Data-Fig4_Tab1'!O$3*'Data-Fig4_Tab1'!J14+'Data-Fig4_Tab1'!P$3*'Data-Fig4_Tab1'!K14+'Data-Fig4_Tab1'!L14) -> 0.2576 | H13: =AVERAGE(I13:N13) -> 209.23317 | I13: 143.562 | J13: 207.272 | K13: 190.661 | L13: 195.089 | M13: 206.914 | N13: 311.901
A14: Sweden | B14: =ROUND(B$4*H14/H$4,-1) -> 20 | C14: =B14/B$24 -> 0.0086956522 | D14: ='Data-Fig4_Tab1'!B15*(1-'Data-Fig4_Tab1'!H15)*('Data-Fig4_Tab1'!O$3*'Data-Fig4_Tab1'!J15+'Data-Fig4_Tab1'!P$3*'Data-Fig4_Tab1'!K15+'Data-Fig4_Tab1'!L15) -> 0.384 | H14: =AVERAGE(I14:N14) -> 230.32867 | I14: 105.161 | J14: 179.598 | K14: 195.389 | L14: 217.956 | M14: 180.987 | N14: 502.881
A15: Norway | B15: =ROUND(B$4*H15/H$4,-1) -> 10 | C15: =B15/B$24 -> 0.0043478261 | D15: ='Data-Fig4_Tab1'!B16*(1-'Data-Fig4_Tab1'!H16)*('Data-Fig4_Tab1'!O$3*'Data-Fig4_Tab1'!J16+'Data-Fig4_Tab1'!P$3*'Data-Fig4_Tab1'!K16+'Data-Fig4_Tab1'!L16) -> 0.3152 | H15: =AVERAGE(I15:N15) -> 95.467167 | I15: 50.685 | J15: 58.908 | K15: 65.48 | L15: 93.711 | M15: 137.815 | N15: 166.204
A16: Other | B16: =ROUND(B$4*H16/H$4,-1) -> 180 | C16: =B16/B$24 -> 0.07826087 | D16: ='Data-Fig4_Tab1'!B17*(1-'Data-Fig4_Tab1'!H17)*('Data-Fig4_Tab1'!O$3*'Data-Fig4_Tab1'!J17+'Data-Fig4_Tab1'!P$3*'Data-Fig4_Tab1'!K17+'Data-Fig4_Tab1'!L17) -> 4.7441455 | H16: =AVERAGE(I16:N16) -> 2460.35 | I16: =I4-SUM(I5:I15) -> 1420.863 | J16: =J4-SUM(J5:J15) -> 1171.038 | K16: =K4-SUM(K5:K15) -> 2360.647 | L16: =L4-SUM(L5:L15) -> 2858.374 | M16: =M4-SUM(M5:M15) -> 2704.805 | N16: =N4-SUM(N5:N15) -> 4246.373
A17: Gulf countries | B17: =ROUND(C17*B$24,-1) -> 230 | C17: 0.1 | D17: ='Data-Fig4_Tab1'!B18*(1-'Data-Fig4_Tab1'!H18)*('Data-Fig4_Tab1'!O$3*'Data-Fig4_Tab1'!J18+'Data-Fig4_Tab1'!P$3*'Data-Fig4_Tab1'!K18+'Data-Fig4_Tab1'!L18) -> 0
A18: Asia | B18: =ROUND(C18*B$24,-1) -> 230 | C18: 0.1 | D18: ='Data-Fig4_Tab1'!B19*(1-'Data-Fig4_Tab1'!H19)*('Data-Fig4_Tab1'!O$3*'Data-Fig4_Tab1'!J19+'Data-Fig4_Tab1'!P$3*'Data-Fig4_Tab1'!K19+'Data-Fig4_Tab1'!L19) -> 6.072
A19: Latin America | B19: =ROUND(C19*B$24,-1) -> 220 | C19: =11.5%-2% -> 0.095 | D19: ='Data-Fig4_Tab1'!B20*(1-'Data-Fig4_Tab1'!H20)*('Data-Fig4_Tab1'!O$3*'Data-Fig4_Tab1'!J20+'Data-Fig4_Tab1'!P$3*'Data-Fig4_Tab1'!K20+'Data-Fig4_Tab1'!L20) -> 6.2928
A20: Africa | B20: =ROUND(C20*B$24,-1) -> 150 | C20: 0.065 | D20: ='Data-Fig4_Tab1'!B21*(1-'Data-Fig4_Tab1'!H21)*('Data-Fig4_Tab1'!O$3*'Data-Fig4_Tab1'!J21+'Data-Fig4_Tab1'!P$3*'Data-Fig4_Tab1'!K21+'Data-Fig4_Tab1'!L21) -> 4.3056
A21: United States | B21: =ROUND(C21*B$24,-1) -> 80 | C21: =0.05*2/3 -> 0.033333333 | H21: =AVERAGE(I21:N21) -> 2680.9245 | I21: 1226.013 | J21: 1411.906 | K21: 1411.906 | L21: 2990.565 | M21: 3097.081 | N21: 5948.076
A22: Canada | B22: =ROUND(C22*B$24,-1) -> 40 | C22: =0.05*1/3 -> 0.016666667 | H22: =AVERAGE(I22:N22) -> 1170.9032 | I22: 754.843 | J22: 695.81 | K22: 921.935 | L22: 1473.971 | M22: 1356.444 | N22: 1822.416
A23: Russia | B23: =ROUND(C23*B$24,-1) -> 70 | C23: 0.03 | D23: ='Data-Fig4_Tab1'!B24*(1-'Data-Fig4_Tab1'!H24)*('Data-Fig4_Tab1'!O$3*'Data-Fig4_Tab1'!J24+'Data-Fig4_Tab1'!P$3*'Data-Fig4_Tab1'!K24+'Data-Fig4_Tab1'!L24) -> 0.39744 | H23: =AVERAGE(I23:N23) -> 3246.8855 | I23: 2534.479 | J23: 2508.164 | K23: 2802.473 | L23: 2843.699 | M23: 3518.252 | N23: 5274.246
A24: Total | B24: 2300 | C24: =C4+SUM(C17:C23) -> 1 | D24: =D4+SUM(D17:D23) -> 55.511505 | G24: Total excl. Liechtenstein | H24: =AVERAGE(I24:N24) -> 153998.21 | I24: 91448.792 | J24: 98892.075 | K24: 129209.07 | L24: 145181.39 | M24: 179027.08 | N24: 280230.87
A25: Of which: through shell companies | B25: =ROUND(C25*B24,-2) -> 1400 | C25: 0.6 | G25: Tax havens excl. Liechtenstein | H25: =AVERAGE(I25:N25) -> 84962.761 | I25: 50734.891 | J25: 54886.173 | K25: 68461.426 | L25: 81942.425 | M25: 100525.7 | N25: 153225.96
G26: Liechtenstein | H26: =AVERAGE(I26:N26) -> 27088.187 | I26: 15215.918 | J26: 17761.015 | K26: 21553.273 | L26: 26140.689 | M26: 33818.559 | N26: 48039.669
G27: Total incl. Liechtenstein | H27: =AVERAGE(I27:N27) -> 181086.4 | I27: =I24+I26 -> 106664.71 | J27: =J24+J26 -> 116653.09 | K27: =K24+K26 -> 150762.34 | L27: =L24+L26 -> 171322.07 | M27: =M24+M26 -> 212845.64 | N27: =N24+N26 -> 328270.54
G28: Tax havens incl. Liechtenstein | H28: =AVERAGE(I28:N28) -> 112050.95 | I28: =I26+I25 -> 65950.808 | J28: =J26+J25 -> 72647.188 | K28: =K26+K25 -> 90014.699 | L28: =L26+L25 -> 108083.11 | M28: =M26+M25 -> 134344.26 | N28: =N26+N25 -> 201265.62
G29: Share shell | H29: =AVERAGE(I29:N29) -> 0.61888229 | I29: =I28/I27 -> 0.61830017 | J29: =J28/J27 -> 0.62276265 | K29: =K28/K27 -> 0.59706354 | L29: =L28/L27 -> 0.63087676 | M29: =M28/M27 -> 0.63118162 | N29: =N28/N27 -> 0.61310901
G30: Share Europe | H30: =AVERAGE(I30:N30) -> 0.091927799 | I30: =I4/I27 -> 0.084189678 | J30: =J4/J27 -> 0.076585053 | K30: =K4/K27 -> 0.094325768 | L30: =L4/L27 -> 0.090852769 | M30: =M4/M27 -> 0.092123525 | N30: =N4/N27 -> 0.11349
A32: Notes: Continental shares are from Zucman (2013, Table A26, line for 2004, the last year which is note contaminated by the saving directive), with the following changes:
A33: Russia (3%) is isolated from Asia (which thus decreases from 13% to 10%).
A34: Latin America is reduced by 2 points and Gulf countries increased by 2 points to account for recent evolution
A35: Non-oil Middle East countries (about 2%) are merged with Africa (which thus increases from 5% to 7%)
A36: North America is split into USA (2/3 of North America based on average share of US in 2008-2013 North American fiduciary deposits) and Canada (1/3)
A37: Within Europe, shares are obtained from 2008-2013 average shares of individual European countries in European-owned fiduciary deposits
A38: UK deposits are divided by 4 to account for sham corporations; this is very uncertain

Sheet Fig3
B3: Financial wealth in tax havens (2014)
B7: In 2014, on a global scale households on average owned 8% of their financial wealth through bank accounts in tax havens. One-third of the world’s offshore wealth was in Switzerland
B12: World financial wealth: 95.5 trillion $ (100%) | D12: Held onshore (in the U.S., Japan, France…) : 87.9 trillion $ (92 %)
F22: Around 30% of offshore wealth is in Switzerland: 2.3 trillion $
D26: Held offshore (in tax havens throughout the world): 7.6 trillion $ (8%)
F28: 70% is in tax havens other than Switzerland (Singapore, Cayman islands…): 5.3 trillion $

Sheet Data-Fig3
F2: bn euros | H2: bn US$
C3: World income | F3: =ROUND(H3/E$13,-3) -> 62000 | H3: =0.85*80000 -> 68000
C4: World financial wealth | F4: =ROUND(H4/E$13,-3) -> 87000 | G4: =F4/F3 -> 1.4032258 | H4: =H3*0.3*4.4/(1-0.06) -> 95489.362
C5: Of which: held offshore | F5: =ROUND(H5/E$13,-2) -> 6900 | G5: 0.08 | H5: ='Tab1'!B13 -> 7600
C6: Of which: held offshore in Switzerland | F6: =ROUND(H6/E$13,-2) -> 2100 | G6: =F6/F5 -> 0.30434783 | H6: =DataFig2!B24 -> 2300
C7: Of which: held in havens other than Sw. | F7: =ROUND(H7/E$13,-2) -> 4800 | H7: =H5-H6 -> 5300
C9: European financial wealth | F9: =ROUND(H9/E$13,-2) -> 21800 | H9: =H10+'Data-Fig1'!P14 -> 23979.548
C10: Offshore financial wealth of Europeans | F10: =ROUND(H10/E$13,-2) -> 2400 | G10: =F10/F9 -> 0.11009174 | H10: ='Tab1'!B5 -> 2600
D13: 1 euro = | E13: 1.1 | F13: dollars

Sheet Fig4
B3: The global cost of offshore tax evasion (2014)
B7: En 2013, la fraude permise par le secret bancaire a coûé 130 milliards d'euros aux États du monde entier.
B12: Global household wealth in tax havens: $7,600bn (100%)
J13: =5800*1.3 -> 7540
J14: =J13*0.2 -> 1508
B18: Of which declared: $1,500bn (20%) | D18: Of which undeclared : $6,100bn (80%)
D24: Yearly tax revenue losses due to offshore tax evasion $190bn
J26: =130*1.3 -> 169
D30: Of which income tax (interest, dividends): $125bn | F30: Of which inheritance tax: $55bn | H30: Of which wealth tax: $10bn
J37: =80*1.3 -> 104
J38: =45*1.3 -> 58.5
J39: =5*1.3 -> 6.5

Sheet Tab1
B4: Offshore wealth ($ bn) | C4: Share of financial wealth held offshore | D4: Tax revenue loss ($ bn) | J4: Net onshore financial wealth (bn$) | K4: Gross financial wealth per adult ($) | L4: Debt per adult ($) | M4: Number of adults (mn)
A5: Europe | B5: =ROUND('Data-Fig4_Tab1'!F5,-2) -> 2600 | C5: ='Data-Fig4_Tab1'!G5*0.08*J13/(J5+'Data-Fig4_Tab1'!G5*0.08*J13) -> 0.098715125 | D5: =ROUND('Data-Fig4_Tab1'!N5*D$13,0) -> 78 | J5: 23980 | M5: =583.373-M11 -> 473.008
A6: USA | B6: =ROUND('Data-Fig4_Tab1'!F22,-2) -> 1200 | C6: ='Data-Fig4_Tab1'!G22*0.08*J13/(J6+'Data-Fig4_Tab1'!G22*0.08*J13) -> 0.035031864 | D6: =ROUND('Data-Fig4_Tab1'!N22*D$13,0) -> 35 | J6: 33296.92 | M6: 239
A7: Asia | B7: =ROUND('Data-Fig4_Tab1'!F19,-2) -> 1300 | C7: ='Data-Fig4_Tab1'!G19*0.08*J13/(J7+'Data-Fig4_Tab1'!G19*0.08*J13) -> 0.041725283 | D7: =ROUND('Data-Fig4_Tab1'!N19*D$13,0) -> 34 | J7: =(K7-L7)*M7/1000 -> 29779.118 | K7: =(26019*1107+10752*998+700*768)/M7 -> 14065.178 | L7: =(7827*1107+1403*998+296*768)/M7 -> 3612.5502 | M7: =1107+998+768-M12 -> 2848.96
A8: Latin America | B8: =ROUND('Data-Fig4_Tab1'!F20,-2) -> 700 | C8: ='Data-Fig4_Tab1'!G20*0.08*J13/(J8+'Data-Fig4_Tab1'!G20*0.08*J13) -> 0.2164944 | D8: =ROUND('Data-Fig4_Tab1'!N20*D$13,0) -> 21 | J8: =(K8-L8)*M8/1000 -> 2626.419 | K8: 10036 | L8: 3353 | M8: 393
A9: Africa | B9: =ROUND('Data-Fig4_Tab1'!F21,-2) -> 500 | C9: ='Data-Fig4_Tab1'!G21*0.08*J13/(J9+'Data-Fig4_Tab1'!G21*0.08*J13) -> 0.29896217 | D9: =ROUND('Data-Fig4_Tab1'!N21*D$13,0) -> 14 | J9: =(K9-L9)*M9/1000 -> 1164.35 | K9: 2629 | L9: 512 | M9: 550
A10: Canada | B10: =ROUND('Data-Fig4_Tab1'!F23,-2) -> 300 | C10: ='Data-Fig4_Tab1'!G23*0.08*J13/(J10+'Data-Fig4_Tab1'!G23*0.08*J13) -> 0.092044985 | D10: =ROUND('Data-Fig4_Tab1'!N23*D$13,0) -> 6 | J10: =(K10-L10)*M10/1000 -> 2814.966 | K10: 166409 | L10: 62151 | M10: 27
A11: Russia | B11: =ROUND('Data-Fig4_Tab1'!F24,-2) -> 200 | C11: ='Data-Fig4_Tab1'!G24*0.08*J13/(J11+'Data-Fig4_Tab1'!G24*0.08*J13) -> 0.51802588 | D11: =ROUND('Data-Fig4_Tab1'!N24*D$13,0) -> 1 | J11: =(K11-L11)*M11/1000 -> 213.22518 | K11: 4484 | L11: 2552 | M11: 110.365
A12: Gulf countries | B12: 800 | C12: ='Data-Fig4_Tab1'!G18*0.08*J13/(J12+'Data-Fig4_Tab1'!G18*0.08*J13) -> 0.5680577 | D12: =ROUND('Data-Fig4_Tab1'!N18*D$13,0) -> 0 | J12: =(K12-L12)*M12/1000 -> 580.86908 | K12: =(16.694*19652+1.278*99415+2.291*64918+3.777*83377)/M12 -> 38218.175 | L12: =(16.694*5862+1.278*18652+2.291*23631+3.777*42907)/M12 -> 14055.568 | M12: =16.694+1.278+2.291+3.777 -> 24.04
A13: Total | B13: =ROUND(0.08*J13,-2) -> 7600 | C13: =B13/J13 -> 0.079590018 | D13: =ROUND(0.08*J13*'Data-Fig4_Tab1'!M25/'Data-Fig4_Tab1'!F25,-1) -> 190 | J13: ='Data-Fig3'!H4 -> 95489.362
J15: USA: Saez-Zucman, 2014 (= Flow of Funds); Europe: Zucman, 2013 (= Eurostat); total = onshore + offshore total in Zucman 2013; rest: Credit Suisse (2013)

Sheet Data-Fig4_Tab1
O2: r (nominal) | P2: m x mu
O3: 0.08 | P3: 0.03
B4: Offshore wealth in Switzerland | C4: (%) | D4: Offshore wealth in other tax havens | E4: (%) | F4: Offshore wealth in all tax havens | G4: (%) | H4: % of offshore wealth declared | I4: Undeclared offshore wealth | J4: Dividend income tax rate (OECD) | K4: Top marginal inheritance/estate tax rate | L4: Welath tax rate | M4: Total tax revenue losses | N4: (%) | O4: Income tax revenue losses | P4: Inheritance/Estate tax revenue losses | Q4: Wealth tax revenue losses | R4: Income + wealth tax revenue losses | S4: Income + wealth tax revenue losses (% undeclared income)
A5: Europe | B5: =C5*DataFig2!B$24 -> 1288 | C5: =DataFig2!C4 -> 0.56 | D5: =E5*D$25 -> 1325 | E5: 0.25 | F5: =B5+D5 -> 2613 | G5: =F5/F$25 -> 0.34381579 | H5: 0.2 | I5: =(1-H5)*F5 -> 2090.4 | M5: =O5+P5+Q5 -> 77.991691 | N5: =M5/M$25 -> 0.41180646 | O5: =SUM(O6:O17) -> 48.196999 | P5: =SUM(P6:P17) -> 19.310232 | Q5: =SUM(Q6:Q17) -> 10.48446 | R5: =(O5+Q5) -> 58.681459 | S5: =R5/(O$3*I5) -> 0.3508985
A6: Germany | B6: =C6*DataFig2!B$24 -> 260 | C6: =DataFig2!C5 -> 0.11304348 | D6: =E6*D$25 -> 267.46894 | E6: =E$5*C6/C$5 -> 0.050465839 | F6: =B6+D6 -> 527.46894 | G6: =F6/F$25 -> 0.069403808 | H6: 0.2 | I6: =(1-H6)*F6 -> 421.97516 | J6: 0.264 | K6: 0.3 | L6: 0 | M6: =O6+P6+Q6 -> 12.709892 | N6: =M6/M$25 -> 0.067109912 | O6: =O$3*J6*I6 -> 8.9121153 | P6: =I6*P$3*K6 -> 3.7977764 | Q6: =L6*I6 -> 0 | R6: =(O6+Q6) -> 8.9121153 | S6: =R6/(O$3*I6) -> 0.264
A7: France | B7: =C7*DataFig2!B$24 -> 240 | C7: =DataFig2!C6 -> 0.10434783 | D7: =E7*D$25 -> 246.89441 | E7: =E$5*C7/C$5 -> 0.046583851 | F7: =B7+D7 -> 486.89441 | G7: =F7/F$25 -> 0.064065054 | H7: 0.2 | I7: =(1-H7)*F7 -> 389.51553 | J7: 0.44 | K7: 0.45 | L7: 0.015 | M7: =O7+P7+Q7 -> 24.812139 | N7: =M7/M$25 -> 0.13101138 | O7: =O$3*J7*I7 -> 13.710947 | P7: =I7*P$3*K7 -> 5.2584596 | Q7: =L7*I7 -> 5.8427329 | R7: =(O7+Q7) -> 19.55368 | S7: =R7/(O$3*I7) -> 0.6275
A8: Italy | B8: =C8*DataFig2!B$24 -> 140 | C8: =DataFig2!C7 -> 0.060869565 | D8: =E8*D$25 -> 144.02174 | E8: =E$5*C8/C$5 -> 0.027173913 | F8: =B8+D8 -> 284.02174 | G8: =F8/F$25 -> 0.037371281 | H8: 0.2 | I8: =(1-H8)*F8 -> 227.21739 | J8: 0.2 | K8: 0.04 | L8: 0 | M8: =O8+P8+Q8 -> 3.9081391 | N8: =M8/M$25 -> 0.020635492 | O8: =O$3*J8*I8 -> 3.6354783 | P8: =I8*P$3*K8 -> 0.27266087 | Q8: =L8*I8 -> 0 | R8: =(O8+Q8) -> 3.6354783 | S8: =R8/(O$3*I8) -> 0.2
A9: UK | B9: =C9*DataFig2!B$24 -> 140 | C9: =DataFig2!C8 -> 0.060869565 | D9: =E9*D$25 -> 144.02174 | E9: =E$5*C9/C$5 -> 0.027173913 | F9: =B9+D9 -> 284.02174 | G9: =F9/F$25 -> 0.037371281 | H9: 0.2 | I9: =(1-H9)*F9 -> 227.21739 | J9: 0.306 | K9: 0.4 | L9: 0 | M9: =O9+P9+Q9 -> 8.2888904 | N9: =M9/M$25 -> 0.043766439 | O9: =O$3*J9*I9 -> 5.5622817 | P9: =I9*P$3*K9 -> 2.7266087 | Q9: =L9*I9 -> 0 | R9: =(O9+Q9) -> 5.5622817 | S9: =R9/(O$3*I9) -> 0.306
A10: Spain | B10: =C10*DataFig2!B$24 -> 110 | C10: =DataFig2!C9 -> 0.047826087 | D10: =E10*D$25 -> 113.15994 | E10: =E$5*C10/C$5 -> 0.021350932 | F10: =B10+D10 -> 223.15994 | G10: =F10/F$25 -> 0.02936315 | H10: 0.2 | I10: =(1-H10)*F10 -> 178.52795 | J10: 0.27 | K10: 0.34 | L10: 0.025 | M10: =O10+P10+Q10 -> 10.140388 | N10: =M10/M$25 -> 0.05354259 | O10: =O$3*J10*I10 -> 3.8562037 | P10: =I10*P$3*K10 -> 1.8209851 | Q10: =L10*I10 -> 4.4631988 | R10: =(O10+Q10) -> 8.3194025 | S10: =R10/(O$3*I10) -> 0.5825
A11: Greece | B11: =C11*DataFig2!B$24 -> 80 | C11: =DataFig2!C10 -> 0.034782609 | D11: =E11*D$25 -> 82.298137 | E11: =E$5*C11/C$5 -> 0.01552795 | F11: =B11+D11 -> 162.29814 | G11: =F11/F$25 -> 0.021355018 | H11: 0.2 | I11: =(1-H11)*F11 -> 129.83851 | J11: 0.1 | K11: 0.2 | L11: 0 | M11: =O11+P11+Q11 -> 1.8177391 | N11: =M11/M$25 -> 0.0095979034 | O11: =O$3*J11*I11 -> 1.0387081 | P11: =I11*P$3*K11 -> 0.77903106 | Q11: =L11*I11 -> 0 | R11: =(O11+Q11) -> 1.0387081 | S11: =R11/(O$3*I11) -> 0.1
A12: Belgium | B12: =C12*DataFig2!B$24 -> 70 | C12: =DataFig2!C11 -> 0.030434783 | D12: =E12*D$25 -> 72.01087 | E12: =E$5*C12/C$5 -> 0.013586957 | F12: =B12+D12 -> 142.01087 | G12: =F12/F$25 -> 0.018685641 | H12: 0.2 | I12: =(1-H12)*F12 -> 113.6087 | J12: 0.25 | K12: 0.3 | L12: 0 | M12: =O12+P12+Q12 -> 3.2946522 | N12: =M12/M$25 -> 0.0173962 | O12: =O$3*J12*I12 -> 2.2721739 | P12: =I12*P$3*K12 -> 1.0224783 | Q12: =L12*I12 -> 0 | R12: =(O12+Q12) -> 2.2721739 | S12: =R12/(O$3*I12) -> 0.25
A13: Portugal | B13: =C13*DataFig2!B$24 -> 40 | C13: =DataFig2!C12 -> 0.017391304 | D13: =E13*D$25 -> 41.149068 | E13: =E$5*C13/C$5 -> 0.0077639752 | F13: =B13+D13 -> 81.149068 | G13: =F13/F$25 -> 0.010677509 | H13: 0.2 | I13: =(1-H13)*F13 -> 64.919255 | J13: 0.28 | K13: 0 | L13: 0 | M13: =O13+P13+Q13 -> 1.4541913 | N13: =M13/M$25 -> 0.0076783227 | O13: =O$3*J13*I13 -> 1.4541913 | P13: =I13*P$3*K13 -> 0 | Q13: =L13*I13 -> 0 | R13: =(O13+Q13) -> 1.4541913 | S13: =R13/(O$3*I13) -> 0.28
A14: Poland | B14: =C14*DataFig2!B$24 -> 20 | C14: =DataFig2!C13 -> 0.0086956522 | D14: =E14*D$25 -> 20.574534 | E14: =E$5*C14/C$5 -> 0.0038819876 | F14: =B14+D14 -> 40.574534 | G14: =F14/F$25 -> 0.0053387545 | H14: 0.2 | I14: =(1-H14)*F14 -> 32.459627 | J14: 0.19 | K14: 0.03 | L14: 0 | M14: =O14+P14+Q14 -> 0.5226 | N14: =M14/M$25 -> 0.0027593972 | O14: =O$3*J14*I14 -> 0.49338634 | P14: =I14*P$3*K14 -> 0.029213665 | Q14: =L14*I14 -> 0 | R14: =(O14+Q14) -> 0.49338634 | S14: =R14/(O$3*I14) -> 0.19
A15: Sweden | B15: =C15*DataFig2!B$24 -> 20 | C15: =DataFig2!C14 -> 0.0086956522 | D15: =E15*D$25 -> 20.574534 | E15: =E$5*C15/C$5 -> 0.0038819876 | F15: =B15+D15 -> 40.574534 | G15: =F15/F$25 -> 0.0053387545 | H15: 0.2 | I15: =(1-H15)*F15 -> 32.459627 | J15: 0.3 | K15: 0 | L15: 0 | M15: =O15+P15+Q15 -> 0.77903106 | N15: =M15/M$25 -> 0.0041133872 | O15: =O$3*J15*I15 -> 0.77903106 | P15: =I15*P$3*K15 -> 0 | Q15: =L15*I15 -> 0 | R15: =(O15+Q15) -> 0.77903106 | S15: =R15/(O$3*I15) -> 0.3
A16: Norway | B16: =C16*DataFig2!B$24 -> 10 | C16: =DataFig2!C15 -> 0.0043478261 | D16: =E16*D$25 -> 10.287267 | E16: =E$5*C16/C$5 -> 0.0019409938 | F16: =B16+D16 -> 20.287267 | G16: =F16/F$25 -> 0.0026693772 | H16: 0.2 | I16: =(1-H16)*F16 -> 16.229814 | J16: 0.28 | K16: 0.2 | L16: 0.011 | M16: =O16+P16+Q16 -> 0.63945466 | N16: =M16/M$25 -> 0.0033764053 | O16: =O$3*J16*I16 -> 0.36354783 | P16: =I16*P$3*K16 -> 0.097378882 | Q16: =L16*I16 -> 0.17852795 | R16: =(O16+Q16) -> 0.54207578 | S16: =R16/(O$3*I16) -> 0.4175
A17: Other | B17: =C17*DataFig2!B$24 -> 180 | C17: =DataFig2!C16 -> 0.07826087 | D17: =E17*D$25 -> 185.17081 | E17: =E$5*C17/C$5 -> 0.034937888 | F17: =B17+D17 -> 365.17081 | G17: =F17/F$25 -> 0.04804879 | H17: 0.2 | I17: =(1-H17)*F17 -> 292.13665 | J17: =AVERAGE(J6:J16) -> 0.26181818 | K17: 0.4 | L17: 0 | M17: =O17+P17+Q17 -> 9.6245746 | N17: =M17/M$25 -> 0.050819029 | O17: =O$3*J17*I17 -> 6.1189348 | P17: =I17*P$3*K17 -> 3.5056398 | Q17: =L17*I17 -> 0 | R17: =(O17+Q17) -> 6.1189348 | S17: =R17/(O$3*I17) -> 0.26181818
A18: Gulf countries | B18: =C18*DataFig2!B$24 -> 230 | C18: =DataFig2!C17 -> 0.1 | D18: =E18*D$25 -> 530 | E18: =C18 -> 0.1 | F18: =B18+D18 -> 760 | G18: =F18/F$25 -> 0.1 | H18: 0.2 | I18: =(1-H18)*F18 -> 608 | J18: 0 | K18: 0 | L18: 0 | M18: =O18+P18+Q18 -> 0 | N18: =M18/M$25 -> 0 | O18: =O$3*J18*I18 -> 0 | P18: =I18*P$3*K18 -> 0 | Q18: =L18*I18 -> 0 | R18: =(O18+Q18) -> 0
A19: Asia | B19: =C19*DataFig2!B$24 -> 230 | C19: =DataFig2!C18 -> 0.1 | D19: =E19*D$25 -> 1060 | E19: 0.2 | F19: =B19+D19 -> 1290 | G19: =F19/F$25 -> 0.16973684 | H19: 0.2 | I19: =(1-H19)*F19 -> 1032 | J19: 0.3 | K19: 0.3 | L19: 0 | M19: =O19+P19+Q19 -> 34.056 | N19: =M19/M$25 -> 0.17982019 | O19: =O$3*J19*I19 -> 24.768 | P19: =I19*P$3*K19 -> 9.288 | Q19: =L19*I19 -> 0 | R19: =(O19+Q19) -> 24.768 | S19: =R19/(O$3*I19) -> 0.3
A20: Latin America | B20: =C20*DataFig2!B$24 -> 218.5 | C20: =DataFig2!C19 -> 0.095 | D20: =E20*D$25 -> 503.5 | E20: =C20 -> 0.095 | F20: =B20+D20 -> 722 | G20: =F20/F$25 -> 0.095 | H20: 0.2 | I20: =(1-H20)*F20 -> 577.6 | J20: 0.3 | K20: 0.4 | L20: 0 | M20: =O20+P20+Q20 -> 20.7936 | N20: =M20/M$25 -> 0.10979296 | O20: =O$3*J20*I20 -> 13.8624 | P20: =I20*P$3*K20 -> 6.9312 | Q20: =L20*I20 -> 0 | R20: =(O20+Q20) -> 13.8624 | S20: =R20/(O$3*I20) -> 0.3
A21: Africa | B21: =C21*DataFig2!B$24 -> 149.5 | C21: =DataFig2!C20 -> 0.065 | D21: =E21*D$25 -> 344.5 | E21: =C21 -> 0.065 | F21: =B21+D21 -> 494 | G21: =F21/F$25 -> 0.065 | H21: 0.2 | I21: =(1-H21)*F21 -> 395.2 | J21: 0.3 | K21: 0.4 | L21: 0 | M21: =O21+P21+Q21 -> 14.2272 | N21: =M21/M$25 -> 0.075121501 | O21: =O$3*J21*I21 -> 9.4848 | P21: =I21*P$3*K21 -> 4.7424 | Q21: =L21*I21 -> 0 | R21: =(O21+Q21) -> 9.4848 | S21: =R21/(O$3*I21) -> 0.3
A22: United States | B22: =C22*DataFig2!B$24 -> 76.666667 | C22: =DataFig2!C21 -> 0.033333333 | D22: =F22-B22 -> 1125.9382 | E22: =D22/D$25 -> 0.21244117 | F22: =G22*F$25 -> 1202.6049 | G22: 0.15823748 | H22: 0.2 | I22: =(1-H22)*F22 -> 962.0839 | J22: 0.303 | K22: 0.4 | L22: 0 | M22: =O22+P22+Q22 -> 34.86592 | N22: =M22/M$25 -> 0.18409668 | O22: =O$3*J22*I22 -> 23.320914 | P22: =I22*P$3*K22 -> 11.545007 | Q22: =L22*I22 -> 0 | R22: =(O22+Q22) -> 23.320914 | S22: =R22/(O$3*I22) -> 0.303
A23: Canada | B23: =C23*DataFig2!B$24 -> 38.333333 | C23: =DataFig2!C22 -> 0.016666667 | D23: =F23-B23 -> 245.57463 | E23: =D23/D$25 -> 0.046334835 | F23: =G23*F$25 -> 283.90796 | G23: 0.03735631 | H23: 0.2 | I23: =(1-H23)*F23 -> 227.12637 | J23: 0.338 | K23: 0 | L23: 0 | M23: =O23+P23+Q23 -> 6.141497 | N23: =M23/M$25 -> 0.032427917 | O23: =O$3*J23*I23 -> 6.141497 | P23: =I23*P$3*K23 -> 0 | Q23: =L23*I23 -> 0 | R23: =(O23+Q23) -> 6.141497 | S23: =R23/(O$3*I23) -> 0.338
A24: Russia | B24: =C24*DataFig2!B$24 -> 69 | C24: =DataFig2!C23 -> 0.03 | D24: =E24*D$25 -> 159 | E24: =C24 -> 0.03 | F24: =B24+D24 -> 228 | G24: =F24/F$25 -> 0.03 | H24: 0.2 | I24: =(1-H24)*F24 -> 182.4 | J24: 0.09 | K24: 0 | L24: 0 | M24: =O24+P24+Q24 -> 1.31328 | N24: =M24/M$25 -> 0.0069342924 | O24: =O$3*J24*I24 -> 1.31328 | P24: =I24*P$3*K24 -> 0 | Q24: =L24*I24 -> 0 | R24: =(O24+Q24) -> 1.31328 | S24: =R24/(O$3*I24) -> 0.09
A25: Total | B25: =DataFig2!B24 -> 2300 | C25: =B25/B$25 -> 1 | D25: =7600-'Data-Fig4_Tab1'!B25 -> 5300 | E25: =SUM(E18:E24)+E5 -> 0.99877601 | F25: =B25+D25 -> 7600 | G25: =F25/F$25 -> 1 | H25: 0.2 | I25: =SUM(I18:I24)+I5 -> 6074.8103 | M25: =O25+P25+Q25 -> 189.38919 | N25: =M25/M$25 -> 1 | O25: =SUM(O18:O24)+O5 -> 127.08789 | P25: =SUM(P18:P24)+P5 -> 51.816839 | Q25: =SUM(Q18:Q24)+Q5 -> 10.48446 | R25: =(O25+Q25) -> 137.57235 | S25: =R25/(O$3*I25) -> 0.28307952
P27: =P25/(P$3*I25) -> 0.28432624
A29: Source: Zucman 2014 JEP. I make 4 changes: (i) based on the latest Fiduciary Statistics data from the 2013 edition of "Banks in Switzerland", share of Swiss offshore wealth assigned to the US is increased by 1 point and that assigned to Canada decreased by 1 point. I am adjusting the non-Swiss offshore wealth of US and Canada accordingly so that total offshore wealth matches the figures given in the JEP paper. (ii) Fraction of offshore wealth declared is set at 20% for all countries, based on latest AFC STD data (see update to Johannesen Zucman 2014 and December 2014 update to JEP appendix: http://gabriel-zucman.eu/files/Zucman2014JEPAppendix.pdf); (iii) Nominal rate of return on offshore assets changed to 8% based on latest values of 10-years returns on Venduard diversified funds (see link in cell O3). (iv) Wealth tax rates are updated and improved (e.g., I now take int account the new wealth tax in Spain).

Sheet Data-Fig5
B1: Tax havens | C1: Europe | D1: Middle East | E1: Latin and South America | F1: Asia | G1: Africa | H1: North America | I1: (Memo: Caribbean)
A2: 1976 | B2: 0.3142881 | C2: 0.383268 | D2: 0.14346484 | E2: 0.052798399 | F2: 0.032321295 | G2: 0.044874468 | H2: 0.028984903 | I2: 0
A3: 1977 | B3: 0.3306751 | C3: 0.40017874 | D3: 0.11759247 | E3: 0.051491819 | F3: 0.03279252 | G3: 0.045957652 | H3: 0.021311701 | I3: 0
A4: 1978 | B4: 0.34341296 | C4: 0.35723073 | D4: 0.14106709 | E4: 0.052724932 | F4: 0.027120584 | G4: 0.055070805 | H4: 0.023372908 | I4: 0
A5: 1979 | B5: 0.31128158 | C5: 0.38623512 | D5: 0.14029815 | E5: 0.053976037 | F5: 0.026691447 | G5: 0.055261181 | H5: 0.026256475 | I5: 0
A6: 1980 | B6: 0.27521767 | C6: 0.41674304 | D6: 0.14493355 | E6: 0.058067934 | F6: 0.029255929 | G6: 0.049891167 | H6: 0.025890709 | I6: 0
A7: 1981 | B7: 0.25785437 | C7: 0.44283856 | D7: 0.12873097 | E7: 0.072365618 | F7: 0.027762205 | G7: 0.04418855 | H7: 0.026259727 | I7: 0
A8: 1982 | B8: 0.26838302 | C8: 0.39270133 | D8: 0.17117342 | E8: 0.065783494 | F8: 0.03096028 | G8: 0.044446464 | H8: 0.026551991 | I8: 0
A9: 1983 | B9: 0.28996576 | C9: 0.35507826 | D9: 0.18609925 | E9: 0.062466649 | F9: 0.035096496 | G9: 0.043000711 | H9: 0.028292867 | I9: 0
A10: 1984 | B10: 0.31450227 | C10: 0.30732502 | D10: 0.20626049 | E10: 0.063228154 | F10: 0.044309969 | G10: 0.031724651 | H10: 0.032378042 | I10: 0.00027140861
A11: 1985 | B11: 0.3211251 | C11: 0.30381032 | D11: 0.20444627 | E11: 0.060325632 | F11: 0.048060994 | G11: 0.030612608 | H11: 0.031414219 | I11: 0.00020485598
A12: 1986 | B12: 0.33761827 | C12: 0.30588823 | D12: 0.18129725 | E12: 0.062041619 | F12: 0.04906591 | G12: 0.030271281 | H12: 0.033599832 | I12: 0.00021760505
A13: 1987 | B13: 0.34666633 | C13: 0.31276382 | D13: 0.16543127 | E13: 0.062554035 | F13: 0.046553171 | G13: 0.029541525 | H13: 0.036292783 | I13: 0.00019707064
... A34: 2008 | B34: 0.61401599 | C34: 0.15679436 | D34: 0.078365778 | E34: 0.045494606 | F34: 0.062434711 | G34: 0.017455091 | H34: 0.025014497 | I34: 0.00042496802
A35: 2009 | B35: =DataFig2!M29 -> 0.63118162 | C35: =DataFig2!M30/DataFig2!N30*C34 -> 0.12727508
A36: 2010 | B36: =DataFig2!L29 -> 0.63087676 | C36: =C35*DataFig2!L30/DataFig2!M30 -> 0.12551944
A37: 2011 | B37: =DataFig2!K29 -> 0.59706354 | C37: =C36*DataFig2!K30/DataFig2!L30 -> 0.13031763
A38: 2012 | B38: =DataFig2!J29 -> 0.62276265 | C38: =C37*DataFig2!J30/DataFig2!K30 -> 0.10580759
A39: 2013 | B39: =DataFig2!I29 -> 0.61830017 | C39: =C38*DataFig2!I30/DataFig2!J30 -> 0.11631391
A40: 2014
A41: 2015
B43: Source: Zucman (2013, Appendix Table A25) through to 2008; 2009-2013: update based on SNB's Banks in Switzerland yearly data

Sheet Data-Fig6
B1: Finance | C1: Industry
A2: 1970 | B2: 0.018088811 | C2: 0.45012818
A3: 1971 | B3: 0.041427958 | C3: 0.390531
A4: 1972 | B4: 0.073390782 | C4: 0.36250889
A5: 1973 | B5: 0.063235996 | C5: 0.39211404
A6: 1974 | B6: 0.060347298 | C6: 0.41294522
A7: 1975 | B7: 0.15858149 | C7: 0.27833434
A8: 1976 | B8: 0.1745468 | C8: 0.29064719
A9: 1977 | B9: 0.19524552 | C9: 0.25920675
A10: 1978 | B10: 0.1848296 | C10: 0.26856304
A11: 1979 | B11: 0.14042651 | C11: 0.2828928
A12: 1980 | B12: 0.11177975 | C12: 0.2792505
A13: 1981 | B13: 0.13803883 | C13: 0.26420699
... A45: 2013 | B45: 0.40805417 | C45: 0.077748391

Sheet Fig7
B3: The case for a world financial register
B7: The companies Clearstream, Euroclear, etc. feed the world financial register. Tax authorities can verify that tax-payers indeed declare all the financial securities included in the register
B16: Despository Trust Corporation (USA) | D16: World financial register | F16: U.S. tax authority
B21: Clearstream (Luxembourg) | F21: U.K. tax authority
B26: Euroclear France (France) | F26: French tax authority
B31: Other central securities depositories & other sources | F31: Other tax administrations

Sheet DataFig8-9
A1: (May 2014 JEP comps) | D1: Domestic vs. foreign profits | O1: From IRS to BEA profits | Y1: S corporations | AG1: Corporate tax revenue | AU1: Tax rate computations | BC1: Distributed vs retained profits | BQ1: Decomposition of foreign profits by country | CT1: Decomposition of foreign retained earnings by country | DJ1: Decomposition of USDIA flows (= outflows of both equity & debt + retained earnings) by country | DU1: Decomposition of equity & debt DI outflows (USDIA flows - DI retained) | EP1: Decomposition of DI assets by country | FA1: Returns on USDIA by country (exploratory, not used in JEP)
A2: (Revised August 2014)
B3: Series | C3: National income | D3: Pre-tax corporate profits with IVA and CCAdj (BEA) | E3: (corporate profits % national income) | F3: Equals | G3: Domestic profits | H3: (domestic profits % national income) | I3: Net foreign profits | J3: (net foreign profits % of national income) | K3: (net foreign profits % of BEA profits) | L3: (Foreign profits inflows) | M3: (Foreign profits inflows % NI) | N3: (Foreign profits inflows, % BEA profits) | O3: Pre-tax corporate profits with IVA and CCAdj (BEA) | P3: Equals | Q3: Corporate profits (IRS) | R3: Misreporting on IRS returns | S3: (misreporting % of BEA profits) | T3: Fed profits | U3: IVA and CCAdj | V3: Less: Capital gains | W3: (capital gains % of BEA profits) | X3: Other adjustmetns to IRS data | Y3: Total receipts less total deductions, IRS | Z3: Revisions to IRS "Total Receipts Less Total Deductions", BEA | AA3: (Of which: bad debt expenses) | AB3: (Of which: other) | AC3: S corporations profits included in BEA profits | AD3: Memo: share of S corp profits in BEA profits | AE3: Memo: S corporation dividends included in NIPA corporate dividends | AF3: Memo: S corporation net profits taxed at individual level | AG3: Taxes on corporate income | AH3: (corporate tax % of national income) | AI3: (corporate tax excluding fed profits % of national income) | AJ3: Equals | AK3: Paid to federal gov, net of credits | AL3: Paid to local & state gov | AM3: Paid by domestic corp to foreign gov on income earned abroad | AN3: Paid by Fed | AO3: Memo: credits for foreign taxes paid [more or less = total nonresident income tax paid] | AP3: Memo: Federal corporate tax revenu, OMB, calendar year estimate | AQ3: Memo: foreign taxes paid, accrued, and deemed paid, IRS | AR3: Memo: foreign profits repatriated, IRS | AS3: Memo: foreign profits repatriated, IRS | AT3: After-tax corporate profits / national income | AU3: Staturoy federal corporate tax rate | AV3: Effective tax rate paid to US (fed+local) | AW3: Excluding S corp | AX3: Effective tax rate paid to US (including KG in profits) | AY3: Effective tax rate paid worldwide | AZ3: Excluding S corp | BA3: Effective tax rate IRS | BB3: Effective tax rate IRS after misreporting | BC3: Pre-tax corporate profits with IVA and CCAdj (BEA) | BD3: Equals | BE3: Corporate income taxes | BF3: Distributed earnings | BG3: Retained earnings | BH3: (retained earnings % BEA profits) | BI3: Retained domestic | BJ3: Retained abroad | BK3: (Retained foreign, % of BEA profits) | BL3: (Retained havens, % of BEA profits) | BM3: (Retained havens, % of DI income) | BN3: (check) | BO3: (Retained abroad, % of foreign profits) | BP3: Memo: distributions on US DI = repatriations | BQ3: Foreign profits | BR3: Equals | BS3: Diff geographical coverage btw NIPA and BoP | BT3: PI dividends | BU3: DI (divs+retained) with CCAdj | BV3: CCAdj | BW3: Memo: share of DI in foreign profits | BX3: USDIA without CCAdj | BY3: Ireland | BZ3: Netherlands | CA3: Luxembourg | CB3: Switzerland | CC3: Bermuda & other Caribbean | CD3: Bermuda | CE3: Other Caribbean | CF3: Singapore | CG3: Top 6 havens | CH3: Non havens | CI3: Ireland | CJ3: Netherlands | CK3: Luxembourg | CL3: Switzerland | CM3: Bermuda & other Caribbean | CN3: Bermuda | CO3: Other Caribbean | CP3: Singapore | CQ3: Top 6 havens % of total DI income | CR3: Top 6 havens % of all U.S. corporate profits | CS3: DI without CCAdj | CT3: USDIA without CCAdj | CU3: Equals | CV3: DI distributed | CW3: DI retained | CX3: Ireland | CY3: Netherlands | CZ3: Luxembourg | DA3: Switzerland | DB3: Bermuda & other Caribbean | DC3: Singapore | DD3: Top 6 havens | DE3: In constant $? | DF3: Top 6 havens retained / top 6 heavens profits | DG3: Non havens | DH3: Top 6 havens % of total DI retained | DI3: DI retained/total DI | DJ3: DI outflows | DK3: Ireland | DL3: Netherlands | DM3: Luxembourg | DN3: Switzerland | DO3: Bermuda & other Caribbean | DP3: (Bermuda) | DQ3: Singapore | DR3: Top 6 havens | DS3: Non havens | DT3: Top 6 havens % of total DI outflows | DU3: DI equity & debt ouflows | DV3: (check) | DW3: Ireland | DX3: Netherlands | DY3: Luxembourg | DZ3: Switzerland | EA3: Bermuda & other Caribbean | EB3: Singapore | EC3: Top 6 havens | ED3: Non havens | EE3: Top 6 havens % of total DI outflows | EF3: DI equity outflow | EG3: Ireland | EH3: Netherlands | EI3: Luxembourg | EJ3: Switzerland | EK3: Bermuda & other Caribbean | EL3: Singapore | EM3: Top 6 havens | EN3: Non havens | EO3: Top 6 havens % of total DI equity outflows | EP3: DI assets historical cost | EQ3: Ireland | ER3: Netherlands | ES3: Luxembourg | ET3: Switzerland | EU3: Bermuda & other Caribbean | EV3: (Bermuda) | EW3: Singapore | EX3: Top 6 havens | EY3: Non havens | EZ3: Top 6 havens % of total DI assets | FA3: Historical cost total return | FB3: Ireland | FC3: Netherlands | FD3: Luxembourg | FE3: Switzerland | FF3: Bermuda & other Caribbean | FG3: (Bermuda) | FH3: Singapore | FI3: Top 6 havens | FJ3: Non havens | FK3: Non-havens, pre-foreign corp tax (assuming havens =0 tax) | FL3: Yield (historical cost) | FM3: Ireland | FN3: Netherlands | FO3: Luxembourg | FP3: Switzerland | FQ3: Bermuda & other Caribbean | FR3: (Bermuda) | FS3: Singapore | FT3: Top 6 havens | FU3: Non havens | FV3: Royalties etc.
B4: Notes | D4: Net of interest payments | G4: Gross of income taxes (both US taxes and the small amount of taxes paid by domestic businesses to foreign governments) | I4: US profits abroad minus foreign profits in the US. Includes DI + dividend portion of PI (but not retained earnings on PI). Is net of nonresident corporate income tax. | L4: US profits abroad. No data prior to 1948 assume same evolution as net foreign profits | R4: The IRS audit consists of three steps. First, the IRS audits a small sampling of corporations and recommends how much, if any, additional tax liability is owed. Next, the corporations can appeal those recommendations. Finally, a resolution between the corporation and the IRS is reached, and the corporation pays the IRS. The methodology for the misreporting adjustment is to capture only the amount of tax actually collected (see the section “Taxes on Corporate Income”), raise it to a universe total, and then convert it from a tax-liability measure to a profits measure. | X4: Mosty equal to bad debt expense in recent years | Y4: From SOI S corp stats Table 1.-, S-Corporation, All Returns: Total Receipts and Deductions | Z4: Definitional adjustment: To restate profits of small business corporations to reflect the income and expenses that are passed to shareholders rather than reported by the corporation. See http://www.bea.gov/national/pdf/chapter13.pdf. Only known in 2010 (-21bn), assume constant fraction of IRS profits before. | AA4: Part of what corporations can deduct from their IRS profits, but not deduced for NIPA profit computations. Data here from SOI S corp Table 1 | AC4: 1995-on: see formula; before: based on evolution of net S corp income reported by individual taxpayers | AE4: Bigger than 100% of S corporation net profits because of S corp losses (which do not generate negative dividends) | AF4: From Saez-Zucman 2014 total | AG4: Excludes nonresident income tax paid by affiliates | AL4: 2013 data point from Table 1: http://www.census.gov/govs/qtax/ | AN4: Alsmot all Fed profits are treated as corporate taxes by BEA (this is a bit weird; might make more sense for BEA to record that as dividend) | AO4: NB: (i) sometimes foreign tax rates are bigger than US tax rate so no credit; (ii) credits triggered only when repatriation; (iii) since 2007 this is exactly equal to "foreign tax credit claim" from IRS form 1118; before however, this is bigger than IRS 1118 total, with a gap increasing the further one goes back (eg in 1992: total IRS 1118 =21.5bn vs. 25.3bn here), unclear why | AP4: Raw data are fiscal year, here I attempt a calander year conversion. The U.S. federal government's fiscal year begins on 1 October of the previous calendar year and ends on 30 September of the year with which it is numbered. Prior to 1976, the fiscal year began on 1 July and ended on 30 June. | AQ4: From tabulations of IRS form 1118, http://www.irs.gov/uac/SOI-Tax-Stats-Corporate-Foreign-Tax-Credit-Table-1 | AR4: Taxable income (less loss) before adjustments From tabulations of IRS form 1118, http://www.irs.gov/uac/SOI-Tax-Stats-Corporate-Foreign-Tax-Credit-Table-1. Bigger than repatriations from BoP because (i) includes subpart F income; (ii) here is gross of foreign corporate taxes paid (vs. net in BoP) | AS4: Taxable income (less loss) after adjustments From tabulations of IRS form 1118, http://www.irs.gov/uac/SOI-Tax-Stats-Corporate-Foreign-Tax-Credit-Table-1 | AU4: Source Tax Policy Center http://www.taxpolicycenter.org/taxfacts/content/pdf/corporate_historical_bracket.pdf | AV4: Excluding Fed payments | AX4: Excluding Fed payments | AY4: Excluding Fed payments; and assuming that the foreign tax credit equals tax liability on income earned abroad (the convention used in the national accounts), ie in particular that foreign taxes paid on unrepatriated earnings are negligible (consistent with corporate filings, e.g. Microsoft 2014, but would need to be investigated more systematically) | BA4: Does not decline because of growing misreporting | BC4: Net of interest payments | BQ4: PI divs + DI divs & retained. (As always, corporate profits = net of interest payments) | BS4: Puerto Rico etc. | BW4: Note that DI include retained earnings but PI do not | CU4: Unclear where this discrepancy comes from, revisions? | DD4: This is lower than the $2tr one often hears because this is historical cost data; also not all foreign subsidiaries of US firms belong 100% to the US | FA4: What we'd like is market-value total return; pb = not published at country level; plus unclear how to measure MV of Goodle BM?. On the other hand (i) historical cost include some KG (unclear what exactly; also my method to compute KG will include other changes, like data revisions etc.; however not clear why it should benefit havens more than non-havens); (ii) it's useful to have "book values" to detect profit shifting in yieds (ie high yield = BM generates huge profits compared to low book value assets); pb= yield differential havens/non havens does not seem huge and it seems it can be accounted for by the fact that inv flows are post foreign corp taxes | FI4: Positive valuation effect only for havens | FK4: Still positive returns diff after corp tax, entirely due to valuation effect. Why?? | FT4: This differential is what we would expect, because DI profits are net of foreign corporate taxes paid. Ce qu'il faudrait c'est réattribuer les foreign taxes paid pour pouvoir calculer des pre-tax yields = à faire avec BEA data on affiliates
B5: 1929 | C5: 94.2 | D5: 10.8 | E5: =D5/C5 -> 0.11464968 | F5: =D5-(G5+I5) -> 0 | G5: =D5-I5 -> 10.6 | H5: =G5/C5 -> 0.11252654 | I5: 0.2 | J5: =I5/C5 -> 0.0021231423 | K5: =I5/D5 -> 0.018518519 | L5: =I5 -> 0.2 | M5: =L5/C5 -> 0.0021231423 | N5: =L5/D5 -> 0.018518519 | O5: =D5 -> 10.8 | P5: =O5-(Q5+R5+T5+U5+X5-V5) -> 0 | Q5: 11.9 | R5: 0.7 | S5: =R5/D5 -> 0.064814815 | T5: 0 | U5: -0.1 | V5: 0.7 | W5: =V5/D5 -> 0.064814815 | X5: =O5-(Q5+R5+T5+U5-V5) -> -1 | AC5: 0 | AD5: =AC5/D5 -> 0 | AG5: 1.4 | AH5: =AG5/C5 -> 0.014861996 | AI5: =(AG5-AN5)/C5 -> 0.014861996 | AJ5: =AG5-(AK5+AL5+AM5+AN5) -> 0 | AK5: 1.3 | AL5: 0.1 | AM5: 0 | AN5: 0 | AO5: 0 | AT5: =(O5-AG5)/C5 -> 0.099787686 | AU5: 0.11 | BC5: =D5 -> 10.8 | BD5: =BC5-(BE5+BF5+BG5) -> -0.1 | BE5: =AG5 -> 1.4 | BF5: 5.8 | BG5: 3.7 | BI5: 3.7 | BJ5: =BG5-BI5 -> 0 | BK5: =BJ5/D5 -> 0
B6: 1930 | C6: 83.1 | D6: 7.5 | E6: =D6/C6 -> 0.090252708 | F6: =D6-(G6+I6) -> 0 | G6: =D6-I6 -> 7.4 | H6: =G6/C6 -> 0.089049338 | I6: 0.1 | J6: =I6/C6 -> 0.0012033694 | K6: =I6/D6 -> 0.013333333 | L6: =I6 -> 0.1 | M6: =L6/C6 -> 0.0012033694 | N6: =L6/D6 -> 0.013333333 | O6: =D6 -> 7.5 | P6: =O6-(Q6+R6+T6+U6+X6-V6) -> 0 | Q6: 4.6 | R6: 0.6 | S6: =R6/D6 -> 0.08 | T6: 0 | U6: 3 | V6: -0.2 | W6: =V6/D6 -> -0.026666667 | X6: =O6-(Q6+R6+T6+U6-V6) -> -0.9 | AC6: 0 | AD6: =AC6/D6 -> 0 | AG6: 0.8 | AH6: =AG6/C6 -> 0.0096269555 | AI6: =(AG6-AN6)/C6 -> 0.0096269555 | AJ6: =AG6-(AK6+AL6+AM6+AN6) -> -0.1 | AK6: 0.8 | AL6: 0.1 | AM6: 0 | AN6: 0 | AO6: 0 | AT6: =(O6-AG6)/C6 -> 0.080625752 | AU6: 0.12 | BC6: =D6 -> 7.5 | BD6: =BC6-(BE6+BF6+BG6) -> 0 | BE6: =AG6 -> 0.8 | BF6: 5.5 | BG6: 1.2 | BI6: 1.2 | BJ6: =BG6-BI6 -> 0 | BK6: =BJ6/D6 -> 0
B7: 1931 | C7: 67.7 | D7: 3 | E7: =D7/C7 -> 0.044313146 | F7: =D7-(G7+I7) -> 0 | G7: =D7-I7 -> 3 | H7: =G7/C7 -> 0.044313146 | I7: 0 | J7: =I7/C7 -> 0 | K7: =I7/D7 -> 0 | L7: =I7 -> 0 | M7: =L7/C7 -> 0 | N7: =L7/D7 -> 0 | O7: =D7 -> 3 | P7: =O7-(Q7+R7+T7+U7+X7-V7) -> 0 | Q7: -0.8 | R7: 0.4 | S7: =R7/D7 -> 0.13333333 | T7: 0 | U7: 2.4 | V7: -1.3 | W7: =V7/D7 -> -0.43333333 | X7: =O7-(Q7+R7+T7+U7-V7) -> -0.3 | AC7: 0 | AD7: =AC7/D7 -> 0 | AG7: 0.5 | AH7: =AG7/C7 -> 0.0073855244 | AI7: =(AG7-AN7)/C7 -> 0.0073855244 | AJ7: =AG7-(AK7+AL7+AM7+AN7) -> 0 | AK7: 0.4 | AL7: 0.1 | AM7: 0 | AN7: 0 | AO7: 0 | AT7: =(O7-AG7)/C7 -> 0.036927622 | AU7: 0.12 | BC7: =D7 -> 3 | BD7: =BC7-(BE7+BF7+BG7) -> 0 | BE7: =AG7 -> 0.5 | BF7: 4.1 | BG7: -1.6 | BI7: -1.6 | BJ7: =BG7-BI7 -> 0 | BK7: =BJ7/D7 -> 0
B8: 1932 | C8: 51.3 | D8: -0.2 | E8: =D8/C8 -> -0.0038986355 | F8: =D8-(G8+I8) -> 0 | G8: =D8-I8 -> -0.2 | H8: =G8/C8 -> -0.0038986355 | I8: 0 | J8: =I8/C8 -> 0 | K8: =I8/D8 -> 0 | L8: =I8 -> 0 | M8: =L8/C8 -> 0 | N8: =L8/D8 -> 0 | O8: =D8 -> -0.2 | P8: =O8-(Q8+R8+T8+U8+X8-V8) -> 0 | Q8: -3.8 | R8: 0.3 | S8: =R8/D8 -> -1.5 | T8: 0 | U8: 1.1 | V8: -1.6 | W8: =V8/D8 -> 8 | X8: =O8-(Q8+R8+T8+U8-V8) -> 0.6 | AC8: 0 | AD8: =AC8/D8 -> 0 | AG8: 0.4 | AH8: =AG8/C8 -> 0.007797271 | AI8: =(AG8-AN8)/C8 -> 0.007797271 | AJ8: =AG8-(AK8+AL8+AM8+AN8) -> 0 | AK8: 0.3 | AL8: 0.1 | AM8: 0 | AN8: 0 | AO8: 0 | AT8: =(O8-AG8)/C8 -> -0.011695906 | AU8: 0.1375 | BC8: =D8 -> -0.2 | BD8: =BC8-(BE8+BF8+BG8) -> 0 | BE8: =AG8 -> 0.4 | BF8: 2.5 | BG8: -3.1 | BI8: -3.1 | BJ8: =BG8-BI8 -> 0 | BK8: =BJ8/D8 -> 0
B9: 1933 | C9: 49 | D9: -0.2 | E9: =D9/C9 -> -0.0040816327 | F9: =D9-(G9+I9) -> 0 | G9: =D9-I9 -> -0.2 | H9: =G9/C9 -> -0.0040816327 | I9: 0 | J9: =I9/C9 -> 0 | K9: =I9/D9 -> 0 | L9: =L10*I9/I10 -> 0 | M9: =L9/C9 -> 0 | N9: =L9/D9 -> 0 | O9: =D9 -> -0.2 | P9: =O9-(Q9+R9+T9+U9+X9-V9) -> 0 | Q9: -0.9 | R9: 0.4 | S9: =R9/D9 -> -2 | T9: 0 | U9: -2 | V9: -1.4 | W9: =V9/D9 -> 7 | X9: =O9-(Q9+R9+T9+U9-V9) -> 0.9 | AC9: 0 | AD9: =AC9/D9 -> 0 | AG9: 0.5 | AH9: =AG9/C9 -> 0.010204082 | AI9: =(AG9-AN9)/C9 -> 0.010204082 | AJ9: =AG9-(AK9+AL9+AM9+AN9) -> -0.1 | AK9: 0.5 | AL9: 0.1 | AM9: 0 | AN9: 0 | AO9: 0 | AT9: =(O9-AG9)/C9 -> -0.014285714 | AU9: 0.1375 | BC9: =D9 -> -0.2 | BD9: =BC9-(BE9+BF9+BG9) -> 0 | BE9: =AG9 -> 0.5 | BF9: 2 | BG9: -2.7 | BI9: -2.7 | BJ9: =BG9-BI9 -> 0 | BK9: =BJ9/D9 -> 0
B10: 1934 | C10: 58.3 | D10: 2.5 | E10: =D10/C10 -> 0.042881647 | F10: =D10-(G10+I10) -> 0 | G10: =D10-I10 -> 2.4 | H10: =G10/C10 -> 0.041166381 | I10: 0.1 | J10: =I10/C10 -> 0.0017152659 | K10: =I10/D10 -> 0.04 | L10: =L11*I10/I11 -> 0.13076923 | M10: =L10/C10 -> 0.00224304 | N10: =L10/D10 -> 0.052307692 | O10: =D10 -> 2.5 | P10: =O10-(Q10+R10+T10+U10+X10-V10) -> 0 | Q10: 3 | R10: 0.6 | S10: =R10/D10 -> 0.24 | T10: 0 | U10: -0.7 | V10: -0.1 | W10: =V10/D10 -> -0.04 | X10: =O10-(Q10+R10+T10+U10-V10) -> -0.5 | AC10: 0 | AD10: =AC10/D10 -> 0 | AG10: 0.7 | AH10: =AG10/C10 -> 0.012006861 | AI10: =(AG10-AN10)/C10 -> 0.012006861 | AJ10: =AG10-(AK10+AL10+AM10+AN10) -> -0.1 | AK10: 0.7 | AL10: 0.1 | AM10: 0 | AN10: 0 | AO10: 0 | AP10: 0.4465 | AT10: =(O10-AG10)/C10 -> 0.030874786 | AU10: 0.1375 | AV10: =(AK10+AL10)/(G10+L10-T10) -> 0.31610942 | AX10: =(AG10-AN10-AM10)/(G10+L10-T10+V10) -> 0.28797468 | AY10: =(AG10-AN10-AM10+AO10)/(G10+L10-T10+AO10) -> 0.27659574 | AZ10: =(AG10-AN10-AM10+AO10)/(G10+L10-T10+AO10-AC10) -> 0.27659574 | BA10: =(AG10-AN10)/Q10 -> 0.23333333 | BB10: =(AG10-AN10)/(Q10+R10) -> 0.19444444 | BC10: =D10 -> 2.5 | BD10: =BC10-(BE10+BF10+BG10) -> 0 | BE10: =AG10 -> 0.7 | BF10: 2.6 | BG10: -0.8 | BI10: -0.8 | BJ10: =BG10-BI10 -> 0 | BK10: =BJ10/D10 -> 0
B11: 1935 | C11: 66.4 | D11: 4 | E11: =D11/C11 -> 0.060240964 | F11: =D11-(G11+I11) -> 0 | G11: =D11-I11 -> 3.8 | H11: =G11/C11 -> 0.057228916 | I11: 0.2 | J11: =I11/C11 -> 0.0030120482 | K11: =I11/D11 -> 0.05 | L11: =L12*I11/I12 -> 0.26153846 | M11: =L11/C11 -> 0.0039388323 | N11: =L11/D11 -> 0.065384615 | O11: =D11 -> 4 | P11: =O11-(Q11+R11+T11+U11+X11-V11) -> 0 | Q11: 5.4 | R11: 0.5 | S11: =R11/D11 -> 0.125 | T11: 0 | U11: -0.3 | V11: 0.2 | W11: =V11/D11 -> 0.05 | X11: =O11-(Q11+R11+T11+U11-V11) -> -1.4 | AC11: 0 | AD11: =AC11/D11 -> 0 | AG11: 1 | AH11: =AG11/C11 -> 0.015060241 | AI11: =(AG11-AN11)/C11 -> 0.015060241 | AJ11: =AG11-(AK11+AL11+AM11+AN11) -> 0 | AK11: 0.9 | AL11: 0.1 | AM11: 0 | AN11: 0 | AO11: 0 | AP11: 0.624 | AT11: =(O11-AG11)/C11 -> 0.045180723 | AU11: 0.1375 | AV11: =(AK11+AL11)/(G11+L11-T11) -> 0.24621212 | AX11: =(AG11-AN11-AM11)/(G11+L11-T11+V11) -> 0.23465704 | AY11: =(AG11-AN11-AM11+AO11)/(G11+L11-T11+AO11) -> 0.24621212 | AZ11: =(AG11-AN11-AM11+AO11)/(G11+L11-T11+AO11-AC11) -> 0.24621212 | BA11: =(AG11-AN11)/Q11 -> 0.18518519 | BB11: =(AG11-AN11)/(Q11+R11) -> 0.16949153 | BC11: =D11 -> 4 | BD11: =BC11-(BE11+BF11+BG11) -> 0 | BE11: =AG11 -> 1 | BF11: 2.8 | BG11: 0.2 | BH11: =BG11/D11 -> 0.05 | BI11: 0.2 | BJ11: =BG11-BI11 -> 0 | BK11: =BJ11/D11 -> 0
B12: 1936 | C12: 75.2 | D12: 6.2 | E12: =D12/C12 -> 0.082446809 | F12: =D12-(G12+I12) -> 0 | G12: =D12-I12 -> 6.1 | H12: =G12/C12 -> 0.081117021 | I12: 0.1 | J12: =I12/C12 -> 0.0013297872 | K12: =I12/D12 -> 0.016129032 | L12: =L13*I12/I13 -> 0.13076923 | M12: =L12/C12 -> 0.0017389525 | N12: =L12/D12 -> 0.021091811 | O12: =D12 -> 6.2 | P12: =O12-(Q12+R12+T12+U12+X12-V12) -> 0 | Q12: 7.8 | R12: 0.6 | S12: =R12/D12 -> 0.096774194 | T12: 0 | U12: -0.8 | V12: 0.4 | W12: =V12/D12 -> 0.064516129 | X12: =O12-(Q12+R12+T12+U12-V12) -> -1 | AC12: 0 | AD12: =AC12/D12 -> 0 | AG12: 1.4 | AH12: =AG12/C12 -> 0.018617021 | AI12: =(AG12-AN12)/C12 -> 0.018617021 | AJ12: =AG12-(AK12+AL12+AM12+AN12) -> -0.1 | AK12: 1.3 | AL12: 0.2 | AM12: 0 | AN12: 0 | AO12: 0 | AP12: 0.8785 | AT12: =(O12-AG12)/C12 -> 0.063829787 | AU12: 0.15 | AV12: =(AK12+AL12)/(G12+L12-T12) -> 0.24074074 | AX12: =(AG12-AN12-AM12)/(G12+L12-T12+V12) -> 0.21113689 | AY12: =(AG12-AN12-AM12+AO12)/(G12+L12-T12+AO12) -> 0.22469136 | AZ12: =(AG12-AN12-AM12+AO12)/(G12+L12-T12+AO12-AC12) -> 0.22469136 | BA12: =(AG12-AN12)/Q12 -> 0.17948718 | BB12: =(AG12-AN12)/(Q12+R12) -> 0.16666667 | BC12: =D12 -> 6.2 | BD12: =BC12-(BE12+BF12+BG12) -> 0 | BE12: =AG12 -> 1.4 | BF12: 4.5 | BG12: 0.3 | BH12: =BG12/D12 -> 0.048387097 | BI12: 0.3 | BJ12: =BG12-BI12 -> 0 | BK12: =BJ12/D12 -> 0
B13: 1937 | C13: 83.7 | D13: 7.1 | E13: =D13/C13 -> 0.084826762 | F13: =D13-(G13+I13) -> 0 | G13: =D13-I13 -> 6.8 | H13: =G13/C13 -> 0.081242533 | I13: 0.3 | J13: =I13/C13 -> 0.0035842294 | K13: =I13/D13 -> 0.042253521 | L13: =L14*I13/I14 -> 0.39230769 | M13: =L13/C13 -> 0.0046870692 | N13: =L13/D13 -> 0.055254605 | O13: =D13 -> 7.1 | P13: =O13-(Q13+R13+T13+U13+X13-V13) -> 0 | Q13: 7.8 | R13: 0.7 | S13: =R13/D13 -> 0.098591549 | T13: 0 | U13: -0.5 | V13: 0.1 | W13: =V13/D13 -> 0.014084507 | X13: =O13-(Q13+R13+T13+U13-V13) -> -0.8 | AC13: 0 | AD13: =AC13/D13 -> 0 | AG13: 1.5 | AH13: =AG13/C13 -> 0.017921147 | AI13: =(AG13-AN13)/C13 -> 0.017921147 | AJ13: =AG13-(AK13+AL13+AM13+AN13) -> -0.1 | AK13: 1.4 | AL13: 0.2 | AM13: 0 | AN13: 0 | AO13: 0 | AP13: 1.1625 | AT13: =(O13-AG13)/C13 -> 0.066905615 | AU13: 0.15 | AV13: =(AK13+AL13)/(G13+L13-T13) -> 0.22245989 | AX13: =(AG13-AN13-AM13)/(G13+L13-T13+V13) -> 0.2056962 | AY13: =(AG13-AN13-AM13+AO13)/(G13+L13-T13+AO13) -> 0.20855615 | AZ13: =(AG13-AN13-AM13+AO13)/(G13+L13-T13+AO13-AC13) -> 0.20855615 | BA13: =(AG13-AN13)/Q13 -> 0.19230769 | BB13: =(AG13-AN13)/(Q13+R13) -> 0.17647059 | BC13: =D13 -> 7.1 | BD13: =BC13-(BE13+BF13+BG13) -> 0 | BE13: =AG13 -> 1.5 | BF13: 4.7 | BG13: 0.9 | BH13: =BG13/D13 -> 0.12676056 | BI13: 0.7 | BJ13: =BG13-BI13 -> 0.2 | BK13: =BJ13/D13 -> 0.028169014
B14: 1938 | C14: 77.1 | D14: 5 | E14: =D14/C14 -> 0.064850843 | F14: =D14-(G14+I14) -> 0 | G14: =D14-I14 -> 4.7 | H14: =G14/C14 -> 0.060959792 | I14: 0.3 | J14: =I14/C14 -> 0.0038910506 | K14: =I14/D14 -> 0.06 | L14: =L15*I14/I15 -> 0.39230769 | M14: =L14/C14 -> 0.0050882969 | N14: =L14/D14 -> 0.078461538 | O14: =D14 -> 5 | P14: =O14-(Q14+R14+T14+U14+X14-V14) -> 0 | Q14: 4.1 | R14: 0.5 | S14: =R14/D14 -> 0.1 | T14: 0 | U14: 0.4 | V14: 0 | W14: =V14/D14 -> 0 | X14: =O14-(Q14+R14+T14+U14-V14) -> 0 | AC14: 0 | AD14: =AC14/D14 -> 0 | AG14: 1 | AH14: =AG14/C14 -> 0.012970169 | AI14: =(AG14-AN14)/C14 -> 0.012970169 | AJ14: =AG14-(AK14+AL14+AM14+AN14) -> -0.1 | AK14: 1 | AL14: 0.1 | AM14: 0 | AN14: 0 | AO14: 0 | AP14: 1.207 | AT14: =(O14-AG14)/C14 -> 0.051880674 | AU14: 0.19 | AV14: =(AK14+AL14)/(G14+L14-T14) -> 0.21601208 | AX14: =(AG14-AN14-AM14)/(G14+L14-T14+V14) -> 0.19637462 | AY14: =(AG14-AN14-AM14+AO14)/(G14+L14-T14+AO14) -> 0.19637462 | AZ14: =(AG14-AN14-AM14+AO14)/(G14+L14-T14+AO14-AC14) -> 0.19637462 | BA14: =(AG14-AN14)/Q14 -> 0.24390244 | BB14: =(AG14-AN14)/(Q14+R14) -> 0.2173913 | BC14: =D14 -> 5 | BD14: =BC14-(BE14+BF14+BG14) -> 0 | BE14: =AG14 -> 1 | BF14: 3.2 | BG14: 0.8 | BH14: =BG14/D14 -> 0.16 | BI14: 0.8 | BJ14: =BG14-BI14 -> 0 | BK14: =BJ14/D14 -> 0
B15: 1939 | C15: 82.5 | D15: 6.6 | E15: =D15/C15 -> 0.08 | F15: =D15-(G15+I15) -> 0 | G15: =D15-I15 -> 6.3 | H15: =G15/C15 -> 0.076363636 | I15: 0.3 | J15: =I15/C15 -> 0.0036363636 | K15: =I15/D15 -> 0.045454545 | L15: =L16*I15/I16 -> 0.39230769 | M15: =L15/C15 -> 0.0047552448 | N15: =L15/D15 -> 0.059440559 | O15: =D15 -> 6.6 | P15: =O15-(Q15+R15+T15+U15+X15-V15) -> 0 | Q15: 7.2 | R15: 0.6 | S15: =R15/D15 -> 0.090909091 | T15: 0 | U15: -1.2 | V15: 0 | W15: =V15/D15 -> 0 | X15: =O15-(Q15+R15+T15+U15-V15) -> 0 | AC15: 0 | AD15: =AC15/D15 -> 0 | AG15: 1.4 | AH15: =AG15/C15 -> 0.016969697 | AI15: =(AG15-AN15)/C15 -> 0.016969697 | AJ15: =AG15-(AK15+AL15+AM15+AN15) -> -0.1 | AK15: 1.3 | AL15: 0.2 | AM15: 0 | AN15: 0 | AO15: 0 | AP15: 1.162 | AT15: =(O15-AG15)/C15 -> 0.063030303 | AU15: 0.19 | AV15: =(AK15+AL15)/(G15+L15-T15) -> 0.22413793 | AX15: =(AG15-AN15-AM15)/(G15+L15-T15+V15) -> 0.2091954 | AY15: =(AG15-AN15-AM15+AO15)/(G15+L15-T15+AO15) -> 0.2091954 | AZ15: =(AG15-AN15-AM15+AO15)/(G15+L15-T15+AO15-AC15) -> 0.2091954 | BA15: =(AG15-AN15)/Q15 -> 0.19444444 | BB15: =(AG15-AN15)/(Q15+R15) -> 0.17948718 | BC15: =D15 -> 6.6 | BD15: =BC15-(BE15+BF15+BG15) -> 0 | BE15: =AG15 -> 1.4 | BF15: 3.8 | BG15: 1.4 | BH15: =BG15/D15 -> 0.21212121 | BI15: 1.2 | BJ15: =BG15-BI15 -> 0.2 | BK15: =BJ15/D15 -> 0.03030303
B16: 1940 | C16: 91.6 | D16: 9.9 | E16: =D16/C16 -> 0.1080786 | F16: =D16-(G16+I16) -> 0 | G16: =D16-I16 -> 9.6 | H16: =G16/C16 -> 0.10480349 | I16: 0.3 | J16: =I16/C16 -> 0.0032751092 | K16: =I16/D16 -> 0.03030303 | L16: =L17*I16/I17 -> 0.39230769 | M16: =L16/C16 -> 0.0042828351 | N16: =L16/D16 -> 0.03962704 | O16: =D16 -> 9.9 | P16: =O16-(Q16+R16+T16+U16+X16-V16) -> 0 | Q16: 9.3 | R16: 0.6 | S16: =R16/D16 -> 0.060606061 | T16: 0 | U16: -0.8 | V16: -0.7 | W16: =V16/D16 -> -0.070707071 | X16: =O16-(Q16+R16+T16+U16-V16) -> 0.1 | AC16: 0 | AD16: =AC16/D16 -> 0 | AG16: 2.8 | AH16: =AG16/C16 -> 0.030567686 | AI16: =(AG16-AN16)/C16 -> 0.030567686 | AJ16: =AG16-(AK16+AL16+AM16+AN16) -> 0.1 | AK16: 2.5 | AL16: 0.2 | AM16: 0 | AN16: 0 | AO16: 0.1 | AP16: 1.6605 | AT16: =(O16-AG16)/C16 -> 0.077510917 | AU16: 0.24 | AV16: =(AK16+AL16)/(G16+L16-T16) -> 0.27020785 | AX16: =(AG16-AN16-AM16)/(G16+L16-T16+V16) -> 0.3013245 | AY16: =(AG16-AN16-AM16+AO16)/(G16+L16-T16+AO16) -> 0.28734756 | AZ16: =(AG16-AN16-AM16+AO16)/(G16+L16-T16+AO16-AC16) -> 0.28734756 | BA16: =(AG16-AN16)/Q16 -> 0.30107527 | BB16: =(AG16-AN16)/(Q16+R16) -> 0.28282828 | BC16: =D16 -> 9.9 | BD16: =BC16-(BE16+BF16+BG16) -> 0.1 | BE16: =AG16 -> 2.8 | BF16: 4 | BG16: 3 | BH16: =BG16/D16 -> 0.3030303 | BI16: 3 | BJ16: =BG16-BI16 -> 0 | BK16: =BJ16/D16 -> 0
B17: 1941 | C17: 117.4 | D17: 15.7 | E17: =D17/C17 -> 0.13373083 | F17: =D17-(G17+I17) -> 0 | G17: =D17-I17 -> 15.3 | H17: =G17/C17 -> 0.13032368 | I17: 0.4 | J17: =I17/C17 -> 0.003407155 | K17: =I17/D17 -> 0.025477707 | L17: =L18*I17/I18 -> 0.52307692 | M17: =L17/C17 -> 0.0044555104 | N17: =L17/D17 -> 0.033317001 | O17: =D17 -> 15.7 | P17: =O17-(Q17+R17+T17+U17+X17-V17) -> 0 | Q17: 16.7 | R17: 0.7 | S17: =R17/D17 -> 0.044585987 | T17: 0 | U17: -3.1 | V17: -1 | W17: =V17/D17 -> -0.063694268 | X17: =O17-(Q17+R17+T17+U17-V17) -> 0.4 | AC17: 0 | AD17: =AC17/D17 -> 0 | AG17: 7.6 | AH17: =AG17/C17 -> 0.064735945 | AI17: =(AG17-AN17)/C17 -> 0.064735945 | AJ17: =AG17-(AK17+AL17+AM17+AN17) -> 0 | AK17: 7.3 | AL17: 0.3 | AM17: 0 | AN17: 0 | AO17: 0.1 | AP17: 3.4215 | AT17: =(O17-AG17)/C17 -> 0.068994889 | AU17: 0.31 | AV17: =(AK17+AL17)/(G17+L17-T17) -> 0.48031113 | AX17: =(AG17-AN17-AM17)/(G17+L17-T17+V17) -> 0.51271406 | AY17: =(AG17-AN17-AM17+AO17)/(G17+L17-T17+AO17) -> 0.48357488 | AZ17: =(AG17-AN17-AM17+AO17)/(G17+L17-T17+AO17-AC17) -> 0.48357488 | BA17: =(AG17-AN17)/Q17 -> 0.45508982 | BB17: =(AG17-AN17)/(Q17+R17) -> 0.43678161 | BC17: =D17 -> 15.7 | BD17: =BC17-(BE17+BF17+BG17) -> 0 | BE17: =AG17 -> 7.6 | BF17: 4.4 | BG17: 3.7 | BH17: =BG17/D17 -> 0.23566879 | BI17: 3.5 | BJ17: =BG17-BI17 -> 0.2 | BK17: =BJ17/D17 -> 0.012738854 | BO17: =BJ17/I17 -> 0.5
B18: 1942 | C18: 152.4 | D18: 20.8 | E18: =D18/C18 -> 0.13648294 | F18: =D18-(G18+I18) -> 0 | G18: =D18-I18 -> 20.4 | H18: =G18/C18 -> 0.13385827 | I18: 0.4 | J18: =I18/C18 -> 0.0026246719 | K18: =I18/D18 -> 0.019230769 | L18: =L19*I18/I19 -> 0.52307692 | M18: =L18/C18 -> 0.0034322633 | N18: =L18/D18 -> 0.025147929 | O18: =D18 -> 20.8 | P18: =O18-(Q18+R18+T18+U18+X18-V18) -> 0 | Q18: 23.4 | R18: 0.7 | S18: =R18/D18 -> 0.033653846 | T18: 0 | U18: -1.7 | V18: -0.2 | W18: =V18/D18 -> -0.0096153846 | X18: =O18-(Q18+R18+T18+U18-V18) -> -1.8 | AC18: 0 | AD18: =AC18/D18 -> 0 | AG18: 11.4 | AH18: =AG18/C18 -> 0.07480315 | AI18: =(AG18-AN18)/C18 -> 0.07480315 | AJ18: =AG18-(AK18+AL18+AM18+AN18) -> -0.1 | AK18: 11.1 | AL18: 0.4 | AM18: 0 | AN18: 0 | AO18: 0.1 | AP18: 7.138 | AT18: =(O18-AG18)/C18 -> 0.06167979 | AU18: 0.4 | AV18: =(AK18+AL18)/(G18+L18-T18) -> 0.54963235 | AX18: =(AG18-AN18-AM18)/(G18+L18-T18+V18) -> 0.55011136 | AY18: =(AG18-AN18-AM18+AO18)/(G18+L18-T18+AO18) -> 0.54701793 | AZ18: =(AG18-AN18-AM18+AO18)/(G18+L18-T18+AO18-AC18) -> 0.54701793 | BA18: =(AG18-AN18)/Q18 -> 0.48717949 | BB18: =(AG18-AN18)/(Q18+R18) -> 0.47302905 | BC18: =D18 -> 20.8 | BD18: =BC18-(BE18+BF18+BG18) -> 0 | BE18: =AG18 -> 11.4 | BF18: 4.3 | BG18: 5.1 | BH18: =BG18/D18 -> 0.24519231 | BI18: 5 | BJ18: =BG18-BI18 -> 0.1 | BK18: =BJ18/D18 -> 0.0048076923 | BO18: =BJ18/I18 -> 0.25
B19: 1943 | C19: 187.3 | D19: 24.9 | E19: =D19/C19 -> 0.1329418 | F19: =D19-(G19+I19) -> 0 | G19: =D19-I19 -> 24.5 | H19: =G19/C19 -> 0.13080619 | I19: 0.4 | J19: =I19/C19 -> 0.0021356113 | K19: =I19/D19 -> 0.016064257 | L19: =L20*I19/I20 -> 0.52307692 | M19: =L19/C19 -> 0.0027927225 | N19: =L19/D19 -> 0.021007105 | O19: =D19 -> 24.9 | P19: =O19-(Q19+R19+T19+U19+X19-V19) -> 0 | Q19: 28.1 | R19: 0.8 | S19: =R19/D19 -> 0.032128514 | T19: 0 | U19: -1 | V19: -0.2 | W19: =V19/D19 -> -0.0080321285 | X19: =O19-(Q19+R19+T19+U19-V19) -> -3.2 | AC19: 0 | AD19: =AC19/D19 -> 0 | AG19: 14.1 | AH19: =AG19/C19 -> 0.075280299 | AI19: =(AG19-AN19)/C19 -> 0.075280299 | AJ19: =AG19-(AK19+AL19+AM19+AN19) -> 0 | AK19: 13.6 | AL19: 0.5 | AM19: 0 | AN19: 0 | AO19: 0.1 | AP19: 12.1975 | AT19: =(O19-AG19)/C19 -> 0.057661506 | AU19: 0.4 | AV19: =(AK19+AL19)/(G19+L19-T19) -> 0.56347986 | AX19: =(AG19-AN19-AM19)/(G19+L19-T19+V19) -> 0.56801983 | AY19: =(AG19-AN19-AM19+AO19)/(G19+L19-T19+AO19) -> 0.56521739 | AZ19: =(AG19-AN19-AM19+AO19)/(G19+L19-T19+AO19-AC19) -> 0.56521739 | BA19: =(AG19-AN19)/Q19 -> 0.50177936 | BB19: =(AG19-AN19)/(Q19+R19) -> 0.48788927 | BC19: =D19 -> 24.9 | BD19: =BC19-(BE19+BF19+BG19) -> 0 | BE19: =AG19 -> 14.1 | BF19: 4.4 | BG19: 6.4 | BH19: =BG19/D19 -> 0.25702811 | BI19: 6.2 | BJ19: =BG19-BI19 -> 0.2 | BK19: =BJ19/D19 -> 0.0080321285 | BO19: =BJ19/I19 -> 0.5
B20: 1944 | C20: 201 | D20: 25 | E20: =D20/C20 -> 0.12437811 | F20: =D20-(G20+I20) -> 0 | G20: =D20-I20 -> 24.6 | H20: =G20/C20 -> 0.12238806 | I20: 0.4 | J20: =I20/C20 -> 0.0019900498 | K20: =I20/D20 -> 0.016 | L20: =L21*I20/I21 -> 0.52307692 | M20: =L20/C20 -> 0.0026023728 | N20: =L20/D20 -> 0.020923077 | O20: =D20 -> 25 | P20: =O20-(Q20+R20+T20+U20+X20-V20) -> 0 | Q20: 26.5 | R20: 0.5 | S20: =R20/D20 -> 0.02 | T20: 0.1 | U20: 0.2 | V20: 0 | W20: =V20/D20 -> 0 | X20: =O20-(Q20+R20+T20+U20-V20) -> -2.3 | AC20: 0 | AD20: =AC20/D20 -> 0 | AG20: 12.9 | AH20: =AG20/C20 -> 0.064179104 | AI20: =(AG20-AN20)/C20 -> 0.064179104 | AJ20: =AG20-(AK20+AL20+AM20+AN20) -> -0.1 | AK20: 12.5 | AL20: 0.5 | AM20: 0 | AN20: 0 | AO20: 0.1 | AP20: 15.413 | AT20: =(O20-AG20)/C20 -> 0.060199005 | AU20: 0.4 | AV20: =(AK20+AL20)/(G20+L20-T20) -> 0.51952044 | AX20: =(AG20-AN20-AM20)/(G20+L20-T20+V20) -> 0.51552413 | AY20: =(AG20-AN20-AM20+AO20)/(G20+L20-T20+AO20) -> 0.51745254 | AZ20: =(AG20-AN20-AM20+AO20)/(G20+L20-T20+AO20-AC20) -> 0.51745254 | BA20: =(AG20-AN20)/Q20 -> 0.48679245 | BB20: =(AG20-AN20)/(Q20+R20) -> 0.47777778 | BC20: =D20 -> 25 | BD20: =BC20-(BE20+BF20+BG20) -> 0.1 | BE20: =AG20 -> 12.9 | BF20: 4.6 | BG20: 7.4 | BH20: =BG20/D20 -> 0.296 | BI20: 7.3 | BJ20: =BG20-BI20 -> 0.1 | BK20: =BJ20/D20 -> 0.004 | BO20: =BJ20/I20 -> 0.25
B21: 1945 | C21: 201.4 | D21: 20.5 | E21: =D21/C21 -> 0.10178749 | F21: =D21-(G21+I21) -> 0 | G21: =D21-I21 -> 20.2 | H21: =G21/C21 -> 0.10029791 | I21: 0.3 | J21: =I21/C21 -> 0.001489573 | K21: =I21/D21 -> 0.014634146 | L21: =L22*I21/I22 -> 0.39230769 | M21: =L21/C21 -> 0.0019479031 | N21: =L21/D21 -> 0.019136961 | O21: =D21 -> 20.5 | P21: =O21-(Q21+R21+T21+U21+X21-V21) -> 0 | Q21: 21.3 | R21: 0.4 | S21: =R21/D21 -> 0.019512195 | T21: 0.1 | U21: 0 | V21: 0.6 | W21: =V21/D21 -> 0.029268293 | X21: =O21-(Q21+R21+T21+U21-V21) -> -0.7 | AC21: 0 | AD21: =AC21/D21 -> 0 | AG21: 10.7 | AH21: =AG21/C21 -> 0.053128103 | AI21: =(AG21-AN21)/C21 -> 0.053128103 | AJ21: =AG21-(AK21+AL21+AM21+AN21) -> 0 | AK21: 10.2 | AL21: 0.5 | AM21: 0 | AN21: 0 | AO21: 0.1 | AP21: 13.9355 | AT21: =(O21-AG21)/C21 -> 0.048659384 | AU21: 0.4 | AV21: =(AK21+AL21)/(G21+L21-T21) -> 0.52214715 | AX21: =(AG21-AN21-AM21)/(G21+L21-T21+V21) -> 0.50729395 | AY21: =(AG21-AN21-AM21+AO21)/(G21+L21-T21+AO21) -> 0.52446769 | AZ21: =(AG21-AN21-AM21+AO21)/(G21+L21-T21+AO21-AC21) -> 0.52446769 | BA21: =(AG21-AN21)/Q21 -> 0.50234742 | BB21: =(AG21-AN21)/(Q21+R21) -> 0.49308756 | BC21: =D21 -> 20.5 | BD21: =BC21-(BE21+BF21+BG21) -> 0 | BE21: =AG21 -> 10.7 | BF21: 4.6 | BG21: 5.2 | BH21: =BG21/D21 -> 0.25365854 | BI21: 5 | BJ21: =BG21-BI21 -> 0.2 | BK21: =BJ21/D21 -> 0.0097560976 | BO21: =BJ21/I21 -> 0.66666667
B22: 1946 | C22: 201.5 | D22: 18.2 | E22: =D22/C22 -> 0.090322581 | F22: =D22-(G22+I22) -> 0 | G22: =D22-I22 -> 17.5 | H22: =G22/C22 -> 0.086848635 | I22: 0.7 | J22: =I22/C22 -> 0.0034739454 | K22: =I22/D22 -> 0.038461538 | L22: =L23*I22/I23 -> 0.91538462 | M22: =L22/C22 -> 0.0045428517 | N22: =L22/D22 -> 0.050295858 | O22: =D22 -> 18.2 | P22: =O22-(Q22+R22+T22+U22+X22-V22) -> 0 | Q22: 25.4 | R22: 1.1 | S22: =R22/D22 -> 0.06043956 | T22: 0.1 | U22: -7.4 | V22: 1.1 | W22: =V22/D22 -> 0.06043956 | X22: =O22-(Q22+R22+T22+U22-V22) -> 0.1 | AC22: 0 | AD22: =AC22/D22 -> 0 | AG22: 9.1 | AH22: =AG22/C22 -> 0.04516129 | AI22: =(AG22-AN22)/C22 -> 0.04516129 | AJ22: =AG22-(AK22+AL22+AM22+AN22) -> 0 | AK22: 8.6 | AL22: 0.5 | AM22: 0 | AN22: 0 | AO22: 0.2 | AP22: 10.249 | AT22: =(O22-AG22)/C22 -> 0.04516129 | AU22: 0.38 | AV22: =(AK22+AL22)/(G22+L22-T22) -> 0.49685006 | AX22: =(AG22-AN22-AM22)/(G22+L22-T22+V22) -> 0.46870048 | AY22: =(AG22-AN22-AM22+AO22)/(G22+L22-T22+AO22) -> 0.502285 | AZ22: =(AG22-AN22-AM22+AO22)/(G22+L22-T22+AO22-AC22) -> 0.502285 | BA22: =(AG22-AN22)/Q22 -> 0.35826772 | BB22: =(AG22-AN22)/(Q22+R22) -> 0.34339623 | BC22: =D22 -> 18.2 | BD22: =BC22-(BE22+BF22+BG22) -> -0.1 | BE22: =AG22 -> 9.1 | BF22: 5.6 | BG22: 3.6 | BH22: =BG22/D22 -> 0.1978022 | BI22: 3.3 | BJ22: =BG22-BI22 -> 0.3 | BK22: =BJ22/D22 -> 0.016483516 | BO22: =BJ22/I22 -> 0.42857143
B23: 1947 | C23: 219 | D23: 24.2 | E23: =D23/C23 -> 0.11050228 | F23: =D23-(G23+I23) -> 0 | G23: =D23-I23 -> 23.2 | H23: =G23/C23 -> 0.10593607 | I23: 1 | J23: =I23/C23 -> 0.00456621 | K23: =I23/D23 -> 0.041322314 | L23: =L24*I23/I24 -> 1.3076923 | M23: =L23/C23 -> 0.0059711978 | N23: =L23/D23 -> 0.054036872 | O23: =D23 -> 24.2 | P23: =O23-(Q23+R23+T23+U23+X23-V23) -> 0 | Q23: 31.6 | R23: 1.1 | S23: =R23/D23 -> 0.045454545 | T23: 0.1 | U23: -8.5 | V23: 0.7 | W23: =V23/D23 -> 0.02892562 | X23: =O23-(Q23+R23+T23+U23-V23) -> 0.6 | AC23: 0 | AD23: =AC23/D23 -> 0 | AG23: 11.3 | AH23: =AG23/C23 -> 0.051598174 | AI23: =(AG23-AN23)/C23 -> 0.051141553 | AJ23: =AG23-(AK23+AL23+AM23+AN23) -> 0 | AK23: 10.6 | AL23: 0.6 | AM23: 0 | AN23: 0.1 | AO23: 0.2 | AP23: 9.1465 | AT23: =(O23-AG23)/C23 -> 0.05890411 | AU23: 0.38 | AV23: =(AK23+AL23)/(G23+L23-T23) -> 0.45887173 | AX23: =(AG23-AN23-AM23)/(G23+L23-T23+V23) -> 0.44607843 | AY23: =(AG23-AN23-AM23+AO23)/(G23+L23-T23+AO23) -> 0.46326977 | AZ23: =(AG23-AN23-AM23+AO23)/(G23+L23-T23+AO23-AC23) -> 0.46326977 | BA23: =(AG23-AN23)/Q23 -> 0.35443038 | BB23: =(AG23-AN23)/(Q23+R23) -> 0.34250765 | BC23: =D23 -> 24.2 | BD23: =BC23-(BE23+BF23+BG23) -> 0 | BE23: =AG23 -> 11.3 | BF23: 6.3 | BG23: 6.6 | BH23: =BG23/D23 -> 0.27272727 | BI23: 6.3 | BJ23: =BG23-BI23 -> 0.3 | BK23: =BJ23/D23 -> 0.012396694 | BO23: =BJ23/I23 -> 0.3
B24: 1948 | C24: 245.1 | D24: 31.4 | E24: =D24/C24 -> 0.12811098 | F24: =D24-(G24+I24) -> 0 | G24: =D24-I24 -> 30.1 | H24: =G24/C24 -> 0.12280702 | I24: 1.3 | J24: =I24/C24 -> 0.0053039576 | K24: =I24/D24 -> 0.041401274 | L24: 1.7 | M24: =L24/C24 -> 0.0069359445 | N24: =L24/D24 -> 0.054140127 | O24: =D24 -> 31.4 | P24: =O24-(Q24+R24+T24+U24+X24-V24) -> 0 | Q24: 34.6 | R24: 1.2 | S24: =R24/D24 -> 0.038216561 | T24: 0.2 | U24: -5.2 | V24: 0.7 | W24: =V24/D24 -> 0.022292994 | X24: =O24-(Q24+R24+T24+U24-V24) -> 1.3 | AC24: 0 | AD24: =AC24/D24 -> 0 | AG24: 12.4 | AH24: =AG24/C24 -> 0.050591595 | AI24: =(AG24-AN24)/C24 -> 0.049775602 | AJ24: =AG24-(AK24+AL24+AM24+AN24) -> 0 | AK24: 11.5 | AL24: 0.7 | AM24: 0 | AN24: 0.2 | AO24: 0.3 | AP24: 10.435 | AT24: =(O24-AG24)/C24 -> 0.07751938 | AU24: 0.38 | AV24: =(AK24+AL24)/(G24+L24-T24) -> 0.38607595 | AX24: =(AG24-AN24-AM24)/(G24+L24-T24+V24) -> 0.37770898 | AY24: =(AG24-AN24-AM24+AO24)/(G24+L24-T24+AO24) -> 0.39184953 | AZ24: =(AG24-AN24-AM24+AO24)/(G24+L24-T24+AO24-AC24) -> 0.39184953 | BA24: =(AG24-AN24)/Q24 -> 0.35260116 | BB24: =(AG24-AN24)/(Q24+R24) -> 0.34078212 | BC24: =D24 -> 31.4 | BD24: =BC24-(BE24+BF24+BG24) -> 0.1 | BE24: =AG24 -> 12.4 | BF24: 7 | BG24: 11.9 | BH24: =BG24/D24 -> 0.37898089 | BI24: 11.5 | BJ24: =BG24-BI24 -> 0.4 | BK24: =BJ24/D24 -> 0.012738854 | BO24: =BJ24/I24 -> 0.30769231 | BQ24: =L24 -> 1.7
B25: 1949 | C25: 240 | D25: 29.1 | E25: =D25/C25 -> 0.12125 | F25: =D25-(G25+I25) -> 0 | G25: =D25-I25 -> 28 | H25: =G25/C25 -> 0.11666667 | I25: 1.1 | J25: =I25/C25 -> 0.0045833333 | K25: =I25/D25 -> 0.037800687 | L25: 1.5 | M25: =L25/C25 -> 0.00625 | N25: =L25/D25 -> 0.051546392 | O25: =D25 -> 29.1 | P25: =O25-(Q25+R25+T25+U25+X25-V25) -> 0 | Q25: 28.4 | R25: 1.3 | S25: =R25/D25 -> 0.04467354 | T25: 0.2 | U25: -0.9 | V25: 0.6 | W25: =V25/D25 -> 0.020618557 | X25: =O25-(Q25+R25+T25+U25-V25) -> 0.7 | AC25: 0 | AD25: =AC25/D25 -> 0 | AG25: 10.2 | AH25: =AG25/C25 -> 0.0425 | AI25: =(AG25-AN25)/C25 -> 0.041666667 | AJ25: =AG25-(AK25+AL25+AM25+AN25) -> 0 | AK25: 9.4 | AL25: 0.6 | AM25: 0 | AN25: 0.2 | AO25: 0.3 | AP25: 10.8205 | AT25: =(O25-AG25)/C25 -> 0.07875 | AU25: 0.38 | AV25: =(AK25+AL25)/(G25+L25-T25) -> 0.34129693 | AX25: =(AG25-AN25-AM25)/(G25+L25-T25+V25) -> 0.33444816 | AY25: =(AG25-AN25-AM25+AO25)/(G25+L25-T25+AO25) -> 0.34797297 | AZ25: =(AG25-AN25-AM25+AO25)/(G25+L25-T25+AO25-AC25) -> 0.34797297 | BA25: =(AG25-AN25)/Q25 -> 0.35211268 | BB25: =(AG25-AN25)/(Q25+R25) -> 0.33670034 | BC25: =D25 -> 29.1 | BD25: =BC25-(BE25+BF25+BG25) -> 0.1 | BE25: =AG25 -> 10.2 | BF25: 7.2 | BG25: 11.6 | BH25: =BG25/D25 -> 0.39862543 | BI25: 11.3 | BJ25: =BG25-BI25 -> 0.3 | BK25: =BJ25/D25 -> 0.010309278 | BO25: =BJ25/I25 -> 0.27272727 | BQ25: =L25 -> 1.5
B26: 1950 | C26: 267 | D26: 36.1 | E26: =D26/C26 -> 0.13520599 | F26: =D26-(G26+I26) -> 0 | G26: =D26-I26 -> 34.8 | H26: =G26/C26 -> 0.13033708 | I26: 1.3 | J26: =I26/C26 -> 0.0048689139 | K26: =I26/D26 -> 0.03601108 | L26: 1.8 | M26: =L26/C26 -> 0.006741573 | N26: =L26/D26 -> 0.049861496 | O26: =D26 -> 36.1 | P26: =O26-(Q26+R26+T26+U26+X26-V26) -> 0 | Q26: 42.8 | R26: 1.2 | S26: =R26/D26 -> 0.033240997 | T26: 0.2 | U26: -7.8 | V26: 1 | W26: =V26/D26 -> 0.027700831 | X26: =O26-(Q26+R26+T26+U26-V26) -> 0.7 | AC26: 0 | AD26: =AC26/D26 -> 0 | AG26: 17.9 | AH26: =AG26/C26 -> 0.067041199 | AI26: =(AG26-AN26)/C26 -> 0.066292135 | AJ26: =AG26-(AK26+AL26+AM26+AN26) -> 0 | AK26: 16.9 | AL26: 0.8 | AM26: 0 | AN26: 0.2 | AO26: 0.5 | AP26: 12.275 | AT26: =(O26-AG26)/C26 -> 0.068164794 | AU26: 0.42 | AV26: =(AK26+AL26)/(G26+L26-T26) -> 0.48626374 | AX26: =(AG26-AN26-AM26)/(G26+L26-T26+V26) -> 0.47326203 | AY26: =(AG26-AN26-AM26+AO26)/(G26+L26-T26+AO26) -> 0.49322493 | AZ26: =(AG26-AN26-AM26+AO26)/(G26+L26-T26+AO26-AC26) -> 0.49322493 | BA26: =(AG26-AN26)/Q26 -> 0.4135514 | BB26: =(AG26-AN26)/(Q26+R26) -> 0.40227273 | BC26: =D26 -> 36.1 | BD26: =BC26-(BE26+BF26+BG26) -> 0.1 | BE26: =AG26 -> 17.9 | BF26: 8.8 | BG26: 9.3 | BH26: =BG26/D26 -> 0.25761773 | BI26: 9 | BJ26: =BG26-BI26 -> 0.3 | BK26: =BJ26/D26 -> 0.0083102493 | BO26: =BJ26/I26 -> 0.23076923 | BQ26: =L26 -> 1.8
B27: 1951 | C27: 308 | D27: 41.2 | E27: =D27/C27 -> 0.13376623 | F27: =D27-(G27+I27) -> 0 | G27: =D27-I27 -> 39.5 | H27: =G27/C27 -> 0.12824675 | I27: 1.7 | J27: =I27/C27 -> 0.0055194805 | K27: =I27/D27 -> 0.041262136 | L27: 2.3 | M27: =L27/C27 -> 0.0074675325 | N27: =L27/D27 -> 0.055825243 | O27: =D27 -> 41.2 | P27: =O27-(Q27+R27+T27+U27+X27-V27) -> 0 | Q27: 43.8 | R27: 1.3 | S27: =R27/D27 -> 0.031553398 | T27: 0.3 | U27: -4.2 | V27: 1.1 | W27: =V27/D27 -> 0.026699029 | X27: =O27-(Q27+R27+T27+U27-V27) -> 1.1 | AC27: 0 | AD27: =AC27/D27 -> 0 | AG27: 22.6 | AH27: =AG27/C27 -> 0.073376623 | AI27: =(AG27-AN27)/C27 -> 0.072402597 | AJ27: =AG27-(AK27+AL27+AM27+AN27) -> -0.1 | AK27: 21.5 | AL27: 0.9 | AM27: 0 | AN27: 0.3 | AO27: 0.6 | AP27: 17.6635 | AT27: =(O27-AG27)/C27 -> 0.06038961 | AU27: 0.51 | AV27: =(AK27+AL27)/(G27+L27-T27) -> 0.53975904 | AX27: =(AG27-AN27-AM27)/(G27+L27-T27+V27) -> 0.52347418 | AY27: =(AG27-AN27-AM27+AO27)/(G27+L27-T27+AO27) -> 0.54394299 | AZ27: =(AG27-AN27-AM27+AO27)/(G27+L27-T27+AO27-AC27) -> 0.54394299 | BA27: =(AG27-AN27)/Q27 -> 0.50913242 | BB27: =(AG27-AN27)/(Q27+R27) -> 0.49445676 | BC27: =D27 -> 41.2 | BD27: =BC27-(BE27+BF27+BG27) -> -0.1 | BE27: =AG27 -> 22.6 | BF27: 8.6 | BG27: 10.1 | BH27: =BG27/D27 -> 0.24514563 | BI27: 9.5 | BJ27: =BG27-BI27 -> 0.6 | BK27: =BJ27/D27 -> 0.014563107 | BO27: =BJ27/I27 -> 0.35294118 | BQ27: =L27 -> 2.3
B28: 1952 | C28: 326.5 | D28: 39.7 | E28: =D28/C28 -> 0.12159265 | F28: =D28-(G28+I28) -> 0 | G28: =D28-I28 -> 37.8 | H28: =G28/C28 -> 0.11577335 | I28: 1.9 | J28: =I28/C28 -> 0.0058192956 | K28: =I28/D28 -> 0.047858942 | L28: 2.3 | M28: =L28/C28 -> 0.0070444104 | N28: =L28/D28 -> 0.057934509 | O28: =D28 -> 39.7 | P28: =O28-(Q28+R28+T28+U28+X28-V28) -> 0 | Q28: 38.7 | R28: 1.4 | S28: =R28/D28 -> 0.035264484 | T28: 0.3 | U28: -1.6 | V28: 1.1 | W28: =V28/D28 -> 0.027707809 | X28: =O28-(Q28+R28+T28+U28-V28) -> 2 | AC28: 0 | AD28: =AC28/D28 -> 0 | AG28: 19.4 | AH28: =AG28/C28 -> 0.05941807 | AI28: =(AG28-AN28)/C28 -> 0.058499234 | AJ28: =AG28-(AK28+AL28+AM28+AN28) -> 0.1 | AK28: 18.2 | AL28: 0.8 | AM28: 0 | AN28: 0.3 | AO28: 0.6 | AP28: 21.232 | AT28: =(O28-AG28)/C28 -> 0.062174579 | AU28: 0.52 | AV28: =(AK28+AL28)/(G28+L28-T28) -> 0.47738693 | AX28: =(AG28-AN28-AM28)/(G28+L28-T28+V28) -> 0.46699267 | AY28: =(AG28-AN28-AM28+AO28)/(G28+L28-T28+AO28) -> 0.48762376 | AZ28: =(AG28-AN28-AM28+AO28)/(G28+L28-T28+AO28-AC28) -> 0.48762376 | BA28: =(AG28-AN28)/Q28 -> 0.49354005 | BB28: =(AG28-AN28)/(Q28+R28) -> 0.47630923 | BC28: =D28 -> 39.7 | BD28: =BC28-(BE28+BF28+BG28) -> 0 | BE28: =AG28 -> 19.4 | BF28: 8.6 | BG28: 11.7 | BH28: =BG28/D28 -> 0.29471033 | BI28: 10.9 | BJ28: =BG28-BI28 -> 0.8 | BK28: =BJ28/D28 -> 0.020151134 | BO28: =BJ28/I28 -> 0.42105263 | BQ28: =L28 -> 2.3
B29: 1953 | C29: 344.4 | D29: 40.3 | E29: =D29/C29 -> 0.1170151 | F29: =D29-(G29+I29) -> 0 | G29: =D29-I29 -> 38.5 | H29: =G29/C29 -> 0.11178862 | I29: 1.8 | J29: =I29/C29 -> 0.0052264808 | K29: =I29/D29 -> 0.044665012 | L29: 2.3 | M29: =L29/C29 -> 0.0066782811 | N29: =L29/D29 -> 0.05707196 | O29: =D29 -> 40.3 | P29: =O29-(Q29+R29+T29+U29+X29-V29) -> 0 | Q29: 39.8 | R29: 1.5 | S29: =R29/D29 -> 0.037220844 | T29: 0.4 | U29: -2.9 | V29: 0.8 | W29: =V29/D29 -> 0.019851117 | X29: =O29-(Q29+R29+T29+U29-V29) -> 2.3 | AC29: 0 | AD29: =AC29/D29 -> 0 | AG29: 20.3 | AH29: =AG29/C29 -> 0.058943089 | AI29: =(AG29-AN29)/C29 -> 0.058072009 | AJ29: =AG29-(AK29+AL29+AM29+AN29) -> 0 | AK29: 19.2 | AL29: 0.8 | AM29: 0 | AN29: 0.3 | AO29: 0.6 | AP29: 21.1695 | AT29: =(O29-AG29)/C29 -> 0.058072009 | AU29: 0.52 | AV29: =(AK29+AL29)/(G29+L29-T29) -> 0.4950495 | AX29: =(AG29-AN29-AM29)/(G29+L29-T29+V29) -> 0.48543689 | AY29: =(AG29-AN29-AM29+AO29)/(G29+L29-T29+AO29) -> 0.50243902 | AZ29: =(AG29-AN29-AM29+AO29)/(G29+L29-T29+AO29-AC29) -> 0.50243902 | BA29: =(AG29-AN29)/Q29 -> 0.50251256 | BB29: =(AG29-AN29)/(Q29+R29) -> 0.4842615 | BC29: =D29 -> 40.3 | BD29: =BC29-(BE29+BF29+BG29) -> 0 | BE29: =AG29 -> 20.3 | BF29: 8.9 | BG29: 11.1 | BH29: =BG29/D29 -> 0.27543424 | BI29: 10.5 | BJ29: =BG29-BI29 -> 0.6 | BK29: =BJ29/D29 -> 0.014888337 | BO29: =BJ29/I29 -> 0.33333333 | BQ29: =L29 -> 2.3
B30: 1954 | C30: 344.4 | D30: 39.5 | E30: =D30/C30 -> 0.11469222 | F30: =D30-(G30+I30) -> 0 | G30: =D30-I30 -> 37.5 | H30: =G30/C30 -> 0.10888502 | I30: 2 | J30: =I30/C30 -> 0.0058072009 | K30: =I30/D30 -> 0.050632911 | L30: 2.4 | M30: =L30/C30 -> 0.0069686411 | N30: =L30/D30 -> 0.060759494 | O30: =D30 -> 39.5 | P30: =O30-(Q30+R30+T30+U30+X30-V30) -> 0 | Q30: 36.7 | R30: 1.7 | S30: =R30/D30 -> 0.043037975 | T30: 0.3 | U30: -1.3 | V30: 1.8 | W30: =V30/D30 -> 0.04556962 | X30: =O30-(Q30+R30+T30+U30-V30) -> 3.9 | AC30: 0 | AD30: =AC30/D30 -> 0 | AG30: 17.6 | AH30: =AG30/C30 -> 0.051103368 | AI30: =(AG30-AN30)/C30 -> 0.050232288 | AJ30: =AG30-(AK30+AL30+AM30+AN30) -> -0.1 | AK30: 16.6 | AL30: 0.8 | AM30: 0 | AN30: 0.3 | AO30: 0.7 | AP30: 19.481 | AT30: =(O30-AG30)/C30 -> 0.06358885 | AU30: 0.52 | AV30: =(AK30+AL30)/(G30+L30-T30) -> 0.43939394 | AX30: =(AG30-AN30-AM30)/(G30+L30-T30+V30) -> 0.4178744 | AY30: =(AG30-AN30-AM30+AO30)/(G30+L30-T30+AO30) -> 0.44665012 | AZ30: =(AG30-AN30-AM30+AO30)/(G30+L30-T30+AO30-AC30) -> 0.44665012 | BA30: =(AG30-AN30)/Q30 -> 0.47138965 | BB30: =(AG30-AN30)/(Q30+R30) -> 0.45052083 | BC30: =D30 -> 39.5 | BD30: =BC30-(BE30+BF30+BG30) -> 0 | BE30: =AG30 -> 17.6 | BF30: 9.3 | BG30: 12.6 | BH30: =BG30/D30 -> 0.31898734 | BI30: 12 | BJ30: =BG30-BI30 -> 0.6 | BK30: =BJ30/D30 -> 0.015189873 | BO30: =BJ30/I30 -> 0.3 | BQ30: =L30 -> 2.4
B31: 1955 | C31: 377.6 | D31: 50.2 | E31: =D31/C31 -> 0.13294492 | F31: =D31-(G31+I31) -> 0 | G31: =D31-I31 -> 47.8 | H31: =G31/C31 -> 0.12658898 | I31: 2.4 | J31: =I31/C31 -> 0.0063559322 | K31: =I31/D31 -> 0.047808765 | L31: 2.9 | M31: =L31/C31 -> 0.0076800847 | N31: =L31/D31 -> 0.057768924 | O31: =D31 -> 50.2 | P31: =O31-(Q31+R31+T31+U31+X31-V31) -> 0 | Q31: 47.9 | R31: 2 | S31: =R31/D31 -> 0.039840637 | T31: 0.3 | U31: -1.2 | V31: 1.7 | W31: =V31/D31 -> 0.033864542 | X31: =O31-(Q31+R31+T31+U31-V31) -> 2.9 | AC31: 0 | AD31: =AC31/D31 -> 0 | AG31: 22 | AH31: =AG31/C31 -> 0.058262712 | AI31: =(AG31-AN31)/C31 -> 0.05746822 | AJ31: =AG31-(AK31+AL31+AM31+AN31) -> 0 | AK31: 20.7 | AL31: 1 | AM31: 0 | AN31: 0.3 | AO31: 1 | AP31: 19.3705 | AT31: =(O31-AG31)/C31 -> 0.074682203 | AU31: 0.52 | AV31: =(AK31+AL31)/(G31+L31-T31) -> 0.43055556 | AX31: =(AG31-AN31-AM31)/(G31+L31-T31+V31) -> 0.41650672 | AY31: =(AG31-AN31-AM31+AO31)/(G31+L31-T31+AO31) -> 0.44163424 | AZ31: =(AG31-AN31-AM31+AO31)/(G31+L31-T31+AO31-AC31) -> 0.44163424 | BA31: =(AG31-AN31)/Q31 -> 0.45302714 | BB31: =(AG31-AN31)/(Q31+R31) -> 0.43486974 | BC31: =D31 -> 50.2 | BD31: =BC31-(BE31+BF31+BG31) -> 0.1 | BE31: =AG31 -> 22 | BF31: 10.5 | BG31: 17.6 | BH31: =BG31/D31 -> 0.35059761 | BI31: 16.9 | BJ31: =BG31-BI31 -> 0.7 | BK31: =BJ31/D31 -> 0.013944223 | BO31: =BJ31/I31 -> 0.29166667 | BQ31: =L31 -> 2.9
B32: 1956 | C32: 400.9 | D32: 49.6 | E32: =D32/C32 -> 0.12372163 | F32: =D32-(G32+I32) -> 0 | G32: =D32-I32 -> 46.8 | H32: =G32/C32 -> 0.11673734 | I32: 2.8 | J32: =I32/C32 -> 0.0069842854 | K32: =I32/D32 -> 0.056451613 | L32: 3.4 | M32: =L32/C32 -> 0.0084809179 | N32: =L32/D32 -> 0.068548387 | O32: =D32 -> 49.6 | P32: =O32-(Q32+R32+T32+U32+X32-V32) -> 0 | Q32: 47.4 | R32: 2.3 | S32: =R32/D32 -> 0.046370968 | T32: 0.5 | U32: -3 | V32: 1.7 | W32: =V32/D32 -> 0.034274194 | X32: =O32-(Q32+R32+T32+U32-V32) -> 4.1 | AC32: 0 | AD32: =AC32/D32 -> 0 | AG32: 22 | AH32: =AG32/C32 -> 0.054876528 | AI32: =(AG32-AN32)/C32 -> 0.053878773 | AJ32: =AG32-(AK32+AL32+AM32+AN32) -> 0 | AK32: 20.6 | AL32: 1 | AM32: 0 | AN32: 0.4 | AO32: 1 | AP32: 21.0235 | AT32: =(O32-AG32)/C32 -> 0.068845099 | AU32: 0.52 | AV32: =(AK32+AL32)/(G32+L32-T32) -> 0.43460765 | AX32: =(AG32-AN32-AM32)/(G32+L32-T32+V32) -> 0.42023346 | AY32: =(AG32-AN32-AM32+AO32)/(G32+L32-T32+AO32) -> 0.44575937 | AZ32: =(AG32-AN32-AM32+AO32)/(G32+L32-T32+AO32-AC32) -> 0.44575937 | BA32: =(AG32-AN32)/Q32 -> 0.4556962 | BB32: =(AG32-AN32)/(Q32+R32) -> 0.43460765 | BC32: =D32 -> 49.6 | BD32: =BC32-(BE32+BF32+BG32) -> -0.1 | BE32: =AG32 -> 22 | BF32: 11.3 | BG32: 16.4 | BH32: =BG32/D32 -> 0.33064516 | BI32: 15.4 | BJ32: =BG32-BI32 -> 1 | BK32: =BJ32/D32 -> 0.02016129 | BO32: =BJ32/I32 -> 0.35714286 | BQ32: =L32 -> 3.4
B33: 1957 | C33: 419.4 | D33: 49.1 | E33: =D33/C33 -> 0.11707201 | F33: =D33-(G33+I33) -> 0 | G33: =D33-I33 -> 46 | H33: =G33/C33 -> 0.1096805 | I33: 3.1 | J33: =I33/C33 -> 0.0073915117 | K33: =I33/D33 -> 0.063136456 | L33: 3.7 | M33: =L33/C33 -> 0.0088221268 | N33: =L33/D33 -> 0.075356415 | O33: =D33 -> 49.1 | P33: =O33-(Q33+R33+T33+U33+X33-V33) -> 0 | Q33: 45.1 | R33: 2.9 | S33: =R33/D33 -> 0.059063136 | T33: 0.6 | U33: -2 | V33: 1.6 | W33: =V33/D33 -> 0.032586558 | X33: =O33-(Q33+R33+T33+U33-V33) -> 4.1 | AC33: 0 | AD33: =AC33/D33 -> 0 | AG33: 21.4 | AH33: =AG33/C33 -> 0.051025274 | AI33: =(AG33-AN33)/C33 -> 0.049833095 | AJ33: =AG33-(AK33+AL33+AM33+AN33) -> 0.1 | AK33: 19.8 | AL33: 1 | AM33: 0 | AN33: 0.5 | AO33: 1.1 | AP33: 20.6205 | AT33: =(O33-AG33)/C33 -> 0.066046733 | AU33: 0.52 | AV33: =(AK33+AL33)/(G33+L33-T33) -> 0.42362525 | AX33: =(AG33-AN33-AM33)/(G33+L33-T33+V33) -> 0.4122288 | AY33: =(AG33-AN33-AM33+AO33)/(G33+L33-T33+AO33) -> 0.43824701 | AZ33: =(AG33-AN33-AM33+AO33)/(G33+L33-T33+AO33-AC33) -> 0.43824701 | BA33: =(AG33-AN33)/Q33 -> 0.46341463 | BB33: =(AG33-AN33)/(Q33+R33) -> 0.43541667 | BC33: =D33 -> 49.1 | BD33: =BC33-(BE33+BF33+BG33) -> 0 | BE33: =AG33 -> 21.4 | BF33: 11.7 | BG33: 16 | BH33: =BG33/D33 -> 0.32586558 | BI33: 14.8 | BJ33: =BG33-BI33 -> 1.2 | BK33: =BJ33/D33 -> 0.024439919 | BO33: =BJ33/I33 -> 0.38709677 | BQ33: =L33 -> 3.7
B34: 1958 | C34: 421.6 | D34: 43.9 | E34: =D34/C34 -> 0.10412713 | F34: =D34-(G34+I34) -> 0 | G34: =D34-I34 -> 41.4 | H34: =G34/C34 -> 0.098197343 | I34: 2.5 | J34: =I34/C34 -> 0.0059297913 | K34: =I34/D34 -> 0.056947608 | L34: 3 | M34: =L34/C34 -> 0.0071157495 | N34: =L34/D34 -> 0.06833713 | O34: =D34 -> 43.9 | P34: =O34-(Q34+R34+T34+U34+X34-V34) -> 0 | Q34: 39.2 | R34: 3 | S34: =R34/D34 -> 0.06833713 | T34: 0.6 | U34: -1.2 | V34: 2.8 | W34: =V34/D34 -> 0.063781321 | X34: =O34-(Q34+R34+T34+U34-V34) -> 5.1 | AC34: 0 | AD34: =AC34/D34 -> 0 | AG34: 19 | AH34: =AG34/C34 -> 0.045066414 | AI34: =(AG34-AN34)/C34 -> 0.043880455 | AJ34: =AG34-(AK34+AL34+AM34+AN34) -> 0.1 | AK34: 17.4 | AL34: 1 | AM34: 0 | AN34: 0.5 | AO34: 1.1 | AP34: 18.6915 | AT34: =(O34-AG34)/C34 -> 0.059060721 | AU34: 0.52 | AV34: =(AK34+AL34)/(G34+L34-T34) -> 0.42009132 | AW34: =(AK34+AL34)/(G34+L34-T34-AE34) -> 0.42009132 | AX34: =(AG34-AN34-AM34)/(G34+L34-T34+V34) -> 0.39699571 | AY34: =(AG34-AN34-AM34+AO34)/(G34+L34-T34+AO34) -> 0.43652561 | AZ34: =(AG34-AN34-AM34+AO34)/(G34+L34-T34+AO34-AC34) -> 0.43652561 | BA34: =(AG34-AN34)/Q34 -> 0.47193878 | BB34: =(AG34-AN34)/(Q34+R34) -> 0.43838863 | BC34: =D34 -> 43.9 | BD34: =BC34-(BE34+BF34+BG34) -> 0 | BE34: =AG34 -> 19 | BF34: 11.6 | BG34: 13.3 | BH34: =BG34/D34 -> 0.30296128 | BI34: 12.5 | BJ34: =BG34-BI34 -> 0.8 | BK34: =BJ34/D34 -> 0.018223235 | BO34: =BJ34/I34 -> 0.32 | BQ34: =L34 -> 3
B35: 1959 | C35: 459.6 | D35: 55.5 | E35: =D35/C35 -> 0.12075718 | F35: =D35-(G35+I35) -> 0 | G35: =D35-I35 -> 52.8 | H35: =G35/C35 -> 0.11488251 | I35: 2.7 | J35: =I35/C35 -> 0.0058746736 | K35: =I35/D35 -> 0.048648649 | L35: 3.4 | M35: =L35/C35 -> 0.0073977372 | N35: =L35/D35 -> 0.061261261 | O35: =D35 -> 55.5 | P35: =O35-(Q35+R35+T35+U35+X35-V35) -> 0 | Q35: 47.7 | R35: 2.9 | S35: =R35/D35 -> 0.052252252 | T35: 0.7 | U35: -0.5 | V35: 1.8 | W35: =V35/D35 -> 0.032432432 | X35: =O35-(Q35+R35+T35+U35-V35) -> 6.5 | AC35: 0 | AD35: =AC35/D35 -> 0 | AG35: 23.7 | AH35: =AG35/C35 -> 0.05156658 | AI35: =(AG35-AN35)/C35 -> 0.049608355 | AJ35: =AG35-(AK35+AL35+AM35+AN35) -> 0 | AK35: 21.5 | AL35: 1.2 | AM35: 0.1 | AN35: 0.9 | AO35: 1.2 | AP35: 19.4015 | AT35: =(O35-AG35)/C35 -> 0.069190601 | AU35: 0.52 | AV35: =(AK35+AL35)/(G35+L35-T35) -> 0.40900901 | AW35: =(AK35+AL35)/(G35+L35-T35-AE35) -> 0.40900901 | AX35: =(AG35-AN35-AM35)/(G35+L35-T35+V35) -> 0.39616056 | AY35: =(AG35-AN35-AM35+AO35)/(G35+L35-T35+AO35) -> 0.42151675 | AZ35: =(AG35-AN35-AM35+AO35)/(G35+L35-T35+AO35-AC35) -> 0.42151675 | BA35: =(AG35-AN35)/Q35 -> 0.47798742 | BB35: =(AG35-AN35)/(Q35+R35) -> 0.45059289 | BC35: =D35 -> 55.5 | BD35: =BC35-(BE35+BF35+BG35) -> 0 | BE35: =AG35 -> 23.7 | BF35: 12.6 | BG35: 19.2 | BH35: =BG35/D35 -> 0.34594595 | BI35: 18.4 | BJ35: =BG35-BI35 -> 0.8 | BK35: =BJ35/D35 -> 0.014414414 | BO35: =BJ35/I35 -> 0.2962963 | BQ35: =L35 -> 3.4
B36: 1960 | C36: 479.9 | D36: 54.7 | E36: =D36/C36 -> 0.11398208 | F36: =D36-(G36+I36) -> 0 | G36: =D36-I36 -> 51.6 | H36: =G36/C36 -> 0.1075224 | I36: 3.1 | J36: =I36/C36 -> 0.0064596791 | K36: =I36/D36 -> 0.056672761 | L36: 3.8 | M36: =L36/C36 -> 0.0079183163 | N36: =L36/D36 -> 0.069469835 | O36: =D36 -> 54.7 | P36: =O36-(Q36+R36+T36+U36+X36-V36) -> 0 | Q36: 44.5 | R36: 3 | S36: =R36/D36 -> 0.054844607 | T36: 0.9 | U36: 0.8 | V36: 2.6 | W36: =V36/D36 -> 0.047531993 | X36: =O36-(Q36+R36+T36+U36-V36) -> 8.1 | AC36: 0 | AD36: =AC36/D36 -> 0 | AG36: 22.8 | AH36: =AG36/C36 -> 0.047509898 | AI36: =(AG36-AN36)/C36 -> 0.045634507 | AJ36: =AG36-(AK36+AL36+AM36+AN36) -> 0 | AK36: 20.6 | AL36: 1.2 | AM36: 0.1 | AN36: 0.9 | AO36: 1.2 | AP36: 21.224 | AT36: =(O36-AG36)/C36 -> 0.066472182 | AU36: 0.52 | AV36: =(AK36+AL36)/(G36+L36-T36) -> 0.4 | AW36: =(AK36+AL36)/(G36+L36-T36-AE36) -> 0.4 | AX36: =(AG36-AN36-AM36)/(G36+L36-T36+V36) -> 0.38178634 | AY36: =(AG36-AN36-AM36+AO36)/(G36+L36-T36+AO36) -> 0.41292639 | AZ36: =(AG36-AN36-AM36+AO36)/(G36+L36-T36+AO36-AC36) -> 0.41292639 | BA36: =(AG36-AN36)/Q36 -> 0.49213483 | BB36: =(AG36-AN36)/(Q36+R36) -> 0.46105263 | BC36: =D36 -> 54.7 | BD36: =BC36-(BE36+BF36+BG36) -> 0 | BE36: =AG36 -> 22.8 | BF36: 13.4 | BG36: 18.5 | BH36: =BG36/D36 -> 0.33820841 | BI36: 17.4 | BJ36: =BG36-BI36 -> 1.1 | BK36: =BJ36/D36 -> 0.020109689 | BO36: =BJ36/I36 -> 0.35483871 | BQ36: =L36 -> 3.8
B37: 1961 | C37: 497.2 | D37: 55.9 | E37: =D37/C37 -> 0.11242961 | F37: =D37-(G37+I37) -> 0 | G37: =D37-I37 -> 52.6 | H37: =G37/C37 -> 0.10579244 | I37: 3.3 | J37: =I37/C37 -> 0.0066371681 | K37: =I37/D37 -> 0.059033989 | L37: 4.1 | M37: =L37/C37 -> 0.0082461786 | N37: =L37/D37 -> 0.073345259 | O37: =D37 -> 55.9 | P37: =O37-(Q37+R37+T37+U37+X37-V37) -> 0 | Q37: 47 | R37: 3.1 | S37: =R37/D37 -> 0.055456172 | T37: 0.8 | U37: 2.1 | V37: 4 | W37: =V37/D37 -> 0.071556351 | X37: =O37-(Q37+R37+T37+U37-V37) -> 6.9 | AC37: 0 | AD37: =AC37/D37 -> 0 | AG37: 22.9 | AH37: =AG37/C37 -> 0.046057924 | AI37: =(AG37-AN37)/C37 -> 0.04465004 | AJ37: =AG37-(AK37+AL37+AM37+AN37) -> 0 | AK37: 20.8 | AL37: 1.3 | AM37: 0.1 | AN37: 0.7 | AO37: 1.5 | AP37: 20.7385 | AT37: =(O37-AG37)/C37 -> 0.066371681 | AU37: 0.52 | AV37: =(AK37+AL37)/(G37+L37-T37) -> 0.39534884 | AW37: =(AK37+AL37)/(G37+L37-T37-AE37) -> 0.39534884 | AX37: =(AG37-AN37-AM37)/(G37+L37-T37+V37) -> 0.36894825 | AY37: =(AG37-AN37-AM37+AO37)/(G37+L37-T37+AO37) -> 0.41114983 | AZ37: =(AG37-AN37-AM37+AO37)/(G37+L37-T37+AO37-AC37) -> 0.41114983 | BA37: =(AG37-AN37)/Q37 -> 0.47234043 | BB37: =(AG37-AN37)/(Q37+R37) -> 0.44311377 | BC37: =D37 -> 55.9 | BD37: =BC37-(BE37+BF37+BG37) -> -0.1 | BE37: =AG37 -> 22.9 | BF37: 13.9 | BG37: 19.2 | BH37: =BG37/D37 -> 0.34347048 | BI37: 18.2 | BJ37: =BG37-BI37 -> 1 | BK37: =BJ37/D37 -> 0.017889088 | BO37: =BJ37/I37 -> 0.3030303 | BQ37: =L37 -> 4.1
B38: 1962 | C38: 535.2 | D38: 64 | E38: =D38/C38 -> 0.11958146 | F38: =D38-(G38+I38) -> 0 | G38: =D38-I38 -> 60.2 | H38: =G38/C38 -> 0.11248132 | I38: 3.8 | J38: =I38/C38 -> 0.0071001495 | K38: =I38/D38 -> 0.059375 | L38: 4.5 | M38: =L38/C38 -> 0.0084080717 | N38: =L38/D38 -> 0.0703125 | O38: =D38 -> 64 | P38: =O38-(Q38+R38+T38+U38+X38-V38) -> 0 | Q38: 50.8 | R38: 3.6 | S38: =R38/D38 -> 0.05625 | T38: 0.9 | U38: 4.8 | V38: 3.4 | W38: =V38/D38 -> 0.053125 | X38: =O38-(Q38+R38+T38+U38-V38) -> 7.3 | AC38: 0 | AD38: =AC38/D38 -> 0 | AG38: 24.1 | AH38: =AG38/C38 -> 0.045029895 | AI38: =(AG38-AN38)/C38 -> 0.043535127 | AJ38: =AG38-(AK38+AL38+AM38+AN38) -> 0.1 | AK38: 21.6 | AL38: 1.5 | AM38: 0.1 | AN38: 0.8 | AO38: 1.6 | AP38: 21.051 | AT38: =(O38-AG38)/C38 -> 0.07455157 | AU38: 0.52 | AV38: =(AK38+AL38)/(G38+L38-T38) -> 0.36206897 | AW38: =(AK38+AL38)/(G38+L38-T38-AE38) -> 0.36206897 | AX38: =(AG38-AN38-AM38)/(G38+L38-T38+V38) -> 0.3452381 | AY38: =(AG38-AN38-AM38+AO38)/(G38+L38-T38+AO38) -> 0.37920489 | AZ38: =(AG38-AN38-AM38+AO38)/(G38+L38-T38+AO38-AC38) -> 0.37920489 | BA38: =(AG38-AN38)/Q38 -> 0.45866142 | BB38: =(AG38-AN38)/(Q38+R38) -> 0.42830882 | BC38: =D38 -> 64 | BD38: =BC38-(BE38+BF38+BG38) -> 0 | BE38: =AG38 -> 24.1 | BF38: 15 | BG38: 24.9 | BH38: =BG38/D38 -> 0.3890625 | BI38: 23.8 | BJ38: =BG38-BI38 -> 1.1 | BK38: =BJ38/D38 -> 0.0171875 | BO38: =BJ38/I38 -> 0.28947368 | BQ38: =L38 -> 4.5
B39: 1963 | C39: 566.6 | D39: 70.5 | E39: =D39/C39 -> 0.1244264 | F39: =D39-(G39+I39) -> 0 | G39: =D39-I39 -> 66.4 | H39: =G39/C39 -> 0.11719026 | I39: 4.1 | J39: =I39/C39 -> 0.0072361454 | K39: =I39/D39 -> 0.058156028 | L39: 4.8 | M39: =L39/C39 -> 0.0084715849 | N39: =L39/D39 -> 0.068085106 | O39: =D39 -> 70.5 | P39: =O39-(Q39+R39+T39+U39+X39-V39) -> 0 | Q39: 55.7 | R39: 4.2 | S39: =R39/D39 -> 0.059574468 | T39: 1 | U39: 6.1 | V39: 3.6 | W39: =V39/D39 -> 0.05106383 | X39: =O39-(Q39+R39+T39+U39-V39) -> 7.1 | AC39: 0 | AD39: =AC39/D39 -> 0 | AG39: 26.4 | AH39: =AG39/C39 -> 0.046593717 | AI39: =(AG39-AN39)/C39 -> 0.045005295 | AJ39: =AG39-(AK39+AL39+AM39+AN39) -> 0 | AK39: 23.7 | AL39: 1.7 | AM39: 0.1 | AN39: 0.9 | AO39: 1.9 | AP39: 22.536 | AT39: =(O39-AG39)/C39 -> 0.077832686 | AU39: 0.52 | AV39: =(AK39+AL39)/(G39+L39-T39) -> 0.36182336 | AW39: =(AK39+AL39)/(G39+L39-T39-AE39) -> 0.36182336 | AX39: =(AG39-AN39-AM39)/(G39+L39-T39+V39) -> 0.34417344 | AY39: =(AG39-AN39-AM39+AO39)/(G39+L39-T39+AO39) -> 0.37864078 | AZ39: =(AG39-AN39-AM39+AO39)/(G39+L39-T39+AO39-AC39) -> 0.37864078 | BA39: =(AG39-AN39)/Q39 -> 0.45780969 | BB39: =(AG39-AN39)/(Q39+R39) -> 0.42570952 | BC39: =D39 -> 70.5 | BD39: =BC39-(BE39+BF39+BG39) -> 0 | BE39: =AG39 -> 26.4 | BF39: 16.2 | BG39: 27.9 | BH39: =BG39/D39 -> 0.39574468 | BI39: 26.5 | BJ39: =BG39-BI39 -> 1.4 | BK39: =BJ39/D39 -> 0.019858156 | BO39: =BJ39/I39 -> 0.34146341 | BQ39: =L39 -> 4.8
B40: 1964 | C40: 608.3 | D40: 77.7 | E40: =D40/C40 -> 0.12773303 | F40: =D40-(G40+I40) -> 0 | G40: =D40-I40 -> 73.2 | H40: =G40/C40 -> 0.12033536 | I40: 4.5 | J40: =I40/C40 -> 0.0073976656 | K40: =I40/D40 -> 0.057915058 | L40: 5.4 | M40: =L40/C40 -> 0.0088771988 | N40: =L40/D40 -> 0.069498069 | O40: =D40 -> 77.7 | P40: =O40-(Q40+R40+T40+U40+X40-V40) -> 0 | Q40: 63.1 | R40: 3.8 | S40: =R40/D40 -> 0.048906049 | T40: 1.1 | U40: 6.3 | V40: 3.9 | W40: =V40/D40 -> 0.05019305 | X40: =O40-(Q40+R40+T40+U40-V40) -> 7.3 | AC40: 0 | AD40: =AC40/D40 -> 0 | AF40: 0 | AG40: 28.2 | AH40: =AG40/C40 -> 0.046358705 | AI40: =(AG40-AN40)/C40 -> 0.043728423 | AJ40: =AG40-(AK40+AL40+AM40+AN40) -> 0 | AK40: 24.6 | AL40: 1.8 | AM40: 0.2 | AN40: 1.6 | AO40: 2.3 | AP40: 24.477 | AT40: =(O40-AG40)/C40 -> 0.081374322 | AU40: 0.5 | AV40: =(AK40+AL40)/(G40+L40-T40) -> 0.34064516 | AW40: =(AK40+AL40)/(G40+L40-T40-AE40) -> 0.34064516 | AX40: =(AG40-AN40-AM40)/(G40+L40-T40+V40) -> 0.32432432 | AY40: =(AG40-AN40-AM40+AO40)/(G40+L40-T40+AO40) -> 0.35964912 | AZ40: =(AG40-AN40-AM40+AO40)/(G40+L40-T40+AO40-AC40) -> 0.35964912 | BA40: =(AG40-AN40)/Q40 -> 0.42155309 | BB40: =(AG40-AN40)/(Q40+R40) -> 0.39760837 | BC40: =D40 -> 77.7 | BD40: =BC40-(BE40+BF40+BG40) -> -0.1 | BE40: =AG40 -> 28.2 | BF40: 18.2 | BG40: 31.4 | BH40: =BG40/D40 -> 0.4041184 | BI40: 30.1 | BJ40: =BG40-BI40 -> 1.3 | BK40: =BJ40/D40 -> 0.016731017 | BO40: =BJ40/I40 -> 0.28888889 | BQ40: =L40 -> 5.4
B41: 1965 | C41: 660.3 | D41: 89.3 | E41: =D41/C41 -> 0.13524156 | F41: =D41-(G41+I41) -> 0 | G41: =D41-I41 -> 84.6 | H41: =G41/C41 -> 0.12812358 | I41: 4.7 | J41: =I41/C41 -> 0.0071179767 | K41: =I41/D41 -> 0.052631579 | L41: 5.7 | M41: =L41/C41 -> 0.0086324398 | N41: =L41/D41 -> 0.063829787 | O41: =D41 -> 89.3 | P41: =O41-(Q41+R41+T41+U41+X41-V41) -> 0 | Q41: 74.7 | R41: 3.9 | S41: =R41/D41 -> 0.043673012 | T41: 1.3 | U41: 6.2 | V41: 5.2 | W41: =V41/D41 -> 0.058230683 | X41: =O41-(Q41+R41+T41+U41-V41) -> 8.4 | AC41: =AC42*AF41/AF42 -> 0 | AD41: =AC41/D41 -> 0 | AF41: 0 | AG41: 31.1 | AH41: =AG41/C41 -> 0.047099803 | AI41: =(AG41-AN41)/C41 -> 0.045131001 | AJ41: =AG41-(AK41+AL41+AM41+AN41) -> -0.1 | AK41: 27.7 | AL41: 2 | AM41: 0.2 | AN41: 1.3 | AO41: 2.6 | AP41: 27.767 | AT41: =(O41-AG41)/C41 -> 0.088141754 | AU41: 0.48 | AV41: =(AK41+AL41)/(G41+L41-T41) -> 0.33370787 | AW41: =(AK41+AL41)/(G41+L41-T41-AE41) -> 0.33370787 | AX41: =(AG41-AN41-AM41)/(G41+L41-T41+V41) -> 0.31422505 | AY41: =(AG41-AN41-AM41+AO41)/(G41+L41-T41+AO41) -> 0.35152838 | AZ41: =(AG41-AN41-AM41+AO41)/(G41+L41-T41+AO41-AC41) -> 0.35152838 | BA41: =(AG41-AN41)/Q41 -> 0.39892905 | BB41: =(AG41-AN41)/(Q41+R41) -> 0.37913486 | BC41: =D41 -> 89.3 | BD41: =BC41-(BE41+BF41+BG41) -> 0 | BE41: =AG41 -> 31.1 | BF41: 20.2 | BG41: 38 | BH41: =BG41/D41 -> 0.42553191 | BI41: 36.6 | BJ41: =BG41-BI41 -> 1.4 | BK41: =BJ41/D41 -> 0.015677492 | BO41: =BJ41/I41 -> 0.29787234 | BQ41: =L41 -> 5.7
B42: 1966 | C42: 719.7 | D42: 96.1 | E42: =D42/C42 -> 0.13352786 | F42: =D42-(G42+I42) -> 0 | G42: =D42-I42 -> 91.6 | H42: =G42/C42 -> 0.12727525 | I42: 4.5 | J42: =I42/C42 -> 0.0062526053 | K42: =I42/D42 -> 0.046826223 | L42: 5.6 | M42: =L42/C42 -> 0.0077810199 | N42: =L42/D42 -> 0.058272633 | O42: =D42 -> 96.1 | P42: =O42-(Q42+R42+T42+U42+X42-V42) -> 0 | Q42: 81.3 | R42: 4.3 | S42: =R42/D42 -> 0.044745057 | T42: 1.7 | U42: 5.7 | V42: 5.4 | W42: =V42/D42 -> 0.056191467 | X42: =O42-(Q42+R42+T42+U42-V42) -> 8.5 | AC42: =AC43*AF42/AF43 -> 1.4492673 | AD42: =AC42/D42 -> 0.015080825 | AF42: 1.5810475 | AG42: 33.9 | AH42: =AG42/C42 -> 0.04710296 | AI42: =(AG42-AN42)/C42 -> 0.044879811 | AJ42: =AG42-(AK42+AL42+AM42+AN42) -> 0.2 | AK42: 29.7 | AL42: 2.2 | AM42: 0.2 | AN42: 1.6 | AO42: 2.9 | AP42: 32.022 | AT42: =(O42-AG42)/C42 -> 0.086424899 | AU42: 0.48 | AV42: =(AK42+AL42)/(G42+L42-T42) -> 0.33403141 | AW42: =(AK42+AL42)/(G42+L42-T42-AE42) -> 0.33403141 | AX42: =(AG42-AN42-AM42)/(G42+L42-T42+V42) -> 0.31813677 | AY42: =(AG42-AN42-AM42+AO42)/(G42+L42-T42+AO42) -> 0.35569106 | AZ42: =(AG42-AN42-AM42+AO42)/(G42+L42-T42+AO42-AC42) -> 0.3610081 | BA42: =(AG42-AN42)/Q42 -> 0.39729397 | BB42: =(AG42-AN42)/(Q42+R42) -> 0.37733645 | BC42: =D42 -> 96.1 | BD42: =BC42-(BE42+BF42+BG42) -> -0.1 | BE42: =AG42 -> 33.9 | BF42: 20.7 | BG42: 41.6 | BH42: =BG42/D42 -> 0.43288241 | BI42: 39.9 | BJ42: =BG42-BI42 -> 1.7 | BK42: =BJ42/D42 -> 0.017689906 | BO42: =BJ42/I42 -> 0.37777778 | BQ42: =L42 -> 5.6
B43: 1967 | C43: 760.2 | D43: 93.9 | E43: =D43/C43 -> 0.12352013 | F43: =D43-(G43+I43) -> 0 | G43: =D43-I43 -> 89.1 | H43: =G43/C43 -> 0.117206 | I43: 4.8 | J43: =I43/C43 -> 0.0063141279 | K43: =I43/D43 -> 0.051118211 | L43: 5.9 | M43: =L43/C43 -> 0.0077611155 | N43: =L43/D43 -> 0.062832801 | O43: =D43 -> 93.9 | P43: =O43-(Q43+R43+T43+U43+X43-V43) -> 0 | Q43: 79.3 | R43: 5 | S43: =R43/D43 -> 0.053248136 | T43: 2 | U43: 6.2 | V43: 7.5 | W43: =V43/D43 -> 0.079872204 | X43: =O43-(Q43+R43+T43+U43-V43) -> 8.9 | AC43: =AC44*AF43/AF44 -> 1.3972162 | AD43: =AC43/D43 -> 0.014879831 | AF43: 1.5242634 | AG43: 32.9 | AH43: =AG43/C43 -> 0.043278085 | AI43: =(AG43-AN43)/C43 -> 0.040778742 | AJ43: =AG43-(AK43+AL43+AM43+AN43) -> 0.1 | AK43: 28.1 | AL43: 2.6 | AM43: 0.2 | AN43: 1.9 | AO43: 3.2 | AP43: 31.318 | AT43: =(O43-AG43)/C43 -> 0.080242042 | AU43: 0.48 | AV43: =(AK43+AL43)/(G43+L43-T43) -> 0.33010753 | AW43: =(AK43+AL43)/(G43+L43-T43-AE43) -> 0.33010753 | AX43: =(AG43-AN43-AM43)/(G43+L43-T43+V43) -> 0.30646766 | AY43: =(AG43-AN43-AM43+AO43)/(G43+L43-T43+AO43) -> 0.35343035 | AZ43: =(AG43-AN43-AM43+AO43)/(G43+L43-T43+AO43-AC43) -> 0.35863926 | BA43: =(AG43-AN43)/Q43 -> 0.39092055 | BB43: =(AG43-AN43)/(Q43+R43) -> 0.36773428 | BC43: =D43 -> 93.9 | BD43: =BC43-(BE43+BF43+BG43) -> 0 | BE43: =AG43 -> 32.9 | BF43: 21.5 | BG43: 39.5 | BH43: =BG43/D43 -> 0.42066028 | BI43: 37.9 | BJ43: =BG43-BI43 -> 1.6 | BK43: =BJ43/D43 -> 0.017039404 | BO43: =BJ43/I43 -> 0.33333333 | BQ43: =L43 -> 5.9
B44: 1968 | C44: 832.1 | D44: 101.7 | E44: =D44/C44 -> 0.12222089 | F44: =D44-(G44+I44) -> 0 | G44: =D44-I44 -> 96.1 | H44: =G44/C44 -> 0.11549093 | I44: 5.6 | J44: =I44/C44 -> 0.0067299603 | K44: =I44/D44 -> 0.055063913 | L44: 7 | M44: =L44/C44 -> 0.0084124504 | N44: =L44/D44 -> 0.068829892 | O44: =D44 -> 101.7 | P44: =O44-(Q44+R44+T44+U44+X44-V44) -> 0 | Q44: 87.5 | R44: 5.4 | S44: =R44/D44 -> 0.053097345 | T44: 2.5 | U44: 3.8 | V44: 8.9 | W44: =V44/D44 -> 0.087512291 | X44: =O44-(Q44+R44+T44+U44-V44) -> 11.4 | AC44: =AC45*AF44/AF45 -> 1.5324177 | AD44: =AC44/D44 -> 0.015068021 | AF44: =(AF45+AF43)/2 -> 1.6717587 | AG44: 39.6 | AH44: =AG44/C44 -> 0.047590434 | AI44: =(AG44-AN44)/C44 -> 0.044585987 | AJ44: =AG44-(AK44+AL44+AM44+AN44) -> 0 | AK44: 33.5 | AL44: 3.3 | AM44: 0.3 | AN44: 2.5 | AO44: 3.7 | AP44: 32.6715 | AT44: =(O44-AG44)/C44 -> 0.074630453 | AU44: 0.528 | AV44: =(AK44+AL44)/(G44+L44-T44) -> 0.36580517 | AW44: =(AK44+AL44)/(G44+L44-T44-AE44) -> 0.36580517 | AX44: =(AG44-AN44-AM44)/(G44+L44-T44+V44) -> 0.33607306 | AY44: =(AG44-AN44-AM44+AO44)/(G44+L44-T44+AO44) -> 0.38830297 | AZ44: =(AG44-AN44-AM44+AO44)/(G44+L44-T44+AO44-AC44) -> 0.39409315 | BA44: =(AG44-AN44)/Q44 -> 0.424 | BB44: =(AG44-AN44)/(Q44+R44) -> 0.39935414 | BC44: =D44 -> 101.7 | BD44: =BC44-(BE44+BF44+BG44) -> 0 | BE44: =AG44 -> 39.6 | BF44: 23.5 | BG44: 38.6 | BH44: =BG44/D44 -> 0.37954769 | BI44: 36.3 | BJ44: =BG44-BI44 -> 2.3 | BK44: =BJ44/D44 -> 0.022615536 | BO44: =BJ44/I44 -> 0.41071429 | BQ44: =L44 -> 7
B45: 1969 | C45: 899.5 | D45: 98.4 | E45: =D45/C45 -> 0.10939411 | F45: =D45-(G45+I45) -> 0 | G45: =D45-I45 -> 91.8 | H45: =G45/C45 -> 0.1020567 | I45: 6.6 | J45: =I45/C45 -> 0.0073374097 | K45: =I45/D45 -> 0.067073171 | L45: 8 | M45: =L45/C45 -> 0.0088938299 | N45: =L45/D45 -> 0.081300813 | O45: =D45 -> 98.4 | P45: =O45-(Q45+R45+T45+U45+X45-V45) -> 0 | Q45: 82.1 | R45: 6.5 | S45: =R45/D45 -> 0.066056911 | T45: 3.1 | U45: 1.7 | V45: 7.8 | W45: =V45/D45 -> 0.079268293 | X45: =O45-(Q45+R45+T45+U45-V45) -> 12.8 | AC45: =AC46*AF45/AF46 -> 1.6676193 | AD45: =AC45/D45 -> 0.01694735 | AF45: 1.819254 | AG45: 40 | AH45: =AG45/C45 -> 0.04446915 | AI45: =(AG45-AN45)/C45 -> 0.041133963 | AJ45: =AG45-(AK45+AL45+AM45+AN45) -> 0 | AK45: 33.1 | AL45: 3.6 | AM45: 0.3 | AN45: 3 | AO45: 4 | AP45: 34.7535 | AT45: =(O45-AG45)/C45 -> 0.064924958 | AU45: 0.528 | AV45: =(AK45+AL45)/(G45+L45-T45) -> 0.3795243 | AW45: =(AK45+AL45)/(G45+L45-T45-AE45) -> 0.3795243 | AX45: =(AG45-AN45-AM45)/(G45+L45-T45+V45) -> 0.35119617 | AY45: =(AG45-AN45-AM45+AO45)/(G45+L45-T45+AO45) -> 0.4041708 | AZ45: =(AG45-AN45-AM45+AO45)/(G45+L45-T45+AO45-AC45) -> 0.41097669 | BA45: =(AG45-AN45)/Q45 -> 0.45066991 | BB45: =(AG45-AN45)/(Q45+R45) -> 0.41760722 | BC45: =D45 -> 98.4 | BD45: =BC45-(BE45+BF45+BG45) -> 0 | BE45: =AG45 -> 40 | BF45: 24.2 | BG45: 34.2 | BH45: =BG45/D45 -> 0.34756098 | BI45: 31.4 | BJ45: =BG45-BI45 -> 2.8 | BK45: =BJ45/D45 -> 0.028455285 | BO45: =BJ45/I45 -> 0.42424242 | BQ45: =L45 -> 8
B46: 1970 | C46: 940.1 | D46: 86.2 | E46: =D46/C46 -> 0.091692373 | F46: =D46-(G46+I46) -> 0 | G46: =D46-I46 -> 79.1 | H46: =G46/C46 -> 0.084139985 | I46: 7.1 | J46: =I46/C46 -> 0.007552388 | K46: =I46/D46 -> 0.082366589 | L46: 8.6 | M46: =L46/C46 -> 0.009147963 | N46: =L46/D46 -> 0.099767981 | O46: =D46 -> 86.2 | P46: =O46-(Q46+R46+T46+U46+X46-V46) -> 0 | Q46: 68 | R46: 7.6 | S46: =R46/D46 -> 0.088167053 | T46: 3.5 | U46: -0.1 | V46: 5.2 | W46: =V46/D46 -> 0.060324826 | X46: =O46-(Q46+R46+T46+U46-V46) -> 12.4 | AC46: =AC47*AF46/AF47 -> 1.5487008 | AD46: =AC46/D46 -> 0.017966366 | AF46: 1.6895224 | AG46: 34.8 | AH46: =AG46/C46 -> 0.037017339 | AI46: =(AG46-AN46)/C46 -> 0.03329433 | AJ46: =AG46-(AK46+AL46+AM46+AN46) -> 0.1 | AK46: 27.1 | AL46: 3.7 | AM46: 0.4 | AN46: 3.5 | AO46: 4.5 | AP46: 29.807 | AT46: =(O46-AG46)/C46 -> 0.054675035 | AU46: 0.492 | AV46: =(AK46+AL46)/(G46+L46-T46) -> 0.36579572 | AW46: =(AK46+AL46)/(G46+L46-T46-AE46) -> 0.36579572 | AX46: =(AG46-AN46-AM46)/(G46+L46-T46+V46) -> 0.34563758 | AY46: =(AG46-AN46-AM46+AO46)/(G46+L46-T46+AO46) -> 0.39909808 | AZ46: =(AG46-AN46-AM46+AO46)/(G46+L46-T46+AO46-AC46) -> 0.40619016 | BA46: =(AG46-AN46)/Q46 -> 0.46029412 | BB46: =(AG46-AN46)/(Q46+R46) -> 0.41402116 | BC46: =D46 -> 86.2 | BD46: =BC46-(BE46+BF46+BG46) -> -0.1 | BE46: =AG46 -> 34.8 | BF46: 24.3 | BG46: 27.2 | BH46: =BG46/D46 -> 0.31554524 | BI46: 24 | BJ46: =BG46-BI46 -> 3.2 | BK46: =BJ46/D46 -> 0.03712297 | BO46: =BJ46/I46 -> 0.45070423 | BQ46: =L46 -> 8.6
B47: 1971 | C47: 1017 | D47: 100.6 | E47: =D47/C47 -> 0.098918387 | F47: =D47-(G47+I47) -> 0 | G47: =D47-I47 -> 92.7 | H47: =G47/C47 -> 0.091150442 | I47: 7.9 | J47: =I47/C47 -> 0.0077679449 | K47: =I47/D47 -> 0.078528827 | L47: 9.8 | M47: =L47/C47 -> 0.0096361849 | N47: =L47/D47 -> 0.097415507 | O47: =D47 -> 100.6 | P47: =O47-(Q47+R47+T47+U47+X47-V47) -> 0 | Q47: 81.9 | R47: 7.3 | S47: =R47/D47 -> 0.072564612 | T47: 3.3 | U47: 1.4 | V47: 7.4 | W47: =V47/D47 -> 0.073558648 | X47: =O47-(Q47+R47+T47+U47-V47) -> 14.1 | AC47: =AC48*AF47/AF48 -> 1.8141239 | AD47: =AC47/D47 -> 0.01803304 | AF47: 1.9790801 | AG47: 38.2 | AH47: =AG47/C47 -> 0.037561455 | AI47: =(AG47-AN47)/C47 -> 0.034218289 | AJ47: =AG47-(AK47+AL47+AM47+AN47) -> 0 | AK47: 30.1 | AL47: 4.3 | AM47: 0.4 | AN47: 3.4 | AO47: 5.7 | AP47: 29.4755 | AT47: =(O47-AG47)/C47 -> 0.061356932 | AU47: 0.48 | AV47: =(AK47+AL47)/(G47+L47-T47) -> 0.34677419 | AW47: =(AK47+AL47)/(G47+L47-T47-AE47) -> 0.34677419 | AX47: =(AG47-AN47-AM47)/(G47+L47-T47+V47) -> 0.32270169 | AY47: =(AG47-AN47-AM47+AO47)/(G47+L47-T47+AO47) -> 0.38226883 | AZ47: =(AG47-AN47-AM47+AO47)/(G47+L47-T47+AO47-AC47) -> 0.38899606 | BA47: =(AG47-AN47)/Q47 -> 0.42490842 | BB47: =(AG47-AN47)/(Q47+R47) -> 0.39013453 | BC47: =D47 -> 100.6 | BD47: =BC47-(BE47+BF47+BG47) -> -0.1 | BE47: =AG47 -> 38.2 | BF47: 25 | BG47: 37.5 | BH47: =BG47/D47 -> 0.37276342 | BI47: 34.3 | BJ47: =BG47-BI47 -> 3.2 | BK47: =BJ47/D47 -> 0.031809145 | BO47: =BJ47/I47 -> 0.40506329 | BQ47: =L47 -> 9.8
B48: 1972 | C48: 1123 | D48: 117.2 | E48: =D48/C48 -> 0.10436331 | F48: =D48-(G48+I48) -> 0 | G48: =D48-I48 -> 107.7 | H48: =G48/C48 -> 0.095903829 | I48: 9.5 | J48: =I48/C48 -> 0.0084594835 | K48: =I48/D48 -> 0.08105802 | L48: 11.7 | M48: =L48/C48 -> 0.010418522 | N48: =L48/D48 -> 0.099829352 | O48: =D48 -> 117.2 | P48: =O48-(Q48+R48+T48+U48+X48-V48) -> 0 | Q48: 99.5 | R48: 7.2 | S48: =R48/D48 -> 0.061433447 | T48: 3.3 | U48: 1.3 | V48: 10.1 | W48: =V48/D48 -> 0.086177474 | X48: =O48-(Q48+R48+T48+U48-V48) -> 16 | AC48: =AC49*AF48/AF49 -> 2.0350359 | AD48: =AC48/D48 -> 0.017363787 | AF48: 2.2200793 | AG48: 42.3 | AH48: =AG48/C48 -> 0.037666963 | AI48: =(AG48-AN48)/C48 -> 0.034817453 | AJ48: =AG48-(AK48+AL48+AM48+AN48) -> -0.1 | AK48: 33.4 | AL48: 5.3 | AM48: 0.5 | AN48: 3.2 | AO48: 6.3 | AP48: 34.1595 | AT48: =(O48-AG48)/C48 -> 0.066696349 | AU48: 0.48 | AV48: =(AK48+AL48)/(G48+L48-T48) -> 0.33333333 | AW48: =(AK48+AL48)/(G48+L48-T48-AE48) -> 0.33333333 | AX48: =(AG48-AN48-AM48)/(G48+L48-T48+V48) -> 0.30586371 | AY48: =(AG48-AN48-AM48+AO48)/(G48+L48-T48+AO48) -> 0.36683007 | AZ48: =(AG48-AN48-AM48+AO48)/(G48+L48-T48+AO48-AC48) -> 0.37303214 | BA48: =(AG48-AN48)/Q48 -> 0.39296482 | BB48: =(AG48-AN48)/(Q48+R48) -> 0.36644799 | BC48: =D48 -> 117.2 | BD48: =BC48-(BE48+BF48+BG48) -> 0.1 | BE48: =AG48 -> 42.3 | BF48: 26.8 | BG48: 48 | BH48: =BG48/D48 -> 0.40955631 | BI48: 43.4 | BJ48: =BG48-BI48 -> 4.6 | BK48: =BJ48/D48 -> 0.039249147 | BO48: =BJ48/I48 -> 0.48421053 | BQ48: =L48 -> 11.7
B49: 1973 | C49: 1257 | D49: 133.4 | E49: =D49/C49 -> 0.1061257 | F49: =D49-(G49+I49) -> 0 | G49: =D49-I49 -> 118.5 | H49: =G49/C49 -> 0.094272076 | I49: 14.9 | J49: =I49/C49 -> 0.01185362 | K49: =I49/D49 -> 0.11169415 | L49: 17.6 | M49: =L49/C49 -> 0.014001591 | N49: =L49/D49 -> 0.13193403 | O49: =D49 -> 133.4 | P49: =O49-(Q49+R49+T49+U49+X49-V49) -> 0 | Q49: 122.6 | R49: 9.6 | S49: =R49/D49 -> 0.071964018 | T49: 4.5 | U49: -12.8 | V49: 9.5 | W49: =V49/D49 -> 0.071214393 | X49: =O49-(Q49+R49+T49+U49-V49) -> 19 | AC49: =AC50*AF49/AF50 -> 2.0284705 | AD49: =AC49/D49 -> 0.015205925 | AF49: 2.212917 | AG49: 50 | AH49: =AG49/C49 -> 0.039777247 | AI49: =(AG49-AN49)/C49 -> 0.036356404 | AJ49: =AG49-(AK49+AL49+AM49+AN49) -> 0.1 | AK49: 38.9 | AL49: 6 | AM49: 0.7 | AN49: 4.3 | AO49: 9.6 | AP49: 37.3865 | AT49: =(O49-AG49)/C49 -> 0.066348449 | AU49: 0.48 | AV49: =(AK49+AL49)/(G49+L49-T49) -> 0.34118541 | AW49: =(AK49+AL49)/(G49+L49-T49-AE49) -> 0.34118541 | AX49: =(AG49-AN49-AM49)/(G49+L49-T49+V49) -> 0.31892275 | AY49: =(AG49-AN49-AM49+AO49)/(G49+L49-T49+AO49) -> 0.38668555 | AZ49: =(AG49-AN49-AM49+AO49)/(G49+L49-T49+AO49-AC49) -> 0.39232162 | BA49: =(AG49-AN49)/Q49 -> 0.37275693 | BB49: =(AG49-AN49)/(Q49+R49) -> 0.34568835 | BC49: =D49 -> 133.4 | BD49: =BC49-(BE49+BF49+BG49) -> 0 | BE49: =AG49 -> 50 | BF49: 29.9 | BG49: 53.5 | BH49: =BG49/D49 -> 0.40104948 | BI49: 45.4 | BJ49: =BG49-BI49 -> 8.1 | BK49: =BJ49/D49 -> 0.06071964 | BO49: =BJ49/I49 -> 0.54362416 | BQ49: =L49 -> 17.6
B50: 1974 | C50: 1350.8 | D50: 125.7 | E50: =D50/C50 -> 0.093055967 | F50: =D50-(G50+I50) -> 0 | G50: =D50-I50 -> 108.2 | H50: =G50/C50 -> 0.080100681 | I50: 17.5 | J50: =I50/C50 -> 0.012955286 | K50: =I50/D50 -> 0.13922037 | L50: 20.4 | M50: =L50/C50 -> 0.015102162 | N50: =L50/D50 -> 0.16229117 | O50: =D50 -> 125.7 | P50: =O50-(Q50+R50+T50+U50+X50-V50) -> 0 | Q50: 148.2 | R50: 10.4 | S50: =R50/D50 -> 0.082736675 | T50: 5.7 | U50: -35.8 | V50: 7.7 | W50: =V50/D50 -> 0.061256961 | X50: =O50-(Q50+R50+T50+U50-V50) -> 4.9 | AC50: =AC51*AF50/AF51 -> 2.4859607 | AD50: =AC50/D50 -> 0.019776934 | AF50: 2.7120062 | AG50: 52.8 | AH50: =AG50/C50 -> 0.039087948 | AI50: =(AG50-AN50)/C50 -> 0.034942256 | AJ50: =AG50-(AK50+AL50+AM50+AN50) -> 0 | AK50: 39.5 | AL50: 6.7 | AM50: 1 | AN50: 5.6 | AO50: 20.8 | AP50: 39.6205 | AT50: =(O50-AG50)/C50 -> 0.053968019 | AU50: 0.48 | AV50: =(AK50+AL50)/(G50+L50-T50) -> 0.37591538 | AW50: =(AK50+AL50)/(G50+L50-T50-AE50) -> 0.37591538 | AX50: =(AG50-AN50-AM50)/(G50+L50-T50+V50) -> 0.35375191 | AY50: =(AG50-AN50-AM50+AO50)/(G50+L50-T50+AO50) -> 0.46624913 | AZ50: =(AG50-AN50-AM50+AO50)/(G50+L50-T50+AO50-AC50) -> 0.47445707 | BA50: =(AG50-AN50)/Q50 -> 0.31848853 | BB50: =(AG50-AN50)/(Q50+R50) -> 0.29760404 | BC50: =D50 -> 125.7 | BD50: =BC50-(BE50+BF50+BG50) -> 0 | BE50: =AG50 -> 52.8 | BF50: 33.2 | BG50: 39.7 | BH50: =BG50/D50 -> 0.31583134 | BI50: 32 | BJ50: =BG50-BI50 -> 7.7 | BK50: =BJ50/D50 -> 0.061256961 | BO50: =BJ50/I50 -> 0.44 | BQ50: =L50 -> 20.4
B51: 1975 | C51: 1451.1 | D51: 138.9 | E51: =D51/C51 -> 0.095720488 | F51: =D51-(G51+I51) -> 0 | G51: =D51-I51 -> 124.3 | H51: =G51/C51 -> 0.085659155 | I51: 14.6 | J51: =I51/C51 -> 0.010061333 | K51: =I51/D51 -> 0.10511159 | L51: 17.9 | M51: =L51/C51 -> 0.01233547 | N51: =L51/D51 -> 0.12886969 | O51: =D51 -> 138.9 | P51: =O51-(Q51+R51+T51+U51+X51-V51) -> 0 | Q51: 146 | R51: 10 | S51: =R51/D51 -> 0.07199424 | T51: 5.6 | U51: -15.9 | V51: 8.9 | W51: =V51/D51 -> 0.064074874 | X51: =O51-(Q51+R51+T51+U51-V51) -> 2.1 | AC51: =AC52*AF51/AF52 -> 1.8552537 | AD51: =AC51/D51 -> 0.013356758 | AF51: 2.0239498 | AG51: 51.6 | AH51: =AG51/C51 -> 0.035559231 | AI51: =(AG51-AN51)/C51 -> 0.031837916 | AJ51: =AG51-(AK51+AL51+AM51+AN51) -> 0.1 | AK51: 38.1 | AL51: 7.3 | AM51: 0.7 | AN51: 5.4 | AO51: 20 | AP51: 41.015 | AT51: =(O51-AG51)/C51 -> 0.060161257 | AU51: 0.48 | AV51: =(AK51+AL51)/(G51+L51-T51) -> 0.33235725 | AW51: =(AK51+AL51)/(G51+L51-T51-AE51) -> 0.33235725 | AX51: =(AG51-AN51-AM51)/(G51+L51-T51+V51) -> 0.31271478 | AY51: =(AG51-AN51-AM51+AO51)/(G51+L51-T51+AO51) -> 0.41826309 | AZ51: =(AG51-AN51-AM51+AO51)/(G51+L51-T51+AO51-AC51) -> 0.4232777 | BA51: =(AG51-AN51)/Q51 -> 0.31643836 | BB51: =(AG51-AN51)/(Q51+R51) -> 0.29615385 | BC51: =D51 -> 138.9 | BD51: =BC51-(BE51+BF51+BG51) -> 0 | BE51: =AG51 -> 51.6 | BF51: 33 | BG51: 54.3 | BH51: =BG51/D51 -> 0.39092873 | BI51: 46.2 | BJ51: =BG51-BI51 -> 8.1 | BK51: =BJ51/D51 -> 0.058315335 | BO51: =BJ51/I51 -> 0.55479452 | BQ51: =L51 -> 17.9
B52: 1976 | C52: 1614.8 | D52: 174.3 | E52: =D52/C52 -> 0.10793906 | F52: =D52-(G52+I52) -> 0 | G52: =D52-I52 -> 157.8 | H52: =G52/C52 -> 0.09772108 | I52: 16.5 | J52: =I52/C52 -> 0.010217984 | K52: =I52/D52 -> 0.094664372 | L52: 21 | M52: =L52/C52 -> 0.013004706 | N52: =L52/D52 -> 0.12048193 | O52: =D52 -> 174.3 | P52: =O52-(Q52+R52+T52+U52+X52-V52) -> 0 | Q52: 186.6 | R52: 11.6 | S52: =R52/D52 -> 0.066551922 | T52: 5.9 | U52: -21.9 | V52: 10.6 | W52: =V52/D52 -> 0.060814687 | X52: =O52-(Q52+R52+T52+U52-V52) -> 2.7 | AC52: =AC53*AF52/AF53 -> 1.7193835 | AD52: =AC52/D52 -> 0.0098645066 | AF52: 1.8757251 | AG52: 65.3 | AH52: =AG52/C52 -> 0.040438444 | AI52: =(AG52-AN52)/C52 -> 0.036784741 | AJ52: =AG52-(AK52+AL52+AM52+AN52) -> 0.1 | AK52: 48.6 | AL52: 9.6 | AM52: 1.1 | AN52: 5.9 | AO52: 24.3 | AP52: =AP51+(AP$54-AP$51)/3 -> 47.804417 | AT52: =(O52-AG52)/C52 -> 0.067500619 | AU52: 0.48 | AV52: =(AK52+AL52)/(G52+L52-T52) -> 0.33661076 | AW52: =(AK52+AL52)/(G52+L52-T52-AE52) -> 0.33661076 | AX52: =(AG52-AN52-AM52)/(G52+L52-T52+V52) -> 0.31771117 | AY52: =(AG52-AN52-AM52+AO52)/(G52+L52-T52+AO52) -> 0.4188641 | AZ52: =(AG52-AN52-AM52+AO52)/(G52+L52-T52+AO52-AC52) -> 0.42254829 | BA52: =(AG52-AN52)/Q52 -> 0.31832797 | BB52: =(AG52-AN52)/(Q52+R52) -> 0.29969728 | BC52: =D52 -> 174.3 | BD52: =BC52-(BE52+BF52+BG52) -> 0 | BE52: =AG52 -> 65.3 | BF52: 39 | BG52: 70 | BH52: =BG52/D52 -> 0.40160643 | BI52: 62.4 | BJ52: =BG52-BI52 -> 7.6 | BK52: =BJ52/D52 -> 0.043602983 | BO52: =BJ52/I52 -> 0.46060606 | BQ52: =L52 -> 21
B53: 1977 | C53: 1798.7 | D53: 205.8 | E53: =D53/C53 -> 0.11441597 | F53: =D53-(G53+I53) -> 0 | G53: =D53-I53 -> 186.7 | H53: =G53/C53 -> 0.10379719 | I53: 19.1 | J53: =I53/C53 -> 0.01061878 | K53: =I53/D53 -> 0.092808552 | L53: 23.7 | M53: =L53/C53 -> 0.013176183 | N53: =L53/D53 -> 0.11516035 | O53: =D53 -> 205.8 | P53: =O53-(Q53+R53+T53+U53+X53-V53) -> 0 | Q53: 219.5 | R53: 12.2 | S53: =R53/D53 -> 0.059280855 | T53: 6.1 | U53: -22.7 | V53: 14 | W53: =V53/D53 -> 0.068027211 | X53: =O53-(Q53+R53+T53+U53-V53) -> 4.7 | AC53: =AC54*AF53/AF54 -> 1.8094899 | AD53: =AC53/D53 -> 0.0087924679 | AF53: 1.9740247 | AG53: 74.4 | AH53: =AG53/C53 -> 0.041363207 | AI53: =(AG53-AN53)/C53 -> 0.03808306 | AJ53: =AG53-(AK53+AL53+AM53+AN53) -> 0 | AK53: 55.7 | AL53: 11.4 | AM53: 1.4 | AN53: 5.9 | AO53: 26.8 | AP53: =AP52+(AP$54-AP$51)/3 -> 54.593833 | AT53: =(O53-AG53)/C53 -> 0.07305276 | AU53: 0.48 | AV53: =(AK53+AL53)/(G53+L53-T53) -> 0.32843857 | AW53: =(AK53+AL53)/(G53+L53-T53-AE53) -> 0.32843857 | AX53: =(AG53-AN53-AM53)/(G53+L53-T53+V53) -> 0.30737517 | AY53: =(AG53-AN53-AM53+AO53)/(G53+L53-T53+AO53) -> 0.40631761 | AZ53: =(AG53-AN53-AM53+AO53)/(G53+L53-T53+AO53-AC53) -> 0.40952414 | BA53: =(AG53-AN53)/Q53 -> 0.31207289 | BB53: =(AG53-AN53)/(Q53+R53) -> 0.29564091 | BC53: =D53 -> 205.8 | BD53: =BC53-(BE53+BF53+BG53) -> 0 | BE53: =AG53 -> 74.4 | BF53: 44.8 | BG53: 86.6 | BH53: =BG53/D53 -> 0.42079689 | BI53: 78.5 | BJ53: =BG53-BI53 -> 8.1 | BK53: =BJ53/D53 -> 0.039358601 | BO53: =BJ53/I53 -> 0.42408377 | BQ53: =L53 -> 23.7
B54: 1978 | C54: 2029.9 | D54: 238.6 | E54: =D54/C54 -> 0.11754274 | F54: =D54-(G54+I54) -> 0 | G54: =D54-I54 -> 215.7 | H54: =G54/C54 -> 0.10626139 | I54: 22.9 | J54: =I54/C54 -> 0.011281344 | K54: =I54/D54 -> 0.09597653 | L54: 29 | M54: =L54/C54 -> 0.014286418 | N54: =L54/D54 -> 0.12154233 | O54: =D54 -> 238.6 | P54: =O54-(Q54+R54+T54+U54+X54-V54) -> 0 | Q54: 247.4 | R54: 14.8 | S54: =R54/D54 -> 0.0620285 | T54: 7.6 | U54: -31.8 | V54: 16.7 | W54: =V54/D54 -> 0.069991618 | X54: =O54-(Q54+R54+T54+U54-V54) -> 17.3 | AC54: =AC55*AF54/AF55 -> 2.0938779 | AD54: =AC54/D54 -> 0.0087756828 | AF54: 2.2842718 | AG54: 84.9 | AH54: =AG54/C54 -> 0.04182472 | AI54: =(AG54-AN54)/C54 -> 0.038376275 | AJ54: =AG54-(AK54+AL54+AM54+AN54) -> 0 | AK54: 64.4 | AL54: 12.1 | AM54: 1.4 | AN54: 7 | AO54: 27.5 | AP54: 61.38325 | AT54: =(O54-AG54)/C54 -> 0.075718016 | AU54: 0.48 | AV54: =(AK54+AL54)/(G54+L54-T54) -> 0.32264867 | AW54: =(AK54+AL54)/(G54+L54-T54-AE54) -> 0.32264867 | AX54: =(AG54-AN54-AM54)/(G54+L54-T54+V54) -> 0.30141844 | AY54: =(AG54-AN54-AM54+AO54)/(G54+L54-T54+AO54) -> 0.39304611 | AZ54: =(AG54-AN54-AM54+AO54)/(G54+L54-T54+AO54-AC54) -> 0.39618124 | BA54: =(AG54-AN54)/Q54 -> 0.3148747 | BB54: =(AG54-AN54)/(Q54+R54) -> 0.29710145 | BC54: =D54 -> 238.6 | BD54: =BC54-(BE54+BF54+BG54) -> 0 | BE54: =AG54 -> 84.9 | BF54: 50.8 | BG54: 102.9 | BH54: =BG54/D54 -> 0.43126572 | BI54: 91.2 | BJ54: =BG54-BI54 -> 11.7 | BK54: =BJ54/D54 -> 0.049036044 | BO54: =BJ54/I54 -> 0.51091703 | BQ54: =L54 -> 29
B55: 1979 | C55: 2248.2 | D55: 249 | E55: =D55/C55 -> 0.11075527 | F55: =D55-(G55+I55) -> 0 | G55: =D55-I55 -> 214.4 | H55: =G55/C55 -> 0.095365181 | I55: 34.6 | J55: =I55/C55 -> 0.01539009 | K55: =I55/D55 -> 0.13895582 | L55: 42.6 | M55: =L55/C55 -> 0.018948492 | N55: =L55/D55 -> 0.17108434 | O55: =D55 -> 249 | P55: =O55-(Q55+R55+T55+U55+X55-V55) -> 0 | Q55: 283 | R55: 16.5 | S55: =R55/D55 -> 0.06626506 | T55: 9.4 | U55: -52.1 | V55: 21 | W55: =V55/D55 -> 0.084337349 | X55: =O55-(Q55+R55+T55+U55-V55) -> 13.2 | AC55: =AC56*AF55/AF56 -> 2.0447714 | AD55: =AC55/D55 -> 0.0082119332 | AF55: 2.2307001 | AG55: 90 | AH55: =AG55/C55 -> 0.040032026 | AI55: =(AG55-AN55)/C55 -> 0.035895383 | AJ55: =AG55-(AK55+AL55+AM55+AN55) -> -0.1 | AK55: 65.2 | AL55: 13.6 | AM55: 2 | AN55: 9.3 | AO55: 38.2 | AP55: 65.40775 | AT55: =(O55-AG55)/C55 -> 0.070723245 | AU55: 0.46 | AV55: =(AK55+AL55)/(G55+L55-T55) -> 0.31825525 | AW55: =(AK55+AL55)/(G55+L55-T55-AE55) -> 0.31825525 | AX55: =(AG55-AN55-AM55)/(G55+L55-T55+V55) -> 0.29300074 | AY55: =(AG55-AN55-AM55+AO55)/(G55+L55-T55+AO55) -> 0.40902729 | AZ55: =(AG55-AN55-AM55+AO55)/(G55+L55-T55+AO55-AC55) -> 0.41197479 | BA55: =(AG55-AN55)/Q55 -> 0.28515901 | BB55: =(AG55-AN55)/(Q55+R55) -> 0.26944908 | BC55: =D55 -> 249 | BD55: =BC55-(BE55+BF55+BG55) -> 0.1 | BE55: =AG55 -> 90 | BF55: 57.5 | BG55: 101.4 | BH55: =BG55/D55 -> 0.40722892 | BI55: 82.9 | BJ55: =BG55-BI55 -> 18.5 | BK55: =BJ55/D55 -> 0.074297189 | BO55: =BJ55/I55 -> 0.53468208 | BQ55: =L55 -> 42.6
B56: 1980 | C56: 2426.8 | D56: 223.6 | E56: =D56/C56 -> 0.092137795 | F56: =D56-(G56+I56) -> 0 | G56: =D56-I56 -> 188.1 | H56: =G56/C56 -> 0.077509478 | I56: 35.5 | J56: =I56/C56 -> 0.014628317 | K56: =I56/D56 -> 0.15876565 | L56: 43.9 | M56: =L56/C56 -> 0.018089665 | N56: =L56/D56 -> 0.19633274 | O56: =D56 -> 223.6 | P56: =O56-(Q56+R56+T56+U56+X56-V56) -> 0 | Q56: 235.9 | R56: 20.1 | S56: =R56/D56 -> 0.089892665 | T56: 11.8 | U56: -59.2 | V56: 27.1 | W56: =V56/D56 -> 0.12119857 | X56: =O56-(Q56+R56+T56+U56-V56) -> 42.1 | AC56: =AC57*AF56/AF57 -> 0.61430887 | AD56: =AC56/D56 -> 0.0027473563 | AF56: 0.67016727 | AG56: 87.2 | AH56: =AG56/C56 -> 0.035932092 | AI56: =(AG56-AN56)/C56 -> 0.031110928 | AJ56: =AG56-(AK56+AL56+AM56+AN56) -> 0 | AK56: 58.6 | AL56: 14.5 | AM56: 2.4 | AN56: 11.7 | AO56: 26.4 | AP56: 63.73425 | AT56: =(O56-AG56)/C56 -> 0.056205703 | AU56: 0.46 | AV56: =(AK56+AL56)/(G56+L56-T56) -> 0.33197094 | AW56: =(AK56+AL56)/(G56+L56-T56-AE56) -> 0.33197094 | AX56: =(AG56-AN56-AM56)/(G56+L56-T56+V56) -> 0.2955924 | AY56: =(AG56-AN56-AM56+AO56)/(G56+L56-T56+AO56) -> 0.40348743 | AZ56: =(AG56-AN56-AM56+AO56)/(G56+L56-T56+AO56-AC56) -> 0.40449507 | BA56: =(AG56-AN56)/Q56 -> 0.32005087 | BB56: =(AG56-AN56)/(Q56+R56) -> 0.29492188 | BC56: =D56 -> 223.6 | BD56: =BC56-(BE56+BF56+BG56) -> 0 | BE56: =AG56 -> 87.2 | BF56: 64.1 | BG56: 72.3 | BH56: =BG56/D56 -> 0.32334526 | BI56: 53.6 | BJ56: =BG56-BI56 -> 18.7 | BK56: =BJ56/D56 -> 0.083631485 | BO56: =BJ56/I56 -> 0.52676056 | BQ56: =L56 -> 43.9
B57: 1981 | C57: 2722.1 | D57: 247.5 | E57: =D57/C57 -> 0.09092245 | F57: =D57-(G57+I57) -> 0 | G57: =D57-I57 -> 217.8 | H57: =G57/C57 -> 0.080011756 | I57: 29.7 | J57: =I57/C57 -> 0.010910694 | K57: =I57/D57 -> 0.12 | L57: 38 | M57: =L57/C57 -> 0.01395981 | N57: =L57/D57 -> 0.15353535 | O57: =D57 -> 247.5 | P57: =O57-(Q57+R57+T57+U57+X57-V57) -> 0 | Q57: 212.5 | R57: 26.3 | S57: =R57/D57 -> 0.10626263 | T57: 14.4 | U57: -29.1 | V57: 28.8 | W57: =V57/D57 -> 0.11636364 | X57: =O57-(Q57+R57+T57+U57-V57) -> 52.2 | AC57: =AC58*AF57/AF58 -> -0.74822169 | AD57: =AC57/D57 -> -0.003023118 | AF57: -0.81625663 | AG57: 84.3 | AH57: =AG57/C57 -> 0.030968737 | AI57: =(AG57-AN57)/C57 -> 0.025825649 | AJ57: =AG57-(AK57+AL57+AM57+AN57) -> 0.1 | AK57: 51.6 | AL57: 15.4 | AM57: 3.2 | AN57: 14 | AO57: 23.8 | AP57: 58.1545 | AT57: =(O57-AG57)/C57 -> 0.059953712 | AU57: 0.46 | AV57: =(AK57+AL57)/(G57+L57-T57) -> 0.27754764 | AW57: =(AK57+AL57)/(G57+L57-T57-AE57) -> 0.27754764 | AX57: =(AG57-AN57-AM57)/(G57+L57-T57+V57) -> 0.24833457 | AY57: =(AG57-AN57-AM57+AO57)/(G57+L57-T57+AO57) -> 0.34276018 | AZ57: =(AG57-AN57-AM57+AO57)/(G57+L57-T57+AO57-AC57) -> 0.34179586 | BA57: =(AG57-AN57)/Q57 -> 0.33082353 | BB57: =(AG57-AN57)/(Q57+R57) -> 0.29438861 | BC57: =D57 -> 247.5 | BD57: =BC57-(BE57+BF57+BG57) -> 0 | BE57: =AG57 -> 84.3 | BF57: 73.8 | BG57: 89.4 | BH57: =BG57/D57 -> 0.36121212 | BI57: 75.2 | BJ57: =BG57-BI57 -> 14.2 | BK57: =BJ57/D57 -> 0.057373737 | BO57: =BJ57/I57 -> 0.47811448 | BQ57: =L57 -> 38
B58: 1982 | C58: 2840.4 | D58: 229.9 | E58: =D58/C58 -> 0.080939304 | F58: =D58-(G58+I58) -> 0 | G58: =D58-I58 -> 197.3 | H58: =G58/C58 -> 0.069462048 | I58: 32.6 | J58: =I58/C58 -> 0.011477257 | K58: =I58/D58 -> 0.14180078 | L58: 36.7 | M58: =L58/C58 -> 0.012920715 | N58: =L58/D58 -> 0.15963462 | O58: =D58 -> 229.9 | P58: =O58-(Q58+R58+T58+U58+X58-V58) -> 0 | Q58: 154.8 | R58: 29.8 | S58: =R58/D58 -> 0.12962157 | T58: 15.2 | U58: -2.5 | V58: 29.1 | W58: =V58/D58 -> 0.12657677 | X58: =O58-(Q58+R58+T58+U58-V58) -> 61.7 | AC58: =AC59*AF58/AF59 -> -0.78325796 | AD58: =AC58/D58 -> -0.0034069507 | AF58: -0.85447871 | AG58: 66.5 | AH58: =AG58/C58 -> 0.023412195 | AI58: =(AG58-AN58)/C58 -> 0.018060837 | AJ58: =AG58-(AK58+AL58+AM58+AN58) -> 0 | AK58: 33.9 | AL58: 14 | AM58: 3.4 | AN58: 15.2 | AO58: 21.2 | AP58: 46.16075 | AT58: =(O58-AG58)/C58 -> 0.057527109 | AU58: 0.46 | AV58: =(AK58+AL58)/(G58+L58-T58) -> 0.21892139 | AW58: =(AK58+AL58)/(G58+L58-T58-AE58) -> 0.21892139 | AX58: =(AG58-AN58-AM58)/(G58+L58-T58+V58) -> 0.19322307 | AY58: =(AG58-AN58-AM58+AO58)/(G58+L58-T58+AO58) -> 0.28791667 | AZ58: =(AG58-AN58-AM58+AO58)/(G58+L58-T58+AO58-AC58) -> 0.28698009 | BA58: =(AG58-AN58)/Q58 -> 0.33139535 | BB58: =(AG58-AN58)/(Q58+R58) -> 0.27789816 | BC58: =D58 -> 229.9 | BD58: =BC58-(BE58+BF58+BG58) -> 0.1 | BE58: =AG58 -> 66.5 | BF58: 77.7 | BG58: 85.6 | BH58: =BG58/D58 -> 0.3723358 | BI58: 69.4 | BJ58: =BG58-BI58 -> 16.2 | BK58: =BJ58/D58 -> 0.07046542 | BL58: =DD58/(D58) -> 0.013471074 | BM58: =DD58/(CV58+CW58) -> 0.111147 | BN58: =CQ58*DF58 -> 0.1247382 | BO58: =BJ58/I58 -> 0.49693252 | BP58: 23.058 | BQ58: =L58 -> 36.7 | BX58: 24.828 | BY58: 0.421 | BZ58: 1.073 | CA58: 0.161 | CB58: 1.434 | CC58: =CD58+CE58 -> 2.105 | CD58: 1.395 | CE58: 0.71 | CF58: 0.473 | CG58: =BY58+BZ58+CA58+CB58+CD58+CE58+CF58 -> 5.667 | CH58: =BX58-CG58 -> 19.161 | CI58: =BY58/$BX58 -> 0.016956662 | CJ58: =BZ58/$BX58 -> 0.043217335 | CK58: =CA58/$BX58 -> 0.0064846141 | CL58: =CB58/$BX58 -> 0.057757371 | CM58: =CN58+CO58 -> 0.084783309 | CN58: =CD58/$BX58 -> 0.056186564 | CO58: =CE58/$BX58 -> 0.028596746 | CP58: =CF58/$BX58 -> 0.019051071 | CQ58: =CG58/$BX58 -> 0.22825036 | CR58: =CQ58*N58 -> 0.036436661 | CS58: =BX58 -> 24.828 | CT58: =BX58 -> 24.828 | CU58: =CT58-(CV58+CW58) -> -3.036 | CV58: 23.058 | CW58: 4.806 | CX58: 0.202 | CY58: -0.16 | CZ58: 0.125 | DA58: 0.807 | DB58: 1.876 | DC58: 0.247 | DD58: =DC58+DB58+DA58+CZ58+CY58+CX58 -> 3.097 | DF58: =DD58/CG58 -> 0.54649726 | DG58: =CW58-DD58 -> 1.709 | DH58: =DD58/CW58 -> 0.64440283 | DI58: =CW58/(CW58+CV58) -> 0.17248062 | DJ58: 1.078 | DK58: 0.333 | DL58: -0.105 | DM58: 0.179 | DN58: 0.775 | DO58: -6.959 | DP58: 0.945 | DQ58: 0.042 | DR58: =DQ58+DO58+DN58+DM58+DL58+DK58 -> -5.735 | DS58: =DJ58-DR58 -> 6.813 | DT58: =DR58/DJ58 -> -5.3200371 | DU58: =DJ58-CW58 -> -3.728 | DV58: -3.728 | DW58: =DK58-CX58 -> 0.131 | DX58: =DL58-CY58 -> 0.055 | DY58: =DM58-CZ58 -> 0.054 | DZ58: =DN58-DA58 -> -0.032 | EA58: =DO58-DB58 -> -8.835 | EB58: =DQ58-DC58 -> -0.205 | EC58: =EB58+EA58+DZ58+DY58+DX58+DW58 -> -8.832 | ED58: =DU58-EC58 -> 5.104 | EE58: =EC58/DU58 -> 2.3690987 | EF58: 9.708 | EG58: 0.09 | EH58: 0.535 | EI58: 0.023 | EJ58: 0.166 | EK58: 4.653 | EL58: 0.047 | EM58: =EL58+EK58+EJ58+EI58+EH58+EG58 -> 5.514 | EN58: =EF58-EM58 -> 4.194 | EO58: =EM58/EF58 -> 0.56798517 | EP58: 207.752 | EQ58: 2.031 | ER58: 6.76 | ES58: 1.098 | ET58: 12.863 | EU58: -1.847 | EV58: 11.519 | EW58: 1.72 | EX58: =EW58+EU58+ET58+ES58+ER58+EQ58 -> 22.625 | EY58: =EP58-EX58 -> 185.127 | EZ58: =EX58/EP58 -> 0.10890389
B59: 1983 | C59: 3060.5 | D59: 279.8 | E59: =D59/C59 -> 0.09142297 | F59: =D59-(G59+I59) -> 0 | G59: =D59-I59 -> 244.7 | H59: =G59/C59 -> 0.079954256 | I59: 35.1 | J59: =I59/C59 -> 0.011468714 | K59: =I59/D59 -> 0.12544675 | L59: 41.1 | M59: =L59/C59 -> 0.013429178 | N59: =L59/D59 -> 0.14689064 | O59: =D59 -> 279.8 | P59: =O59-(Q59+R59+T59+U59+X59-V59) -> 0 | Q59: 190 | R59: 41.4 | S59: =R59/D59 -> 0.14796283 | T59: 14.6 | U59: 15.9 | V59: 42 | W59: =V59/D59 -> 0.15010722 | X59: =O59-(Q59+R59+T59+U59-V59) -> 59.9 | AC59: =AC60*AF59/AF60 -> 1.9149687 | AD59: =AC59/D59 -> 0.0068440626 | AF59: 2.0890946 | AG59: 80.6 | AH59: =AG59/C59 -> 0.026335566 | AI59: =(AG59-AN59)/C59 -> 0.021695801 | AJ59: =AG59-(AK59+AL59+AM59+AN59) -> -0.1 | AK59: 47.2 | AL59: 15.9 | AM59: 3.4 | AN59: 14.2 | AO59: 21.5 | AP59: 41.98975 | AT59: =(O59-AG59)/C59 -> 0.065087404 | AU59: 0.46 | AV59: =(AK59+AL59)/(G59+L59-T59) -> 0.23266962 | AW59: =(AK59+AL59)/(G59+L59-T59-AE59) -> 0.23266962 | AX59: =(AG59-AN59-AM59)/(G59+L59-T59+V59) -> 0.20114943 | AY59: =(AG59-AN59-AM59+AO59)/(G59+L59-T59+AO59) -> 0.28869149 | AZ59: =(AG59-AN59-AM59+AO59)/(G59+L59-T59+AO59-AC59) -> 0.29059267 | BA59: =(AG59-AN59)/Q59 -> 0.34947368 | BB59: =(AG59-AN59)/(Q59+R59) -> 0.28694901 | BC59: =D59 -> 279.8 | BD59: =BC59-(BE59+BF59+BG59) -> 0 | BE59: =AG59 -> 80.6 | BF59: 83.5 | BG59: 115.7 | BH59: =BG59/D59 -> 0.41350965 | BI59: 92.7 | BJ59: =BG59-BI59 -> 23 | BK59: =BJ59/D59 -> 0.082201573 | BL59: =DD59/(D59) -> 0.02038599 | BM59: =DD59/(CV59+CW59) -> 0.1765507 | BN59: =CQ59*DF59 -> 0.20924431 | BO59: =BJ59/I59 -> 0.65527066 | BP59: 18.628 | BQ59: =L59 -> 41.1 | BX59: 27.26 | BY59: 0.515 | BZ59: 1.431 | CA59: 0.17 | CB59: 1.402 | CC59: =CD59+CE59 -> 0.527 | CD59: 1.342 | CE59: -0.815 | CF59: 0.524 | CG59: =BY59+BZ59+CA59+CB59+CD59+CE59+CF59 -> 4.569 | CH59: =BX59-CG59 -> 22.691 | CI59: =BY59/$BX59 -> 0.01889215 | CJ59: =BZ59/$BX59 -> 0.052494497 | CK59: =CA59/$BX59 -> 0.0062362436 | CL59: =CB59/$BX59 -> 0.051430668 | CM59: =CN59+CO59 -> 0.019332355 | CN59: =CD59/$BX59 -> 0.04922964 | CO59: =CE59/$BX59 -> -0.029897285 | CP59: =CF59/$BX59 -> 0.019222304 | CQ59: =CG59/$BX59 -> 0.16760822 | CR59: =CQ59*N59 -> 0.024620078 | CS59: =BX59 -> 27.26 | CT59: =BX59 -> 27.26 | CU59: =CT59-(CV59+CW59) -> -5.048 | CV59: 18.628 | CW59: 13.68 | CX59: 0.394 | CY59: 0.733 | CZ59: 0.159 | DA59: 1.073 | DB59: 2.989 | DC59: 0.356 | DD59: =DC59+DB59+DA59+CZ59+CY59+CX59 -> 5.704 | DF59: =DD59/CG59 -> 1.2484132 | DG59: =CW59-DD59 -> 7.976 | DH59: =DD59/CW59 -> 0.41695906 | DI59: =CW59/(CW59+CV59) -> 0.42342454 | DJ59: 9.525 | DK59: 0.479 | DL59: 0.443 | DM59: 0.205 | DN59: 1.577 | DO59: -2.043 | DP59: -0.062 | DQ59: 0.139 | DR59: =DQ59+DO59+DN59+DM59+DL59+DK59 -> 0.8 | DS59: =DJ59-DR59 -> 8.725 | DT59: =DR59/DJ59 -> 0.083989501 | DU59: =DJ59-CW59 -> -4.155 | DV59: -4.155 | DW59: =DK59-CX59 -> 0.085 | DX59: =DL59-CY59 -> -0.29 | DY59: =DM59-CZ59 -> 0.046 | DZ59: =DN59-DA59 -> 0.504 | EA59: =DO59-DB59 -> -5.032 | EB59: =DQ59-DC59 -> -0.217 | EC59: =EB59+EA59+DZ59+DY59+DX59+DW59 -> -4.904 | ED59: =DU59-EC59 -> 0.749 | EE59: =EC59/DU59 -> 1.1802647 | EF59: 7.249 | EG59: 0.093 | EH59: 0.252 | EI59: =(EI58+EI60)/2 -> 0.0205 | EJ59: 0.463 | EK59: 1.26 | EL59: 0.035 | EM59: =EL59+EK59+EJ59+EI59+EH59+EG59 -> 2.1235 | EN59: =EF59-EM59 -> 5.1255 | EO59: =EM59/EF59 -> 0.29293696 | EP59: 212.15 | EQ59: 2.517 | ER59: 6.917 | ES59: 1.24 | ET59: 14.257 | EU59: -3.352 | EV59: 11.4 | EW59: 1.881 | EX59: =EW59+EU59+ET59+ES59+ER59+EQ59 -> 23.46 | EY59: =EP59-EX59 -> 188.69 | EZ59: =EX59/EP59 -> 0.11058214 | FA59: =(BX59+(EP59-EP58)-DJ59)/EP58 -> 0.10653568 | FB59: =(BY59+(EQ59-EQ58)-DK59)/EQ58 -> 0.25701625 | FC59: =(BZ59+(ER59-ER58)-DL59)/ER58 -> 0.1693787 | FD59: =(CA59+(ES59-ES58)-DM59)/ES58 -> 0.097449909 | FE59: =(CB59+(ET59-ET58)-DN59)/ET58 -> 0.094767939 | FF59: =(CC59+(EU59-EU58)-DO59)/EU58 -> -0.57661072 | FG59: =(CD59+(EV59-EV58)-DP59)/EV58 -> 0.11155482 | FH59: =(CF59+(EW59-EW58)-DQ59)/EW58 -> 0.31744186 | FI59: =(CG59+(EX59-EX58)-DR59)/EX58 -> 0.20349171 | FJ59: =(CH59+(EY59-EY58)-DS59)/EY58 -> 0.09468635 | FK59: =(CH59+AO59+(EY59-EY58)-DS59)/EY58 -> 0.21082284 | FL59: =BX59/EP58 -> 0.13121414 | FM59: =BY59/EQ58 -> 0.25356967 | FN59: =BZ59/ER58 -> 0.21168639 | FO59: =CA59/ES58 -> 0.15482696 | FP59: =CB59/ET58 -> 0.10899479 | FQ59: =CC59/EU58 -> -0.28532756 | FR59: =CD59/EV58 -> 0.11650317 | FS59: =CF59/EW58 -> 0.30465116 | FT59: =CG59/EX58 -> 0.20194475 | FU59: =CH59/EY58 -> 0.12256991
B60: 1984 | C60: 3444 | D60: 337.9 | E60: =D60/C60 -> 0.09811266 | F60: =D60-(G60+I60) -> 0 | G60: =D60-I60 -> 301.3 | H60: =G60/C60 -> 0.087485482 | I60: 36.6 | J60: =I60/C60 -> 0.010627178 | K60: =I60/D60 -> 0.10831607 | L60: 46.2 | M60: =L60/C60 -> 0.013414634 | N60: =L60/D60 -> 0.13672684 | O60: =D60 -> 337.9 | P60: =O60-(Q60+R60+T60+U60+X60-V60) -> 0 | Q60: 232.5 | R60: 41.2 | S60: =R60/D60 -> 0.12192956 | T60: 16.4 | U60: 39.6 | V60: 46.7 | W60: =V60/D60 -> 0.13820657 | X60: =O60-(Q60+R60+T60+U60-V60) -> 54.9 | AC60: =AC61*AF60/AF61 -> 6.0226234 | AD60: =AC60/D60 -> 0.017823686 | AF60: 6.5702536 | AG60: 97.5 | AH60: =AG60/C60 -> 0.028310105 | AI60: =(AG60-AN60)/C60 -> 0.023635308 | AJ60: =AG60-(AK60+AL60+AM60+AN60) -> -0.1 | AK60: 59.2 | AL60: 18.8 | AM60: 3.5 | AN60: 16.1 | AO60: 23.1 | AP60: 58.0025 | AT60: =(O60-AG60)/C60 -> 0.069802555 | AU60: 0.46 | AV60: =(AK60+AL60)/(G60+L60-T60) -> 0.23557838 | AW60: =(AK60+AL60)/(G60+L60-T60-AE60) -> 0.23557838 | AX60: =(AG60-AN60-AM60)/(G60+L60-T60+V60) -> 0.20619375 | AY60: =(AG60-AN60-AM60+AO60)/(G60+L60-T60+AO60) -> 0.28514963 | AZ60: =(AG60-AN60-AM60+AO60)/(G60+L60-T60+AO60-AC60) -> 0.29008203 | BA60: =(AG60-AN60)/Q60 -> 0.35010753 | BB60: =(AG60-AN60)/(Q60+R60) -> 0.29740592 | BC60: =D60 -> 337.9 | BD60: =BC60-(BE60+BF60+BG60) -> 0.1 | BE60: =AG60 -> 97.5 | BF60: 90.8 | BG60: 149.5 | BH60: =BG60/D60 -> 0.44243859 | BI60: 125.3 | BJ60: =BG60-BI60 -> 24.2 | BK60: =BJ60/D60 -> 0.071618822 | BL60: =DD60/(D60) -> 0.016424978 | BM60: =DD60/(CV60+CW60) -> 0.15291784 | BN60: =CQ60*DF60 -> 0.18051129 | BO60: =BJ60/I60 -> 0.66120219 | BP60: 18.687 | BQ60: =L60 -> 46.2 | BX60: 30.746 | BY60: 0.527 | BZ60: 1.213 | CA60: 0.123 | CB60: 1.64 | CC60: =CD60+CE60 -> 0.306 | CD60: 1.507 | CE60: -1.201 | CF60: 0.524 | CG60: =BY60+BZ60+CA60+CB60+CD60+CE60+CF60 -> 4.333 | CH60: =BX60-CG60 -> 26.413 | CI60: =BY60/$BX60 -> 0.017140441 | CJ60: =BZ60/$BX60 -> 0.039452286 | CK60: =CA60/$BX60 -> 0.0040005204 | CL60: =CB60/$BX60 -> 0.053340272 | CM60: =CN60+CO60 -> 0.0099525141 | CN60: =CD60/$BX60 -> 0.049014506 | CO60: =CE60/$BX60 -> -0.039061992 | CP60: =CF60/$BX60 -> 0.017042867 | CQ60: =CG60/$BX60 -> 0.1409289 | CR60: =CQ60*N60 -> 0.019268764 | CS60: =BX60 -> 30.746 | CT60: =BX60 -> 30.746 | CU60: =CT60-(CV60+CW60) -> -5.548 | CV60: 18.687 | CW60: 17.607 | CX60: 0.447 | CY60: 0.429 | CZ60: 0.109 | DA60: 1.076 | DB60: 3.232 | DC60: 0.257 | DD60: =DC60+DB60+DA60+CZ60+CY60+CX60 -> 5.55 | DF60: =DD60/CG60 -> 1.2808678 | DG60: =CW60-DD60 -> 12.057 | DH60: =DD60/CW60 -> 0.31521554 | DI60: =CW60/(CW60+CV60) -> 0.48512151 | DJ60: 13.045 | DK60: 0.463 | DL60: -0.051 | DM60: 0.122 | DN60: 0.755 | DO60: 0.39 | DP60: 1.178 | DQ60: 0.225 | DR60: =DQ60+DO60+DN60+DM60+DL60+DK60 -> 1.904 | DS60: =DJ60-DR60 -> 11.141 | DT60: =DR60/DJ60 -> 0.14595631 | DU60: =DJ60-CW60 -> -4.562 | DV60: -4.562 | DW60: =DK60-CX60 -> 0.016 | DX60: =DL60-CY60 -> -0.48 | DY60: =DM60-CZ60 -> 0.013 | DZ60: =DN60-DA60 -> -0.321 | EA60: =DO60-DB60 -> -2.842 | EB60: =DQ60-DC60 -> -0.032 | EC60: =EB60+EA60+DZ60+DY60+DX60+DW60 -> -3.646 | ED60: =DU60-EC60 -> -0.916 | EE60: =EC60/DU60 -> 0.79921087 | EF60: 2.394 | EG60: 0.09 | EH60: 0.129 | EI60: 0.018 | EJ60: -0.14 | EK60: 1.03 | EL60: 0.022 | EM60: =EL60+EK60+EJ60+EI60+EH60+EG60 -> 1.149 | EN60: =EF60-EM60 -> 1.245 | EO60: =EM60/EF60 -> 0.47994987 | EP60: 218.093 | EQ60: 2.964 | ER60: 6.207 | ES60: 0.493 | ET60: 14.877 | EU60: -2.655 | EV60: 13.322 | EW60: 2.018 | EX60: =EW60+EU60+ET60+ES60+ER60+EQ60 -> 23.904 | EY60: =EP60-EX60 -> 194.189 | EZ60: =EX60/EP60 -> 0.10960462 | FA60: =(BX60+(EP60-EP59)-DJ60)/EP59 -> 0.11144945 | FB60: =(BY60+(EQ60-EQ59)-DK60)/EQ59 -> 0.20301947 | FC60: =(BZ60+(ER60-ER59)-DL60)/ER59 -> 0.080092526 | FD60: =(CA60+(ES60-ES59)-DM60)/ES59 -> -0.6016129 | FE60: =(CB60+(ET60-ET59)-DN60)/ET59 -> 0.10556218 | FF60: =(CC60+(EU60-EU59)-DO60)/EU59 -> -0.18287589 | FG60: =(CD60+(EV60-EV59)-DP60)/EV59 -> 0.19745614 | FH60: =(CF60+(EW60-EW59)-DQ60)/EW59 -> 0.2317916 | FI60: =(CG60+(EX60-EX59)-DR60)/EX59 -> 0.12246377 | FJ60: =(CH60+(EY60-EY59)-DS60)/EY59 -> 0.11008003 | FK60: =(CH60+AO60+(EY60-EY59)-DS60)/EY59 -> 0.23250305 | FL60: =BX60/EP59 -> 0.14492576 | FM60: =BY60/EQ59 -> 0.20937624 | FN60: =BZ60/ER59 -> 0.17536504 | FO60: =CA60/ES59 -> 0.099193548 | FP60: =CB60/ET59 -> 0.11503121 | FQ60: =CC60/EU59 -> -0.091288783 | FR60: =CD60/EV59 -> 0.13219298 | FS60: =CF60/EW59 -> 0.27857523 | FT60: =CG60/EX59 -> 0.18469736 | FU60: =CH60/EY59 -> 0.13998092
B61: 1985 | C61: 3684.2 | D61: 354.5 | E61: =D61/C61 -> 0.096221703 | F61: =D61-(G61+I61) -> 0 | G61: =D61-I61 -> 316.4 | H61: =G61/C61 -> 0.085880245 | I61: 38.1 | J61: =I61/C61 -> 0.010341458 | K61: =I61/D61 -> 0.10747532 | L61: 46.8 | M61: =L61/C61 -> 0.012702893 | N61: =L61/D61 -> 0.13201693 | O61: =D61 -> 354.5 | P61: =O61-(Q61+R61+T61+U61+X61-V61) -> 0 | Q61: 240.1 | R61: 48.8 | S61: =R61/D61 -> 0.13765867 | T61: 16.3 | U61: 64.8 | V61: 75.2 | W61: =V61/D61 -> 0.21212976 | X61: =O61-(Q61+R61+T61+U61-V61) -> 59.7 | AC61: =AC62*AF61/AF62 -> 6.0727121 | AD61: =AC61/D61 -> 0.017130358 | AF61: 6.6248968 | AG61: 99.4 | AH61: =AG61/C61 -> 0.026980077 | AI61: =(AG61-AN61)/C61 -> 0.022148635 | AJ61: =AG61-(AK61+AL61+AM61+AN61) -> 0.1 | AK61: 58.4 | AL61: 20.2 | AM61: 2.9 | AN61: 17.8 | AO61: 26.7 | AP61: 61.784 | AT61: =(O61-AG61)/C61 -> 0.069241626 | AU61: 0.46 | AV61: =(AK61+AL61)/(G61+L61-T61) -> 0.22657826 | AW61: =(AK61+AL61)/(G61+L61-T61-AE61) -> 0.22657826 | AX61: =(AG61-AN61-AM61)/(G61+L61-T61+V61) -> 0.18644871 | AY61: =(AG61-AN61-AM61+AO61)/(G61+L61-T61+AO61) -> 0.28211991 | AZ61: =(AG61-AN61-AM61+AO61)/(G61+L61-T61+AO61-AC61) -> 0.28678143 | BA61: =(AG61-AN61)/Q61 -> 0.33985839 | BB61: =(AG61-AN61)/(Q61+R61) -> 0.28245067 | BC61: =D61 -> 354.5 | BD61: =BC61-(BE61+BF61+BG61) -> 0.1 | BE61: =AG61 -> 99.4 | BF61: 97.5 | BG61: 157.5 | BH61: =BG61/D61 -> 0.44428773 | BI61: 131.3 | BJ61: =BG61-BI61 -> 26.2 | BK61: =BJ61/D61 -> 0.073906911 | BL61: =DD61/(D61) -> 0.012434415 | BM61: =DD61/(CV61+CW61) -> 0.12985712 | BN61: =CQ61*DF61 -> 0.15317256 | BO61: =BJ61/I61 -> 0.68766404 | BP61: 19.78 | BQ61: =L61 -> 46.8 | BX61: 28.778 | BY61: 0.708 | BZ61: 1.514 | CA61: 0.074 | CB61: 1.479 | CC61: =CD61+CE61 -> 0.347 | CD61: 1.311 | CE61: -0.964 | CF61: 0.402 | CG61: =BY61+BZ61+CA61+CB61+CD61+CE61+CF61 -> 4.524 | CH61: =BX61-CG61 -> 24.254 | CI61: =BY61/$BX61 -> 0.024602127 | CJ61: =BZ61/$BX61 -> 0.052609632 | CK61: =CA61/$BX61 -> 0.0025714087 | CL61: =CB61/$BX61 -> 0.051393426 | CM61: =CN61+CO61 -> 0.012057822 | CN61: =CD61/$BX61 -> 0.045555633 | CO61: =CE61/$BX61 -> -0.033497811 | CP61: =CF61/$BX61 -> 0.013969004 | CQ61: =CG61/$BX61 -> 0.15720342 | CR61: =CQ61*N61 -> 0.020753512 | CS61: =BX61 -> 28.778 | CT61: =BX61 -> 28.778 | CU61: =CT61-(CV61+CW61) -> -5.167 | CV61: 19.78 | CW61: 14.165 | CX61: 0.589 | CY61: 0.749 | CZ61: 0.011 | DA61: 0.957 | DB61: 1.949 | DC61: 0.153 | DD61: =DC61+DB61+DA61+CZ61+CY61+CX61 -> 4.408 | DF61: =DD61/CG61 -> 0.97435897 | DG61: =CW61-DD61 -> 9.757 | DH61: =DD61/CW61 -> 0.31118955 | DI61: =CW61/(CW61+CV61) -> 0.41729268 | DJ61: 13.388 | DK61: 0.645 | DL61: 0.641 | DM61: 0.053 | DN61: 0.308 | DO61: 4.685 | DP61: 0.325 | DQ61: -0.03 | DR61: =DQ61+DO61+DN61+DM61+DL61+DK61 -> 6.302 | DS61: =DJ61-DR61 -> 7.086 | DT61: =DR61/DJ61 -> 0.47072005 | DU61: =DJ61-CW61 -> -0.777 | DV61: -0.777 | DW61: =DK61-CX61 -> 0.056 | DX61: =DL61-CY61 -> -0.108 | DY61: =DM61-CZ61 -> 0.042 | DZ61: =DN61-DA61 -> -0.649 | EA61: =DO61-DB61 -> 2.736 | EB61: =DQ61-DC61 -> -0.183 | EC61: =EB61+EA61+DZ61+DY61+DX61+DW61 -> 1.894 | ED61: =DU61-EC61 -> -2.671 | EE61: =EC61/DU61 -> -2.4375804 | EF61: -1.672 | EG61: 0.039 | EH61: -0.035 | EI61: 0.024 | EJ61: -0.093 | EK61: -1.342 | EL61: 0.056 | EM61: =EL61+EK61+EJ61+EI61+EH61+EG61 -> -1.351 | EN61: =EF61-EM61 -> -0.321 | EO61: =EM61/EF61 -> 0.80801435 | EP61: 238.369 | EQ61: 3.762 | ER61: 7.552 | ES61: 0.795 | ET61: 15.888 | EU61: 2.201 | EV61: 13.343 | EW61: 2.008 | EX61: =EW61+EU61+ET61+ES61+ER61+EQ61 -> 32.206 | EY61: =EP61-EX61 -> 206.163 | EZ61: =EX61/EP61 -> 0.13510985 | FA61: =(BX61+(EP61-EP60)-DJ61)/EP60 -> 0.16353574 | FB61: =(BY61+(EQ61-EQ60)-DK61)/EQ60 -> 0.29048583 | FC61: =(BZ61+(ER61-ER60)-DL61)/ER60 -> 0.35733849 | FD61: =(CA61+(ES61-ES60)-DM61)/ES60 -> 0.65517241 | FE61: =(CB61+(ET61-ET60)-DN61)/ET60 -> 0.14666936 | FF61: =(CC61+(EU61-EU60)-DO61)/EU60 -> -0.19510358 | FG61: =(CD61+(EV61-EV60)-DP61)/EV60 -> 0.075589251 | FH61: =(CF61+(EW61-EW60)-DQ61)/EW60 -> 0.20911794 | FI61: =(CG61+(EX61-EX60)-DR61)/EX60 -> 0.27292503 | FJ61: =(CH61+(EY61-EY60)-DS61)/EY60 -> 0.15007029 | FK61: =(CH61+AO61+(EY61-EY60)-DS61)/EY60 -> 0.28756521 | FL61: =BX61/EP60 -> 0.13195288 | FM61: =BY61/EQ60 -> 0.2388664 | FN61: =BZ61/ER60 -> 0.24391816 | FO61: =CA61/ES60 -> 0.15010142 | FP61: =CB61/ET60 -> 0.099415205 | FQ61: =CC61/EU60 -> -0.1306968 | FR61: =CD61/EV60 -> 0.098408647 | FS61: =CF61/EW60 -> 0.19920714 | FT61: =CG61/EX60 -> 0.18925703 | FU61: =CH61/EY60 -> 0.12489894
B62: 1986 | C62: 3848.2 | D62: 324.4 | E62: =D62/C62 -> 0.084299153 | F62: =D62-(G62+I62) -> 0 | G62: =D62-I62 -> 284.9 | H62: =G62/C62 -> 0.074034614 | I62: 39.5 | J62: =I62/C62 -> 0.010264539 | K62: =I62/D62 -> 0.12176326 | L62: 48.7 | M62: =L62/C62 -> 0.012655267 | N62: =L62/D62 -> 0.1501233 | O62: =D62 -> 324.4 | P62: =O62-(Q62+R62+T62+U62+X62-V62) -> 0 | Q62: 274.4 | R62: 53.8 | S62: =R62/D62 -> 0.16584464 | T62: 15.5 | U62: 58.2 | V62: 124 | W62: =V62/D62 -> 0.38224414 | X62: =O62-(Q62+R62+T62+U62-V62) -> 46.5 | AC62: =AC63*AF62/AF63 -> 7.0384889 | AD62: =AC62/D62 -> 0.021696945 | AF62: 7.6784907 | AG62: 109.7 | AH62: =AG62/C62 -> 0.028506834 | AI62: =(AG62-AN62)/C62 -> 0.023881295 | AJ62: =AG62-(AK62+AL62+AM62+AN62) -> 0.1 | AK62: 65.9 | AL62: 22.7 | AM62: 3.2 | AN62: 17.8 | AO62: 24.4 | AP62: 68.33875 | AT62: =(O62-AG62)/C62 -> 0.055792318 | AU62: 0.46 | AV62: =(AK62+AL62)/(G62+L62-T62) -> 0.27852876 | AW62: =(AK62+AL62)/(G62+L62-T62-AE62) -> 0.27852876 | AX62: =(AG62-AN62-AM62)/(G62+L62-T62+V62) -> 0.20063334 | AY62: =(AG62-AN62-AM62+AO62)/(G62+L62-T62+AO62) -> 0.33021898 | AZ62: =(AG62-AN62-AM62+AO62)/(G62+L62-T62+AO62-AC62) -> 0.33714747 | BA62: =(AG62-AN62)/Q62 -> 0.33491254 | BB62: =(AG62-AN62)/(Q62+R62) -> 0.28001219 | BC62: =D62 -> 324.4 | BD62: =BC62-(BE62+BF62+BG62) -> 0 | BE62: =AG62 -> 109.7 | BF62: 106.2 | BG62: 108.5 | BH62: =BG62/D62 -> 0.33446363 | BI62: 86.9 | BJ62: =BG62-BI62 -> 21.6 | BK62: =BJ62/D62 -> 0.066584464 | BL62: =DD62/(D62) -> 0.013159679 | BM62: =DD62/(CV62+CW62) -> 0.11942595 | BN62: =CQ62*DF62 -> 0.13753222 | BO62: =BJ62/I62 -> 0.54683544 | BP62: 26.077 | BQ62: =L62 -> 48.7 | BX62: 31.04 | BY62: 0.774 | BZ62: 2.332 | CA62: 0.114 | CB62: 1.666 | CC62: =CD62+CE62 -> 0.598 | CD62: 1.579 | CE62: -0.981 | CF62: 0.519 | CG62: =BY62+BZ62+CA62+CB62+CD62+CE62+CF62 -> 6.003 | CH62: =BX62-CG62 -> 25.037 | CI62: =BY62/$BX62 -> 0.024935567 | CJ62: =BZ62/$BX62 -> 0.075128866 | CK62: =CA62/$BX62 -> 0.0036726804 | CL62: =CB62/$BX62 -> 0.05367268 | CM62: =CN62+CO62 -> 0.019265464 | CN62: =CD62/$BX62 -> 0.050869845 | CO62: =CE62/$BX62 -> -0.031604381 | CP62: =CF62/$BX62 -> 0.016720361 | CQ62: =CG62/$BX62 -> 0.19339562 | CR62: =CQ62*N62 -> 0.029033189 | CS62: =BX62 -> 31.04 | CT62: =BX62 -> 31.04 | CU62: =CT62-(CV62+CW62) -> -4.706 | CV62: 26.077 | CW62: 9.669 | CX62: 0.654 | CY62: 1.835 | CZ62: 0.094 | DA62: 0.427 | DB62: 0.998 | DC62: 0.261 | DD62: =DC62+DB62+DA62+CZ62+CY62+CX62 -> 4.269 | DF62: =DD62/CG62 -> 0.71114443 | DG62: =CW62-DD62 -> 5.4 | DH62: =DD62/CW62 -> 0.44151412 | DI62: =CW62/(CW62+CV62) -> 0.2704918 | DJ62: 19.641 | DK62: 0.606 | DL62: 3.396 | DM62: 0.027 | DN62: 0.235 | DO62: 6.141 | DP62: 1.338 | DQ62: 0.29 | DR62: =DQ62+DO62+DN62+DM62+DL62+DK62 -> 10.695 | DS62: =DJ62-DR62 -> 8.946 | DT62: =DR62/DJ62 -> 0.54452421 | DU62: =DJ62-CW62 -> 9.972 | DV62: 9.972 | DW62: =DK62-CX62 -> -0.048 | DX62: =DL62-CY62 -> 1.561 | DY62: =DM62-CZ62 -> -0.067 | DZ62: =DN62-DA62 -> -0.192 | EA62: =DO62-DB62 -> 5.143 | EB62: =DQ62-DC62 -> 0.029 | EC62: =EB62+EA62+DZ62+DY62+DX62+DW62 -> 6.426 | ED62: =DU62-EC62 -> 3.546 | EE62: =EC62/DU62 -> 0.64440433 | EF62: 1.147 | EG62: 0.008 | EH62: =(EH61+EH63)/2 -> -0.02 | EI62: 0.021 | EJ62: -0.281 | EK62: -0.083 | EL62: 0.007 | EM62: =EL62+EK62+EJ62+EI62+EH62+EG62 -> -0.348 | EN62: =EF62-EM62 -> 1.495 | EO62: =EM62/EF62 -> -0.30340017 | EP62: 270.472 | EQ62: 4.412 | ER62: 12.203 | ES62: 0.957 | ET62: 16.608 | EU62: 8.058 | EV62: 15.717 | EW62: 2.481 | EX62: =EW62+EU62+ET62+ES62+ER62+EQ62 -> 44.719 | EY62: =EP62-EX62 -> 225.753 | EZ62: =EX62/EP62 -> 0.16533689 | FA62: =(BX62+(EP62-EP61)-DJ62)/EP61 -> 0.18249856 | FB62: =(BY62+(EQ62-EQ61)-DK62)/EQ61 -> 0.21743753 | FC62: =(BZ62+(ER62-ER61)-DL62)/ER61 -> 0.47497352 | FD62: =(CA62+(ES62-ES61)-DM62)/ES61 -> 0.31320755 | FE62: =(CB62+(ET62-ET61)-DN62)/ET61 -> 0.1353852 | FF62: =(CC62+(EU62-EU61)-DO62)/EU61 -> 0.14266243 | FG62: =(CD62+(EV62-EV61)-DP62)/EV61 -> 0.19598291 | FH62: =(CF62+(EW62-EW61)-DQ62)/EW61 -> 0.34960159 | FI62: =(CG62+(EX62-EX61)-DR62)/EX61 -> 0.24284295 | FJ62: =(CH62+(EY62-EY61)-DS62)/EY61 -> 0.17307179 | FK62: =(CH62+AO62+(EY62-EY61)-DS62)/EY61 -> 0.29142475 | FL62: =BX62/EP61 -> 0.13021828 | FM62: =BY62/EQ61 -> 0.20574163 | FN62: =BZ62/ER61 -> 0.30879237 | FO62: =CA62/ES61 -> 0.14339623 | FP62: =CB62/ET61 -> 0.10485901 | FQ62: =CC62/EU61 -> 0.27169468 | FR62: =CD62/EV61 -> 0.1183392 | FS62: =CF62/EW61 -> 0.25846614 | FT62: =CG62/EX61 -> 0.18639384 | FU62: =CH62/EY61 -> 0.12144274
B63: 1987 | C63: 4119.2 | D63: 366 | E63: =D63/C63 -> 0.088852204 | F63: =D63-(G63+I63) -> 0 | G63: =D63-I63 -> 318 | H63: =G63/C63 -> 0.077199456 | I63: 48 | J63: =I63/C63 -> 0.011652748 | K63: =I63/D63 -> 0.13114754 | L63: 58.9 | M63: =L63/C63 -> 0.014298893 | N63: =L63/D63 -> 0.16092896 | O63: =D63 -> 366 | P63: =O63-(Q63+R63+T63+U63+X63-V63) -> 0 | Q63: 336.8 | R63: 56.6 | S63: =R63/D63 -> 0.15464481 | T63: 16.2 | U63: 35.2 | V63: 82.9 | W63: =V63/D63 -> 0.22650273 | X63: =O63-(Q63+R63+T63+U63-V63) -> 4.1 | AC63: =AC64*AF63/AF64 -> 16.824837 | AD63: =AC63/D63 -> 0.045969501 | AF63: 18.3547 | AG63: 130.4 | AH63: =AG63/C63 -> 0.031656632 | AI63: =(AG63-AN63)/C63 -> 0.027359681 | AJ63: =AG63-(AK63+AL63+AM63+AN63) -> -0.1 | AK63: 85.5 | AL63: 23.9 | AM63: 3.4 | AN63: 17.7 | AO63: 23.5 | AP63: 86.5715 | AT63: =(O63-AG63)/C63 -> 0.057195572 | AU63: 0.4 | AV63: =(AK63+AL63)/(G63+L63-T63) -> 0.30329914 | AW63: =(AK63+AL63)/(G63+L63-T63-AE63) -> 0.30329914 | AX63: =(AG63-AN63-AM63)/(G63+L63-T63+V63) -> 0.24639315 | AY63: =(AG63-AN63-AM63+AO63)/(G63+L63-T63+AO63) -> 0.34565331 | AZ63: =(AG63-AN63-AM63+AO63)/(G63+L63-T63+AO63-AC63) -> 0.36148334 | BA63: =(AG63-AN63)/Q63 -> 0.33461995 | BB63: =(AG63-AN63)/(Q63+R63) -> 0.28647687 | BC63: =D63 -> 366 | BD63: =BC63-(BE63+BF63+BG63) -> 0.1 | BE63: =AG63 -> 130.4 | BF63: 112.3 | BG63: 123.2 | BH63: =BG63/D63 -> 0.33661202 | BI63: 91.9 | BJ63: =BG63-BI63 -> 31.3 | BK63: =BJ63/D63 -> 0.085519126 | BL63: =DD63/(D63) -> 0.014314208 | BM63: =DD63/(CV63+CW63) -> 0.11983622 | BN63: =CQ63*DF63 -> 0.13088338 | BO63: =BJ63/I63 -> 0.65208333 | BP63: 25.264 | BQ63: =L63 -> 58.9 | BX63: 40.028 | BY63: 1.046 | BZ63: 2.976 | CA63: 0.084 | CB63: 2.705 | CC63: =CD63+CE63 -> 0.438 | CD63: 1.702 | CE63: -1.264 | CF63: 0.729 | CG63: =BY63+BZ63+CA63+CB63+CD63+CE63+CF63 -> 7.978 | CH63: =BX63-CG63 -> 32.05 | CI63: =BY63/$BX63 -> 0.026131708 | CJ63: =BZ63/$BX63 -> 0.074347956 | CK63: =CA63/$BX63 -> 0.002098531 | CL63: =CB63/$BX63 -> 0.067577696 | CM63: =CN63+CO63 -> 0.01094234 | CN63: =CD63/$BX63 -> 0.042520236 | CO63: =CE63/$BX63 -> -0.031577895 | CP63: =CF63/$BX63 -> 0.018212251 | CQ63: =CG63/$BX63 -> 0.19931048 | CR63: =CQ63*N63 -> 0.032074829 | CS63: =BX63 -> 40.028 | CT63: =BX63 -> 40.028 | CU63: =CT63-(CV63+CW63) -> -3.69 | CV63: 25.264 | CW63: 18.454 | CX63: 0.767 | CY63: 1.212 | CZ63: -0.006 | DA63: 1.508 | DB63: 1.346 | DC63: 0.412 | DD63: =DC63+DB63+DA63+CZ63+CY63+CX63 -> 5.239 | DF63: =DD63/CG63 -> 0.65668087 | DG63: =CW63-DD63 -> 13.215 | DH63: =DD63/CW63 -> 0.28389509 | DI63: =CW63/(CW63+CV63) -> 0.42211446 | DJ63: 30.154 | DK63: 0.909 | DL63: 2.104 | DM63: -0.047 | DN63: 1.458 | DO63: 6.029 | DP63: 2.795 | DQ63: 0.29 | DR63: =DQ63+DO63+DN63+DM63+DL63+DK63 -> 10.743 | DS63: =DJ63-DR63 -> 19.411 | DT63: =DR63/DJ63 -> 0.35627114 | DU63: =DJ63-CW63 -> 11.7 | DV63: 11.7 | DW63: =DK63-CX63 -> 0.142 | DX63: =DL63-CY63 -> 0.892 | DY63: =DM63-CZ63 -> -0.041 | DZ63: =DN63-DA63 -> -0.05 | EA63: =DO63-DB63 -> 4.683 | EB63: =DQ63-DC63 -> -0.122 | EC63: =EB63+EA63+DZ63+DY63+DX63+DW63 -> 5.504 | ED63: =DU63-EC63 -> 6.196 | EE63: =EC63/DU63 -> 0.47042735 | EF63: 4.868 | EG63: =(EG62+EG64)/2 -> -0.005 | EH63: -0.005 | EI63: 0.07 | EJ63: -0.361 | EK63: -0.11 | EL63: 0.103 | EM63: =EL63+EK63+EJ63+EI63+EH63+EG63 -> -0.308 | EN63: =EF63-EM63 -> 5.176 | EO63: =EM63/EF63 -> -0.063270337 | EP63: 326.253 | EQ63: 5.53 | ER63: 15.507 | ES63: 0.874 | ET63: 19.691 | EU63: 15.801 | EV63: 19.166 | EW63: 2.722 | EX63: =EW63+EU63+ET63+ES63+ER63+EQ63 -> 60.125 | EY63: =EP63-EX63 -> 266.128 | EZ63: =EX63/EP63 -> 0.18428949 | FA63: =(BX63+(EP63-EP62)-DJ63)/EP62 -> 0.24274232 | FB63: =(BY63+(EQ63-EQ62)-DK63)/EQ62 -> 0.2844515 | FC63: =(BZ63+(ER63-ER62)-DL63)/ER62 -> 0.34221093 | FD63: =(CA63+(ES63-ES62)-DM63)/ES62 -> 0.05015674 | FE63: =(CB63+(ET63-ET62)-DN63)/ET62 -> 0.26071773 | FF63: =(CC63+(EU63-EU62)-DO63)/EU62 -> 0.26706379 | FG63: =(CD63+(EV63-EV62)-DP63)/EV62 -> 0.14990138 | FH63: =(CF63+(EW63-EW62)-DQ63)/EW62 -> 0.27408303 | FI63: =(CG63+(EX63-EX62)-DR63)/EX62 -> 0.28267627 | FJ63: =(CH63+(EY63-EY62)-DS63)/EY62 -> 0.23483187 | FK63: =(CH63+AO63+(EY63-EY62)-DS63)/EY62 -> 0.33892794 | FL63: =BX63/EP62 -> 0.14799314 | FM63: =BY63/EQ62 -> 0.23708069 | FN63: =BZ63/ER62 -> 0.24387446 | FO63: =CA63/ES62 -> 0.087774295 | FP63: =CB63/ET62 -> 0.16287331 | FQ63: =CC63/EU62 -> 0.05435592 | FR63: =CD63/EV62 -> 0.10829039 | FS63: =CF63/EW62 -> 0.29383313 | FT63: =CG63/EX62 -> 0.17840292 | FU63: =CH63/EY62 -> 0.14196932
B64: 1988 | C64: 4493.4 | D64: 414.9 | E64: =D64/C64 -> 0.092335425 | F64: =D64-(G64+I64) -> 0 | G64: =D64-I64 -> 357.9 | H64: =G64/C64 -> 0.079650154 | I64: 57 | J64: =I64/C64 -> 0.012685272 | K64: =I64/D64 -> 0.1373825 | L64: 71.6 | M64: =L64/C64 -> 0.015934482 | N64: =L64/D64 -> 0.1725717 | O64: =D64 -> 414.9 | P64: =O64-(Q64+R64+T64+U64+X64-V64) -> 0 | Q64: 412.1 | R64: 60.9 | S64: =R64/D64 -> 0.14678236 | T64: 18.1 | U64: 26.5 | V64: 80.1 | W64: =V64/D64 -> 0.19305857 | X64: =O64-(Q64+R64+T64+U64-V64) -> -22.6 | AC64: =AC65*AF64/AF65 -> 32.386685 | AD64: =AC64/D64 -> 0.078059015 | AF64: 35.331569 | AG64: 141.6 | AH64: =AG64/C64 -> 0.031512886 | AI64: =(AG64-AN64)/C64 -> 0.027640539 | AJ64: =AG64-(AK64+AL64+AM64+AN64) -> 0 | AK64: 93.7 | AL64: 26 | AM64: 4.5 | AN64: 17.4 | AO64: 29.4 | AP64: 96.70375 | AT64: =(O64-AG64)/C64 -> 0.06082254 | AU64: 0.34 | AV64: =(AK64+AL64)/(G64+L64-T64) -> 0.29095771 | AW64: =(AK64+AL64)/(G64+L64-T64-AE64) -> 0.29095771 | AX64: =(AG64-AN64-AM64)/(G64+L64-T64+V64) -> 0.24354018 | AY64: =(AG64-AN64-AM64+AO64)/(G64+L64-T64+AO64) -> 0.33824864 | AZ64: =(AG64-AN64-AM64+AO64)/(G64+L64-T64+AO64-AC64) -> 0.36507135 | BA64: =(AG64-AN64)/Q64 -> 0.30138316 | BB64: =(AG64-AN64)/(Q64+R64) -> 0.26257928 | BC64: =D64 -> 414.9 | BD64: =BC64-(BE64+BF64+BG64) -> 0.1 | BE64: =AG64 -> 141.6 | BF64: 129.9 | BG64: 143.3 | BH64: =BG64/D64 -> 0.34538443 | BI64: 118.2 | BJ64: =BG64-BI64 -> 25.1 | BK64: =BJ64/D64 -> 0.060496505 | BL64: =DD64/(D64) -> 0.0055362738 | BM64: =DD64/(CV64+CW64) -> 0.041152337 | BN64: =CQ64*DF64 -> 0.044124709 | BO64: =BJ64/I64 -> 0.44035088 | BP64: 41.744 | BQ64: =L64 -> 71.6 | BX64: 52.057 | BY64: 1.172 | BZ64: 2.977 | CA64: 0.104 | CB64: 2.713 | CC64: =CD64+CE64 -> 1.969 | CD64: 2.214 | CE64: -0.245 | CF64: 0.825 | CG64: =BY64+BZ64+CA64+CB64+CD64+CE64+CF64 -> 9.76 | CH64: =BX64-CG64 -> 42.297 | CI64: =BY64/$BX64 -> 0.022513783 | CJ64: =BZ64/$BX64 -> 0.057187314 | CK64: =CA64/$BX64 -> 0.0019978101 | CL64: =CB64/$BX64 -> 0.05211595 | CM64: =CN64+CO64 -> 0.037823924 | CN64: =CD64/$BX64 -> 0.042530303 | CO64: =CE64/$BX64 -> -0.0047063795 | CP64: =CF64/$BX64 -> 0.015848013 | CQ64: =CG64/$BX64 -> 0.18748679 | CR64: =CQ64*N64 -> 0.032354915 | CS64: =BX64 -> 52.057 | CT64: =BX64 -> 52.057 | CU64: =CT64-(CV64+CW64) -> -3.76 | CV64: 41.744 | CW64: 14.073 | CX64: 0.668 | CY64: 1.217 | CZ64: 0.075 | DA64: -0.843 | DB64: 1.358 | DC64: -0.178 | DD64: =DC64+DB64+DA64+CZ64+CY64+CX64 -> 2.297 | DF64: =DD64/CG64 -> 0.23534836 | DG64: =CW64-DD64 -> 11.776 | DH64: =DD64/CW64 -> 0.16322035 | DI64: =CW64/(CW64+CV64) -> 0.25212749 | DJ64: 18.599 | DK64: 0.725 | DL64: 1.446 | DM64: 0.427 | DN64: -1.145 | DO64: 4.458 | DP64: 0.621 | DQ64: -0.191 | DR64: =DQ64+DO64+DN64+DM64+DL64+DK64 -> 5.72 | DS64: =DJ64-DR64 -> 12.879 | DT64: =DR64/DJ64 -> 0.30754342 | DU64: =DJ64-CW64 -> 4.526 | DV64: 4.525 | DW64: =DK64-CX64 -> 0.057 | DX64: =DL64-CY64 -> 0.229 | DY64: =DM64-CZ64 -> 0.352 | DZ64: =DN64-DA64 -> -0.302 | EA64: =DO64-DB64 -> 3.1 | EB64: =DQ64-DC64 -> -0.013 | EC64: =EB64+EA64+DZ64+DY64+DX64+DW64 -> 3.423 | ED64: =DU64-EC64 -> 1.103 | EE64: =EC64/DU64 -> 0.75629695 | EF64: -6.662 | EG64: -0.018 | EH64: -0.354 | EI64: -0.052 | EJ64: 0.311 | EK64: -2.807 | EL64: -0.142 | EM64: =EL64+EK64+EJ64+EI64+EH64+EG64 -> -3.062 | EN64: =EF64-EM64 -> -3.6 | EO64: =EM64/EF64 -> 0.45962174 | EP64: 347.179 | EQ64: 6.063 | ER64: 16.765 | ES64: 1.122 | ET64: 18.709 | EU64: 19.313 | EV64: 18.916 | EW64: 2.662 | EX64: =EW64+EU64+ET64+ES64+ER64+EQ64 -> 64.634 | EY64: =EP64-EX64 -> 282.545 | EZ64: =EX64/EP64 -> 0.18616909 | FA64: =(BX64+(EP64-EP63)-DJ64)/EP63 -> 0.16669272 | FB64: =(BY64+(EQ64-EQ63)-DK64)/EQ63 -> 0.17721519 | FC64: =(BZ64+(ER64-ER63)-DL64)/ER63 -> 0.17985426 | FD64: =(CA64+(ES64-ES63)-DM64)/ES63 -> -0.085812357 | FE64: =(CB64+(ET64-ET63)-DN64)/ET63 -> 0.14605657 | FF64: =(CC64+(EU64-EU63)-DO64)/EU63 -> 0.064742738 | FG64: =(CD64+(EV64-EV63)-DP64)/EV63 -> 0.070072003 | FH64: =(CF64+(EW64-EW63)-DQ64)/EW63 -> 0.35121234 | FI64: =(CG64+(EX64-EX63)-DR64)/EX63 -> 0.14218711 | FJ64: =(CH64+(EY64-EY63)-DS64)/EY63 -> 0.17222915 | FK64: =(CH64+AO64+(EY64-EY63)-DS64)/EY63 -> 0.28270231 | FL64: =BX64/EP63 -> 0.15956022 | FM64: =BY64/EQ63 -> 0.2119349 | FN64: =BZ64/ER63 -> 0.19197782 | FO64: =CA64/ES63 -> 0.11899314 | FP64: =CB64/ET63 -> 0.13777868 | FQ64: =CC64/EU63 -> 0.12461237 | FR64: =CD64/EV63 -> 0.11551706 | FS64: =CF64/EW63 -> 0.30308597 | FT64: =CG64/EX63 -> 0.16232848 | FU64: =CH64/EY63 -> 0.1589348
B65: 1989 | C65: 4782.2 | D65: 414.2 | E65: =D65/C65 -> 0.086612856 | F65: =D65-(G65+I65) -> 0 | G65: =D65-I65 -> 347.1 | H65: =G65/C65 -> 0.072581657 | I65: 67.1 | J65: =I65/C65 -> 0.014031199 | K65: =I65/D65 -> 0.16199903 | L65: 75.5 | M65: =L65/C65 -> 0.015787713 | N65: =L65/D65 -> 0.18227909 | O65: =D65 -> 414.2 | P65: =O65-(Q65+R65+T65+U65+X65-V65) -> 0 | Q65: 391.6 | R65: 66.7 | S65: =R65/D65 -> 0.16103332 | T65: 20.7 | U65: 24.9 | V65: 82.9 | W65: =V65/D65 -> 0.20014486 | X65: =O65-(Q65+R65+T65+U65-V65) -> -6.8 | AC65: =AC66*AF65/AF66 -> 33.734096 | AD65: =AC65/D65 -> 0.081443979 | AF65: 36.801499 | AG65: 146.1 | AH65: =AG65/C65 -> 0.030550793 | AI65: =(AG65-AN65)/C65 -> 0.026034043 | AJ65: =AG65-(AK65+AL65+AM65+AN65) -> 0.1 | AK65: 95.6 | AL65: 24.2 | AM65: 4.6 | AN65: 21.6 | AO65: 26.8 | AP65: 100.845 | AT65: =(O65-AG65)/C65 -> 0.056062063 | AU65: 0.34 | AV65: =(AK65+AL65)/(G65+L65-T65) -> 0.2980841 | AW65: =(AK65+AL65)/(G65+L65-T65-AE65) -> 0.2980841 | AX65: =(AG65-AN65-AM65)/(G65+L65-T65+V65) -> 0.24731848 | AY65: =(AG65-AN65-AM65+AO65)/(G65+L65-T65+AO65) -> 0.34219734 | AZ65: =(AG65-AN65-AM65+AO65)/(G65+L65-T65+AO65-AC65) -> 0.37142447 | BA65: =(AG65-AN65)/Q65 -> 0.31792646 | BB65: =(AG65-AN65)/(Q65+R65) -> 0.27165612 | BC65: =D65 -> 414.2 | BD65: =BC65-(BE65+BF65+BG65) -> -0.1 | BE65: =AG65 -> 146.1 | BF65: 158 | BG65: 110.2 | BH65: =BG65/D65 -> 0.26605505 | BI65: 74.7 | BJ65: =BG65-BI65 -> 35.5 | BK65: =BJ65/D65 -> 0.085707388 | BL65: =DD65/(D65) -> 0.0068807339 | BM65: =DD65/(CV65+CW65) -> 0.050934696 | BN65: =CQ65*DF65 -> 0.052847262 | BO65: =BJ65/I65 -> 0.5290611 | BP65: 43.257 | BQ65: =L65 -> 75.5 | BX65: 53.929 | BY65: 1.286 | BZ65: 3.129 | CA65: 0.182 | CB65: 3.805 | CC65: =CD65+CE65 -> 2.761 | CD65: 2.652 | CE65: 0.109 | CF65: 0.727 | CG65: =BY65+BZ65+CA65+CB65+CD65+CE65+CF65 -> 11.89 | CH65: =BX65-CG65 -> 42.039 | CI65: =BY65/$BX65 -> 0.023846168 | CJ65: =BZ65/$BX65 -> 0.058020731 | CK65: =CA65/$BX65 -> 0.0033748076 | CL65: =CB65/$BX65 -> 0.070555731 | CM65: =CN65+CO65 -> 0.051196944 | CN65: =CD65/$BX65 -> 0.049175768 | CO65: =CE65/$BX65 -> 0.002021176 | CP65: =CF65/$BX65 -> 0.013480688 | CQ65: =CG65/$BX65 -> 0.22047507 | CR65: =CQ65*N65 -> 0.040187995 | CS65: =BX65 -> 53.929 | CT65: =BX65 -> 53.929 | CU65: =CT65-(CV65+CW65) -> -2.025 | CV65: 43.257 | CW65: 12.697 | CX65: 0.599 | CY65: 1.335 | CZ65: 0.096 | DA65: 1.521 | DB65: -0.958 | DC65: 0.257 | DD65: =DC65+DB65+DA65+CZ65+CY65+CX65 -> 2.85 | DF65: =DD65/CG65 -> 0.23969722 | DG65: =CW65-DD65 -> 9.847 | DH65: =DD65/CW65 -> 0.22446247 | DI65: =CW65/(CW65+CV65) -> 0.22691854 | DJ65: 37.604 | DK65: 0.793 | DL65: 3.112 | DM65: 0.065 | DN65: 1.269 | DO65: 4.392 | DP65: -0.502 | DQ65: 0.165 | DR65: =DQ65+DO65+DN65+DM65+DL65+DK65 -> 9.796 | DS65: =DJ65-DR65 -> 27.808 | DT65: =DR65/DJ65 -> 0.2605042 | DU65: =DJ65-CW65 -> 24.907 | DV65: 24.907 | DW65: =DK65-CX65 -> 0.194 | DX65: =DL65-CY65 -> 1.777 | DY65: =DM65-CZ65 -> -0.031 | DZ65: =DN65-DA65 -> -0.252 | EA65: =DO65-DB65 -> 5.35 | EB65: =DQ65-DC65 -> -0.092 | EC65: =EB65+EA65+DZ65+DY65+DX65+DW65 -> 6.946 | ED65: =DU65-EC65 -> 17.961 | EE65: =EC65/DU65 -> 0.27887742 | EF65: 6.395 | EG65: 0.209 | EH65: 0.556 | EI65: -0.009 | EJ65: 0.098 | EK65: 1.425 | EL65: 0.037 | EM65: =EL65+EK65+EJ65+EI65+EH65+EG65 -> 2.316 | EN65: =EF65-EM65 -> 4.079 | EO65: =EM65/EF65 -> 0.36215794 | EP65: 381.781 | EQ65: 4.665 | ER65: 19.16 | ES65: 1.56 | ET65: 21.144 | EU65: 22.493 | EV65: 18.297 | EW65: 2.998 | EX65: =EW65+EU65+ET65+ES65+ER65+EQ65 -> 72.02 | EY65: =EP65-EX65 -> 309.761 | EZ65: =EX65/EP65 -> 0.18864218 | FA65: =(BX65+(EP65-EP64)-DJ65)/EP64 -> 0.14668802 | FB65: =(BY65+(EQ65-EQ64)-DK65)/EQ64 -> -0.14926604 | FC65: =(BZ65+(ER65-ER64)-DL65)/ER64 -> 0.14387116 | FD65: =(CA65+(ES65-ES64)-DM65)/ES64 -> 0.49465241 | FE65: =(CB65+(ET65-ET64)-DN65)/ET64 -> 0.265701 | FF65: =(CC65+(EU65-EU64)-DO65)/EU64 -> 0.080205043 | FG65: =(CD65+(EV65-EV64)-DP65)/EV64 -> 0.13401353 | FH65: =(CF65+(EW65-EW64)-DQ65)/EW64 -> 0.33734035 | FI65: =(CG65+(EX65-EX64)-DR65)/EX64 -> 0.14667203 | FJ65: =(CH65+(EY65-EY64)-DS65)/EY64 -> 0.14669168 | FK65: =(CH65+AO65+(EY65-EY64)-DS65)/EY64 -> 0.24154382 | FL65: =BX65/EP64 -> 0.15533486 | FM65: =BY65/EQ64 -> 0.21210622 | FN65: =BZ65/ER64 -> 0.18663883 | FO65: =CA65/ES64 -> 0.16221034 | FP65: =CB65/ET64 -> 0.20337805 | FQ65: =CC65/EU64 -> 0.1429607 | FR65: =CD65/EV64 -> 0.14019877 | FS65: =CF65/EW64 -> 0.27310293 | FT65: =CG65/EX64 -> 0.18395891 | FU65: =CH65/EY64 -> 0.14878692
B66: 1990 | C66: 5036.1 | D66: 417.2 | E66: =D66/C66 -> 0.082841882 | F66: =D66-(G66+I66) -> 0 | G66: =D66-I66 -> 341.1 | H66: =G66/C66 -> 0.067730982 | I66: 76.1 | J66: =I66/C66 -> 0.015110899 | K66: =I66/D66 -> 0.18240652 | L66: 81 | M66: =L66/C66 -> 0.016083874 | N66: =L66/D66 -> 0.19415149 | O66: =D66 -> 417.2 | P66: =O66-(Q66+R66+T66+U66+X66-V66) -> 0 | Q66: 378.8 | R66: 65.2 | S66: =R66/D66 -> 0.15627996 | T66: 21.9 | U66: 13.1 | V66: 62.8 | W66: =V66/D66 -> 0.15052733 | X66: =O66-(Q66+R66+T66+U66-V66) -> 1 | AC66: =AC67*AF66/AF67 -> 33.915379 | AD66: =AC66/D66 -> 0.081292855 | AF66: 36.999266 | AG66: 145.4 | AH66: =AG66/C66 -> 0.028871547 | AI66: =(AG66-AN66)/C66 -> 0.024185382 | AJ66: =AG66-(AK66+AL66+AM66+AN66) -> 0 | AK66: 94.5 | AL66: 22.5 | AM66: 4.8 | AN66: 23.6 | AO66: 28.2 | AP66: 94.65175 | AT66: =(O66-AG66)/C66 -> 0.053970334 | AU66: 0.34 | AV66: =(AK66+AL66)/(G66+L66-T66) -> 0.29235382 | AW66: =(AK66+AL66)/(G66+L66-T66-AE66) -> 0.29235382 | AX66: =(AG66-AN66-AM66)/(G66+L66-T66+V66) -> 0.25269978 | AY66: =(AG66-AN66-AM66+AO66)/(G66+L66-T66+AO66) -> 0.33893557 | AZ66: =(AG66-AN66-AM66+AO66)/(G66+L66-T66+AO66-AC66) -> 0.36807519 | BA66: =(AG66-AN66)/Q66 -> 0.32154171 | BB66: =(AG66-AN66)/(Q66+R66) -> 0.27432432 | BC66: =D66 -> 417.2 | BD66: =BC66-(BE66+BF66+BG66) -> 0 | BE66: =AG66 -> 145.4 | BF66: 169.1 | BG66: 102.7 | BH66: =BG66/D66 -> 0.24616491 | BI66: 51.6 | BJ66: =BG66-BI66 -> 51.1 | BK66: =BJ66/D66 -> 0.12248322 | BL66: =DD66/(D66) -> 0.01840604 | BM66: =DD66/(CV66+CW66) -> 0.13242167 | BN66: =CQ66*DF66 -> 0.13238742 | BO66: =BJ66/I66 -> 0.67148489 | BP66: 36.553 | BQ66: =L66 -> 81 | BX66: 58.004 | BY66: 1.433 | BZ66: 4.117 | CA66: 0.177 | CB66: 4.423 | CC66: =CD66+CE66 -> 3.019 | CD66: 2.067 | CE66: 0.952 | CF66: 1.127 | CG66: =BY66+BZ66+CA66+CB66+CD66+CE66+CF66 -> 14.296 | CH66: =BX66-CG66 -> 43.708 | CI66: =BY66/$BX66 -> 0.024705193 | CJ66: =BZ66/$BX66 -> 0.070977864 | CK66: =CA66/$BX66 -> 0.0030515137 | CL66: =CB66/$BX66 -> 0.076253362 | CM66: =CN66+CO66 -> 0.052048135 | CN66: =CD66/$BX66 -> 0.035635473 | CO66: =CE66/$BX66 -> 0.016412661 | CP66: =CF66/$BX66 -> 0.019429695 | CQ66: =CG66/$BX66 -> 0.24646576 | CR66: =CQ66*N66 -> 0.047851694 | CS66: =BX66 -> 58.004 | CT66: =BX66 -> 58.004 | CU66: =CT66-(CV66+CW66) -> 0.015 | CV66: 36.553 | CW66: 21.436 | CX66: 0.781 | CY66: 2.403 | CZ66: -0.09 | DA66: 2.123 | DB66: 1.798 | DC66: 0.664 | DD66: =DC66+DB66+DA66+CZ66+CY66+CX66 -> 7.679 | DF66: =DD66/CG66 -> 0.53714326 | DG66: =CW66-DD66 -> 13.757 | DH66: =DD66/CW66 -> 0.35822915 | DI66: =CW66/(CW66+CV66) -> 0.36965631 | DJ66: 30.982 | DK66: 0.926 | DL66: -2.004 | DM66: -0.129 | DN66: 5.314 | DO66: 5.58 | DP66: 1.431 | DQ66: 0.62 | DR66: =DQ66+DO66+DN66+DM66+DL66+DK66 -> 10.307 | DS66: =DJ66-DR66 -> 20.675 | DT66: =DR66/DJ66 -> 0.33267704 | DU66: =DJ66-CW66 -> 9.546 | DV66: 9.546 | DW66: =DK66-CX66 -> 0.145 | DX66: =DL66-CY66 -> -4.407 | DY66: =DM66-CZ66 -> -0.039 | DZ66: =DN66-DA66 -> 3.191 | EA66: =DO66-DB66 -> 3.782 | EB66: =DQ66-DC66 -> -0.044 | EC66: =EB66+EA66+DZ66+DY66+DX66+DW66 -> 2.628 | ED66: =DU66-EC66 -> 6.918 | EE66: =EC66/DU66 -> 0.27529855 | EF66: 8.739 | EG66: -0.184 | EH66: -0.314 | EI66: -0.188 | EJ66: 2.999 | EK66: -0.382 | EL66: 0.015 | EM66: =EL66+EK66+EJ66+EI66+EH66+EG66 -> 1.946 | EN66: =EF66-EM66 -> 6.793 | EO66: =EM66/EF66 -> 0.22267994 | EP66: 430.521 | EQ66: 5.894 | ER66: 19.12 | ES66: 1.697 | ET66: 25.099 | EU66: 28.065 | EV66: 20.169 | EW66: 3.975 | EX66: =EW66+EU66+ET66+ES66+ER66+EQ66 -> 83.85 | EY66: =EP66-EX66 -> 346.671 | EZ66: =EX66/EP66 -> 0.19476402 | FA66: =(BX66+(EP66-EP65)-DJ66)/EP65 -> 0.19844361 | FB66: =(BY66+(EQ66-EQ65)-DK66)/EQ65 -> 0.3721329 | FC66: =(BZ66+(ER66-ER65)-DL66)/ER65 -> 0.31737996 | FD66: =(CA66+(ES66-ES65)-DM66)/ES65 -> 0.28397436 | FE66: =(CB66+(ET66-ET65)-DN66)/ET65 -> 0.14491109 | FF66: =(CC66+(EU66-EU65)-DO66)/EU65 -> 0.13386387 | FG66: =(CD66+(EV66-EV65)-DP66)/EV65 -> 0.13707165 | FH66: =(CF66+(EW66-EW65)-DQ66)/EW65 -> 0.49499666 | FI66: =(CG66+(EX66-EX65)-DR66)/EX65 -> 0.21964732 | FJ66: =(CH66+(EY66-EY65)-DS66)/EY65 -> 0.19351371 | FK66: =(CH66+AO66+(EY66-EY65)-DS66)/EY65 -> 0.28455164 | FL66: =BX66/EP65 -> 0.15193003 | FM66: =BY66/EQ65 -> 0.30718114 | FN66: =BZ66/ER65 -> 0.21487474 | FO66: =CA66/ES65 -> 0.11346154 | FP66: =CB66/ET65 -> 0.20918464 | FQ66: =CC66/EU65 -> 0.13421953 | FR66: =CD66/EV65 -> 0.11296934 | FS66: =CF66/EW65 -> 0.37591728 | FT66: =CG66/EX65 -> 0.19850042 | FU66: =CH66/EY65 -> 0.14110233
B67: 1991 | C67: 5186.1 | D67: 451.3 | E67: =D67/C67 -> 0.087021076 | F67: =D67-(G67+I67) -> 0 | G67: =D67-I67 -> 374.8 | H67: =G67/C67 -> 0.072270107 | I67: 76.5 | J67: =I67/C67 -> 0.014750969 | K67: =I67/D67 -> 0.1695103 | L67: 75.4 | M67: =L67/C67 -> 0.014538864 | N67: =L67/D67 -> 0.1670729 | O67: =D67 -> 451.3 | P67: =O67-(Q67+R67+T67+U67+X67-V67) -> 0 | Q67: 352.1 | R67: 67.6 | S67: =R67/D67 -> 0.1497895 | T67: 20.8 | U67: 22 | V67: 62.2 | W67: =V67/D67 -> 0.13782406 | X67: =O67-(Q67+R67+T67+U67-V67) -> 51 | AC67: =AC68*AF67/AF68 -> 29.56014 | AD67: =AC67/D67 -> 0.065499977 | AE67: 36.687 | AF67: 32.248009 | AG67: 138.6 | AH67: =AG67/C67 -> 0.026725285 | AI67: =(AG67-AN67)/C67 -> 0.022714564 | AJ67: =AG67-(AK67+AL67+AM67+AN67) -> 0.1 | AK67: 89.1 | AL67: 23.6 | AM67: 5 | AN67: 20.8 | AO67: 24.6 | AP67: 98.632 | AT67: =(O67-AG67)/C67 -> 0.060295791 | AU67: 0.34 | AV67: =(AK67+AL67)/(G67+L67-T67) -> 0.26245925 | AW67: =(AK67+AL67)/(G67+L67-T67-AE67) -> 0.28697802 | AX67: =(AG67-AN67-AM67)/(G67+L67-T67+V67) -> 0.22945484 | AY67: =(AG67-AN67-AM67+AO67)/(G67+L67-T67+AO67) -> 0.30264317 | AZ67: =(AG67-AN67-AM67+AO67)/(G67+L67-T67+AO67-AC67) -> 0.32372077 | BA67: =(AG67-AN67)/Q67 -> 0.33456404 | BB67: =(AG67-AN67)/(Q67+R67) -> 0.28067667 | BC67: =D67 -> 451.3 | BD67: =BC67-(BE67+BF67+BG67) -> 0 | BE67: =AG67 -> 138.6 | BF67: 180.5 | BG67: 132.2 | BH67: =BG67/D67 -> 0.29293153 | BI67: 80.1 | BJ67: =BG67-BI67 -> 52.1 | BK67: =BJ67/D67 -> 0.11544427 | BL67: =DD67/(D67) -> 0.014797252 | BM67: =DD67/(CV67+CW67) -> 0.12775482 | BN67: =CQ67*DF67 -> 0.12820857 | BO67: =BJ67/I67 -> 0.68104575 | BP67: 33.945 | BQ67: =L67 -> 75.4 | BX67: 52.087 | BY67: 1.556 | BZ67: 3.609 | CA67: 0.192 | CB67: 3.216 | CC67: =CD67+CE67 -> 3.201 | CD67: 2.016 | CE67: 1.185 | CF67: 1.138 | CG67: =BY67+BZ67+CA67+CB67+CD67+CE67+CF67 -> 12.912 | CH67: =BX67-CG67 -> 39.175 | CI67: =BY67/$BX67 -> 0.029873097 | CJ67: =BZ67/$BX67 -> 0.069287922 | CK67: =CA67/$BX67 -> 0.0036861405 | CL67: =CB67/$BX67 -> 0.061742853 | CM67: =CN67+CO67 -> 0.061454874 | CN67: =CD67/$BX67 -> 0.038704475 | CO67: =CE67/$BX67 -> 0.022750398 | CP67: =CF67/$BX67 -> 0.021848062 | CQ67: =CG67/$BX67 -> 0.24789295 | CR67: =CQ67*N67 -> 0.041416194 | CS67: =BX67 -> 52.087 | CT67: =BX67 -> 52.087 | CU67: =CT67-(CV67+CW67) -> -0.185 | CV67: 33.945 | CW67: 18.327 | CX67: 1.145 | CY67: 1.914 | CZ67: 0.126 | DA67: 1.18 | DB67: 1.801 | DC67: 0.512 | DD67: =DC67+DB67+DA67+CZ67+CY67+CX67 -> 6.678 | DF67: =DD67/CG67 -> 0.51719331 | DG67: =CW67-DD67 -> 11.649 | DH67: =DD67/CW67 -> 0.36438042 | DI67: =CW67/(CW67+CV67) -> 0.35060836 | DJ67: 32.696 | DK67: 0.537 | DL67: 1.654 | DM67: -0.003 | DN67: 0.93 | DO67: 1.541 | DP67: 2.797 | DQ67: 1.067 | DR67: =DQ67+DO67+DN67+DM67+DL67+DK67 -> 5.726 | DS67: =DJ67-DR67 -> 26.97 | DT67: =DR67/DJ67 -> 0.17512846 | DU67: =DJ67-CW67 -> 14.369 | DV67: 14.369 | DW67: =DK67-CX67 -> -0.608 | DX67: =DL67-CY67 -> -0.26 | DY67: =DM67-CZ67 -> -0.129 | DZ67: =DN67-DA67 -> -0.25 | EA67: =DO67-DB67 -> -0.26 | EB67: =DQ67-DC67 -> 0.555 | EC67: =EB67+EA67+DZ67+DY67+DX67+DW67 -> -0.952 | ED67: =DU67-EC67 -> 15.321 | EE67: =EC67/DU67 -> -0.066253741 | EF67: 17.682 | EG67: 0.085 | EH67: 0.662 | EI67: -0.03 | EJ67: 0.131 | EK67: 3.854 | EL67: 0.207 | EM67: =EL67+EK67+EJ67+EI67+EH67+EG67 -> 4.909 | EN67: =EF67-EM67 -> 12.773 | EO67: =EM67/EF67 -> 0.27762697 | EP67: 467.844 | EQ67: 6.471 | ER67: 20.293 | ES67: 1.734 | ET67: 25.682 | EU67: 29.131 | EV67: 22.262 | EW67: 5.363 | EX67: =EW67+EU67+ET67+ES67+ER67+EQ67 -> 88.674 | EY67: =EP67-EX67 -> 379.17 | EZ67: =EX67/EP67 -> 0.18953754 | FA67: =(BX67+(EP67-EP66)-DJ67)/EP66 -> 0.13173341 | FB67: =(BY67+(EQ67-EQ66)-DK67)/EQ66 -> 0.27078385 | FC67: =(BZ67+(ER67-ER66)-DL67)/ER66 -> 0.16359833 | FD67: =(CA67+(ES67-ES66)-DM67)/ES66 -> 0.13671184 | FE67: =(CB67+(ET67-ET66)-DN67)/ET66 -> 0.11430734 | FF67: =(CC67+(EU67-EU66)-DO67)/EU66 -> 0.097131659 | FG67: =(CD67+(EV67-EV66)-DP67)/EV66 -> 0.065050325 | FH67: =(CF67+(EW67-EW66)-DQ67)/EW66 -> 0.36704403 | FI67: =(CG67+(EX67-EX66)-DR67)/EX66 -> 0.14323196 | FJ67: =(CH67+(EY67-EY66)-DS67)/EY66 -> 0.12895223 | FK67: =(CH67+AO67+(EY67-EY66)-DS67)/EY66 -> 0.19991289 | FL67: =BX67/EP66 -> 0.12098597 | FM67: =BY67/EQ66 -> 0.26399729 | FN67: =BZ67/ER66 -> 0.18875523 | FO67: =CA67/ES66 -> 0.11314084 | FP67: =CB67/ET66 -> 0.12813259 | FQ67: =CC67/EU66 -> 0.11405665 | FR67: =CD67/EV66 -> 0.099955377 | FS67: =CF67/EW66 -> 0.28628931 | FT67: =CG67/EX66 -> 0.15398927 | FU67: =CH67/EY66 -> 0.1130034
B68: 1992 | C68: 5499.7 | D68: 475.3 | E68: =D68/C68 -> 0.086422896 | F68: =D68-(G68+I68) -> 0 | G68: =D68-I68 -> 402.2 | H68: =G68/C68 -> 0.073131262 | I68: 73.1 | J68: =I68/C68 -> 0.013291634 | K68: =I68/D68 -> 0.1537976 | L68: 78.3 | M68: =L68/C68 -> 0.01423714 | N68: =L68/D68 -> 0.16473806 | O68: =D68 -> 475.3 | P68: =O68-(Q68+R68+T68+U68+X68-V68) -> 0 | Q68: 415 | R68: 70.7 | S68: =R68/D68 -> 0.14874816 | T68: 18.4 | U68: 12.7 | V68: 70.9 | W68: =V68/D68 -> 0.14916895 | X68: =O68-(Q68+R68+T68+U68-V68) -> 29.4 | AC68: =AC69*AF68/AF69 -> 45.293178 | AD68: =AC68/D68 -> 0.095293873 | AE68: 42.594 | AF68: 49.411635 | AG68: 148.7 | AH68: =AG68/C68 -> 0.027037838 | AI68: =(AG68-AN68)/C68 -> 0.023983126 | AJ68: =AG68-(AK68+AL68+AM68+AN68) -> 0.1 | AK68: 101.9 | AL68: 24.4 | AM68: 5.5 | AN68: 16.8 | AO68: 25.3 | AP68: 104.5825 | AQ68: 22.574362 | AT68: =(O68-AG68)/C68 -> 0.059385057 | AU68: 0.34 | AV68: =(AK68+AL68)/(G68+L68-T68) -> 0.27331746 | AW68: =(AK68+AL68)/(G68+L68-T68-AE68) -> 0.3010684 | AX68: =(AG68-AN68-AM68)/(G68+L68-T68+V68) -> 0.23714822 | AY68: =(AG68-AN68-AM68+AO68)/(G68+L68-T68+AO68) -> 0.31124333 | AZ68: =(AG68-AN68-AM68+AO68)/(G68+L68-T68+AO68-AC68) -> 0.34312974 | BA68: =(AG68-AN68)/Q68 -> 0.31783133 | BB68: =(AG68-AN68)/(Q68+R68) -> 0.27156681 | BC68: =D68 -> 475.3 | BD68: =BC68-(BE68+BF68+BG68) -> 0 | BE68: =AG68 -> 148.7 | BF68: 189.5 | BG68: 137.1 | BH68: =BG68/D68 -> 0.2884494 | BI68: 92 | BJ68: =BG68-BI68 -> 45.1 | BK68: =BJ68/D68 -> 0.09488744 | BL68: =DD68/(D68) -> 0.014950558 | BM68: =DD68/(CV68+CW68) -> 0.1400611 | BN68: =CQ68*DF68 -> 0.14053199 | BO68: =BJ68/I68 -> 0.61696306 | BP68: 34.441 | BQ68: =L68 -> 78.3 | BX68: 50.565 | BY68: 1.817 | BZ68: 3.062 | CA68: 0.202 | CB68: 2.711 | CC68: =CD68+CE68 -> 4.208 | CD68: 2.09 | CE68: 2.118 | CF68: 1.539 | CG68: =BY68+BZ68+CA68+CB68+CD68+CE68+CF68 -> 13.539 | CH68: =BX68-CG68 -> 37.026 | CI68: =BY68/$BX68 -> 0.035933946 | CJ68: =BZ68/$BX68 -> 0.06055572 | CK68: =CA68/$BX68 -> 0.0039948581 | CL68: =CB68/$BX68 -> 0.05361416 | CM68: =CN68+CO68 -> 0.083219618 | CN68: =CD68/$BX68 -> 0.041332938 | CO68: =CE68/$BX68 -> 0.041886681 | CP68: =CF68/$BX68 -> 0.030436072 | CQ68: =CG68/$BX68 -> 0.26775438 | CR68: =CQ68*N68 -> 0.044109336 | CS68: =BX68 -> 50.565 | CT68: =BX68 -> 50.565 | CU68: =CT68-(CV68+CW68) -> -0.17 | CV68: 34.441 | CW68: 16.294 | CX68: 1.28 | CY68: 1.34 | CZ68: 0.145 | DA68: 1.633 | DB68: 1.779 | DC68: 0.929 | DD68: =DC68+DB68+DA68+CZ68+CY68+CX68 -> 7.106 | DF68: =DD68/CG68 -> 0.52485413 | DG68: =CW68-DD68 -> 9.188 | DH68: =DD68/CW68 -> 0.43611145 | DI68: =CW68/(CW68+CV68) -> 0.32115896 | DJ68: 42.647 | DK68: 1.191 | DL68: -1.562 | DM68: 0.217 | DN68: 3.26 | DO68: 6.924 | DP68: 2.828 | DQ68: 1.282 | DR68: =DQ68+DO68+DN68+DM68+DL68+DK68 -> 11.312 | DS68: =DJ68-DR68 -> 31.335 | DT68: =DR68/DJ68 -> 0.26524726 | DU68: =DJ68-CW68 -> 26.353 | DV68: 26.352 | DW68: =DK68-CX68 -> -0.089 | DX68: =DL68-CY68 -> -2.902 | DY68: =DM68-CZ68 -> 0.072 | DZ68: =DN68-DA68 -> 1.627 | EA68: =DO68-DB68 -> 5.145 | EB68: =DQ68-DC68 -> 0.353 | EC68: =EB68+EA68+DZ68+DY68+DX68+DW68 -> 4.206 | ED68: =DU68-EC68 -> 22.147 | EE68: =EC68/DU68 -> 0.15960232 | EF68: 14.647 | EG68: 0.1 | EH68: =(EH67+EH69)/2 -> 0.827 | EI68: 0.114 | EJ68: 0.078 | EK68: 1.305 | EL68: 0.101 | EM68: =EL68+EK68+EJ68+EI68+EH68+EG68 -> 2.525 | EN68: =EF68-EM68 -> 12.122 | EO68: =EM68/EF68 -> 0.17239025 | EP68: 502.063 | EQ68: 7.607 | ER68: 20.7 | ES68: 2.031 | ET68: 28.698 | EU68: 36.969 | EV68: 26.736 | EW68: 6.715 | EX68: =EW68+EU68+ET68+ES68+ER68+EQ68 -> 102.72 | EY68: =EP68-EX68 -> 399.343 | EZ68: =EX68/EP68 -> 0.20459584 | FA68: =(BX68+(EP68-EP67)-DJ68)/EP67 -> 0.090066347 | FB68: =(BY68+(EQ68-EQ67)-DK68)/EQ67 -> 0.27229176 | FC68: =(BZ68+(ER68-ER67)-DL68)/ER67 -> 0.247918 | FD68: =(CA68+(ES68-ES67)-DM68)/ES67 -> 0.16262976 | FE68: =(CB68+(ET68-ET67)-DN68)/ET67 -> 0.096059497 | FF68: =(CC68+(EU68-EU67)-DO68)/EU67 -> 0.17582644 | FG68: =(CD68+(EV68-EV67)-DP68)/EV67 -> 0.1678196 | FH68: =(CF68+(EW68-EW67)-DQ68)/EW67 -> 0.30001865 | FI68: =(CG68+(EX68-EX67)-DR68)/EX67 -> 0.1835149 | FJ68: =(CH68+(EY68-EY67)-DS68)/EY67 -> 0.068212148 | FK68: =(CH68+AO68+(EY68-EY67)-DS68)/EY67 -> 0.13493684 | FL68: =BX68/EP67 -> 0.1080809 | FM68: =BY68/EQ67 -> 0.28079122 | FN68: =BZ68/ER67 -> 0.15088947 | FO68: =CA68/ES67 -> 0.11649366 | FP68: =CB68/ET67 -> 0.10556031 | FQ68: =CC68/EU67 -> 0.14445093 | FR68: =CD68/EV67 -> 0.093881951 | FS68: =CF68/EW67 -> 0.28696625 | FT68: =CG68/EX67 -> 0.15268286 | FU68: =CH68/EY67 -> 0.097650131
B69: 1993 | C69: 5754.8 | D69: 522 | E69: =D69/C69 -> 0.090706888 | F69: =D69-(G69+I69) -> 0 | G69: =D69-I69 -> 445.1 | H69: =G69/C69 -> 0.07734413 | I69: 76.9 | J69: =I69/C69 -> 0.013362758 | K69: =I69/D69 -> 0.14731801 | L69: 89 | M69: =L69/C69 -> 0.015465351 | N69: =L69/D69 -> 0.17049808 | O69: =D69 -> 522 | P69: =O69-(Q69+R69+T69+U69+X69-V69) -> 0 | Q69: 507.9 | R69: 72.5 | S69: =R69/D69 -> 0.13888889 | T69: 16.8 | U69: 16.1 | V69: 90.8 | W69: =V69/D69 -> 0.17394636 | X69: =O69-(Q69+R69+T69+U69-V69) -> -0.5 | AC69: =AC70*AF69/AF70 -> 46.046344 | AD69: =AC69/D69 -> 0.088211387 | AE69: 50.241 | AF69: 50.233285 | AG69: 171 | AH69: =AG69/C69 -> 0.029714325 | AI69: =(AG69-AN69)/C69 -> 0.026934038 | AJ69: =AG69-(AK69+AL69+AM69+AN69) -> -0.1 | AK69: 122.5 | AL69: 26.9 | AM69: 5.7 | AN69: 16 | AO69: 27.6 | AP69: 123.23625 | AT69: =(O69-AG69)/C69 -> 0.060992563 | AU69: 0.35 | AV69: =(AK69+AL69)/(G69+L69-T69) -> 0.28880727 | AW69: =(AK69+AL69)/(G69+L69-T69-AE69) -> 0.31987393 | AX69: =(AG69-AN69-AM69)/(G69+L69-T69+V69) -> 0.24551883 | AY69: =(AG69-AN69-AM69+AO69)/(G69+L69-T69+AO69) -> 0.32464672 | AZ69: =(AG69-AN69-AM69+AO69)/(G69+L69-T69+AO69-AC69) -> 0.35461302 | BA69: =(AG69-AN69)/Q69 -> 0.30517818 | BB69: =(AG69-AN69)/(Q69+R69) -> 0.2670572 | BC69: =D69 -> 522 | BD69: =BC69-(BE69+BF69+BG69) -> 0.1 | BE69: =AG69 -> 171 | BF69: 205.3 | BG69: 145.6 | BH69: =BG69/D69 -> 0.2789272 | BI69: 89.3 | BJ69: =BG69-BI69 -> 56.3 | BK69: =BJ69/D69 -> 0.10785441 | BL69: =DD69/(D69) -> 0.017371648 | BM69: =DD69/(CV69+CW69) -> 0.15405787 | BN69: =CQ69*DF69 -> 0.15270878 | BO69: =BJ69/I69 -> 0.73211964 | BP69: 28.847 | BQ69: =L69 -> 89 | BX69: 59.381 | BY69: 1.755 | BZ69: 2.389 | CA69: 0.403 | CB69: 4.296 | CC69: =CD69+CE69 -> 3.843 | CD69: 3.04 | CE69: 0.803 | CF69: 1.932 | CG69: =BY69+BZ69+CA69+CB69+CD69+CE69+CF69 -> 14.618 | CH69: =BX69-CG69 -> 44.763 | CI69: =BY69/$BX69 -> 0.029554908 | CJ69: =BZ69/$BX69 -> 0.040231724 | CK69: =CA69/$BX69 -> 0.0067866826 | CL69: =CB69/$BX69 -> 0.072346373 | CM69: =CN69+CO69 -> 0.064717671 | CN69: =CD69/$BX69 -> 0.051194827 | CO69: =CE69/$BX69 -> 0.013522844 | CP69: =CF69/$BX69 -> 0.03253566 | CQ69: =CG69/$BX69 -> 0.24617302 | CR69: =CQ69*N69 -> 0.041972028 | CS69: =BX69 -> 59.381 | CT69: =BX69 -> 59.381 | CU69: =CT69-(CV69+CW69) -> 0.52 | CV69: 28.847 | CW69: 30.014 | CX69: 1.217 | CY69: 1.101 | CZ69: 0.334 | DA69: 3.225 | DB69: 1.839 | DC69: 1.352 | DD69: =DC69+DB69+DA69+CZ69+CY69+CX69 -> 9.068 | DF69: =DD69/CG69 -> 0.6203311 | DG69: =CW69-DD69 -> 20.946 | DH69: =DD69/CW69 -> 0.30212567 | DI69: =CW69/(CW69+CV69) -> 0.50991319 | DJ69: 77.247 | DK69: 1.506 | DL69: 1.398 | DM69: 3.686 | DN69: 4.566 | DO69: 8.179 | DP69: 3.995 | DQ69: 1.743 | DR69: =DQ69+DO69+DN69+DM69+DL69+DK69 -> 21.078 | DS69: =DJ69-DR69 -> 56.169 | DT69: =DR69/DJ69 -> 0.27286497 | DU69: =DJ69-CW69 -> 47.233 | DV69: 47.233 | DW69: =DK69-CX69 -> 0.289 | DX69: =DL69-CY69 -> 0.297 | DY69: =DM69-CZ69 -> 3.352 | DZ69: =DN69-DA69 -> 1.341 | EA69: =DO69-DB69 -> 6.34 | EB69: =DQ69-DC69 -> 0.391 | EC69: =EB69+EA69+DZ69+DY69+DX69+DW69 -> 12.01 | ED69: =DU69-EC69 -> 35.223 | EE69: =EC69/DU69 -> 0.25427138 | EF69: 24.565 | EG69: 0.326 | EH69: 0.992 | EI69: =(EI68+EI70)/2 -> 0.0735 | EJ69: 0.249 | EK69: 1.631 | EL69: 0.107 | EM69: =EL69+EK69+EJ69+EI69+EH69+EG69 -> 3.3785 | EN69: =EF69-EM69 -> 21.1865 | EO69: =EM69/EF69 -> 0.13753308 | EP69: 564.283 | EQ69: 9.019 | ER69: 20.911 | ES69: 5.611 | ET69: 33.056 | EU69: 41.18 | EV69: 28.666 | EW69: 8.875 | EX69: =EW69+EU69+ET69+ES69+ER69+EQ69 -> 118.652 | EY69: =EP69-EX69 -> 445.631 | EZ69: =EX69/EP69 -> 0.21027038 | FA69: =(BX69+(EP69-EP68)-DJ69)/EP68 -> 0.088343495 | FB69: =(BY69+(EQ69-EQ68)-DK69)/EQ68 -> 0.21835152 | FC69: =(BZ69+(ER69-ER68)-DL69)/ER68 -> 0.058067633 | FD69: =(CA69+(ES69-ES68)-DM69)/ES68 -> 0.14623338 | FE69: =(CB69+(ET69-ET68)-DN69)/ET68 -> 0.14244895 | FF69: =(CC69+(EU69-EU68)-DO69)/EU68 -> -0.0033812113 | FG69: =(CD69+(EV69-EV68)-DP69)/EV68 -> 0.036467684 | FH69: =(CF69+(EW69-EW68)-DQ69)/EW68 -> 0.34981385 | FI69: =(CG69+(EX69-EX68)-DR69)/EX68 -> 0.092211838 | FJ69: =(CH69+(EY69-EY68)-DS69)/EY68 -> 0.08734847 | FK69: =(CH69+AO69+(EY69-EY68)-DS69)/EY68 -> 0.15646199 | FL69: =BX69/EP68 -> 0.118274 | FM69: =BY69/EQ68 -> 0.23070856 | FN69: =BZ69/ER68 -> 0.11541063 | FO69: =CA69/ES68 -> 0.19842442 | FP69: =CB69/ET68 -> 0.14969684 | FQ69: =CC69/EU68 -> 0.10395196 | FR69: =CD69/EV68 -> 0.11370437 | FS69: =CF69/EW68 -> 0.28771407 | FT69: =CG69/EX68 -> 0.14230919 | FU69: =CH69/EY68 -> 0.11209161
B70: 1994 | C70: 6140.2 | D70: 621.9 | E70: =D70/C70 -> 0.10128335 | F70: =D70-(G70+I70) -> 0 | G70: =D70-I70 -> 543.9 | H70: =G70/C70 -> 0.088580177 | I70: 78 | J70: =I70/C70 -> 0.012703169 | K70: =I70/D70 -> 0.12542209 | L70: 104.6 | M70: =L70/C70 -> 0.017035276 | N70: =L70/D70 -> 0.16819424 | O70: =D70 -> 621.9 | P70: =O70-(Q70+R70+T70+U70+X70-V70) -> 0 | Q70: 585.1 | R70: 78.1 | S70: =R70/D70 -> 0.12558289 | T70: 18.6 | U70: 20.2 | V70: 71 | W70: =V70/D70 -> 0.11416626 | X70: =O70-(Q70+R70+T70+U70-V70) -> -9.1 | AC70: =AC71*AF70/AF71 -> 65.879272 | AD70: =AC70/D70 -> 0.10593226 | AE70: 67.444 | AF70: 71.869598 | AG70: 193.1 | AH70: =AG70/C70 -> 0.031448487 | AI70: =(AG70-AN70)/C70 -> 0.028109834 | AJ70: =AG70-(AK70+AL70+AM70+AN70) -> 0 | AK70: 136.2 | AL70: 30 | AM70: 6.4 | AN70: 20.5 | AO70: 29.2 | AP70: 144.53975 | AQ70: 26.469623 | AT70: =(O70-AG70)/C70 -> 0.069834859 | AU70: 0.35 | AV70: =(AK70+AL70)/(G70+L70-T70) -> 0.2638514 | AW70: =(AK70+AL70)/(G70+L70-T70-AE70) -> 0.29548978 | AX70: =(AG70-AN70-AM70)/(G70+L70-T70+V70) -> 0.2371237 | AY70: =(AG70-AN70-AM70+AO70)/(G70+L70-T70+AO70) -> 0.29646488 | AZ70: =(AG70-AN70-AM70+AO70)/(G70+L70-T70+AO70-AC70) -> 0.32938836 | BA70: =(AG70-AN70)/Q70 -> 0.29499231 | BB70: =(AG70-AN70)/(Q70+R70) -> 0.26025332 | BC70: =D70 -> 621.9 | BD70: =BC70-(BE70+BF70+BG70) -> 0 | BE70: =AG70 -> 193.1 | BF70: 236 | BG70: 192.8 | BH70: =BG70/D70 -> 0.31001769 | BI70: 153 | BJ70: =BG70-BI70 -> 39.8 | BK70: =BJ70/D70 -> 0.063997427 | BL70: =DD70/(D70) -> 0.017128156 | BM70: =DD70/(CV70+CW70) -> 0.15637111 | BN70: =CQ70*DF70 -> 0.1544059 | BO70: =BJ70/I70 -> 0.51025641 | BP70: 44.032 | BQ70: =L70 -> 104.6 | BX70: 68.987 | BY70: 1.543 | BZ70: 5.705 | CA70: 1.23 | CB70: 4.468 | CC70: =CD70+CE70 -> 5.52 | CD70: 3.272 | CE70: 2.248 | CF70: 2.135 | CG70: =BY70+BZ70+CA70+CB70+CD70+CE70+CF70 -> 20.601 | CH70: =BX70-CG70 -> 48.386 | CI70: =BY70/$BX70 -> 0.022366533 | CJ70: =BZ70/$BX70 -> 0.08269674 | CK70: =CA70/$BX70 -> 0.017829446 | CL70: =CB70/$BX70 -> 0.064765825 | CM70: =CN70+CO70 -> 0.080015075 | CN70: =CD70/$BX70 -> 0.047429226 | CO70: =CE70/$BX70 -> 0.03258585 | CP70: =CF70/$BX70 -> 0.03094786 | CQ70: =CG70/$BX70 -> 0.29862148 | CR70: =CQ70*N70 -> 0.050226414 | CS70: =BX70 -> 68.987 | CT70: =BX70 -> 68.987 | CU70: =CT70-(CV70+CW70) -> 0.867 | CV70: 44.032 | CW70: 24.088 | CX70: 0.91 | CY70: 3.132 | CZ70: 0.609 | DA70: 2.256 | DB70: 2.506 | DC70: 1.239 | DD70: =DC70+DB70+DA70+CZ70+CY70+CX70 -> 10.652 | DF70: =DD70/CG70 -> 0.51706228 | DG70: =CW70-DD70 -> 13.436 | DH70: =DD70/CW70 -> 0.44221189 | DI70: =CW70/(CW70+CV70) -> 0.35361127 | DJ70: 73.252 | DK70: -0.337 | DL70: 7.605 | DM70: 0.517 | DN70: 0.94 | DO70: 3.598 | DP70: 0.897 | DQ70: 1.836 | DR70: =DQ70+DO70+DN70+DM70+DL70+DK70 -> 14.159 | DS70: =DJ70-DR70 -> 59.093 | DT70: =DR70/DJ70 -> 0.19329165 | DU70: =DJ70-CW70 -> 49.164 | DV70: 49.164 | DW70: =DK70-CX70 -> -1.247 | DX70: =DL70-CY70 -> 4.473 | DY70: =DM70-CZ70 -> -0.092 | DZ70: =DN70-DA70 -> -1.316 | EA70: =DO70-DB70 -> 1.092 | EB70: =DQ70-DC70 -> 0.597 | EC70: =EB70+EA70+DZ70+DY70+DX70+DW70 -> 3.507 | ED70: =DU70-EC70 -> 45.657 | EE70: =EC70/DU70 -> 0.071332682 | EF70: 33.659 | EG70: 0.265 | EH70: 3.838 | EI70: 0.033 | EJ70: =(EJ69+EJ71)/2 -> 0.453 | EK70: 1.241 | EL70: 0.272 | EM70: =EL70+EK70+EJ70+EI70+EH70+EG70 -> 6.102 | EN70: =EF70-EM70 -> 27.557 | EO70: =EM70/EF70 -> 0.18128881 | EP70: 612.893 | EQ70: 7.239 | ER70: 29.889 | ES70: 6.31 | ET70: 27.908 | EU70: 48.722 | EV70: 28.355 | EW70: 10.94 | EX70: =EW70+EU70+ET70+ES70+ER70+EQ70 -> 131.008 | EY70: =EP70-EX70 -> 481.885 | EZ70: =EX70/EP70 -> 0.21375346 | FA70: =(BX70+(EP70-EP69)-DJ70)/EP69 -> 0.078586454 | FB70: =(BY70+(EQ70-EQ69)-DK70)/EQ69 -> 0.011087704 | FC70: =(BZ70+(ER70-ER69)-DL70)/ER69 -> 0.33848214 | FD70: =(CA70+(ES70-ES69)-DM70)/ES69 -> 0.25164855 | FE70: =(CB70+(ET70-ET69)-DN70)/ET69 -> -0.049007744 | FF70: =(CC70+(EU70-EU69)-DO70)/EU69 -> 0.2298203 | FG70: =(CD70+(EV70-EV69)-DP70)/EV69 -> 0.072001674 | FH70: =(CF70+(EW70-EW69)-DQ70)/EW69 -> 0.2663662 | FI70: =(CG70+(EX70-EX69)-DR70)/EX69 -> 0.15842969 | FJ70: =(CH70+(EY70-EY69)-DS70)/EY69 -> 0.057327699 | FK70: =(CH70+AO70+(EY70-EY69)-DS70)/EY69 -> 0.12285276 | FL70: =BX70/EP69 -> 0.12225603 | FM70: =BY70/EQ69 -> 0.17108327 | FN70: =BZ70/ER69 -> 0.27282292 | FO70: =CA70/ES69 -> 0.21921226 | FP70: =CB70/ET69 -> 0.13516457 | FQ70: =CC70/EU69 -> 0.13404565 | FR70: =CD70/EV69 -> 0.11414219 | FS70: =CF70/EW69 -> 0.24056338 | FT70: =CG70/EX69 -> 0.17362539 | FU70: =CH70/EY69 -> 0.10857862
B71: 1995 | C71: 6479.5 | D71: 703 | E71: =D71/C71 -> 0.10849603 | F71: =D71-(G71+I71) -> 0 | G71: =D71-I71 -> 610.1 | H71: =G71/C71 -> 0.0941585 | I71: 92.9 | J71: =I71/C71 -> 0.014337526 | K71: =I71/D71 -> 0.13214794 | L71: 127.4 | M71: =L71/C71 -> 0.019662011 | N71: =L71/D71 -> 0.18122333 | O71: =D71 -> 703 | P71: =O71-(Q71+R71+T71+U71+X71-V71) -> 0 | Q71: 717.8 | R71: 85.7 | S71: =R71/D71 -> 0.12190612 | T71: 23.1 | U71: 17.7 | V71: 115.5 | W71: =V71/D71 -> 0.16429587 | X71: =O71-(Q71+R71+T71+U71-V71) -> -25.8 | Y71: 77.511418 | Z71: =Z72*Y71/Y72 -> -5.9190352 | AA71: -5.445328 | AB71: =Z71-AA71 -> -0.47370723 | AC71: =Y71+Z71 -> 71.592383 | AD71: =AC71/D71 -> 0.10183838 | AE71: 80.755 | AF71: 78.102196 | AG71: 217.8 | AH71: =AG71/C71 -> 0.033613705 | AI71: =(AG71-AN71)/C71 -> 0.030002315 | AJ71: =AG71-(AK71+AL71+AM71+AN71) -> -0.1 | AK71: 155.9 | AL71: 31.7 | AM71: 6.9 | AN71: 23.4 | AO71: 33.5 | AP71: 160.709 | AT71: =(O71-AG71)/C71 -> 0.074882321 | AU71: 0.35 | AV71: =(AK71+AL71)/(G71+L71-T71) -> 0.26259798 | AW71: =(AK71+AL71)/(G71+L71-T71-AE71) -> 0.29606483 | AX71: =(AG71-AN71-AM71)/(G71+L71-T71+V71) -> 0.22593084 | AY71: =(AG71-AN71-AM71+AO71)/(G71+L71-T71+AO71) -> 0.29549405 | AZ71: =(AG71-AN71-AM71+AO71)/(G71+L71-T71+AO71-AC71) -> 0.32677438 | BA71: =(AG71-AN71)/Q71 -> 0.27082753 | BB71: =(AG71-AN71)/(Q71+R71) -> 0.24194151 | BC71: =D71 -> 703 | BD71: =BC71-(BE71+BF71+BG71) -> 0 | BE71: =AG71 -> 217.8 | BF71: 259 | BG71: 226.2 | BH71: =BG71/D71 -> 0.32176387 | BI71: 166.1 | BJ71: =BG71-BI71 -> 60.1 | BK71: =BJ71/D71 -> 0.085490754 | BL71: =DD71/(D71) -> 0.019443812 | BM71: =DD71/(CV71+CW71) -> 0.15871486 | BN71: =CQ71*DF71 -> 0.15649257 | BO71: =BJ71/I71 -> 0.64693219 | BP71: 38.891 | BQ71: =L71 -> 127.4 | BX71: 87.346 | BY71: 2.152 | BZ71: 7.456 | CA71: 1.291 | CB71: 4.201 | CC71: =CD71+CE71 -> 5.341 | CD71: 3.023 | CE71: 2.318 | CF71: 2.466 | CG71: =BY71+BZ71+CA71+CB71+CD71+CE71+CF71 -> 22.907 | CH71: =BX71-CG71 -> 64.439 | CI71: =BY71/$BX71 -> 0.024637648 | CJ71: =BZ71/$BX71 -> 0.085361665 | CK71: =CA71/$BX71 -> 0.014780299 | CL71: =CB71/$BX71 -> 0.048096078 | CM71: =CN71+CO71 -> 0.06114762 | CN71: =CD71/$BX71 -> 0.034609484 | CO71: =CE71/$BX71 -> 0.026538136 | CP71: =CF71/$BX71 -> 0.028232546 | CQ71: =CG71/$BX71 -> 0.26225586 | CR71: =CQ71*N71 -> 0.047526879 | CS71: =BX71 -> 87.346 | CT71: =BX71 -> 87.346 | CU71: =CT71-(CV71+CW71) -> 1.223 | CV71: 38.891 | CW71: 47.232 | CX71: 1.733 | CY71: 5.293 | CZ71: 0.669 | DA71: 1.199 | DB71: 3.012 | DC71: 1.763 | DD71: =DC71+DB71+DA71+CZ71+CY71+CX71 -> 13.669 | DF71: =DD71/CG71 -> 0.59671716 | DG71: =CW71-DD71 -> 33.563 | DH71: =DD71/CW71 -> 0.28940125 | DI71: =CW71/(CW71+CV71) -> 0.54842493 | DJ71: 92.074 | DK71: 0.695 | DL71: 9.386 | DM71: -0.477 | DN71: 1.85 | DO71: 0.245 | DP71: 0.275 | DQ71: 0.947 | DR71: =DQ71+DO71+DN71+DM71+DL71+DK71 -> 12.646 | DS71: =DJ71-DR71 -> 79.428 | DT71: =DR71/DJ71 -> 0.13734605 | DU71: =DJ71-CW71 -> 44.842 | DV71: 44.842 | DW71: =DK71-CX71 -> -1.038 | DX71: =DL71-CY71 -> 4.093 | DY71: =DM71-CZ71 -> -1.146 | DZ71: =DN71-DA71 -> 0.651 | EA71: =DO71-DB71 -> -2.767 | EB71: =DQ71-DC71 -> -0.816 | EC71: =EB71+EA71+DZ71+DY71+DX71+DW71 -> -1.023 | ED71: =DU71-EC71 -> 45.865 | EE71: =EC71/DU71 -> -0.022813434 | EF71: 40.485 | EG71: 0.249 | EH71: 1.238 | EI71: -0.15 | EJ71: 0.657 | EK71: 1.187 | EL71: -0.125 | EM71: =EL71+EK71+EJ71+EI71+EH71+EG71 -> 3.056 | EN71: =EF71-EM71 -> 37.429 | EO71: =EM71/EF71 -> 0.075484747 | EP71: 699.015 | EQ71: 7.996 | ER71: 42.113 | ES71: 5.929 | ET71: 31.125 | EU71: 48.714 | EV71: 28.374 | EW71: 12.14 | EX71: =EW71+EU71+ET71+ES71+ER71+EQ71 -> 148.017 | EY71: =EP71-EX71 -> 550.998 | EZ71: =EX71/EP71 -> 0.21175082 | FA71: =(BX71+(EP71-EP70)-DJ71)/EP70 -> 0.13280295 | FB71: =(BY71+(EQ71-EQ70)-DK71)/EQ70 -> 0.30584335 | FC71: =(BZ71+(ER71-ER70)-DL71)/ER70 -> 0.34440764 | FD71: =(CA71+(ES71-ES70)-DM71)/ES70 -> 0.21980983 | FE71: =(CB71+(ET71-ET70)-DN71)/ET70 -> 0.19951268 | FF71: =(CC71+(EU71-EU70)-DO71)/EU70 -> 0.10442921 | FG71: =(CD71+(EV71-EV70)-DP71)/EV70 -> 0.0975842 | FH71: =(CF71+(EW71-EW70)-DQ71)/EW70 -> 0.24853748 | FI71: =(CG71+(EX71-EX70)-DR71)/EX70 -> 0.20815523 | FJ71: =(CH71+(EY71-EY70)-DS71)/EY70 -> 0.11231725 | FK71: =(CH71+AO71+(EY71-EY70)-DS71)/EY70 -> 0.18183592 | FL71: =BX71/EP70 -> 0.14251427 | FM71: =BY71/EQ70 -> 0.29727863 | FN71: =BZ71/ER70 -> 0.24945632 | FO71: =CA71/ES70 -> 0.20459588 | FP71: =CB71/ET70 -> 0.15053031 | FQ71: =CC71/EU70 -> 0.10962194 | FR71: =CD71/EV70 -> 0.10661259 | FS71: =CF71/EW70 -> 0.22541133 | FT71: =CG71/EX70 -> 0.17485192 | FU71: =CH71/EY70 -> 0.13372278
B72: 1996 | C72: 6899.4 | D72: 786.1 | E72: =D72/C72 -> 0.11393744 | F72: =D72-(G72+I72) -> 0 | G72: =D72-I72 -> 684.1 | H72: =G72/C72 -> 0.09915355 | I72: 102 | J72: =I72/C72 -> 0.014783894 | K72: =I72/D72 -> 0.12975448 | L72: 139.4 | M72: =L72/C72 -> 0.020204655 | N72: =L72/D72 -> 0.17733113 | O72: =D72 -> 786.1 | P72: =O72-(Q72+R72+T72+U72+X72-V72) -> 0 | Q72: 797.6 | R72: 94.1 | S72: =R72/D72 -> 0.11970487 | T72: 22.7 | U72: 47.3 | V72: 132.8 | W72: =V72/D72 -> 0.16893525 | X72: =O72-(Q72+R72+T72+U72-V72) -> -42.8 | Y72: 93.858493 | Z72: =Z73*Y72/Y73 -> -7.1673534 | AC72: =Y72+Z72 -> 86.69114 | AD72: =AC72/D72 -> 0.11028004 | AE72: 102.563 | AF72: 88.092104 | AG72: 231.5 | AH72: =AG72/C72 -> 0.033553642 | AI72: =(AG72-AN72)/C72 -> 0.030640346 | AJ72: =AG72-(AK72+AL72+AM72+AN72) -> 0.1 | AK72: 170.5 | AL72: 33 | AM72: 7.8 | AN72: 20.1 | AO72: 43.3 | AP72: 174.44125 | AT72: =(O72-AG72)/C72 -> 0.080383801 | AU72: 0.35 | AV72: =(AK72+AL72)/(G72+L72-T72) -> 0.25412088 | AW72: =(AK72+AL72)/(G72+L72-T72-AE72) -> 0.29144832 | AX72: =(AG72-AN72-AM72)/(G72+L72-T72+V72) -> 0.21808055 | AY72: =(AG72-AN72-AM72+AO72)/(G72+L72-T72+AO72) -> 0.29250089 | AZ72: =(AG72-AN72-AM72+AO72)/(G72+L72-T72+AO72-AC72) -> 0.32597981 | BA72: =(AG72-AN72)/Q72 -> 0.26504514 | BB72: =(AG72-AN72)/(Q72+R72) -> 0.23707525 | BC72: =D72 -> 786.1 | BD72: =BC72-(BE72+BF72+BG72) -> 0 | BE72: =AG72 -> 231.5 | BF72: 303.5 | BG72: 251.1 | BH72: =BG72/D72 -> 0.31942501 | BI72: 189.5 | BJ72: =BG72-BI72 -> 61.6 | BK72: =BJ72/D72 -> 0.078361532 | BL72: =DD72/(D72) -> 0.020057245 | BM72: =DD72/(CV72+CW72) -> 0.16980055 | BN72: =CQ72*DF72 -> 0.16846165 | BO72: =BJ72/I72 -> 0.60392157 | BP72: 45.623 | BQ72: =L72 -> 139.4 | BX72: 93.594 | BY72: 1.982 | BZ72: 9.632 | CA72: 1.504 | CB72: 4.42 | CC72: =CD72+CE72 -> 5.467 | CD72: 3.362 | CE72: 2.105 | CF72: 2.751 | CG72: =BY72+BZ72+CA72+CB72+CD72+CE72+CF72 -> 25.756 | CH72: =BX72-CG72 -> 67.838 | CI72: =BY72/$BX72 -> 0.021176571 | CJ72: =BZ72/$BX72 -> 0.10291258 | CK72: =CA72/$BX72 -> 0.016069406 | CL72: =CB72/$BX72 -> 0.047225249 | CM72: =CN72+CO72 -> 0.058411864 | CN72: =CD72/$BX72 -> 0.035921106 | CO72: =CE72/$BX72 -> 0.022490758 | CP72: =CF72/$BX72 -> 0.02939291 | CQ72: =CG72/$BX72 -> 0.27518858 | CR72: =CQ72*N72 -> 0.048799501 | CS72: =BX72 -> 93.594 | CT72: =BX72 -> 93.594 | CU72: =CT72-(CV72+CW72) -> 0.738 | CV72: 45.623 | CW72: 47.233 | CX72: 1.403 | CY72: 6.812 | CZ72: 1.019 | DA72: 1.713 | DB72: 2.96 | DC72: 1.86 | DD72: =DC72+DB72+DA72+CZ72+CY72+CX72 -> 15.767 | DF72: =DD72/CG72 -> 0.61216804 | DG72: =CW72-DD72 -> 31.466 | DH72: =DD72/CW72 -> 0.33381322 | DI72: =CW72/(CW72+CV72) -> 0.50866934 | DJ72: 84.426 | DK72: 1.954 | DL72: 6.308 | DM72: 1.041 | DN72: 1.264 | DO72: 6.371 | DP72: 3.17 | DQ72: 2.76 | DR72: =DQ72+DO72+DN72+DM72+DL72+DK72 -> 19.698 | DS72: =DJ72-DR72 -> 64.728 | DT72: =DR72/DJ72 -> 0.23331675 | DU72: =DJ72-CW72 -> 37.193 | DV72: 37.194 | DW72: =DK72-CX72 -> 0.551 | DX72: =DL72-CY72 -> -0.504 | DY72: =DM72-CZ72 -> 0.022 | DZ72: =DN72-DA72 -> -0.449 | EA72: =DO72-DB72 -> 3.411 | EB72: =DQ72-DC72 -> 0.9 | EC72: =EB72+EA72+DZ72+DY72+DX72+DW72 -> 3.931 | ED72: =DU72-EC72 -> 33.262 | EE72: =EC72/DU72 -> 0.10569193 | EF72: 27.533 | EG72: 0.328 | EH72: 1.428 | EI72: -0.042 | EJ72: 0.402 | EK72: 1.247 | EL72: 0.227 | EM72: =EL72+EK72+EJ72+EI72+EH72+EG72 -> 3.59 | EN72: =EF72-EM72 -> 23.943 | EO72: =EM72/EF72 -> 0.13038899 | EP72: 795.195 | EQ72: 10.133 | ER72: 54.118 | ES72: 7.753 | ET72: 30.744 | EU72: 60.886 | EV72: 37.091 | EW72: 14.912 | EX72: =EW72+EU72+ET72+ES72+ER72+EQ72 -> 178.546 | EY72: =EP72-EX72 -> 616.649 | EZ72: =EX72/EP72 -> 0.22453109 | FA72: =(BX72+(EP72-EP71)-DJ72)/EP71 -> 0.15070921 | FB72: =(BY72+(EQ72-EQ71)-DK72)/EQ71 -> 0.27076038 | FC72: =(BZ72+(ER72-ER71)-DL72)/ER71 -> 0.36399687 | FD72: =(CA72+(ES72-ES71)-DM72)/ES71 -> 0.38573115 | FE72: =(CB72+(ET72-ET71)-DN72)/ET71 -> 0.089156627 | FF72: =(CC72+(EU72-EU71)-DO72)/EU71 -> 0.23130927 | FG72: =(CD72+(EV72-EV71)-DP72)/EV71 -> 0.31398463 | FH72: =(CF72+(EW72-EW71)-DQ72)/EW71 -> 0.22759473 | FI72: =(CG72+(EX72-EX71)-DR72)/EX71 -> 0.24718107 | FJ72: =(CH72+(EY72-EY71)-DS72)/EY71 -> 0.12479356 | FK72: =(CH72+AO72+(EY72-EY71)-DS72)/EY71 -> 0.20337823 | FL72: =BX72/EP71 -> 0.13389412 | FM72: =BY72/EQ71 -> 0.24787394 | FN72: =BZ72/ER71 -> 0.22871797 | FO72: =CA72/ES71 -> 0.25366841 | FP72: =CB72/ET71 -> 0.14200803 | FQ72: =CC72/EU71 -> 0.11222646 | FR72: =CD72/EV71 -> 0.11848876 | FS72: =CF72/EW71 -> 0.22660626 | FT72: =CG72/EX71 -> 0.17400704 | FU72: =CH72/EY71 -> 0.12311841
B73: 1997 | C73: 7380.4 | D73: 865.8 | E73: =D73/C73 -> 0.11731071 | F73: =D73-(G73+I73) -> 0 | G73: =D73-I73 -> 758.2 | H73: =G73/C73 -> 0.10273156 | I73: 107.6 | J73: =I73/C73 -> 0.014579156 | K73: =I73/D73 -> 0.12427812 | L73: 155.5 | M73: =L73/C73 -> 0.021069319 | N73: =L73/D73 -> 0.17960268 | O73: =D73 -> 865.8 | P73: =O73-(Q73+R73+T73+U73+X73-V73) -> 0 | Q73: 905.5 | R73: 107.7 | S73: =R73/D73 -> 0.12439362 | T73: 24.4 | U73: 68.9 | V73: 200.8 | W73: =V73/D73 -> 0.23192423 | X73: =O73-(Q73+R73+T73+U73-V73) -> -39.9 | Y73: 112.66593 | Z73: =Z74*Y73/Y74 -> -8.6035534 | AC73: =Y73+Z73 -> 104.06238 | AD73: =AC73/D73 -> 0.12019217 | AE73: 118.073 | AF73: 102.58317 | AG73: 245.4 | AH73: =AG73/C73 -> 0.03325023 | AI73: =(AG73-AN73)/C73 -> 0.030445504 | AJ73: =AG73-(AK73+AL73+AM73+AN73) -> -0.1 | AK73: 182.4 | AL73: 34.1 | AM73: 8.3 | AN73: 20.7 | AO73: 44.9 | AP73: 183.889 | AT73: =(O73-AG73)/C73 -> 0.084060485 | AU73: 0.35 | AV73: =(AK73+AL73)/(G73+L73-T73) -> 0.2434499 | AW73: =(AK73+AL73)/(G73+L73-T73-AE73) -> 0.2807215 | AX73: =(AG73-AN73-AM73)/(G73+L73-T73+V73) -> 0.1985139 | AY73: =(AG73-AN73-AM73+AO73)/(G73+L73-T73+AO73) -> 0.27970456 | AZ73: =(AG73-AN73-AM73+AO73)/(G73+L73-T73+AO73-AC73) -> 0.31476709 | BA73: =(AG73-AN73)/Q73 -> 0.24815019 | BB73: =(AG73-AN73)/(Q73+R73) -> 0.2217726 | BC73: =D73 -> 865.8 | BD73: =BC73-(BE73+BF73+BG73) -> 0 | BE73: =AG73 -> 245.4 | BF73: 339.5 | BG73: 280.9 | BH73: =BG73/D73 -> 0.32443982 | BI73: 220.6 | BJ73: =BG73-BI73 -> 60.3 | BK73: =BJ73/D73 -> 0.06964657 | BL73: =DD73/(D73) -> 0.020359205 | BM73: =DD73/(CV73+CW73) -> 0.16920729 | BN73: =CQ73*DF73 -> 0.1682062 | BO73: =BJ73/I73 -> 0.56040892 | BP73: 55.196 | BQ73: =L73 -> 155.5 | BX73: 104.794 | BY73: 2.348 | BZ73: 11.588 | CA73: 1.558 | CB73: 5.071 | CC73: =CD73+CE73 -> 7.076 | CD73: 3.965 | CE73: 3.111 | CF73: 3.465 | CG73: =BY73+BZ73+CA73+CB73+CD73+CE73+CF73 -> 31.106 | CH73: =BX73-CG73 -> 73.688 | CI73: =BY73/$BX73 -> 0.022405863 | CJ73: =BZ73/$BX73 -> 0.11057885 | CK73: =CA73/$BX73 -> 0.014867263 | CL73: =CB73/$BX73 -> 0.048390175 | CM73: =CN73+CO73 -> 0.06752295 | CN73: =CD73/$BX73 -> 0.037836136 | CO73: =CE73/$BX73 -> 0.029686814 | CP73: =CF73/$BX73 -> 0.03306487 | CQ73: =CG73/$BX73 -> 0.29682997 | CR73: =CQ73*N73 -> 0.053311458 | CS73: =BX73 -> 104.794 | CT73: =BX73 -> 104.794 | CU73: =CT73-(CV73+CW73) -> 0.62 | CV73: 55.196 | CW73: 48.978 | CX73: 1.088 | CY73: 8.785 | CZ73: 1.249 | DA73: 0.423 | DB73: 3.708 | DC73: 2.374 | DD73: =DC73+DB73+DA73+CZ73+CY73+CX73 -> 17.627 | DF73: =DD73/CG73 -> 0.56667524 | DG73: =CW73-DD73 -> 31.351 | DH73: =DD73/CW73 -> 0.35989628 | DI73: =CW73/(CW73+CV73) -> 0.4701557 | DJ73: 95.769 | DK73: 2.266 | DL73: 12.45 | DM73: 2.444 | DN73: -0.792 | DO73: 3.463 | DP73: 0.589 | DQ73: 3.697 | DR73: =DQ73+DO73+DN73+DM73+DL73+DK73 -> 23.528 | DS73: =DJ73-DR73 -> 72.241 | DT73: =DR73/DJ73 -> 0.24567449 | DU73: =DJ73-CW73 -> 46.791 | DV73: 46.791 | DW73: =DK73-CX73 -> 1.178 | DX73: =DL73-CY73 -> 3.665 | DY73: =DM73-CZ73 -> 1.195 | DZ73: =DN73-DA73 -> -1.215 | EA73: =DO73-DB73 -> -0.245 | EB73: =DQ73-DC73 -> 1.323 | EC73: =EB73+EA73+DZ73+DY73+DX73+DW73 -> 5.901 | ED73: =DU73-EC73 -> 40.89 | EE73: =EC73/DU73 -> 0.126114 | EF73: 40.792 | EG73: 0.877 | EH73: 2.939 | EI73: 0.142 | EJ73: 0.835 | EK73: 2.226 | EL73: 0.451 | EM73: =EL73+EK73+EJ73+EI73+EH73+EG73 -> 7.47 | EN73: =EF73-EM73 -> 33.322 | EO73: =EM73/EF73 -> 0.18312414 | EP73: 871.316 | EQ73: 11.339 | ER73: 68.619 | ES73: 10.258 | ET73: 30.634 | EU73: 62.761 | EV73: 38.071 | EW73: 18.026 | EX73: =EW73+EU73+ET73+ES73+ER73+EQ73 -> 201.637 | EY73: =EP73-EX73 -> 669.679 | EZ73: =EX73/EP73 -> 0.23141662 | FA73: =(BX73+(EP73-EP72)-DJ73)/EP72 -> 0.10707562 | FB73: =(BY73+(EQ73-EQ72)-DK73)/EQ72 -> 0.12710944 | FC73: =(BZ73+(ER73-ER72)-DL73)/ER72 -> 0.25202336 | FD73: =(CA73+(ES73-ES72)-DM73)/ES72 -> 0.20882239 | FE73: =(CB73+(ET73-ET72)-DN73)/ET72 -> 0.18712594 | FF73: =(CC73+(EU73-EU72)-DO73)/EU72 -> 0.090135663 | FG73: =(CD73+(EV73-EV72)-DP73)/EV72 -> 0.11744089 | FH73: =(CF73+(EW73-EW72)-DQ73)/EW72 -> 0.19326717 | FI73: =(CG73+(EX73-EX72)-DR73)/EX72 -> 0.17177086 | FJ73: =(CH73+(EY73-EY72)-DS73)/EY72 -> 0.088343612 | FK73: =(CH73+AO73+(EY73-EY72)-DS73)/EY72 -> 0.16115651 | FL73: =BX73/EP72 -> 0.13178403 | FM73: =BY73/EQ72 -> 0.23171815 | FN73: =BZ73/ER72 -> 0.21412469 | FO73: =CA73/ES72 -> 0.20095447 | FP73: =CB73/ET72 -> 0.16494275 | FQ73: =CC73/EU72 -> 0.11621719 | FR73: =CD73/EV72 -> 0.10689925 | FS73: =CF73/EW72 -> 0.2323632 | FT73: =CG73/EX72 -> 0.17421841 | FU73: =CH73/EY72 -> 0.11949748
B74: 1998 | C74: 7857.3 | D74: 804.1 | E74: =D74/C74 -> 0.10233795 | F74: =D74-(G74+I74) -> 0 | G74: =D74-I74 -> 701.3 | H74: =G74/C74 -> 0.089254579 | I74: 102.8 | J74: =I74/C74 -> 0.013083375 | K74: =I74/D74 -> 0.1278448 | L74: 146.7 | M74: =L74/C74 -> 0.018670536 | N74: =L74/D74 -> 0.18244 | O74: =D74 -> 804.1 | P74: =O74-(Q74+R74+T74+U74+X74-V74) -> 0 | Q74: 834.5 | R74: 119.5 | S74: =R74/D74 -> 0.14861336 | T74: 25.8 | U74: 76 | V74: 201 | W74: =V74/D74 -> 0.24996891 | X74: =O74-(Q74+R74+T74+U74-V74) -> -50.7 | Y74: 125.84894 | Z74: =Z75*Y74/Y75 -> -9.6102525 | AC74: =Y74+Z74 -> 116.23869 | AD74: =AC74/D74 -> 0.1445575 | AE74: 149.954 | AF74: 114.47284 | AG74: 248.4 | AH74: =AG74/C74 -> 0.031613913 | AI74: =(AG74-AN74)/C74 -> 0.028228526 | AJ74: =AG74-(AK74+AL74+AM74+AN74) -> 0.1 | AK74: 177.6 | AL74: 34.9 | AM74: 9.2 | AN74: 26.6 | AO74: 39.8 | AP74: 187.67775 | AT74: =(O74-AG74)/C74 -> 0.07072404 | AU74: 0.35 | AV74: =(AK74+AL74)/(G74+L74-T74) -> 0.25845293 | AW74: =(AK74+AL74)/(G74+L74-T74-AE74) -> 0.31610452 | AX74: =(AG74-AN74-AM74)/(G74+L74-T74+V74) -> 0.20777952 | AY74: =(AG74-AN74-AM74+AO74)/(G74+L74-T74+AO74) -> 0.29280742 | AZ74: =(AG74-AN74-AM74+AO74)/(G74+L74-T74+AO74-AC74) -> 0.33844609 | BA74: =(AG74-AN74)/Q74 -> 0.2657879 | BB74: =(AG74-AN74)/(Q74+R74) -> 0.23249476 | BC74: =D74 -> 804.1 | BD74: =BC74-(BE74+BF74+BG74) -> -0.1 | BE74: =AG74 -> 248.4 | BF74: 357.1 | BG74: 198.7 | BH74: =BG74/D74 -> 0.24710857 | BI74: 138.2 | BJ74: =BG74-BI74 -> 60.5 | BK74: =BJ74/D74 -> 0.075239398 | BL74: =DD74/(D74) -> 0.021392862 | BM74: =DD74/(CV74+CW74) -> 0.19270927 | BN74: =CQ74*DF74 -> 0.18970841 | BO74: =BJ74/I74 -> 0.5885214 | BP74: 56.742 | BQ74: =L74 -> 146.7 | BX74: 90.676 | BY74: 4.565 | BZ74: 10.078 | CA74: 1.743 | CB74: 6.152 | CC74: =CD74+CE74 -> 6.838 | CD74: 3.658 | CE74: 3.18 | CF74: 1.771 | CG74: =BY74+BZ74+CA74+CB74+CD74+CE74+CF74 -> 31.147 | CH74: =BX74-CG74 -> 59.529 | CI74: =BY74/$BX74 -> 0.050344082 | CJ74: =BZ74/$BX74 -> 0.11114297 | CK74: =CA74/$BX74 -> 0.019222286 | CL74: =CB74/$BX74 -> 0.067845957 | CM74: =CN74+CO74 -> 0.075411355 | CN74: =CD74/$BX74 -> 0.040341435 | CO74: =CE74/$BX74 -> 0.035069919 | CP74: =CF74/$BX74 -> 0.019531078 | CQ74: =CG74/$BX74 -> 0.34349773 | CR74: =CQ74*N74 -> 0.062667724 | CS74: =BX74 -> 90.676 | CT74: =BX74 -> 90.676 | CU74: =CT74-(CV74+CW74) -> 1.412 | CV74: 56.742 | CW74: 32.522 | CX74: 3.696 | CY74: 7.776 | CZ74: 0.803 | DA74: 4.541 | DB74: 0.135 | DC74: 0.251 | DD74: =DC74+DB74+DA74+CZ74+CY74+CX74 -> 17.202 | DF74: =DD74/CG74 -> 0.55228433 | DG74: =CW74-DD74 -> 15.32 | DH74: =DD74/CW74 -> 0.52893426 | DI74: =CW74/(CW74+CV74) -> 0.36433501 | DJ74: 131.004 | DK74: 7.891 | DL74: 22.213 | DM74: 4.084 | DN74: 8.223 | DO74: 3.684 | DP74: 2.358 | DQ74: 0.261 | DR74: =DQ74+DO74+DN74+DM74+DL74+DK74 -> 46.356 | DS74: =DJ74-DR74 -> 84.648 | DT74: =DR74/DJ74 -> 0.35385179 | DU74: =DJ74-CW74 -> 98.482 | DV74: 98.482 | DW74: =DK74-CX74 -> 4.195 | DX74: =DL74-CY74 -> 14.437 | DY74: =DM74-CZ74 -> 3.281 | DZ74: =DN74-DA74 -> 3.682 | EA74: =DO74-DB74 -> 3.549 | EB74: =DQ74-DC74 -> 0.01 | EC74: =EB74+EA74+DZ74+DY74+DX74+DW74 -> 29.154 | ED74: =DU74-EC74 -> 69.328 | EE74: =EC74/DU74 -> 0.29603379 | EF74: 72.447 | EG74: 1.445 | EH74: 4.776 | EI74: 0.231 | EJ74: 1.186 | EK74: 6.267 | EL74: 0.546 | EM74: =EL74+EK74+EJ74+EI74+EH74+EG74 -> 14.451 | EN74: =EF74-EM74 -> 57.996 | EO74: =EM74/EF74 -> 0.19946996 | EP74: 1000.703 | EQ74: 21.825 | ER74: 89.978 | ES74: 14.571 | ET74: 38.225 | EU74: 68.127 | EV74: 41.908 | EW74: 17.55 | EX74: =EW74+EU74+ET74+ES74+ER74+EQ74 -> 250.276 | EY74: =EP74-EX74 -> 750.427 | EZ74: =EX74/EP74 -> 0.25010018 | FA74: =(BX74+(EP74-EP73)-DJ74)/EP73 -> 0.10221206 | FB74: =(BY74+(EQ74-EQ73)-DK74)/EQ73 -> 0.63144898 | FC74: =(BZ74+(ER74-ER73)-DL74)/ER73 -> 0.13442341 | FD74: =(CA74+(ES74-ES73)-DM74)/ES73 -> 0.1922402 | FE74: =(CB74+(ET74-ET73)-DN74)/ET73 -> 0.18019194 | FF74: =(CC74+(EU74-EU73)-DO74)/EU73 -> 0.1357531 | FG74: =(CD74+(EV74-EV73)-DP74)/EV73 -> 0.1349321 | FH74: =(CF74+(EW74-EW73)-DQ74)/EW73 -> 0.057361589 | FI74: =(CG74+(EX74-EX73)-DR74)/EX73 -> 0.16579298 | FJ74: =(CH74+(EY74-EY73)-DS74)/EY73 -> 0.083068157 | FK74: =(CH74+AO74+(EY74-EY73)-DS74)/EY73 -> 0.14249962 | FL74: =BX74/EP73 -> 0.10406787 | FM74: =BY74/EQ73 -> 0.40259282 | FN74: =BZ74/ER73 -> 0.14686894 | FO74: =CA74/ES73 -> 0.16991616 | FP74: =CB74/ET73 -> 0.20082262 | FQ74: =CC74/EU73 -> 0.10895301 | FR74: =CD74/EV73 -> 0.096083633 | FS74: =CF74/EW73 -> 0.098246977 | FT74: =CG74/EX73 -> 0.15447066 | FU74: =CH74/EY73 -> 0.088891842
