Workbook
Name column_headings: #REF!
Name column_headings: #REF!
Name column_headings: #REF!
Name column_headings: #REF!
Name column_headings: #REF!
Name column_headings: #REF!
Name column_headings: #REF!
Name column_headings: #REF!
Name column_headings: #REF!
Name column_numbers: #REF!
Name column_numbers: #REF!
Name column_numbers: #REF!
Name column_numbers: #REF!
Name column_numbers: #REF!
Name column_numbers: #REF!
Name column_numbers: #REF!
Name column_numbers: #REF!
Name column_numbers: #REF!
Name d: #REF!
Name d: #REF!
Name d: #REF!
Name d: #REF!
Name d: #REF!
Name d: #REF!
Name d: #REF!
Name d: #REF!
Name d: #REF!
Name data: #REF!
Name data: #REF!
Name data: #REF!
Name data: #REF!
Name data: #REF!
Name data: #REF!
Name data: #REF!
Name data: #REF!
Name data: #REF!
Name e: #REF!
Name e: #REF!
Name e: #REF!
Name e: #REF!
Name e: #REF!
Name e: #REF!
Name e: #REF!
Name e: #REF!
Name e: #REF!
Name ea_flux: #REF!
Name ea_flux: #REF!
Name ea_flux: #REF!
Name ea_flux: #REF!
Name ea_flux: #REF!
Name ea_flux: #REF!
Name ea_flux: #REF!
Name ea_flux: #REF!
Name ea_flux: #REF!
Name Equilibre: #REF!
Name Equilibre: #REF!
Name Equilibre: #REF!
Name Equilibre: #REF!
Name Equilibre: #REF!
Name Equilibre: #REF!

Sheet Table A0
B3: Main Tables
B4: Table | C4: A1 | D4: Global Cross-Border Securities Assets
B5: Table | C5: A2 | D5: Global Cross-Border Securities Liabilities
B6: Table | C6: A3 | D6: Global Discrepancy Between Cross-Border Securities Assets and Liabilities
C7: Securities Assets (Appendix Section A)
B8: Table | C8: A4 | D8: Main Holders of Cross-Border Securities
B9: Table | C9: A5 | D9: Sectoral Breakdown of Securities Claims Reported in the CPIS, year-end 2008
B10: Table | C10: A6 | D10: Cayman Islands' Cross-Border Securities Assets and Liabilities
B11: Table | C11: A7 | D11: China's Cross-Border Securities Assets
B12: Table | C12: A8 | D12: Middle-East Oil Exporting Countries' Cross-Border Securities Assets
B13: Table | C13: A9 | D13: Other non-CPIS Countries Cross-Border Securities Assets
B14: Table | C14: A9b | D14: Bilateral Portfoio Holdings, Panel Regressions
B15: Table | C15: A9c | D15: Bilateral Portfoio Holdings in and of Offshore Financial Centers, Panel Regressions
C16: Securities Liabilities (Appendix Section B)
B17: Table | C17: A10 | D17: Cross-Border Equity Liabilities of Small Offshore Financial Centers
B18: Table | C18: A11 | D18: Cross-Border Debt Liabilities of Small Offshore Financial Centers
B19: Table | C19: A12 | D19: Raw CPIS-derived liabilities > reported liabilities (bn of USD)
D20: Missing Securities (Appendix Section C)
B21: Table | C21: A13 | D21: Reported Equity Liabilities Minus Creditor-Derived Liabilities
B22: Table | C22: A14 | D22: Reported Debt Liabilities Minus Creditor-Derived Liabilities
B23: Table | C23: A15 | D23: Investment Patterns of Reserve Managers and International Organizations (SEFER-SSIO)
B24: Table | C24: A16 | D24: Recorded vs. Predicted Shares of Each Developed Country in the Global Portfolio of CPIS-Participating Countries
B25: Table | C25: A17 | D25: Recorded vs. predicted shares of each country in the U.S., Japanese, and French portfolios
B26: Table | C26: A18 | D26: Unindentified Investments in U.S. Equities
C27: Flow Data (Appendix Section D)
B28: Table | C28: A19 | D28: The World Current Account: Credits
B29: Table | C29: A20 | D29: The World Current Acount: Debits
B30: Table | C30: A21 | D30: The World Current Account: Discrepancies
B31: Table | C31: A22 | D31: Yield on Global Cross-Border Bank Deposits and Portfolio Claims
C32: Offshore Fortunes in Switzerland (Appendix Section E)
B33: Table | C33: A23 | D33: Securities in Custody in Swiss Banks
B34: Table | C34: A24 | D34: Fiduciary Deposits in Swiss Banks, 1976-2008
B35: Table | C35: A25 | D35: Distribution of Fiduciary Deposits in Swiss Banks by Country of Owner, Uncorrected Shares
B36: Table | C36: A26 | D36: Distribution of Fiduciary Deposits in Swiss Banks by Country of Owner, Corrected Shares
D37: Net Foreign Asset Positions (Appendix Section F)
B38: Table | C38: A27 | D38: Net Foreign Asset Positions of Rich Countries, As Officially Reported
B39: Table | C39: A28 | D39: Euro-Area Net Foreign Asset Position/Euro-Area GDP
B40: Table | C40: A29 | D40: U.S. Net Foreign Asset Position/U.S. GDP
B41: Table | C41: A30 | D41: Households' Unrecorded Offshore Assets vs. Net Debt of the World
B42: Table | C42: A31 | D42: Euro-Area Net Foreign Asset Position/Euro-Area GDP, World IIP balanced
B43: Table | C43: A32 | D43: Rich World Net Foreign Asset Position/Rich World GDP, World IIP balanced

Sheet Table A1
B2: Table A1: Global Cross-Border Securities Assets
C4: [1] | D4: [2] | E4: [3] | F4: [4] | G4: [5] | H4: [6] | I4: [7] | J4: [8] | K4: [9] | L4: [10] | M4: [11] | N4: [12] | O4: [13] | P4: [14] | Q4: [15] | R4: [16]
C5: Billions of current USD
C6: CPIS assets | D6: Of which: SEFER + SSIO | E6: Correction for CPIS reporting countries | G6: Correction for non-CPIS reporting countries | O6: Total securities assets | P6: Of which: reserves + int'l orga.
E7: Cayman Islands non-bank sector | F7: Other | G7: China | I7: Middle-East oil exporters (onshore) | L7: Other
H8: Of which: held as reserve | J8: Of which: held as reserve | K8: Of which: reported in CPIS | L8: Middle-East oil exporters onshore assets | M8: Of which: private portfolios | N8: Of which: reserve | Q8: Memo: (CPIS + SEFER) / Total assets | R8: Memo: reserve minus bank deposits
C9: Panel A: All securities
B11: 2001 | C11: =C21+C31 -> 12710.853 | D11: =D21+D31 -> 1281.8058 | E11: =E21+E31 -> 291.65509 | F11: =F21+F31 -> 36.468623 | G11: =G21+G31 -> 213.7776 | H11: =H21+H31 -> 180.34025 | I11: =I21+I31 -> 146.4572 | J11: {=0.75*TRANSPOSE('Table A8'!D24:K24)} -> 49.197753 | K11: =K21+K31 -> 21.680933 | L11: =L21+L31 -> 363.03952 | M11: =M21+M31 -> 174.01075 | N11: =N21+N31 -> 189.02877 | O11: =C11+E11+F11+G11+I11-K11+L11 -> 13740.57 | P11: =P21+P31 -> 1700.3726 | Q11: =C11/O11 -> 0.92506009 | R11: =(RawDataSources!AI41-RawDataSources!AM41)/1000 -> 1657.247
B12: =B11+1 -> 2002 | C12: =C22+C32 -> 14115.852 | D12: =D22+D32 -> 1429.1011 | E12: =E22+E32 -> 371.16791 | F12: =F22+F32 -> 46.760597 | G12: =G22+G32 -> 290.22395 | H12: =H22+H32 -> 243.44595 | I12: =I22+I32 -> 136.91837 | J12: 55.144694 | K12: =K22+K32 -> 21.372506 | L12: =L22+L32 -> 422.43993 | M12: =M22+M32 -> 192.039 | N12: =N22+N32 -> 230.40093 | O12: =C12+E12+F12+G12+I12-K12+L12 -> 15361.99 | P12: =P22+P32 -> 1958.0927 | Q12: =C12/O12 -> 0.91888172 | R12: =(RawDataSources!AI42-RawDataSources!AM42)/1000 -> 1986.048
B13: =B12+1 -> 2003 | C13: =C23+C33 -> 19046.516 | D13: =D23+D33 -> 1849.7833 | E13: =E23+E33 -> 555.8249 | F13: =F23+F33 -> 59.053496 | G13: =G23+G33 -> 407.24592 | H13: =H23+H33 -> 342.76335 | I13: =I23+I33 -> 166.65121 | J13: 58.258316 | K13: =K23+K33 -> 28.836573 | L13: =L23+L33 -> 573.39657 | M13: =M23+M33 -> 281.51793 | N13: =N23+N33 -> 291.87863 | O13: =C13+E13+F13+G13+I13-K13+L13 -> 20779.851 | P13: =P23+P33 -> 2542.6836 | Q13: =C13/O13 -> 0.91658576 | R13: =(RawDataSources!AI43-RawDataSources!AM43)/1000 -> 2442.239
B14: =B13+1 -> 2004 | C14: =C24+C34 -> 23268.837 | D14: =D24+D34 -> 2145.013 | E14: =E24+E34 -> 799.76576 | F14: =F24+F34 -> 46.932239 | G14: =G24+G34 -> 611.26998 | H14: =H24+H34 -> 518.4422 | I14: =I24+I34 -> 247.71803 | J14: 77.82074 | K14: =K24+K34 -> 35.311256 | L14: =L24+L34 -> 694.88537 | M14: =M24+M34 -> 340.07844 | N14: =N24+N34 -> 354.80693 | O14: =C14+E14+F14+G14+I14-K14+L14 -> 25634.097 | P14: =P24+P34 -> 3096.0829 | Q14: =C14/O14 -> 0.90772992 | R14: =(RawDataSources!AI44-RawDataSources!AM44)/1000 -> 2985.902
B15: =B14+1 -> 2005 | C15: =C25+C35 -> 25892.148 | D15: =D25+D35 -> 2221.1363 | E15: =E25+E35 -> 839.10843 | F15: =F25+F35 -> 64.922443 | G15: =G25+G35 -> 813.72616 | H15: =H25+H35 -> 696.0412 | I15: =I25+I35 -> 309.96829 | J15: 96.484877 | K15: =K25+K35 -> 45.820693 | L15: =L25+L35 -> 848.94141 | M15: =M25+M35 -> 444.21981 | N15: =N25+N35 -> 404.7216 | O15: =C15+E15+F15+G15+I15-K15+L15 -> 28722.994 | P15: =P25+P35 -> 3418.384 | Q15: =C15/O15 -> 0.90144321 | R15: =(RawDataSources!AI45-RawDataSources!AM45)/1000 -> 3371.147
B16: =B15+1 -> 2006 | C16: =C26+C36 -> 32964.246 | D16: =D26+D36 -> 2558.3584 | E16: =E26+E36 -> 1252.293 | F16: =F26+F36 -> 57.730729 | G16: =G26+G36 -> 1174.2003 | H16: =H26+H36 -> 906.389 | I16: =I26+I36 -> 431.42602 | J16: 123.54326 | K16: =K26+K36 -> 62.728798 | L16: =L26+L36 -> 1154.4216 | M16: =M26+M36 -> 659.75461 | N16: =N26+N36 -> 494.66695 | O16: =C16+E16+F16+G16+I16-K16+L16 -> 36971.589 | P16: =P26+P36 -> 4082.9576 | Q16: =C16/O16 -> 0.89161021 | R16: =(RawDataSources!AI46-RawDataSources!AM46)/1000 -> 4068.289
B17: =B16+1 -> 2007 | C17: =C27+C37 -> 39064.507 | D17: =D27+D37 -> 3109.3694 | E17: =E27+E37 -> 1543.7509 | F17: =F27+F37 -> 91.012539 | G17: =G27+G37 -> 1584.8535 | H17: =H27+H37 -> 1299.0125 | I17: =I27+I37 -> 590.4653 | J17: 201.45624 | K17: =K27+K37 -> 79.214444 | L17: =L27+L37 -> 1374.7419 | M17: =M27+M37 -> 789.8375 | N17: =N27+N37 -> 584.90439 | O17: =C17+E17+F17+G17+I17-K17+L17 -> 44170.116 | P17: =P27+P37 -> 5194.7425 | Q17: =C17/O17 -> 0.88441032 | R17: =(RawDataSources!AI47-RawDataSources!AM47)/1000 -> 5257.231
B18: =B17+1 -> 2008 | C18: =C28+C38 -> 30717.961 | D18: =D28+D38 -> 3643.0773 | E18: =E28+E38 -> 1202.651 | F18: =F28+F38 -> 84.203377 | G18: =G28+G38 -> 1906.0057 | H18: =H28+H38 -> 1654.1255 | I18: =I28+I38 -> 587.02789 | J18: 180.19177 | K18: =K28+K38 -> 73.597697 | L18: =L28+L38 -> 1183.0504 | M18: =M28+M38 -> 536.0478 | N18: =N28+N38 -> 647.00258 | O18: =C18+E18+F18+G18+I18-K18+L18 -> 35607.301 | P18: =P28+P38 -> 6124.3972 | Q18: =C18/O18 -> 0.86268713 | R18: =(RawDataSources!AI48-RawDataSources!AM48)/1000 -> 6196.806
C19: Panel B: Equities
B21: 2001 | C21: =RawDataSources!B41/1000 -> 5200.1451 | D21: =RawDataSources!C41/1000 -> 17.159837 | E21: {=TRANSPOSE('Table A6'!D15:K15)-TRANSPOSE('Table A6'!D20:K20)} -> 163.95461 | F21: =(RawDataSources!M41+RawDataSources!O41)/1000 -> 7.3843888 | G21: {=TRANSPOSE('Table A7'!D25:K25)} -> 5.4734656 | H21: {=TRANSPOSE('Table A7'!D9:K9)} -> 4.3428278 | I21: {=TRANSPOSE('Table A8'!D23:K23)} -> 64.55 | J21: =J11*I21/I11 -> 21.683569 | K21: {=TRANSPOSE('Table A8'!$D$11:$K$11)} -> 6.3482286 | L21: =M21+N21 -> 118.5172 | M21: {=TRANSPOSE('Table A9'!D12:K12)} -> 115.99681 | N21: {=TRANSPOSE('Table A9'!D8:K8)} -> 2.5203835 | O21: =C21+E21+F21+G21+I21-K21+L21 -> 5553.6765 | P21: =D21+J21+H21+N21 -> 45.706618 | Q21: =C21/O21 -> 0.93634281
B22: =B21+1 -> 2002 | C22: =RawDataSources!B42/1000 -> 4796.3675 | D22: =RawDataSources!C42/1000 -> 14.372878 | E22: 197.16352 | F22: =(RawDataSources!M42+RawDataSources!O42)/1000 -> 8.8240881 | G22: 3.6354878 | H22: 2.8582829 | I22: 55.686765 | J22: =J12*I22/I12 -> 22.428178 | K22: 5.3800367 | L22: =M22+N22 -> 117.5484 | M22: 114.47639 | N22: 3.0720125 | O22: =C22+E22+F22+G22+I22-K22+L22 -> 5173.8457 | P22: =D22+J22+H22+N22 -> 42.731351 | Q22: =C22/O22 -> 0.92704107
B23: =B22+1 -> 2003 | C23: =RawDataSources!B43/1000 -> 6949.9986 | D23: =RawDataSources!C43/1000 -> 26.814457 | E23: 334.21691 | F23: =(RawDataSources!M43+RawDataSources!O43)/1000 -> 8.8998678 | G23: 3.3292932 | H23: 2.6290851 | I23: 87.266667 | J23: =J13*I23/I13 -> 30.506884 | K23: 7.7957429 | L23: =M23+N23 -> 170.1795 | M23: 166.28779 | N23: 3.8917147 | O23: =C23+E23+F23+G23+I23-K23+L23 -> 7546.0951 | P23: =D23+J23+H23+N23 -> 63.842141 | Q23: =C23/O23 -> 0.92100596
B24: =B23+1 -> 2004 | C24: =RawDataSources!B44/1000 -> 8705.2589 | D24: =RawDataSources!C44/1000 -> 35.078451 | E24: 401.83489 | F24: =(RawDataSources!M44+RawDataSources!O44)/1000 -> 3.8484327 | G24: 3.9627292 | H24: 3.1629463 | I24: 123.13594 | J24: =J14*I24/I14 -> 38.683214 | K24: 10.738219 | L24: =M24+N24 -> 198.25691 | M24: 193.52615 | N24: 4.7307592 | O24: =C24+E24+F24+G24+I24-K24+L24 -> 9425.5596 | P24: =D24+J24+H24+N24 -> 81.65537 | Q24: =C24/O24 -> 0.92358006
B25: =B24+1 -> 2005 | C25: =RawDataSources!B45/1000 -> 10586.279 | D25: =RawDataSources!C45/1000 -> 35.494522 | E25: 430.09094 | F25: =(RawDataSources!M45+RawDataSources!O45)/1000 -> 4.9295695 | G25: 4.3742458 | H25: 3.4282846 | I25: 153.02258 | J25: =J15*I25/I15 -> 47.631856 | K25: 15.751527 | L25: =M25+N25 -> 258.10074 | M25: 252.70445 | N25: 5.3962885 | O25: =C25+E25+F25+G25+I25-K25+L25 -> 11421.045 | P25: =D25+J25+H25+N25 -> 91.950951 | Q25: =C25/O25 -> 0.9269098
B26: =B25+1 -> 2006 | C26: =RawDataSources!B46/1000 -> 14248.964 | D26: =RawDataSources!C46/1000 -> 43.167668 | E26: 616.033 | F26: =(RawDataSources!M46+RawDataSources!O46)/1000 -> 9.5943506 | G26: 20.392324 | H26: 16.305992 | I26: 213.165 | J26: =J16*I26/I16 -> 61.041982 | K26: 24.550534 | L26: =M26+N26 -> 427.50216 | M26: 420.9066 | N26: 6.595559 | O26: =C26+E26+F26+G26+I26-K26+L26 -> 15511.1 | P26: =D26+J26+H26+N26 -> 127.1112 | Q26: =C26/O26 -> 0.91863012
B27: =B26+1 -> 2007 | C27: =RawDataSources!B47/1000 -> 17094.158 | D27: =RawDataSources!C47/1000 -> 54.442976 | E27: 773.38608 | F27: =(RawDataSources!M47+RawDataSources!O47)/1000 -> 24.280806 | G27: 104.23623 | H27: 83.373269 | I27: 258.72931 | J27: =J17*I27/I17 -> 88.27383 | K27: 33.396631 | L27: =M27+N27 -> 516.96149 | M27: 509.16276 | N27: 7.7987255 | O27: =C27+E27+F27+G27+I27-K27+L27 -> 18738.356 | P27: =D27+J27+H27+N27 -> 233.8888 | Q27: =C27/O27 -> 0.91225499
B28: =B27+1 -> 2008 | C28: =RawDataSources!B48/1000 -> 9836.2771 | D28: =RawDataSources!C48/1000 -> 39.445316 | E28: 458.23029 | F28: =(RawDataSources!M48+RawDataSources!O48)/1000 -> 21.706335 | G28: 94.675627 | H28: 73.915427 | I28: 182.59107 | J28: =J18*I28/I18 -> 56.047438 | K28: 39.106084 | L28: =M28+N28 -> 291.82285 | M28: 283.19614 | N28: 8.6267009 | O28: =C28+E28+F28+G28+I28-K28+L28 -> 10846.197 | P28: =D28+J28+H28+N28 -> 178.03488 | Q28: =C28/O28 -> 0.90688717
C29: Panel C: Debt
B31: 2001 | C31: =RawDataSources!D41/1000 -> 7510.7083 | D31: =RawDataSources!E41/1000 -> 1264.646 | E31: {=TRANSPOSE('Table A6'!D16:K16)-TRANSPOSE('Table A6'!D21:K21)} -> 127.70048 | F31: =(RawDataSources!N41+RawDataSources!P41)/1000 -> 29.084234 | G31: {=TRANSPOSE('Table A7'!D26:K26)} -> 208.30413 | H31: {=TRANSPOSE('Table A7'!D10:K10)} -> 175.99742 | I31: {=TRANSPOSE('Table A8'!D22:K22)-TRANSPOSE('Table A8'!D23:K23)} -> 81.907203 | J31: =J11*I31/I11 -> 27.514183 | K31: {=TRANSPOSE('Table A8'!$D$10:$K$10)-TRANSPOSE('Table A8'!$D$11:$K$11)} -> 15.332704 | L31: =M31+N31 -> 244.52232 | M31: {=TRANSPOSE('Table A9'!D13:K13)} -> 58.013934 | N31: {=TRANSPOSE('Table A9'!D9:K9)} -> 186.50839 | O31: =C31+E31+F31+G31+I31-K31+L31 -> 8186.8939 | P31: =D31+J31+H31+N31 -> 1654.6659 | Q31: =C31/O31 -> 0.91740632
B32: =B31+1 -> 2002 | C32: =RawDataSources!D42/1000 -> 9319.4843 | D32: =RawDataSources!E42/1000 -> 1414.7282 | E32: 174.00439 | F32: =(RawDataSources!N42+RawDataSources!P42)/1000 -> 37.936509 | G32: 286.58846 | H32: 240.58767 | I32: 81.23161 | J32: =J12*I32/I12 -> 32.716517 | K32: 15.992469 | L32: =M32+N32 -> 304.89153 | M32: 77.562613 | N32: 227.32892 | O32: =C32+E32+F32+G32+I32-K32+L32 -> 10188.144 | P32: =D32+J32+H32+N32 -> 1915.3613 | Q32: =C32/O32 -> 0.91473815
B33: =B32+1 -> 2003 | C33: =RawDataSources!D43/1000 -> 12096.517 | D33: =RawDataSources!E43/1000 -> 1822.9688 | E33: 221.60799 | F33: =(RawDataSources!N43+RawDataSources!P43)/1000 -> 50.153628 | G33: 403.91662 | H33: 340.13426 | I33: 79.384542 | J33: =J13*I33/I13 -> 27.751432 | K33: 21.04083 | L33: =M33+N33 -> 403.21707 | M33: 115.23015 | N33: 287.98692 | O33: =C33+E33+F33+G33+I33-K33+L33 -> 13233.756 | P33: =D33+J33+H33+N33 -> 2478.8414 | Q33: =C33/O33 -> 0.91406529
B34: =B33+1 -> 2004 | C34: =RawDataSources!D44/1000 -> 14563.578 | D34: =RawDataSources!E44/1000 -> 2109.9345 | E34: 397.93087 | F34: =(RawDataSources!N44+RawDataSources!P44)/1000 -> 43.083806 | G34: 607.30725 | H34: 515.27925 | I34: 124.5821 | J34: =J14*I34/I14 -> 39.137526 | K34: 24.573037 | L34: =M34+N34 -> 496.62846 | M34: 146.55229 | N34: 350.07617 | O34: =C34+E34+F34+G34+I34-K34+L34 -> 16208.538 | P34: =D34+J34+H34+N34 -> 3014.4275 | Q34: =C34/O34 -> 0.89851278
B35: =B34+1 -> 2005 | C35: =RawDataSources!D45/1000 -> 15305.869 | D35: =RawDataSources!E45/1000 -> 2185.6418 | E35: 409.01749 | F35: =(RawDataSources!N45+RawDataSources!P45)/1000 -> 59.992874 | G35: 809.35192 | H35: 692.61292 | I35: 156.94571 | J35: =J15*I35/I15 -> 48.853021 | K35: 30.069166 | L35: =M35+N35 -> 590.84067 | M35: 191.51536 | N35: 399.32531 | O35: =C35+E35+F35+G35+I35-K35+L35 -> 17301.949 | P35: =D35+J35+H35+N35 -> 3326.433 | Q35: =C35/O35 -> 0.88463268
B36: =B35+1 -> 2006 | C36: =RawDataSources!D46/1000 -> 18715.283 | D36: =RawDataSources!E46/1000 -> 2515.1907 | E36: 636.25997 | F36: =(RawDataSources!N46+RawDataSources!P46)/1000 -> 48.136378 | G36: 1153.808 | H36: 890.08301 | I36: 218.26102 | J36: =J16*I36/I16 -> 62.50128 | K36: 38.178264 | L36: =M36+N36 -> 726.9194 | M36: 238.84801 | N36: 488.07139 | O36: =C36+E36+F36+G36+I36-K36+L36 -> 21460.489 | P36: =D36+J36+H36+N36 -> 3955.8464 | Q36: =C36/O36 -> 0.8720809
B37: =B36+1 -> 2007 | C37: =RawDataSources!D47/1000 -> 21970.348 | D37: =RawDataSources!E47/1000 -> 3054.9264 | E37: 770.36478 | F37: =(RawDataSources!N47+RawDataSources!P47)/1000 -> 66.731733 | G37: 1480.6172 | H37: 1215.6392 | I37: 331.73599 | J37: =J17*I37/I17 -> 113.18241 | K37: 45.817813 | L37: =M37+N37 -> 857.7804 | M37: 280.67474 | N37: 577.10567 | O37: =C37+E37+F37+G37+I37-K37+L37 -> 25431.761 | P37: =D37+J37+H37+N37 -> 4960.8537 | Q37: =C37/O37 -> 0.86389411
B38: =B37+1 -> 2008 | C38: =RawDataSources!D48/1000 -> 20881.684 | D38: =RawDataSources!E48/1000 -> 3603.632 | E38: 744.42071 | F38: =(RawDataSources!N48+RawDataSources!P48)/1000 -> 62.497043 | G38: 1811.3301 | H38: 1580.2101 | I38: 404.43681 | J38: =J18*I38/I18 -> 124.14434 | K38: 34.491614 | L38: =M38+N38 -> 891.22753 | M38: 252.85165 | N38: 638.37588 | O38: =C38+E38+F38+G38+I38-K38+L38 -> 24761.104 | P38: =D38+J38+H38+N38 -> 5946.3623 | Q38: =C38/O38 -> 0.84332603

Sheet Table A2
B2: Table A2: Global Cross-Border Securities Liabilities
C3: [1] | D3: [2] | E3: [3] | F3: [4] | G3: [5] | H3: [6] | I3: [7] | J3: [8] | K3: [9] | L3: [10] | M3: [11] | N3: [12] | O3: [13] | P3: [14]
C4: Billions of current USD
C5: EWNII liabilities | D5: Memo: IMF IIPs | E5: Correction to EWNII data | H5: Non EWNII countries | L5: int'l orga. | M5: Total securities liabilities | O5: Memo: Int'l debt securities (BIS)
E6: No debt data | F6: Netherlands SFIs | G6: raw CPIS derived liabilities > reported liabilities | H6: Small OFCs | K6: Other
H7: Cayman Islands | I7: Other small OFCs | J7: Memo: small OFCs / Total | N7: EWNII liabilities / Total liabilities | P7: Cross-border debt / International debt
C8: Panel A: All securities
B10: 2001 | C10: =C20+C30 -> 14055.461 | D10: =D20+D30 -> 13144.364 | E10: =E30 -> 35.256787 | F10: =F20+F30 -> 264.93128 | G10: =G20+G30 -> 242.30787 | H10: =H20+H30 -> 708.37453 | I10: =I20+I30 -> 563.06188 | J10: =(H10+I10)/M10 -> 0.078133857 | K10: =K20+K30 -> 17.041344 | L10: =L20+L30 -> 386.10616 | M10: =C10+E10+F10+G10+H10+I10+K10+L10 -> 16272.541 | N10: =C10/M10 -> 0.86375331
B11: =B10+1 -> 2002 | C11: =C21+C31 -> 15332.219 | D11: =D21+D31 -> 15232.939 | E11: =E31 -> 30.771808 | F11: =F21+F31 -> 326.48418 | G11: =G21+G31 -> 198.41887 | H11: =H21+H31 -> 838.10853 | I11: =I21+I31 -> 565.13942 | J11: =(H11+I11)/M11 -> 0.079038394 | K11: =K21+K31 -> 17.352415 | L11: =L21+L31 -> 445.51023 | M11: =C11+E11+F11+G11+H11+I11+K11+L11 -> 17754.004 | N11: =C11/M11 -> 0.86359215
B12: =B11+1 -> 2003 | C12: =C22+C32 -> 20482.742 | D12: =D22+D32 -> 20256.346 | E12: =E32 -> 47.144951 | F12: =F22+F32 -> 435.16014 | G12: =G22+G32 -> 268.61156 | H12: =H22+H32 -> 1090.2475 | I12: =I22+I32 -> 780.2814 | J12: =(H12+I12)/M12 -> 0.079133846 | K12: =K22+K32 -> 19.191915 | L12: =L22+L32 -> 514.15353 | M12: =C12+E12+F12+G12+H12+I12+K12+L12 -> 23637.533 | N12: =C12/M12 -> 0.86653468
B13: =B12+1 -> 2004 | C13: =C23+C33 -> 25199.734 | D13: =D23+D33 -> 24956.823 | E13: =E33 -> 57.73496 | F13: =F23+F33 -> 458.45184 | G13: =G23+G33 -> 225.1329 | H13: =H23+H33 -> 1456.704 | I13: =I23+I33 -> 952.71686 | J13: =(H13+I13)/M13 -> 0.083226619 | K13: =K23+K33 -> 30.311703 | L13: =L23+L33 -> 569.33627 | M13: =C13+E13+F13+G13+H13+I13+K13+L13 -> 28950.123 | N13: =C13/M13 -> 0.87045345
B14: =B13+1 -> 2005 | C14: =C24+C34 -> 28162.658 | D14: =D24+D34 -> 27763.891 | E14: =E34 -> 74.650013 | F14: =F24+F34 -> 393.80634 | G14: =G24+G34 -> 456.19876 | H14: =H24+H34 -> 1591.9923 | I14: =I24+I34 -> 1119.2626 | J14: =(H14+I14)/M14 -> 0.083684243 | K14: =K24+K34 -> 40.871859 | L14: =L24+L34 -> 559.19179 | M14: =C14+E14+F14+G14+H14+I14+K14+L14 -> 32398.632 | N14: =C14/M14 -> 0.86925455
B15: =B14+1 -> 2006 | C15: =C25+C35 -> 35459.048 | D15: =D25+D35 -> 34691.749 | E15: =E35 -> 103.84103 | F15: =F25+F35 -> 515.67033 | G15: =G25+G35 -> 429.84205 | H15: =H25+H35 -> 2141.7476 | I15: =I25+I35 -> 1430.8112 | J15: =(H15+I15)/M15 -> 0.087709777 | K15: =K25+K35 -> 51.59445 | L15: =L25+L35 -> 599.03793 | M15: =C15+E15+F15+G15+H15+I15+K15+L15 -> 40731.592 | N15: =C15/M15 -> 0.87055393
B16: =B15+1 -> 2007 | C16: =C26+C36 -> 42411.354 | D16: =D26+D36 -> 41564.601 | E16: =E36 -> 167.83476 | F16: =F26+F36 -> 626.32967 | G16: =G26+G36 -> 619.19512 | H16: =H26+H36 -> 2846.5286 | I16: =I26+I36 -> 1867.153 | J16: =(H16+I16)/M16 -> 0.095609407 | K16: =K26+K36 -> 93.439093 | L16: =L26+L36 -> 669.60752 | M16: =C16+E16+F16+G16+H16+I16+K16+L16 -> 49301.442 | N16: =C16/M16 -> 0.86024571
B17: =B16+1 -> 2008 | C17: =C27+C37 -> 34646.626 | D17: =D27+D37 -> 34497.057 | E17: =E37 -> 123.4548 | F17: =F27+F37 -> 606.70994 | G17: =G27+G37 -> 523.33192 | H17: =H27+H37 -> 2241.2158 | I17: =I27+I37 -> 1226.651 | J17: =(H17+I17)/M17 -> 0.086486339 | K17: =K27+K37 -> 58.478971 | L17: =L27+L37 -> 670.80985 | M17: =C17+E17+F17+G17+H17+I17+K17+L17 -> 40097.279 | N17: =C17/M17 -> 0.86406428
C18: Panel B: Equities
B20: 2001 | C20: =(RawDataSources!AS41)/1000 -> 6369.7175 | D20: =RawDataSources!AQ41/1000 -> 5566.1955 | F20: =RawDataSources!AU41/1000 -> 6.6351043 | G20: ='Table A12'!M8 -> 34.081699 | H20: {=TRANSPOSE('Table A6'!D31:K31)} -> 319.11253 | I20: {=TRANSPOSE('Table A10'!D15:K15)-TRANSPOSE('Table A10'!D8:K8)} -> 383.61876 | J20: =(H20+I20)/M20 -> 0.098611427 | K20: =RawDataSources!DE41/1000 -> 9.6685804 | L20: =RawDataSources!DC41/1000 -> 3.4321552 | M20: =C20+F20+G20+H20+I20+K20+L20 -> 7126.2663 | N20: =C20/M20 -> 0.89383658
B21: =B20+1 -> 2002 | C21: =(RawDataSources!AS42)/1000 -> 5863.2301 | D21: =RawDataSources!AQ42/1000 -> 5789.663 | F21: =RawDataSources!AU42/1000 -> 8.1766734 | G21: ='Table A12'!M9 -> 39.650186 | H21: 386.27653 | I21: 359.05778 | J21: =(H21+I21)/M21 -> 0.11166224 | K21: =RawDataSources!DE42/1000 -> 9.4675302 | L21: =RawDataSources!DC42/1000 -> 9.0412327 | M21: =C21+F21+G21+H21+I21+K21+L21 -> 6674.9 | N21: =C21/M21 -> 0.87839969
B22: =B21+1 -> 2003 | C22: =(RawDataSources!AS43)/1000 -> 8339.6884 | D22: =RawDataSources!AQ43/1000 -> 8135.3756 | F22: =RawDataSources!AU43/1000 -> 10.898422 | G22: ='Table A12'!M10 -> 62.790861 | H22: 561.1922 | I22: 493.68009 | J22: =(H22+I22)/M22 -> 0.11120482 | K22: =RawDataSources!DE43/1000 -> 9.3965396 | L22: =RawDataSources!DC43/1000 -> 8.2035312 | M22: =C22+F22+G22+H22+I22+K22+L22 -> 9485.85 | N22: =C22/M22 -> 0.87917144
B23: =B22+1 -> 2004 | C23: =(RawDataSources!AS44)/1000 -> 10222.688 | D23: =RawDataSources!AQ44/1000 -> 10020.618 | F23: =RawDataSources!AU44/1000 -> 11.989212 | G23: ='Table A12'!M11 -> 94.875301 | H23: 783.76227 | I23: 625.6866 | J23: =(H23+I23)/M23 -> 0.11975019 | K23: =RawDataSources!DE44/1000 -> 16.095909 | L23: =RawDataSources!DC44/1000 -> 14.812269 | M23: =C23+F23+G23+H23+I23+K23+L23 -> 11769.91 | N23: =C23/M23 -> 0.86854431
B24: =B23+1 -> 2005 | C24: =(RawDataSources!AS45)/1000 -> 12180.389 | D24: =RawDataSources!AQ45/1000 -> 11810.788 | F24: =RawDataSources!AU45/1000 -> 11.13755 | G24: ='Table A12'!M12 -> 300.51186 | H24: 856.52873 | I24: 757.20271 | J24: =(H24+I24)/M24 -> 0.11412137 | K24: =RawDataSources!DE45/1000 -> 18.76112 | L24: =RawDataSources!DC45/1000 -> 15.953787 | M24: =C24+F24+G24+H24+I24+K24+L24 -> 14140.485 | N24: =C24/M24 -> 0.86138412
B25: =B24+1 -> 2006 | C25: =(RawDataSources!AS46)/1000 -> 16005.888 | D25: =RawDataSources!AQ46/1000 -> 15337.555 | F25: =RawDataSources!AU46/1000 -> 42.537808 | G25: ='Table A12'!M13 -> 260.82035 | H25: 1195.0448 | I25: 988.31684 | J25: =(H25+I25)/M25 -> 0.11782381 | K25: =RawDataSources!DE46/1000 -> 25.641319 | L25: =RawDataSources!DC46/1000 -> 12.483933 | M25: =C25+F25+G25+H25+I25+K25+L25 -> 18530.733 | N25: =C25/M25 -> 0.86374824
B26: =B25+1 -> 2007 | C26: =(RawDataSources!AS47)/1000 -> 19195.122 | D26: =RawDataSources!AQ47/1000 -> 18281.582 | F26: =RawDataSources!AU47/1000 -> 18.458653 | G26: ='Table A12'!M14 -> 469.82941 | H26: 1669.3956 | I26: 1304.0603 | J26: =(H26+I26)/M26 -> 0.13092717 | K26: =RawDataSources!DE47/1000 -> 43.430713 | L26: =RawDataSources!DC47/1000 -> 10.465523 | M26: =C26+F26+G26+H26+I26+K26+L26 -> 22710.763 | N26: =C26/M26 -> 0.84519938
B27: =B26+1 -> 2008 | C27: =(RawDataSources!AS48)/1000 -> 11288.276 | D27: =RawDataSources!AQ48/1000 -> 11144.507 | F27: =RawDataSources!AU48/1000 -> 14.309453 | G27: ='Table A12'!M15 -> 472.30636 | H27: 1105.9018 | I27: 747.63123 | J27: =(H27+I27)/M27 -> 0.135667 | K27: =RawDataSources!DE48/1000 -> 20.458224 | L27: =RawDataSources!DC48/1000 -> 13.488853 | M27: =C27+F27+G27+H27+I27+K27+L27 -> 13662.372 | N27: =C27/M27 -> 0.82623105
C28: Panel C: Debt
B30: 2001 | C30: =(RawDataSources!AT41)/1000 -> 7685.744 | D30: =RawDataSources!AR41/1000 -> 7578.1689 | E30: =(RawDataSources!AY41+RawDataSources!AZ41)/1000 -> 35.256787 | F30: =RawDataSources!AV41/1000 -> 258.29617 | G30: ='Table A12'!M19 -> 208.22617 | H30: {=TRANSPOSE('Table A6'!D28:K28)} -> 389.262 | I30: {=TRANSPOSE('Table A11'!D15:K15)-TRANSPOSE('Table A11'!D8:K8)} -> 179.44312 | J30: =(H30+I30)/M30 -> 0.062178878 | K30: =RawDataSources!DF41/1000 -> 7.3727635 | L30: =RawDataSources!CY41+RawDataSources!CZ41 -> 382.674 | M30: =C30+F30+G30+H30+I30+K30+L30+E30 -> 9146.275 | N30: =C30/M30 -> 0.84031411 | O30: =RawDataSources!CW41 -> 7597.427 | P30: =D30/O30 -> 0.99746518
B31: =B30+1 -> 2002 | C31: =(RawDataSources!AT42)/1000 -> 9468.9885 | D31: =RawDataSources!AR42/1000 -> 9443.2761 | E31: =(RawDataSources!AY42+RawDataSources!AZ42)/1000 -> 30.771808 | F31: =RawDataSources!AV42/1000 -> 318.3075 | G31: ='Table A12'!M20 -> 158.76868 | H31: 451.832 | I31: 206.08164 | J31: =(H31+I31)/M31 -> 0.05938329 | K31: =RawDataSources!DF42/1000 -> 7.8848847 | L31: =RawDataSources!CY42+RawDataSources!CZ42 -> 436.469 | M31: =C31+F31+G31+H31+I31+K31+L31+E31 -> 11079.104 | N31: =C31/M31 -> 0.85467096 | O31: =RawDataSources!CW42 -> 9272.152 | P31: =D31/O31 -> 1.0184557
B32: =B31+1 -> 2003 | C32: =(RawDataSources!AT43)/1000 -> 12143.054 | D32: =RawDataSources!AR43/1000 -> 12120.97 | E32: =(RawDataSources!AY43+RawDataSources!AZ43)/1000 -> 47.144951 | F32: =RawDataSources!AV43/1000 -> 424.26171 | G32: ='Table A12'!M21 -> 205.8207 | H32: 529.0553 | I32: 286.60131 | J32: =(H32+I32)/M32 -> 0.057636721 | K32: =RawDataSources!DF43/1000 -> 9.7953754 | L32: =RawDataSources!CY43+RawDataSources!CZ43 -> 505.95 | M32: =C32+F32+G32+H32+I32+K32+L32+E32 -> 14151.683 | N32: =C32/M32 -> 0.85806428 | O32: =RawDataSources!CW43 -> 11702.099 | P32: =D32/O32 -> 1.0357945
B33: =B32+1 -> 2004 | C33: =(RawDataSources!AT44)/1000 -> 14977.046 | D33: =RawDataSources!AR44/1000 -> 14936.205 | E33: =(RawDataSources!AY44+RawDataSources!AZ44)/1000 -> 57.73496 | F33: =RawDataSources!AV44/1000 -> 446.46262 | G33: ='Table A12'!M22 -> 130.2576 | H33: 672.9417 | I33: 327.03025 | J33: =(H33+I33)/M33 -> 0.058204864 | K33: =RawDataSources!DF44/1000 -> 14.215794 | L33: =RawDataSources!CY44+RawDataSources!CZ44 -> 554.524 | M33: =C33+F33+G33+H33+I33+K33+L33+E33 -> 17180.213 | N33: =C33/M33 -> 0.87176137 | O33: =RawDataSources!CW44 -> 13934.547 | P33: =D33/O33 -> 1.0718831
B34: =B33+1 -> 2005 | C34: =(RawDataSources!AT45)/1000 -> 15982.269 | D34: =RawDataSources!AR45/1000 -> 15953.103 | E34: =(RawDataSources!AY45+RawDataSources!AZ45)/1000 -> 74.650013 | F34: =RawDataSources!AV45/1000 -> 382.66879 | G34: ='Table A12'!M23 -> 155.6869 | H34: 735.4636 | I34: 362.05994 | J34: =(H34+I34)/M34 -> 0.060111442 | K34: =RawDataSources!DF45/1000 -> 22.110739 | L34: =RawDataSources!CY45+RawDataSources!CZ45 -> 543.238 | M34: =C34+F34+G34+H34+I34+K34+L34+E34 -> 18258.147 | N34: =C34/M34 -> 0.87535 | O34: =RawDataSources!CW45 -> 14600.469 | P34: =D34/O34 -> 1.0926432
B35: =B34+1 -> 2006 | C35: =(RawDataSources!AT46)/1000 -> 19453.159 | D35: =RawDataSources!AR46/1000 -> 19354.194 | E35: =(RawDataSources!AY46+RawDataSources!AZ46)/1000 -> 103.84103 | F35: =RawDataSources!AV46/1000 -> 473.13253 | G35: ='Table A12'!M24 -> 169.0217 | H35: 946.7028 | I35: 442.4944 | J35: =(H35+I35)/M35 -> 0.062574029 | K35: =RawDataSources!DF46/1000 -> 25.953131 | L35: =RawDataSources!CY46+RawDataSources!CZ46 -> 586.554 | M35: =C35+F35+G35+H35+I35+K35+L35+E35 -> 22200.859 | N35: =C35/M35 -> 0.87623454 | O35: =RawDataSources!CW46 -> 18415.078 | P35: =D35/O35 -> 1.0509971
B36: =B35+1 -> 2007 | C36: =(RawDataSources!AT47)/1000 -> 23216.231 | D36: =RawDataSources!AR47/1000 -> 23283.019 | E36: =(RawDataSources!AY47+RawDataSources!AZ47)/1000 -> 167.83476 | F36: =RawDataSources!AV47/1000 -> 607.87102 | G36: ='Table A12'!M25 -> 149.3657 | H36: 1177.133 | I36: 563.09264 | J36: =(H36+I36)/M36 -> 0.065444949 | K36: =RawDataSources!DF47/1000 -> 50.008381 | L36: =RawDataSources!CY47+RawDataSources!CZ47 -> 659.142 | M36: =C36+F36+G36+H36+I36+K36+L36+E36 -> 26590.679 | N36: =C36/M36 -> 0.8730966 | O36: =RawDataSources!CW47 -> 22699.536 | P36: =D36/O36 -> 1.0257046
B37: =B36+1 -> 2008 | C37: =(RawDataSources!AT48)/1000 -> 23358.351 | D37: =RawDataSources!AR48/1000 -> 23352.551 | E37: =(RawDataSources!AY48+RawDataSources!AZ48)/1000 -> 123.4548 | F37: =RawDataSources!AV48/1000 -> 592.40049 | G37: ='Table A12'!M26 -> 51.025563 | H37: 1135.314 | I37: 479.0198 | J37: =(H37+I37)/M37 -> 0.061068261 | K37: =RawDataSources!DF48/1000 -> 38.020747 | L37: =RawDataSources!CY48+RawDataSources!CZ48 -> 657.321 | M37: =C37+F37+G37+H37+I37+K37+L37+E37 -> 26434.907 | N37: =C37/M37 -> 0.88361766 | O37: =RawDataSources!CW48 -> 23845.355 | P37: =D37/O37 -> 0.97933331
H51: .

Sheet Table A3
B2: Table A3 – Global Discrepancy Between Cross-Border Securities Assets and Liabilities
C3: [1] | D3: [2] | E3: [3] | F3: [4] | G3: [5] | H3: [6] | I3: [7] | J3: [9] | K3: [10] | L3: [11] | M3: [12] | N3: [13] | O3: [14] | P3: [15]
C4: Billions of current USD
C5: Global Securities Assets | D5: Global Securities Liabilities | E5: Discrepancy | F5: Where the missing securities are invested: Lj - ΣiÂij | M5: Offshore asset allocation | O5: World market cap
F6: Luxembourg | G6: Cayman islands | H6: Ireland | I6: United States | J6: Japan | K6: Swtizerland | L6: Other | N6: Missing wealth / Cross-border securities | P6: Missing wealth / World market cap
C7: ΣiΣj Âij | D7: ΣjLj | E7: Ω = ΣjLj- ΣiΣj Âij
C8: Panel A: All securities
B10: 2001 | C10: ='Table A1'!O11 -> 13740.57 | D10: ='Table A2'!M10 -> 16272.541 | E10: =D10-C10 -> 2531.9709 | F10: =F20+F30 -> 305.34753 | G10: =G20+G30 -> 264.64353 | H10: =H20+H30 -> 165.33253 | I10: =I20+I30 -> 509.09488 | J10: =J20+J30 -> 93.42358 | K10: =K20+K30 -> 124.79165 | L10: =E10-SUM(F10:K10) -> 1069.3372 | N10: =E10/D10 -> 0.15559775 | O10: =O20+O30 -> 65130.164
B11: =B10+1 -> 2002 | C11: ='Table A1'!O12 -> 15361.99 | D11: ='Table A2'!M11 -> 17754.004 | E11: =D11-C11 -> 2392.014 | F11: =F21+F31 -> 361.75921 | G11: =G21+G31 -> 273.88684 | H11: =H21+H31 -> 219.89196 | I11: =I21+I31 -> 401.44325 | J11: =J21+J31 -> 69.66098 | K11: =K21+K31 -> 112.60689 | L11: =E11-SUM(F11:K11) -> 952.76483 | N11: =E11/D11 -> 0.13473096 | O11: =O21+O31 -> 66086.243
B12: =B11+1 -> 2003 | C12: ='Table A1'!O13 -> 20779.851 | D12: ='Table A2'!M12 -> 23637.533 | E12: =D12-C12 -> 2857.6815 | F12: =F22+F32 -> 464.88133 | G12: =G22+G32 -> 346.50519 | H12: =H22+H32 -> 314.3389 | I12: =I22+I32 -> 494.99675 | J12: =J22+J32 -> 93.63187 | K12: =K22+K32 -> 131.20942 | L12: =E12-SUM(F12:K12) -> 1012.1181 | N12: =E12/D12 -> 0.12089593 | O12: =O22+O32 -> 82453.152
B13: =B12+1 -> 2004 | C13: ='Table A1'!O14 -> 25634.097 | D13: ='Table A2'!M13 -> 28950.123 | E13: =D13-C13 -> 3316.0255 | F13: =F23+F33 -> 570.22168 | G13: =G23+G33 -> 476.65731 | H13: =H23+H33 -> 432.90675 | I13: =I23+I33 -> 539.24112 | J13: =J23+J33 -> 150.56893 | K13: =K23+K33 -> 146.66477 | L13: =E13-SUM(F13:K13) -> 999.76498 | N13: =E13/D13 -> 0.11454271 | O13: =O23+O33 -> 95686.193
B14: =B13+1 -> 2005 | C14: ='Table A1'!O15 -> 28722.994 | D14: ='Table A2'!M14 -> 32398.632 | E14: =D14-C14 -> 3675.6375 | F14: =F24+F34 -> 733.31638 | G14: =G24+G34 -> 462.87628 | H14: =H24+H34 -> 515.3299 | I14: =I24+I34 -> 491.82588 | J14: =J24+J34 -> 188.09078 | K14: =K24+K34 -> 136.1833 | L14: =E14-SUM(F14:K14) -> 1148.015 | N14: =E14/D14 -> 0.11345039 | O14: =O24+O34 -> 102464.65
B15: =B14+1 -> 2006 | C15: ='Table A1'!O16 -> 36971.589 | D15: ='Table A2'!M15 -> 40731.592 | E15: =D15-C15 -> 3760.0032 | F15: =F25+F35 -> 766.36747 | G15: =G25+G35 -> 559.29925 | H15: =H25+H35 -> 526.87332 | I15: =I25+I35 -> 354.271 | J15: =J25+J35 -> 230.54982 | K15: =K25+K35 -> 135.42891 | L15: =E15-SUM(F15:K15) -> 1187.2134 | N15: =E15/D15 -> 0.092311715 | O15: =O25+O35 -> 121337.5
B16: =B15+1 -> 2007 | C16: ='Table A1'!O17 -> 44170.116 | D16: ='Table A2'!M16 -> 49301.442 | E16: =D16-C16 -> 5131.3254 | F16: =F26+F36 -> 1039.0949 | G16: =G26+G36 -> 856.5045 | H16: =H26+H36 -> 681.60718 | I16: =I26+I36 -> 264.195 | J16: =J26+J36 -> 359.77703 | K16: =K26+K36 -> 109.75598 | L16: =E16-SUM(F16:K16) -> 1820.3908 | N16: =E16/D16 -> 0.10408064 | O16: =O26+O36 -> 143297.27
B17: =B16+1 -> 2008 | C17: ='Table A1'!O18 -> 35607.301 | D17: ='Table A2'!M17 -> 40097.279 | E17: =D17-C17 -> 4489.9776 | F17: =F27+F37 -> 911.55479 | G17: =G27+G37 -> 840.69737 | H17: =H27+H37 -> 603.17981 | I17: =I27+I37 -> 209.85375 | J17: =J27+J37 -> 291.22925 | K17: =K27+K37 -> 97.87104 | L17: =E17-SUM(F17:K17) -> 1535.5916 | N17: =E17/D17 -> 0.11197711 | O17: =O27+O37 -> 119079.84
C18: Panel B: Equities
B20: 2001 | C20: ='Table A1'!O21 -> 5553.6765 | D20: ='Table A2'!M20 -> 7126.2663 | E20: =D20-C20 -> 1572.5898 | F20: {=TRANSPOSE('Table A13'!B127:I127)} -> 310.92106 | G20: {=TRANSPOSE('Table A13'!B42:I42)} -> 202.65172 | H20: {=TRANSPOSE('Table A13'!B104:I104)} -> 175.07469 | I20: {=TRANSPOSE('Table A13'!B226:I226)} -> 411.12238 | J20: {=TRANSPOSE('Table A13'!B109:I109)} -> 36.54094 | K20: {=TRANSPOSE('Table A13'!B205:I205)} -> 115.71523 | L20: =E20-SUM(F20:K20) -> 320.56379 | M20: =E20/E10 -> 0.62109317 | N20: =E20/D20 -> 0.22067514 | O20: 27906.618 | P20: =E20/O20 -> 0.056351859
B21: =B20+1 -> 2002 | C21: ='Table A1'!O22 -> 5173.8457 | D21: ='Table A2'!M21 -> 6674.9 | E21: =D21-C21 -> 1501.0543 | F21: 368.30819 | G21: 252.18184 | H21: 225.58658 | I21: 298.5475 | J21: 26.97675 | K21: 106.15664 | L21: =E21-SUM(F21:K21) -> 223.29681 | M21: =E21/E11 -> 0.62752741 | N21: =E21/D21 -> 0.22488042 | O21: 23509.657 | P21: =E21/O21 -> 0.063848414
B22: =B21+1 -> 2003 | C22: ='Table A1'!O23 -> 7546.0951 | D22: ='Table A2'!M22 -> 9485.85 | E22: =D22-C22 -> 1939.755 | F22: 475.6965 | G22: 346.50519 | H22: 316.18781 | I22: 340.68575 | J22: 52.99459 | K22: 116.6525 | L22: =E22-SUM(F22:K22) -> 291.03261 | M22: =E22/E12 -> 0.67878626 | N22: =E22/D22 -> 0.20448931 | O22: 32036.7 | P22: =E22/O22 -> 0.060547901
B23: =B22+1 -> 2004 | C23: ='Table A1'!O24 -> 9425.5596 | D23: ='Table A2'!M23 -> 11769.91 | E23: =D23-C23 -> 2344.3501 | F23: 582.21006 | G23: 476.65731 | H23: 385.52834 | I23: 381.82612 | J23: 72.43281 | K23: 122.09516 | L23: =E23-SUM(F23:K23) -> 323.6003 | M23: =E23/E13 -> 0.70697589 | N23: =E23/D23 -> 0.19918166 | O23: 38151.94 | P23: =E23/O23 -> 0.06144773
B24: =B23+1 -> 2005 | C24: ='Table A1'!O25 -> 11421.045 | D24: ='Table A2'!M24 -> 14140.485 | E24: =D24-C24 -> 2719.4393 | F24: 746.53288 | G24: 462.87628 | H24: 441.24312 | I24: 279.15138 | J24: 134.96894 | K24: 117.00569 | L24: =E24-SUM(F24:K24) -> 537.66103 | M24: =E24/E14 -> 0.73985514 | N24: =E24/D24 -> 0.19231585 | O24: 43319.352 | P24: =E24/O24 -> 0.062776547
B25: =B24+1 -> 2006 | C25: ='Table A1'!O26 -> 15511.1 | D25: ='Table A2'!M25 -> 18530.733 | E25: =D25-C25 -> 3019.6332 | F25: 780.56838 | G25: 559.29925 | H25: 523.55944 | I25: 186.756 | J25: 125.04238 | K25: 110.56594 | L25: =E25-SUM(F25:K25) -> 733.84185 | M25: =E25/E15 -> 0.80309327 | N25: =E25/D25 -> 0.16295271 | O25: 53375.287 | P25: =E25/O25 -> 0.056573621
B26: =B25+1 -> 2007 | C26: ='Table A1'!O27 -> 18738.356 | D26: ='Table A2'!M26 -> 22710.763 | E26: =D26-C26 -> 3972.407 | F26: 1060 | G26: 797.87325 | H26: 706.45712 | I26: 192.087 | J26: 149.70762 | K26: 101.46438 | L26: =E26-SUM(F26:K26) -> 964.81765 | M26: =E26/E16 -> 0.77414834 | N26: =E26/D26 -> 0.17491297 | O26: 64563.414 | P26: =E26/O26 -> 0.061527214
B27: =B26+1 -> 2008 | C27: ='Table A1'!O28 -> 10846.197 | D27: ='Table A2'!M27 -> 13662.372 | E27: =D27-C27 -> 2816.1746 | F27: 929.79938 | G27: 599.52825 | H27: 636.667 | I27: 177.02875 | J27: 49.89669 | K27: 93.86097 | L27: =E27-SUM(F27:K27) -> 329.39358 | M27: =E27/E17 -> 0.62721352 | N27: =E27/D27 -> 0.20612633 | O27: 35811.16 | P27: =E27/O27 -> 0.078639581
C28: Panel C: Debt
B30: 2001 | C30: ='Table A1'!O31 -> 8186.8939 | D30: ='Table A2'!M30 -> 9146.275 | E30: =D30-C30 -> 959.38105 | F30: {=TRANSPOSE('Table A14'!B127:I127)} -> -5.57353 | G30: {=TRANSPOSE('Table A14'!B42:I42)} -> 61.99181 | H30: {=TRANSPOSE('Table A14'!B104:I104)} -> -9.74216 | I30: {=TRANSPOSE('Table A14'!B226:I226)} -> 97.9725 | J30: {=TRANSPOSE('Table A14'!B109:I109)} -> 56.88264 | K30: {=TRANSPOSE('Table A14'!B205:I205)} -> 9.07642 | L30: =E30-SUM(F30:K30) -> 748.77337 | M30: =E30/E10 -> 0.37890683 | N30: =E30/D30 -> 0.10489309 | O30: 37223.546 | P30: =E30/O30 -> 0.0257735
B31: =B30+1 -> 2002 | C31: ='Table A1'!O32 -> 10188.144 | D31: ='Table A2'!M31 -> 11079.104 | E31: =D31-C31 -> 890.95964 | F31: -6.54898 | G31: 21.705 | H31: -5.69462 | I31: 102.89575 | J31: 42.68423 | K31: 6.45025 | L31: =E31-SUM(F31:K31) -> 729.46801 | M31: =E31/E11 -> 0.37247259 | N31: =E31/D31 -> 0.080418023 | O31: 42576.586 | P31: =E31/O31 -> 0.020926047
B32: =B31+1 -> 2003 | C32: ='Table A1'!O33 -> 13233.756 | D32: ='Table A2'!M32 -> 14151.683 | E32: =D32-C32 -> 917.92659 | F32: -10.81517 | G32: 0 | H32: -1.84891 | I32: 154.311 | J32: 40.63728 | K32: 14.55692 | L32: =E32-SUM(F32:K32) -> 721.08547 | M32: =E32/E12 -> 0.32121374 | N32: =E32/D32 -> 0.064863422 | O32: 50416.452 | P32: =E32/O32 -> 0.018206886
B33: =B32+1 -> 2004 | C33: ='Table A1'!O34 -> 16208.538 | D33: ='Table A2'!M33 -> 17180.213 | E33: =D33-C33 -> 971.67544 | F33: -11.98838 | G33: 0 | H33: 47.37841 | I33: 157.415 | J33: 78.13612 | K33: 24.56961 | L33: =E33-SUM(F33:K33) -> 676.16468 | M33: =E33/E13 -> 0.29302411 | N33: =E33/D33 -> 0.056557822 | O33: 57534.253 | P33: =E33/O33 -> 0.016888643
B34: =B33+1 -> 2005 | C34: ='Table A1'!O35 -> 17301.949 | D34: ='Table A2'!M34 -> 18258.147 | E34: =D34-C34 -> 956.19819 | F34: -13.2165 | G34: 0 | H34: 74.08678 | I34: 212.6745 | J34: 53.12184 | K34: 19.17761 | L34: =E34-SUM(F34:K34) -> 610.35396 | M34: =E34/E14 -> 0.26014486 | N34: =E34/D34 -> 0.052371043 | O34: 59145.298 | P34: =E34/O34 -> 0.016166935
B35: =B34+1 -> 2006 | C35: ='Table A1'!O36 -> 21460.489 | D35: ='Table A2'!M35 -> 22200.859 | E35: =D35-C35 -> 740.36991 | F35: -14.20091 | G35: 0 | H35: 3.31388 | I35: 167.515 | J35: 105.50744 | K35: 24.86297 | L35: =E35-SUM(F35:K35) -> 453.37153 | M35: =E35/E15 -> 0.19690673 | N35: =E35/D35 -> 0.033348705 | O35: 67962.213 | P35: =E35/O35 -> 0.010893846
B36: =B35+1 -> 2007 | C36: ='Table A1'!O37 -> 25431.761 | D36: ='Table A2'!M36 -> 26590.679 | E36: =D36-C36 -> 1158.9183 | F36: -20.90509 | G36: 58.63125 | H36: -24.84994 | I36: 72.108 | J36: 210.06941 | K36: 8.2916 | L36: =E36-SUM(F36:K36) -> 855.57312 | M36: =E36/E16 -> 0.22585166 | N36: =E36/D36 -> 0.043583631 | O36: 78733.854 | P36: =E36/O36 -> 0.014719441
B37: =B36+1 -> 2008 | C37: ='Table A1'!O38 -> 24761.104 | D37: ='Table A2'!M37 -> 26434.907 | E37: =D37-C37 -> 1673.8029 | F37: -18.24459 | G37: 241.16912 | H37: -33.48719 | I37: 32.825 | J37: 241.33256 | K37: 4.01007 | L37: =E37-SUM(F37:K37) -> 1206.198 | M37: =E37/E17 -> 0.37278648 | N37: =E37/D37 -> 0.063317905 | O37: 83268.678 | P37: =E37/O37 -> 0.020101231

Sheet Table A4
B2: Table A4: Main Holders of Cross-Border Securities
C3: [1] | D3: [2] | E3: [3] | F3: [4] | G3: [5] | H3: [6] | I3: [7] | J3: [8] | K3: [9] | L3: [10] | M3: [11] | N3: [12] | O3: [13] | P3: [14] | Q3: [15] | R3: [16]
C4: Billions of current USD
C5: Industrial, emerging and developing countries | K5: Memo: Unknown Owner (Ω) | L5: Offshore financial centers
C6: United States | D6: United Kingdom | E6: Japan | F6: Germany | G6: France | H6: Other (private) | I6: Reserve + Int'l orga. | J6: Total onshore | L6: Luxem-bourg | M6: Ireland | N6: Cayman Islands | O6: Bermuda | P6: Hong-Kong | Q6: Other | R6: Total offshore centers
C8: Panel A: All securities
B10: 2001 | C10: =C20+C30 -> 2303.6035 | D10: =D20+D30 -> 1304.0445 | E10: =E20+E30 -> 1289.7541 | F10: =F20+F30 -> 791.61626 | G10: =G20+G30 -> 710.33044 | H10: =H20+H30 -> 2749.7028 | I10: =I20+I30 -> 1700.3726 | J10: =J20+J30 -> 10849.424 | ... R10: =R20+R30 -> 2891.1464
B11: =B10+1 -> 2002 | C11: =C21+C31 -> 2246.0338 | D11: =D21+D31 -> 1360.3801 | E11: =E21+E31 -> 1394.5197 | F11: =F21+F31 -> 897.83191 | G11: =G21+G31 -> 931.87644 | H11: =H21+H31 -> 3166.3907 | I11: =I21+I31 -> 1958.0927 | J11: =J21+J31 -> 11955.125 | ... R11: =R21+R31 -> 3406.8645
B12: =B11+1 -> 2003 | C12: =C22+C32 -> 3134.244 | D12: =D22+D32 -> 1670.2043 | E12: =E22+E32 -> 1721.3143 | F12: =F22+F32 -> 1205.1268 | G12: =G22+G32 -> 1369.5769 | H12: =H22+H32 -> 4412.0923 | I12: =I22+I32 -> 2542.6836 | J12: =J22+J32 -> 16055.242 | ... R12: =R22+R32 -> 4724.6093
B13: =B12+1 -> 2004 | C13: =C23+C33 -> 3764.3509 | D13: =D23+D33 -> 2109.701 | E13: =E23+E33 -> 2009.6724 | F13: =F23+F33 -> 1515.4765 | G13: =G23+G33 -> 1750.7056 | H13: =H23+H33 -> 5524.9397 | I13: =I23+I33 -> 3096.0829 | J13: =J23+J33 -> 19770.929 | ... R13: =R23+R33 -> 5863.1682
B14: =B13+1 -> 2005 | C14: =C24+C34 -> 4591.122 | D14: =D24+D34 -> 2373.9237 | E14: =E24+E34 -> 2114.8893 | F14: =F24+F34 -> 1552.8026 | G14: =G24+G34 -> 1873.2591 | H14: =H24+H34 -> 6290.4059 | I14: =I24+I34 -> 3418.384 | J14: =J24+J34 -> 22214.787 | ... R14: =R24+R34 -> 6508.2076
B15: =B14+1 -> 2006 | C15: =C25+C35 -> 5972.356 | D15: =D25+D35 -> 3140.5095 | E15: =E25+E35 -> 2343.4824 | F15: =F25+F35 -> 2310.3827 | G15: =G25+G35 -> 2463.9596 | H15: =H25+H35 -> 7980.0337 | I15: =I25+I35 -> 4082.9576 | J15: =J25+J35 -> 28293.681 | ... R15: =R25+R35 -> 8677.9078
B16: =B15+1 -> 2007 | C16: =C26+C36 -> 7191.779 | D16: =D26+D36 -> 3393.411 | E16: =E26+E36 -> 2523.5667 | F16: =F26+F36 -> 2624.8058 | G16: =G26+G36 -> 2964.9952 | H16: =H26+H36 -> 9656.1799 | I16: =I26+I36 -> 5194.7425 | J16: =J26+J36 -> 33549.48 | ... R16: =R26+R36 -> 10620.636
B17: =B16+1 -> 2008 | C17: =C27+C37 -> 4267.865 | D17: =D27+D37 -> 2426.2515 | E17: =E27+E37 -> 2376.6061 | F17: =F27+F37 -> 2149.155 | G17: =G27+G37 -> 2553.3653 | H17: =H27+H37 -> 7583.5533 | I17: =I27+I37 -> 6124.3972 | J17: =J27+J37 -> 27481.193 | ... R17: =R27+R37 -> 8126.1078
C18: Panel B: Equities
B20: 2001 | C20: 1612.667 | D20: 558.37932 | E20: 227.3514 | F20: 381.18429 | G20: 201.7516 | H20: =J20-I20-SUM(C20:G20) -> 1359.4613 | I20: ='Table A1'!P21 -> 45.706618 | J20: ='Table A1'!O21-R20 -> 4386.5015 | K20: ='Table A3'!E20 -> 1572.5898 | L20: 319.09314 | M20: 133.7549 | N20: 163.9546 | O20: 31.03212 | P20: 94.615 | Q20: =R20-N20-M20-L20-O20-P20 -> 424.72519 | R20: 1167.1749
B21: =B20+1 -> 2002 | C21: 1385.3587 | D21: 493.03513 | E21: 210.81728 | F21: 331.22875 | G21: 200.09415 | H21: =J21-I21-SUM(C21:G21) -> 1305.2524 | I21: ='Table A1'!P22 -> 42.731351 | J21: ='Table A1'!O22-R21 -> 3968.5177 | K21: ='Table A3'!E21 -> 1501.0543 | L21: 304.99659 | M21: 152.85641 | N21: 202.23221 | O21: 30.99825 | P21: 95.721 | Q21: =R21-N21-M21-L21-O21-P21 -> 418.52348 | R21: 1205.3279
B22: =B21+1 -> 2003 | C22: 2080.302 | D22: 663.8727 | E22: 274.45717 | F22: 440.81351 | G22: 340.24034 | H22: =J22-I22-SUM(C22:G22) -> 1860.5773 | I22: ='Table A1'!P23 -> 63.842141 | J22: ='Table A1'!O23-R22 -> 5724.1052 | K22: ='Table A3'!E22 -> 1939.755 | L22: 488.24 | M22: 223.38601 | N22: 339.49899 | O22: 62.03767 | P22: 152.831 | Q22: =R22-N22-M22-L22-O22-P22 -> 555.99624 | R22: 1821.9899
B23: =B22+1 -> 2004 | C23: 2560.4179 | D23: 879.34131 | E23: 364.69028 | F23: 523.83371 | G23: 442.65451 | H23: =J23-I23-SUM(C23:G23) -> 2285.2507 | I23: ='Table A1'!P24 -> 81.65537 | J23: ='Table A1'!O24-R23 -> 7137.8438 | K23: ='Table A3'!E23 -> 2344.3501 | L23: 637.83661 | M23: 304.94285 | N23: 403.84999 | O23: 64.58507 | P23: 199.671 | Q23: =R23-N23-M23-L23-O23-P23 -> 676.83031 | R23: 2287.7158
B24: =B23+1 -> 2005 | C24: 3317.705 | D24: 1075.9968 | E24: 408.5748 | F24: 529.08603 | G24: 524.8873 | H24: =J24-I24-SUM(C24:G24) -> 2739.4861 | I24: ='Table A1'!P25 -> 91.950951 | J24: ='Table A1'!O25-R24 -> 8687.687 | K24: ='Table A3'!E24 -> 2719.4393 | L24: 807.86584 | M24: 383.15477 | N24: 431.90524 | O24: 87.31782 | P24: 227.8341 | Q24: =R24-N24-M24-L24-O24-P24 -> 795.28066 | R24: 2733.3584
B25: =B24+1 -> 2006 | C25: 4328.962 | D25: 1366.4816 | E25: 510.41842 | F25: 928.24397 | G25: 743.02358 | H25: =J25-I25-SUM(C25:G25) -> 3632.6086 | I25: ='Table A1'!P26 -> 127.1112 | J25: ='Table A1'!O26-R25 -> 11636.849 | K25: ='Table A3'!E25 -> 3019.6332 | L25: 1148.2134 | M25: 573.19921 | N25: 618.02803 | O25: 113.92202 | P25: 338.877 | Q25: =R25-N25-M25-L25-O25-P25 -> 1082.0111 | R25: 3874.2508
B26: =B25+1 -> 2007 | C26: 5247.983 | D26: 1508.7104 | E26: 573.46946 | F26: 954.02532 | G26: 826.85822 | H26: =J26-I26-SUM(C26:G26) -> 4482.4554 | I26: ='Table A1'!P27 -> 233.8888 | J26: ='Table A1'!O27-R26 -> 13827.391 | K26: ='Table A3'!E26 -> 3972.407 | L26: 1413.2355 | M26: 649.17252 | N26: 775.6991 | O26: 138.29469 | P26: 514.511 | Q26: =R26-N26-M26-L26-O26-P26 -> 1420.0523 | R26: 4910.9651
B27: =B26+1 -> 2008 | C27: 2748.428 | D27: 824.01854 | E27: 394.67768 | F27: 589.52134 | G27: 454.68896 | H27: =J27-I27-SUM(C27:G27) -> 2707.696 | I27: ='Table A1'!P28 -> 178.03488 | J27: ='Table A1'!O28-R27 -> 7897.0654 | K27: ='Table A3'!E27 -> 2816.1746 | L27: 757.73893 | M27: 431.02619 | N27: 458.84723 | O27: 81.298 | P27: 275.1598 | Q27: =R27-N27-M27-L27-O27-P27 -> 945.06165 | R27: 2949.1318
C28: Panel C: Debt
B30: 2001 | C30: 690.93649 | D30: 745.66517 | E30: 1062.4027 | F30: 410.43197 | G30: 508.57884 | H30: =J30-I30-SUM(C30:G30) -> 1390.2415 | I30: ='Table A1'!P31 -> 1654.6659 | J30: ='Table A1'!O31-'Table A4'!R30 -> 6462.9225 | K30: ='Table A3'!E30 -> 959.38105 | L30: 501.52105 | M30: 299.08415 | N30: 178.51814 | O30: 131.40045 | P30: 178.51814 | Q30: =R30-N30-M30-L30-O30-P30 -> 434.92949 | R30: 1723.9714
B31: =B30+1 -> 2002 | C31: 860.67516 | D31: 867.34502 | E31: 1183.7024 | F31: 566.60316 | G31: 731.78229 | H31: =J31-I31-SUM(C31:G31) -> 1861.1383 | I31: ='Table A1'!P32 -> 1915.3613 | J31: ='Table A1'!O32-'Table A4'!R31 -> 7986.6078 | K31: ='Table A3'!E31 -> 890.95964 | L31: 618.40217 | M31: 421.11069 | N31: 224.12985 | O31: 156.67277 | P31: 224.12985 | Q31: =R31-N31-M31-L31-O31-P31 -> 557.09127 | R31: 2201.5366
B32: =B31+1 -> 2003 | C32: 1053.942 | D32: 1006.3316 | E32: 1446.8571 | F32: 764.31326 | G32: 1029.3365 | H32: =J32-I32-SUM(C32:G32) -> 2551.515 | I32: ='Table A1'!P33 -> 2478.8414 | J32: ='Table A1'!O33-'Table A4'!R32 -> 10331.137 | K32: ='Table A3'!E32 -> 917.92659 | L32: 844.96351 | M32: 612.4093 | N32: 278.69177 | O32: 191.94021 | P32: 278.69177 | Q32: =R32-N32-M32-L32-O32-P32 -> 695.92286 | R32: 2902.6194
B33: =B32+1 -> 2004 | C33: 1203.933 | D33: 1230.3597 | E33: 1644.9821 | F33: 991.64284 | G33: 1308.0511 | H33: =J33-I33-SUM(C33:G33) -> 3239.689 | I33: ='Table A1'!P34 -> 3014.4275 | J33: ='Table A1'!O34-'Table A4'!R33 -> 12633.085 | K33: ='Table A3'!E33 -> 971.67544 | L33: 978.47692 | M33: 767.36899 | N33: 453.9021 | O33: 245.07271 | P33: 453.9021 | Q33: =R33-N33-M33-L33-O33-P33 -> 676.72951 | R33: 3575.4523
B34: =B33+1 -> 2005 | C34: 1273.417 | D34: 1297.9269 | E34: 1706.3146 | F34: 1023.7166 | G34: 1348.3718 | H34: =J34-I34-SUM(C34:G34) -> 3550.9198 | I34: ='Table A1'!P35 -> 3326.433 | J34: ='Table A1'!O35-'Table A4'!R34 -> 13527.1 | K34: ='Table A3'!E34 -> 956.19819 | L34: 1033.0554 | M34: 799.05681 | N34: 479.5053 | O34: 304.81555 | P34: 479.5053 | Q34: =R34-N34-M34-L34-O34-P34 -> 678.91087 | R34: 3774.8492
B35: =B34+1 -> 2006 | C35: 1643.394 | D35: 1774.0279 | E35: 1833.064 | F35: 1382.1388 | G35: 1720.936 | H35: =J35-I35-SUM(C35:G35) -> 4347.4251 | I35: ='Table A1'!P36 -> 3955.8464 | J35: ='Table A1'!O36-'Table A4'!R35 -> 16656.832 | K35: ='Table A3'!E35 -> 740.36991 | L35: 1282.7064 | M35: 1047.019 | N35: 716.45899 | O35: 334.7388 | P35: 716.45899 | Q35: =R35-N35-M35-L35-O35-P35 -> 706.27483 | R35: 4803.657
B36: =B35+1 -> 2007 | C36: 1943.796 | D36: 1884.7006 | E36: 1950.0972 | F36: 1670.7805 | G36: 2138.137 | H36: =J36-I36-SUM(C36:G36) -> 5173.7245 | I36: ='Table A1'!P37 -> 4960.8537 | J36: ='Table A1'!O37-'Table A4'!R36 -> 19722.09 | K36: ='Table A3'!E36 -> 1158.9183 | L36: 1469.3712 | M36: 1321.2951 | N36: 858.05975 | O36: 435.41283 | P36: 858.05975 | Q36: =R36-N36-M36-L36-O36-P36 -> 767.4724 | R36: 5709.6711
B37: =B36+1 -> 2008 | C37: 1519.437 | D37: 1602.233 | E37: 1981.9284 | F37: 1559.6337 | G37: 2098.6764 | H37: =J37-I37-SUM(C37:G37) -> 4875.8574 | I37: ='Table A1'!P38 -> 5946.3623 | J37: ='Table A1'!O38-'Table A4'!R37 -> 19584.128 | K37: ='Table A3'!E37 -> 1673.8029 | L37: 1362.4646 | M37: 1195.7793 | N37: 793.85869 | O37: 314.771 | P37: 793.85869 | Q37: =R37-N37-M37-L37-O37-P37 -> 716.24374 | R37: 5176.976

Sheet Table A5
A1: Table A5: Sectoral Breakdown of Portfolio Claims Reported in the CPIS, 2008
B3: Public sector | C3: Private sector
C4: Total | D4: Of which: banks | E4: Of which: non banks
A5: Argentina | B5: 0.0712987 | C5: =1-B5 -> 0.9287013 | D5: 0.0006427 | E5: 0.9280587
A6: Australia | B6: 0.0449511 | C6: =1-B6 -> 0.9550489 | D6: 0.0536148 | E6: 0.9014341
A7: Austria | B7: 0.0520882 | C7: =1-B7 -> 0.9479118 | D7: 0.3909276 | E7: 0.5569842
A8: Bahrain | B8: 0.0218008 | C8: =1-B8 -> 0.9781992 | D8: 0.9507242 | E8: 0.027475
A9: Barbados | B9: 0 | C9: =1-B9 -> 1 | D9: 1 | E9: 0
A10: Bermuda | B10: 0.0032949 | C10: =1-B10 -> 0.9967051 | D10: 0.0120232 | E10: 0.984682
A11: Bulgaria | B11: 0 | C11: =1-B11 -> 1 | D11: 0.4958141 | E11: 0.5041859
A12: Cayman Islands | B12: 0 | C12: =1-B12 -> 1 | D12: 1 | E12: 0
A13: Chile | B13: 0.3315388 | C13: =1-B13 -> 0.6684612 | D13: 0.0087065 | E13: 0.6597546
A14: Colombia | B14: 0.114978 | C14: =1-B14 -> 0.885022 | D14: 0.0091577 | E14: 0.8758643
A15: Costa Rica | B15: 0 | C15: =1-B15 -> 1 | D15: 0.4363366 | E15: 0.5636634
A16: Cyprus | B16: 0.0001096 | C16: =1-B16 -> 0.9998904 | D16: 0.9369113 | E16: 0.0629791
... A52: Venezuela | B52: 0.6503981 | C52: =1-B52 -> 0.3496019 | D52: 0.1367036 | E52: 0.2128983
A53: Weighted Mean | B53: 0.081367775 | C53: =1-B53 -> 0.91863223 | D53: 0.25378515 | E53: =1-D53-B53 -> 0.66484708

Sheet Table A6
B2: Table A6: Portfolio Assets and Liabilities of the Cayman Islands (bn of USD)
D4: 2001 | E4: 2002 | F4: 2003 | G4: 2004 | H4: 2005 | I4: 2006 | J4: 2007 | K4: 2008
B6: [1] | C6: Holdings of U.S. securities (TIC) | D6: =D7+D8+D9 -> 159.54662 | E6: =E7+E8+E9 -> 193.59021 | F6: =F7+F8+F9 -> 276.457 | G6: =G7+G8+G9 -> 400.553 | H6: =H7+H8+H9 -> 445.233 | I6: =I7+I8+I9 -> 645.993 | J6: =J7+J8+J9 -> 851.468 | K6: =K7+K8+K9 -> 706.376
B7: [2] | C7: Equities | D7: 57.128 | E7: 65.171 | F7: 116.663 | G7: 139.966 | H7: 165.426 | I7: 220.741 | J7: 329.207 | K7: 212.798
B8: [3] | C8: Long term debt | D8: 91.895 | E8: 115.224 | F8: 143.375 | G8: 226.579 | H8: 255.177 | I8: 385.628 | J8: 468.733 | K8: 410.226
B9: [4] | C9: Short term debt | D9: 10.52362 | E9: 13.195207 | F9: 16.419 | G9: 34.008 | H9: 24.63 | I9: 39.624 | J9: 53.528 | K9: 83.352
B10: [5] | C10: Estimated share of U.S. securities (gravity)
B11: [6] | C11: Equities | D11: 0.3484379 | E11: 0.3222583 | F11: 0.3436328 | G11: 0.3465792 | H11: 0.3830146 | I11: 0.3571699 | J11: 0.4244004 | K11: 0.4637665
B12: [7] | C12: Debt | D12: 0.5737176 | E12: 0.572967 | F12: 0.5733718 | G12: 0.574104 | H12: 0.5835326 | I12: 0.5935469 | J12: 0.6086534 | K12: 0.6217454
B14: [8] | C14: Total assets (est. from TIC + gravity) | D14: =D15+D16 -> 342.47209 | E14: =E15+E16 -> 426.36238 | F14: =F15+F16 -> 618.19079 | G14: =G15+G16 -> 857.75205 | H14: =H15+H16 -> 911.41055 | I14: =I15+I16 -> 1334.487 | J14: =J15+J16 -> 1633.7589 | K14: =K15+K16 -> 1252.706
B15: [9] | C15: Of which: equities | D15: =D7/D11 -> 163.95461 | E15: =E7/E11 -> 202.23218 | F15: =F7/F11 -> 339.49902 | G15: =G7/G11 -> 403.84997 | H15: =H7/H11 -> 431.90521 | I15: =I7/I11 -> 618.028 | J15: =J7/J11 -> 775.69908 | K15: =K7/K11 -> 458.84729
B16: [10] | C16: Of which: debt | D16: =(D8+D9)/D12 -> 178.51748 | E16: =(E8+E9)/E12 -> 224.1302 | F16: =(F8+F9)/F12 -> 278.69177 | G16: =(G8+G9)/G12 -> 453.90208 | H16: =(H8+H9)/H12 -> 479.50534 | I16: =(I8+I9)/I12 -> 716.45897 | J16: =(J8+J9)/J12 -> 858.05978 | K16: =(K8+K9)/K12 -> 793.85871
C18: Consistency checks
B19: [11] | C19: Bank assets (CPIS) | D19: 50.817 | E19: 55.19447 | F19: 62.365886 | G19: 57.986295 | H19: 72.30212 | I19: 82.194 | J19: 90.008 | K19: 50.055
B20: [12] | C20: Of which: equities | D20: =D19-D21 -> 0 | E20: =E19-E21 -> 5.068664 | F20: =F19-F21 -> 5.28211 | G20: =G19-G21 -> 2.01508 | H20: =H19-H21 -> 1.81427 | I20: =I19-I21 -> 1.995 | J20: =J19-J21 -> 2.313 | K20: =K19-K21 -> 0.617
B21: [13] | C21: Of which: debt | D21: 50.817 | E21: 50.125806 | F21: 57.083776 | G21: 55.971215 | H21: 70.48785 | I21: 80.199 | J21: 87.695 | K21: 49.438
B22: [14] | C22: Fund assets (CIMA) | D22: n.a. | E22: n.a. | F22: n.a. | G22: n.a. | H22: 768.2512 | I22: 1234.236 | J22: 1707.6144 | K22: 1215.9485
B23: [15] | C23: Of which: equities | D23: n.a. | E23: n.a. | F23: n.a. | G23: n.a. | H23: 607.99138 | I23: 951.72791 | J23: 1187.7842 | K23: 824.88971
B24: [16] | C24: Of which: debt | D24: n.a. | E24: n.a. | F24: n.a. | G24: n.a. | H24: 160.25983 | I24: 282.50813 | J24: 519.83025 | K24: 391.05882
B25: [17] | C25: Banks + Funds (CPIS + CIMA) | D25: n.a. | E25: n.a. | F25: n.a. | G25: n.a. | H25: =H22+H19 -> 840.55332 | I25: =I22+I19 -> 1316.43 | J25: =J22+J19 -> 1797.6224 | K25: =K22+K19 -> 1266.0035
B27: [18] | C27: Liabilities | D27: =D28+D32 -> 677.87753 | E27: =E28+E32 -> 811.14539 | F27: =F28+F32 -> 1050.0305 | G27: =G28+G32 -> 1395.8052 | H27: =H28+H32 -> 1503.5473 | I27: =I28+I32 -> 2012.3156 | J27: =J28+J32 -> 2662.3876 | K27: =K28+K32 -> 2180.6228
B28: [19] | C28: Debt | D28: =MAX(D29,D30) -> 389.262 | E28: =MAX(E29,E30) -> 451.832 | F28: =MAX(F29,F30) -> 529.0553 | G28: =MAX(G29,G30) -> 672.9417 | H28: =MAX(H29,H30) -> 735.4636 | I28: =MAX(I29,I30) -> 946.7028 | J28: =MAX(J29,J30) -> 1177.133 | K28: =MAX(K29,K30) -> 1135.314
B29: [20] | C29: International debt (BIS) | D29: 389.262 | E29: 451.832 | F29: 493.026 | G29: 520.792 | H29: 535.516 | I29: 869.233 | J29: 1177.133 | K29: 1135.314
B30: [21] | C30: Creditor derived debt liabilities | D30: ='Table A11'!D31 -> 327.0328 | E30: ='Table A11'!E31 -> 429.8192 | F30: ='Table A11'!F31 -> 529.0553 | G30: ='Table A11'!G31 -> 672.9417 | H30: ='Table A11'!H31 -> 735.4636 | I30: ='Table A11'!I31 -> 946.7028 | J30: ='Table A11'!J31 -> 1118.502 | K30: ='Table A11'!K31 -> 894.1449
B31: [22] | C31: Equities | D31: =MAX(D32+D33,D34) -> 319.11253 | E31: =MAX(E32+E33,E34) -> 386.27653 | F31: =MAX(F32+F33,F34) -> 561.1922 | G31: =MAX(G32+G33,G34) -> 783.76227 | H31: =MAX(H32+H33,H34) -> 856.52873 | I31: =MAX(I32+I33,I34) -> 1195.0448 | J31: =MAX(J32+J33,J34) -> 1669.3956 | K31: =MAX(K32+K33,K34) -> 1105.9018
B32: [23] | C32: Mutual fund shares (CIMA, est.) | D32: =E32*D14/E14 -> 288.61553 | E32: =F32*E14/F14 -> 359.31339 | F32: =G32*F14/G14 -> 520.9752 | G32: =H32*G14/H14 -> 722.86348 | H32: 768.08373 | I32: 1065.6128 | J32: 1485.2546 | K32: 1045.3088
B33: [24] | C33: U.S. equities on non-fund sector (TIC) | D33: 30.497 | E33: 26.963148 | F33: 40.217 | G33: 60.898792 | H33: 88.445 | I33: 129.432 | J33: 184.141 | K33: 60.593
B34: [25] | C34: Creditor-derived equity liabilities | D34: ='Table A10'!D42 -> 116.6535 | E34: ='Table A10'!E42 -> 134.3438 | F34: ='Table A10'!F42 -> 214.687 | G34: ='Table A10'!G42 -> 307.1049 | H34: ='Table A10'!H42 -> 393.6525 | I34: ='Table A10'!I42 -> 635.7456 | J34: ='Table A10'!J42 -> 871.5224 | K34: ='Table A10'!K42 -> 506.3736
B36: [26] | C36: Net portfolio position | D36: =D14-D27 -> -335.40544 | E36: =E14-E27 -> -384.783 | F36: =F14-F27 -> -431.83971 | G36: =G14-G27 -> -538.05312 | H36: =H14-H27 -> -592.13678 | I36: =I14-I27 -> -677.82868 | J36: =J14-J27 -> -1028.6288 | K36: =K14-K27 -> -927.91683
B37: [27] | C37: Equity | D37: =D15-D32 -> -124.66092 | E37: =E15-E32 -> -157.0812 | F37: =F15-F32 -> -181.47617 | G37: =G15-G32 -> -319.0135 | H37: =H15-H32 -> -336.17853 | I37: =I15-I32 -> -447.58485 | J37: =J15-J32 -> -709.55554 | K37: =K15-K32 -> -586.46154
B38: [28] | C38: Debt | D38: =D16-D28 -> -210.74452 | E38: =E16-E28 -> -227.7018 | F38: =F16-F28 -> -250.36353 | G38: =G16-G28 -> -219.03962 | H38: =H16-H28 -> -255.95826 | I38: =I16-I28 -> -230.24383 | J38: =J16-J28 -> -319.07322 | K38: =K16-K28 -> -341.45529

Sheet Table A7
B2: Table A7: China' Cross-Border Securities Assets (bn of USD)
D4: 2001 | E4: 2002 | F4: 2003 | G4: 2004 | H4: 2005 | I4: 2006 | J4: 2007 | K4: 2008
C5: Public assets
B6: [1] | C6: Memo: total reserve minus gold | D6: 215.605 | E6: 291.128 | F6: 408.151 | G6: 614.5 | H6: 821.514 | I6: 1068.49 | J6: 1530.28 | K6: 1949.26
B7: [2] | C7: Foreign exchange reserves | D7: 212.165 | E7: 286.407 | F7: 403.251 | G7: 609.932 | H7: 818.872 | I7: 1066.34 | J7: 1528.25 | K7: 1946.03
B8: [3] | C8: Foreign portfolio reserves (85% of exchange res.) | D8: =0.85*D7 -> 180.34025 | E8: =0.85*E7 -> 243.44595 | F8: =0.85*F7 -> 342.76335 | G8: =0.85*G7 -> 518.4422 | H8: =0.85*H7 -> 696.0412 | I8: =0.85*I7 -> 906.389 | J8: =0.85*J7 -> 1299.0125 | K8: =0.85*K7 -> 1654.1255
B9: [4] | C9: Of which: equities | D9: 4.3428278 | E9: 2.8582829 | F9: 2.6290851 | G9: 3.1629463 | H9: 3.4282846 | I9: 16.305992 | J9: 83.373269 | K9: 73.915427
B10: [5] | C10: Of which: debt | D10: 175.99742 | E10: 240.58767 | F10: 340.13426 | G10: 515.27925 | H10: 692.61292 | I10: 890.08301 | J10: 1215.6392 | K10: 1580.2101
C12: Private assets
B13: [6] | C13: External Wealth of Nations II, August 2009 | D13: =D14+D15 -> 7.636 | E13: =E14+E15 -> 5.61 | F13: =F14+F15 -> 4.83 | G13: =G14+G15 -> 97.706 | H13: =H14+H15 -> 122.91851 | I13: =I14+I15 -> 272.64949 | J13: =J14+J15 -> 290.25765 | K13: n.a.
B14: [7] | C14: Of which: equities | D14: 7.636 | E14: 5.61 | F14: 4.83 | G14: 5.678 | H14: 6.1790839 | I14: 8.924904 | J14: 25.280064 | K14: n.a.
B15: [8] | C15: Of which: debt | D15: 0 | E15: 0 | F15: 0 | G15: 92.028 | H15: 116.73943 | I15: 263.72459 | J15: 264.97759 | K15: n.a.
B16: [9] | C16: International Investment Position | D16: n.a. | E16: n.a. | F16: n.a. | G16: =G17+G18 -> 92.028 | H16: =H17+H18 -> 116.739 | I16: =I17+I18 -> 265.179 | J16: =J17+J18 -> 284.6206 | K16: =K17+K18 -> 251.8802
B17: [10] | C17: Of which: equities | D17: n.a. | E17: n.a. | F17: n.a. | G17: 0 | H17: 0 | I17: 1.454 | J17: 19.6426 | K17: 20.7602
B18: [11] | C18: Of which: debt | D18: n.a. | E18: n.a. | F18: n.a. | G18: 92.028 | H18: 116.739 | I18: 263.725 | J18: 264.978 | K18: 231.12
B19: [12] | C19: Prefered estimate | D19: =D21+D20 -> 33.43735 | E19: =E21+E20 -> 46.777998 | F19: =F21+F20 -> 64.482567 | G19: =G21+G20 -> 92.827783 | H19: =H21+H20 -> 117.68496 | I19: =I21+I20 -> 267.81133 | J19: =J21+J20 -> 285.84096 | K19: =K21+K20 -> 251.8802
B20: [13] | C20: Of which: equities | D20: 1.1306378 | E20: 0.77720492 | F20: 0.70020808 | G20: 0.79978294 | H20: 0.94596115 | I20: 4.0863322 | J20: 20.862959 | K20: 20.7602
B21: [14] | C21: Of which: debt | D21: =E21*(D33-D31)/(E33-E31) -> 32.306712 | E21: =F21*(E33-E31)/(F33-F31) -> 46.000793 | F21: =G21*(F33-F31)/(G33-G31) -> 63.782359 | G21: =G18 -> 92.028 | H21: =H18 -> 116.739 | I21: =I18 -> 263.725 | J21: =J18 -> 264.978 | K21: =K18 -> 231.12
C23: Total assets
B24: [15] | C24: Total foreign securities held by China | D24: =D8+D19 -> 213.7776 | E24: =E8+E19 -> 290.22395 | F24: =F8+F19 -> 407.24592 | G24: =G8+G19 -> 611.26998 | H24: =H8+H19 -> 813.72616 | I24: =I8+I19 -> 1174.2003 | J24: =J8+J19 -> 1584.8535 | K24: =K8+K19 -> 1906.0057
B25: [16] | C25: Of which: equities | D25: =D31/D33*D24 -> 5.4734656 | E25: =E31/E33*E24 -> 3.6354878 | F25: =F31/F33*F24 -> 3.3292932 | G25: =G31/G33*G24 -> 3.9627292 | H25: =H31/H33*H24 -> 4.3742458 | I25: =I31/I33*I24 -> 20.392324 | J25: =J31/J33*J24 -> 104.23623 | K25: =K31/K33*K24 -> 94.675627
B26: [17] | C26: Of which: debt | D26: =D24*((D33-D31)/D33) -> 208.30413 | E26: =E24*((E33-E31)/E33) -> 286.58846 | F26: =F24*((F33-F31)/F33) -> 403.91662 | G26: =G24*((G33-G31)/G33) -> 607.30725 | H26: =H24*((H33-H31)/H33) -> 809.35192 | I26: =I24*((I33-I31)/I33) -> 1153.808 | J26: =J24*((J33-J31)/J33) -> 1480.6172 | K26: =K24*((K33-K31)/K33) -> 1811.3301
B27: [18] | C27: Public assets / total assets | D27: =D8/D24 -> 0.84358815 | E27: =E8/E24 -> 0.83882103 | F27: =F8/F24 -> 0.84166185 | G27: =G8/G24 -> 0.84813947 | H27: =H8/H24 -> 0.85537523 | I27: =I8/I24 -> 0.77192024 | J27: =J8/J24 -> 0.81964203 | K27: =K8/K24 -> 0.86784919
C29: U.S. assets
B30: [19] | C30: U.S. long term securities held by China (TIC) | D30: 151.565 | E30: 212.952 | F30: 293.973 | G30: 404.782 | H30: 580.523 | I30: 788.182 | J30: 1030.234 | K30: 1274.769
B31: [20] | C31: Of which: equities | D31: 3.906 | E31: 2.685 | F31: 2.419 | G31: 2.763 | H31: 3.268 | I31: 14.117 | J31: 72.075 | K31: 71.72
B32: [21] | C32: U.S. short-term securites held by China (TIC) | D32: 0.99196545 | E32: 1.3937322 | F32: 1.924 | G32: 21.424 | H32: 27.412 | I32: 24.682 | J32: 65.626 | K32: 169.095
B33: [22] | C33: Total U.S. securities held by China (TIC) | D33: 152.55697 | E33: 214.34573 | F33: 295.897 | G33: 426.206 | H33: 607.935 | I33: 812.864 | J33: 1095.86 | K33: 1443.864
B34: [23] | C34: U.S. securities / Total foreign securities | D34: =D33/D24 -> 0.71362465 | E34: =E33/E24 -> 0.73855288 | F34: =F33/F24 -> 0.72658064 | G34: =G33/G24 -> 0.69724674 | H34: =H33/H24 -> 0.74710023 | I34: =I33/I24 -> 0.69227029 | J34: =J33/J24 -> 0.69145825 | K34: =K33/K24 -> 0.75753394

Sheet Table A8
B2: Table A8: Middle-East Oil Exporting Countries' Cross-Border Securities Assets (bn of USD)
D4: 2001 | E4: 2002 | F4: 2003 | G4: 2004 | H4: 2005 | I4: 2006 | J4: 2007 | K4: 2008
C5: Assets reported in the CPIS
B6: [1] | C6: Bahrain | D6: 15.28027 | E6: 14.264342 | F6: 19.245976 | G6: 23.5136 | H6: 30.5476 | I6: 39.572 | J6: 47.084 | K6: 33.485
B7: [2] | C7: Of which: equities | D7: 3.1636 | E7: 2.4426862 | F7: 3.5394839 | G7: 4.4334 | H7: 6.8145 | I7: 8.5496 | J7: 9.508 | K7: 6.129
B8: [3] | C8: Kuwait | D8: 6.4006628 | E8: 7.1081639 | F8: 9.5905969 | G8: 11.797656 | H8: 15.273093 | I8: 23.156798 | J8: 32.130444 | K8: 40.112697
B9: [4] | C9: Of which: equities | D9: 3.1846286 | E9: 2.9373505 | F9: 4.256259 | G9: 6.3048193 | H9: 8.937027 | I9: 16.000934 | J9: 23.888631 | K9: 32.977084
B10: [5] | C10: Bahrain + Kuwait | D10: 21.680933 | E10: 21.372506 | F10: 28.836573 | G10: 35.311256 | H10: 45.820693 | I10: 62.728798 | J10: 79.214444 | K10: 73.597697
B11: [6] | C11: Of which: equities | D11: 6.3482286 | E11: 5.3800367 | F11: 7.7957429 | G11: 10.738219 | H11: 15.751527 | I11: 24.550534 | J11: 33.396631 | K11: 39.106084
C13: Middle East oil exporters' onshore assets
B14: [7] | C14: U.S. long term securities held onshore by ME oil exp. (TIC) | D14: 81.513 | E14: 72.832 | F14: 87.425 | G14: 127.041 | H14: 162.927 | I14: 230.862 | J14: 302.484 | K14: 283.371
B15: [8] | C15: Of which: equities | D15: 45.185 | E15: 37.867 | F15: 57.596 | G15: 78.807 | H15: 94.874 | I15: 127.899 | J15: 150.063 | K15: 102.251
B16: [9] | C16: Of which: long-term debt | D16: 36.328 | E16: 34.965 | F16: 29.829 | G16: 48.234 | H16: 68.053 | I16: 102.963 | J16: 152.421 | K16: 181.12
B17: [10] | C17: U.S. short-term securities held onshore by ME oil exp. (est., TIC) | D17: 21.007042 | E17: 20.272495 | F17: 22.564798 | G17: 31.498542 | H17: 29.253339 | I17: 27.993613 | J17: 39.985875 | K17: 45.364616
B18: [11] | C18: Memo: Total U.S. short term claims (i.e. incl. bank accounts) | D18: n.a. | E18: n.a. | F18: 24.787 | G18: 41.263 | H18: 50.659 | I18: 70.314 | J18: 80.593 | K18: 118.692
B19: [12] | C19: Total U.S.debt securities held onshore by ME oil exp. (est.) | D19: =D17+D16 -> 57.335042 | E19: =E17+E16 -> 55.237495 | F19: =F17+F16 -> 52.393798 | G19: =G17+G16 -> 79.732542 | H19: =H17+H16 -> 97.306339 | I19: =I17+I16 -> 130.95661 | J19: =J17+J16 -> 192.40688 | K19: =K17+K16 -> 226.48462
B20: [13] | C20: Total U.S. securities held onshore by ME oil exp. (est., TIC) | D20: =D19+D15 -> 102.52004 | E20: =E19+E15 -> 93.104495 | F20: =F19+F15 -> 109.9898 | G20: =G19+G15 -> 158.53954 | H20: =H19+H15 -> 192.18034 | I20: =I19+I15 -> 258.85561 | J20: =J19+J15 -> 342.46988 | K20: =K19+K15 -> 328.73562
B21: [14] | C21: Assumed U.S. share | D21: 0.7 | E21: =D21-0.02 -> 0.68 | F21: =E21-0.02 -> 0.66 | G21: =F21-0.02 -> 0.64 | H21: =G21-0.02 -> 0.62 | I21: =H21-0.02 -> 0.6 | J21: =I21-0.02 -> 0.58 | K21: =J21-0.02 -> 0.56
B22: [15] | C22: Implied total securities held onshore by ME oil exporters | D22: =D20/D21 -> 146.4572 | E22: =E20/E21 -> 136.91837 | F22: =F20/F21 -> 166.65121 | G22: =G20/G21 -> 247.71803 | H22: =H20/H21 -> 309.96829 | I22: =I20/I21 -> 431.42602 | J22: =J20/J21 -> 590.4653 | K22: =K20/K21 -> 587.02789
B23: [16] | C23: Of which: equities | D23: =D15/D21 -> 64.55 | E23: =E15/E21 -> 55.686765 | F23: =F15/F21 -> 87.266667 | G23: =G15/G21 -> 123.13594 | H23: =H15/H21 -> 153.02258 | I23: =I15/I21 -> 213.165 | J23: =J15/J21 -> 258.72931 | K23: =K15/K21 -> 182.59107
B24: [17] | C24: Memo: foreign exchange reserves (old classification for Saudi Arabia) | D24: 65.597003 | E24: 73.526259 | F24: 77.677755 | G24: 103.76099 | H24: 128.6465 | I24: 164.72435 | J24: 268.60832 | K24: 240.2557
B25: [18] | C25: Of which: Bahrain + Kuwait | D25: 11.693001 | E25: 11.054639 | F25: 9.487453 | G25: 10.320417 | H25: 11.790497 | I25: 15.629426 | J25: 20.894663 | K25: =J25 -> 20.894663
B26: [19] | C26: Portfolios held as reserve assets (75% of reserves) | D26: =0.75*D24 -> 49.197753 | E26: =0.75*E24 -> 55.144694 | F26: =0.75*F24 -> 58.258316 | G26: =0.75*G24 -> 77.82074 | H26: =0.75*H24 -> 96.484877 | I26: =0.75*I24 -> 123.54326 | J26: =0.75*J24 -> 201.45624 | K26: =0.75*K24 -> 180.19177
B27: [20] | C27: Implied portfolios held onshore by SWFs and by private agents | D27: =D22-D26 -> 97.259451 | E27: =E22-E26 -> 81.77368 | F27: =F22-F26 -> 108.39289 | G27: =G22-G26 -> 169.89729 | H27: =H22-H26 -> 213.48341 | I27: =I22-I26 -> 307.88276 | J27: =J22-J26 -> 389.00906 | K27: =K22-K26 -> 406.83611
B28: [21] | C28: Implied onshore portfolios missed by CPIS | D28: =D22-D10 -> 124.77627 | E28: =E22-E10 -> 115.54587 | F28: =F22-F10 -> 137.81464 | G28: =G22-G10 -> 212.40678 | H28: =H22-H10 -> 264.14759 | I28: =I22-I10 -> 368.69722 | J28: =J22-J10 -> 511.25086 | K28: =K22-K10 -> 513.43019
B29: [22] | C29: Of which: equities | D29: =D23-D11 -> 58.201771 | E29: =E23-E11 -> 50.306728 | F29: =F23-F11 -> 79.470924 | G29: =G23-G11 -> 112.39772 | H29: =H23-H11 -> 137.27105 | I29: =I23-I11 -> 188.61447 | J29: =J23-J11 -> 225.33268 | K29: =K23-K11 -> 143.48499
B30: [23] | C30: Of which: debt | D30: =D22-D23-(D10-D11) -> 66.574499 | E30: =E22-E23-(E10-E11) -> 65.239141 | F30: =F22-F23-(F10-F11) -> 58.343712 | G30: =G22-G23-(G10-G11) -> 100.00906 | H30: =H22-H23-(H10-H11) -> 126.87654 | I30: =I22-I23-(I10-I11) -> 180.08276 | J30: =J22-J23-(J10-J11) -> 285.91818 | K30: =K22-K23-(K10-K11) -> 369.9452
C32: Consistency checks
B33: [24] | C33: Setser & Ziemba (2009) estimate of GCC foreign assets | D33: 280 | E33: 270 | F33: 380 | G33: 500 | H33: 690 | I33: 900 | J33: 1280 | K33: 1200
B34: [25] | C34: Assuming 85% in portfolio assets and Iran=Iraq=0 | D34: =0.85*D33 -> 238 | E34: =0.85*E33 -> 229.5 | F34: =0.85*F33 -> 323 | G34: =0.85*G33 -> 425 | H34: =0.85*H33 -> 586.5 | I34: =0.85*I33 -> 765 | J34: =0.85*J33 -> 1088 | K34: =0.85*K33 -> 1020
B35: [26] | C35: Implied offshore portfolio of ME oil exporters | D35: =D34-D22 -> 91.542797 | E35: =E34-E22 -> 92.581626 | F35: =F34-F22 -> 156.34879 | G35: =G34-G22 -> 177.28197 | H35: =H34-H22 -> 276.53171 | I35: =I34-I22 -> 333.57398 | J35: =J34-J22 -> 497.5347 | K35: =K34-K22 -> 432.97211
B36: [27] | C36: Implied share of ME oil exp' portfolios held offshore | D36: =D35/D34 -> 0.3846336 | E36: =E35/E34 -> 0.40340578 | F36: =F35/F34 -> 0.48405199 | G36: =G35/G34 -> 0.41713404 | H36: =H35/H34 -> 0.47149482 | I36: =I35/I34 -> 0.43604442 | J36: =J35/J34 -> 0.45729292 | K36: =K35/K34 -> 0.42448247
B37: [28] | C37: Implied share of missing wealth Ω belonging to ME oil exp. | D37: {=D35:K35/TRANSPOSE('Table A3'!E10:E17)} -> 0.036154759 | E37: 0.038704467 | F37: 0.054711762 | G37: 0.053462183 | H37: 0.075233673 | I37: 0.088716409 | J37: 0.096960271 | K37: 0.096430797
B38: [29] | C38: Lane & Milesi-Ferretti's (2007) estimate of ME oil exp' foreign secs | D38: =D39+D40 -> 334.17274 | E38: =E39+E40 -> 346.21675 | F38: =F39+F40 -> 430.09203 | G38: =G39+G40 -> 535.15316 | H38: =H39+H40 -> 678.84464 | I38: =I39+I40 -> 883.72846 | J38: =J39+J40 -> 1160.4326 | K38: n.a.
B39: [30] | C39: Portfolio equities (EWNII) | D39: 100.2466 | E39: 85.04547 | F39: 117.2828 | G39: 144.8906 | H39: 175.978 | I39: 238.6816 | J39: 311.8555 | K39: n.a.
B40: [31] | C40: Debt securities (portfolio + reserve) | D40: =0.8*(D41+D42-D43)+D44 -> 233.92614 | E40: =0.8*(E41+E42-E43)+E44 -> 261.17128 | F40: =0.8*(F41+F42-F43)+F44 -> 312.80923 | G40: =0.8*(G41+G42-G43)+G44 -> 390.26256 | H40: =0.8*(H41+H42-H43)+H44 -> 502.86664 | I40: =0.8*(I41+I42-I43)+I44 -> 645.04686 | J40: =0.8*(J41+J42-J43)+J44 -> 848.5771 | K40: n.a.
B41: [32] | C41: Memo: Total debt assets (portfolio+other, EWNII) excl. Bahrain | D41: 360.713 | E41: 378.5714 | F41: 431.4123 | G41: 530.4201 | H41: 695.3006 | I41: 905.0236 | J41: 1164.107 | K41: n.a.
B42: [33] | C42: Memo: Reserve assets (EWNII), excl. Bahrain | D42: 68.05417 | E42: 77.35558 | F42: 82.69974 | G42: 100.4876 | H42: 119.1087 | I42: 144.5906 | J42: 235.4995 | K42: n.a.
B43: [34] | C43: Memo: deposits in BIS banks (BIS Table 7A), excl. Bahrain | D43: 151.282 | E43: 149.381 | F43: 146.277 | G43: 168.623 | H43: 217.39 | I43: 285.278 | J43: 389.01 | K43: 377.601
B44: [35] | C44: Memo: Portfolio debt of Bahrain (EWNII) | D44: 11.938 | E44: 15.9345 | F44: 18.5412 | G44: 20.4348 | H44: 25.2512 | I44: 33.5779 | J44: 40.0999 | K44: n.a.
B45: [36] | C45: Implied offshore portfolio of ME oil exporters | D45: =D38-D22 -> 187.71553 | E45: =E38-E22 -> 209.29838 | F45: =F38-F22 -> 263.44082 | G45: =G38-G22 -> 287.43513 | H45: =H38-H22 -> 368.87635 | I45: =I38-I22 -> 452.30244 | J45: =J38-J22 -> 569.9673 | K45: n.a.
B46: [37] | C46: Implied share of ME oil exp' portfolios held offshore | D46: =D45/(D45+D22) -> 0.56173204 | E46: =E45/(E45+E22) -> 0.6045299 | F46: =F45/(F45+F22) -> 0.61252198 | G46: =G45/(G45+G22) -> 0.53710815 | H46: =H45/(H45+H22) -> 0.54338847 | I46: =I45/(I45+I22) -> 0.51181156 | J46: =J45/(J45+J22) -> 0.49116795 | K46: n.a.
B47: [38] | C47: Implied sahre of missing wealth Ω belonging to ME oil exp. | D47: {=D45:J45/TRANSPOSE('Table A3'!E10:E16)} -> 0.07413811 | E47: 0.087498812 | F47: 0.092186907 | G47: 0.086680613 | H47: 0.10035711 | I47: 0.1202931 | J47: 0.11107604 | K47: n.a.
B48: [39] | C48: Japanese securities held by Middle-East oil exporters (CPIS) | D48: 11.203338 | E48: 13.604671 | F48: 20.162465 | G48: 30.220413 | H48: 48.202933 | I48: 58.465742 | J48: 81.169298 | K48: 100.19835
B49: [40] | C49: Of which: equities | D49: 8.9210926 | E49: 10.880734 | F49: 16.968254 | G49: 21.968882 | H49: 34.053573 | I49: 40.480034 | J49: 43.116667 | K49: 34.027548
B50: [41] | C50: Japanese assets / U.S. assets | D50: =D48/D20 -> 0.10927949 | E50: =E48/E20 -> 0.1461226 | F50: =F48/F20 -> 0.18331214 | G50: =G48/G20 -> 0.19061751 | H50: =H48/H20 -> 0.25082136 | I50: =I48/I20 -> 0.22586237 | J50: =J48/J20 -> 0.2370115 | K50: =K48/K20 -> 0.30479918
B51: [42] | C51: Saudi Arabia's foreign securities (Reserve + SWF + pension) | D51: 75.069958 | E51: 77.833314 | F51: 91.300708 | G51: 117.46272 | H51: 159.39649 | I51: 235.1418 | J51: 289.98167 | K51: 389.67258
B52: [43] | C52: Saudi Arabia's foreign sec. / Middle East est. onshore foreign sec. | D52: =D51/D22 -> 0.51257266 | E52: =E51/E22 -> 0.56846508 | F52: =F51/F22 -> 0.54785506 | G52: =G51/G22 -> 0.47417912 | H52: =H51/H22 -> 0.51423482 | I52: =I51/I22 -> 0.54503389 | J52: =J51/J22 -> 0.49110704 | K52: =K51/K22 -> 0.66380592
B53: [44] | C53: Saudi Arabia's net oil balance / Middle East net oil bal. | D53: 0.43654285 | E53: 0.44336541 | F53: 0.45369014 | G53: 0.46162701 | H53: 0.43234568 | I53: 0.4179914 | J53: 0.40287542 | K53: 0.40625848

Sheet Table A9
B2: Table A9: Other non-CPIS Countries Securities Assets (bn of USD)
D4: 2001 | E4: 2002 | F4: 2003 | G4: 2004 | H4: 2005 | I4: 2006 | J4: 2007 | K4: 2008
C5: Public assets
B6: [1] | C6: Memo: total reserve minus gold | D6: 252.03836 | E6: 307.20124 | F6: 389.17151 | G6: 473.07591 | H6: 539.6288 | I6: 659.55593 | J6: 779.87252 | K6: 862.6701
B7: [2] | C7: Foreign portfolio reserves (75% of exchange res.) | D7: =D8+D9 -> 189.02877 | E7: =E8+E9 -> 230.40093 | F7: =F8+F9 -> 291.87863 | G7: =G8+G9 -> 354.80693 | H7: =H8+H9 -> 404.7216 | I7: =I8+I9 -> 494.66695 | J7: =J8+J9 -> 584.90439 | K7: =K8+K9 -> 647.00258
B8: [3] | C8: Of which: equities (1%) | D8: 2.5203835 | E8: 3.0720125 | F8: 3.8917147 | G8: 4.7307592 | H8: 5.3962885 | I8: 6.595559 | J8: 7.7987255 | K8: 8.6267009
B9: [4] | C9: Of which: debt (74%) | D9: 186.50839 | E9: 227.32892 | F9: 287.98692 | G9: 350.07617 | H9: 399.32531 | I9: 488.07139 | J9: 577.10567 | K9: 638.37588
C11: Private assets
B12: [5] | C12: Of which: equities | D12: =D15+D21 -> 115.99681 | E12: =E15+E21 -> 114.47639 | F12: =F15+F21 -> 166.28779 | G12: =G15+G21 -> 193.52615 | H12: =H15+H21 -> 252.70445 | I12: =I15+I21 -> 420.9066 | J12: =J15+J21 -> 509.16276 | K12: =K15+K21 -> 283.19614
B13: [6] | C13: Of which: debt | D13: =D16+D22 -> 58.013934 | E13: =E16+E22 -> 77.562613 | F13: =F16+F22 -> 115.23015 | G13: =G16+G22 -> 146.55229 | H13: =H16+H22 -> 191.51536 | I13: =I16+I22 -> 238.84801 | J13: =J16+J22 -> 280.67474 | K13: =K16+K22 -> 252.85165
B14: [7] | C14: External Wealth of Nations II countries | D14: =D15+D16 -> 112.28904 | E14: =E15+E16 -> 127.12267 | F14: =F15+F16 -> 191.94928 | G14: =G15+G16 -> 240.59227 | H14: =H15+H16 -> 296.47605 | I14: =I15+I16 -> 376.21221 | J14: =J15+J16 -> 465.90063 | K14: =K15+K16 -> 335.44097
B15: [8] | C15: Of which: equities | D15: 64.270601 | E15: 61.038057 | F15: 94.136951 | G15: 117.0087 | H15: 145.33699 | I15: 199.41455 | J15: 266.05411 | K15: 152.9811
B16: [9] | C16: Of which: debt | D16: 48.018436 | E16: 66.084618 | F16: 97.812331 | G16: 123.58357 | H16: 151.13906 | I16: 176.79766 | J16: 199.84652 | K16: 182.45987
B17: [10] | C17: Memo: Taiwan | D17: =D18+D19 -> 63.338085 | E17: =E18+E19 -> 77.897682 | F17: =F18+F19 -> 130.87979 | G17: =G18+G19 -> 167.57777 | H17: =H18+H19 -> 207.58969 | I17: =I18+I19 -> 255.35678 | J17: =J18+J19 -> 307.32361 | K17: =K18+K19 -> 214.0026
B18: [11] | C18: Of which: equities | D18: 43.253085 | E18: 42.59268 | F18: 67.777791 | G18: 85.773774 | H18: 106.70369 | I18: 146.87778 | J18: 196.99361 | K18: 113.27131
B19: [12] | C19: Of which: debt | D19: 20.085 | E19: 35.305001 | F19: 63.101998 | G19: 81.803998 | H19: 100.886 | I19: 108.479 | J19: 110.33 | K19: 100.73129
B20: [13] | C20: Small International Financial Centers | D20: =D21+D22 -> 61.721711 | E20: =E21+E22 -> 64.916325 | F20: =F21+F22 -> 89.568653 | G20: =G21+G22 -> 99.486168 | H20: =H21+H22 -> 147.74376 | I20: =I21+I22 -> 283.5424 | J20: =J21+J22 -> 323.93687 | K20: =K21+K22 -> 200.60683
B21: [14] | C21: Of which: equities | D21: 51.726213 | E21: 53.43833 | F21: 72.150834 | G21: 76.517447 | H21: 107.36746 | I21: 221.49205 | J21: 243.10865 | K21: 130.21504
B22: [15] | C22: Of which: debt | D22: 9.9954977 | E22: 11.477995 | F22: 17.417819 | G22: 22.968721 | H22: 40.376295 | I22: 62.050353 | J22: 80.828224 | K22: 70.391785
B23: [16] | C23: Memo: British Virgin Islands | D23: =D24+D25 -> 49.510999 | E23: =E24+E25 -> 49.628044 | F23: =F24+F25 -> 76.895713 | G23: =G24+G25 -> 79.26297 | H23: =H24+H25 -> 115.12247 | I23: =I24+I25 -> 235.28122 | J23: =J24+J25 -> 230.53999 | K23: =K24+K25 -> 135.81809
B24: [17] | C24: Of which: equities | D24: 42.123051 | E24: 41.273493 | F24: 64.237626 | G24: 65.209555 | H24: 91.061638 | I24: 196.44553 | J24: 199.08872 | K24: 107.3663
B25: [18] | C25: Of which: debt | D25: 7.3879485 | E25: 8.3545508 | F25: 12.658087 | G25: 14.053416 | H25: 24.060829 | I25: 38.835691 | J25: 31.451266 | K25: 28.451792

Sheet Table A9B
A2: Table A9B: Bilateral Portfolio Holdings, Panel Regressions
B4: Equity | C4: Debt | E4: Equity | F4: Debt
A6: Bilateral controls
A7: Log distance | B7: -0.561*** | C7: -0.733*** | E7: -0.450*** | F7: -0.594***
B8: (0.017) | C8: (0.018) | E8: (0.010) | F8: (0.010)
A9: Longitude gap | B9: 0.003*** | C9: 0.003***
B10: (0.000) | C10: (0.000)
A11: Common language | B11: 0.394*** | C11: -0.110*** | E11: 0.451*** | F11: 0.014
B12: (0.030) | C12: (0.032) | E12: (0.022) | F12: (0.023)
A13: Colonial relationship after 1945 | B13: 0.251*** | C13: 0.447*** | E13: 0.343*** | F13: 0.488***
B14: (0.055) | C14: (0.060) | E14: (0.038) | F14: (0.041)
A15: Both countries industrial | B15: 2.739*** | C15: 2.806*** | E15: 2.499*** | F15: 2.303***
B16: (0.043) | C16: (0.046) | E16: (0.036) | F16: (0.036)
A17: Log of GDP gap | B17: -0.307*** | C17: -0.159*** | E17: -0.230*** | F17: -0.149***
B18: (0.009) | C18: (0.010) | E18: (0.007) | F18: (0.007)
A19: Log of GDP p.c. gap | B19: -0.250*** | C19: -0.149*** | E19: -0.260*** | F19: -0.195***
B20: (0.009) | C20: (0.010) | E20: (0.007) | F20: (0.007)
A21: OFC source x host dummy | B21: No | C21: No | E21: Yes | F21: Yes
A23: Source country controls
A24: Latitude | B24: -0.003*** | C24: -0.003*** | E24: -0.005*** | F24: -0.005***
B25: (0.000) | C25: (0.000) | E25: (0.000) | F25: (0.000)
A26: Landlocked dummy | B26: -0.087*** | C26: 0.208*** | E26: 0.144*** | F26: 0.303***
B27: (0.024) | C27: (0.026) | E27: (0.021) | F27: (0.021)
A28: Population | B28: 0.517*** | C28: 0.518*** | E28: 0.447*** | F28: 0.480***
B29: (0.010) | C29: (0.010) | E29: (0.007) | F29: (0.007)
A30: GDP per capita | B30: 1.123*** | C30: 0.969*** | E30: 1.220*** | F30: 1.157***
B31: (0.015) | C31: (0.016) | E31: (0.012) | F31: (0.012)
A32: OFC dummy | E32: 1.235*** | F32: 1.800***
E33: (0.141) | F33: (0.143)
A35: Year fixed-effect | B35: Yes | C35: Yes | E35: Yes | F35: Yes
A36: Host-country fixed effects | B36: Yes | C36: Yes | E36: Yes | F36: Yes
A37: Offshore centers included | B37: No | C37: No | E37: Yes | F37: Yes
A39: Observations | B39: 33746 | C39: 34037 | E39: 57122 | F39: 57670
A40: Adjusted R-squared | B40: 0.734 | C40: 0.739 | E40: 0.685 | F40: 0.707
A42: OLS regressions, pooled data 2001-2008
A43: * p<0.05, ** p<0.01, *** p<0.001. Standard errors in parentheses.
A44: Data sources: IMF Coordinated Portoflio Survey, 2001-2008

Sheet Table A9C
A2: Table A9C: Bilateral Portfolio Holdings in and of Offshore Financial Canters, Panel Regressions
A4: Source countries | B4: Non-OFCs | D4: OFCs | F4: OFCs
A5: Host countries | B5: OFCs | D5: Non-OFCs | F5: All
B6: Equity | C6: Debt | D6: Equity | E6: Debt | F6: Equity | G6: Debt
A7: Bilateral controls
A8: Log distance | B8: -0.340*** | C8: -0.596*** | D8: -0.774*** | E8: -0.792*** | F8: -0.658*** | G8: -0.651***
B9: (0.028) | C9: (0.028) | D9: (0.022) | E9: (0.02) | F9: (0.019) | G9: (0.017)
A10: Common language | B10: 0.471*** | C10: -0.202*** | D10: 0.376*** | E10: 0.143*** | F10: 0.374*** | G10: 0.125***
B11: (0.059) | C11: (0.059) | D11: (0.046) | E11: (0.043) | F11: (0.04) | G11: (0.038)
A12: Colonial relationship after 1945 | B12: 0.620*** | C12: 1.444*** | D12: 0.274*** | E12: 0.311*** | F12: 0.502*** | G12: 0.307***
B13: (0.126) | C13: (0.13) | D13: (0.076) | E13: (0.077) | F13: (0.062) | G13: (0.062)
A14: Both countries industrial | B14: 1.897*** | C14: 1.972*** | D14: 2.145*** | E14: 1.688*** | F14: 2.030*** | G14: 1.673***
B15: (0.126) | C15: (0.127) | D15: (0.087) | E15: (0.076) | F15: (0.085) | G15: (0.074)
A16: Log of GDP gap | B16: 0.003 | C16: 0.013 | D16: -0.228*** | E16: -0.275*** | F16: -0.203*** | G16: -0.204***
B17: (0.039) | C17: (0.041) | D17: (0.014) | E17: (0.013) | F17: (0.012) | G17: (0.012)
A18: Log of GDP p.c. gap | B18: -0.250*** | C18: -0.139*** | D18: -0.140*** | E18: -0.220*** | F18: -0.159*** | G18: -0.224***
B19: (0.018) | C19: (0.017) | D19: (0.018) | E19: (0.017) | F19: (0.016) | G19: (0.014)
A21: Source country controls
A22: Latitude | B22: -0.003*** | C22: -0.002* | D22: -0.023*** | E22: -0.025*** | F22: -0.022*** | G22: -0.024***
B23: (0.001) | C23: (0.001) | D23: (0.001) | E23: (0.001) | F23: (0.001) | G23: (0.001)
A24: Landlocked dummy | B24: 0.270*** | C24: 0.424*** | D24: 0.562*** | E24: 0.552*** | F24: 0.691*** | G24: 0.647***
B25: (0.061) | C25: (0.062) | D25: (0.053) | E25: (0.05) | F25: (0.05) | G25: (0.046)
A26: Population | B26: 0.410*** | C26: 0.548*** | D26: 0.356*** | E26: 0.433*** | F26: 0.391*** | G26: 0.456***
B27: (0.043) | C27: (0.045) | D27: (0.012) | E27: (0.011) | F27: (0.011) | G27: (0.011)
A28: GDP per capita | B28: 1.055*** | C28: 0.926*** | D28: 1.545*** | E28: 1.740*** | F28: 1.587*** | G28: 1.724***
B29: (0.047) | C29: (0.049) | D29: (0.03) | E29: (0.028) | F29: (0.028) | G29: (0.025)
A31: Year fixed-effect | B31: Yes | C31: Yes | D31: Yes | E31: Yes | F31: Yes | G31: Yes
A32: Host-country fixed effects | B32: Yes | C32: Yes | D32: Yes | E32: Yes | F32: Yes | G32: Yes
A34: Observations | B34: 8466 | C34: 8313 | D34: 11822 | E34: 12257 | F34: 14910 | G34: 15320
A35: Adjusted R-squared | B35: 0.644 | C35: 0.636 | D35: 0.650 | E35: 0.736 | F35: 0.643 | G35: 0.710
A37: OLS regressions, pooled data 2001-2008
A38: * p<0.05, ** p<0.01, *** p<0.001. Standard errors in parentheses.
A39: Data sources: IMF Coordinated Portoflio Survey, 2001-2008

Sheet Table A10
B2: Table A10: Cross-Border Equity Liabilities of Small Offshore Financial Centers (bn of USD)
D4: 2001 | E4: 2002 | F4: 2003 | G4: 2004 | H4: 2005 | I4: 2006 | J4: 2007 | K4: 2008
C5: Portfolio equity liabilities
B6: [1] | C6: Bahamas | D6: =MAX(D18+D29,D40) -> 10.327 | E6: =MAX(E18+E29,E40) -> 15.74009 | F6: =MAX(F18+F29,F40) -> 20.92782 | G6: =MAX(G18+G29,G40) -> 22.10284 | H6: =MAX(H18+H29,H40) -> 29.89134 | I6: =MAX(I18+I29,I40) -> 27.51256 | J6: =MAX(J18+J29,J40) -> 34.99853 | K6: =MAX(K18+K29,K40) -> 20.32008
B7: [2] | C7: Bermuda | D7: =MAX(D19+D30,D41) -> 195.3582 | E7: =MAX(E19+E30,E41) -> 184.1298 | F7: =MAX(F19+F30,F41) -> 250.8066 | G7: =MAX(G19+G30,G41) -> 335.102 | H7: =MAX(H19+H30,H41) -> 360.047 | I7: =MAX(I19+I30,I41) -> 404.2096 | J7: =MAX(J19+J30,J41) -> 556.3519 | K7: =MAX(K19+K30,K41) -> 312.205
B8: [3] | C8: Cayman Islands | D8: =MAX(D20+D31,D42) -> 319.11253 | E8: =MAX(E20+E31,E42) -> 386.27653 | F8: =MAX(F20+F31,F42) -> 561.1922 | G8: =MAX(G20+G31,G42) -> 783.76227 | H8: =MAX(H20+H31,H42) -> 856.52873 | I8: =MAX(I20+I31,I42) -> 1195.0448 | J8: =MAX(J20+J31,J42) -> 1669.3956 | K8: =MAX(K20+K31,K42) -> 1105.9018
B9: [4] | C9: Jersey | D9: =MAX(D21+D32,D43) -> 63.366121 | E9: =MAX(E21+E32,E43) -> 41.147208 | F9: =MAX(F21+F32,F43) -> 49.137906 | G9: =MAX(G21+G32,G43) -> 55.750228 | H9: =MAX(H21+H32,H43) -> 77.143774 | I9: =MAX(I21+I32,I43) -> 92.56373 | J9: =MAX(J21+J32,J43) -> 148.88967 | K9: =MAX(K21+K32,K43) -> 89.210394
B10: [5] | C10: Guernsey | D10: =MAX(D22+D33,D44) -> 33.345703 | E10: =MAX(E22+E33,E44) -> 38.499777 | F10: =MAX(F22+F33,F44) -> 52.764003 | G10: =MAX(G22+G33,G44) -> 77.319322 | H10: =MAX(H22+H33,H44) -> 101.27488 | I10: =MAX(I22+I33,I44) -> 145.56731 | J10: =MAX(J22+J33,J44) -> 194.61704 | K10: =MAX(K22+K33,K44) -> 119.19584
B11: [6] | C11: Isle of Man | D11: =MAX(D23+D34,D45) -> 0.8650818 | E11: =MAX(E23+E34,E45) -> 2.233183 | F11: =MAX(F23+F34,F45) -> 2.968001 | G11: =MAX(G23+G34,G45) -> 9.00592 | H11: =MAX(H23+H34,H45) -> 3.113042 | I11: =MAX(I23+I34,I45) -> 5.647154 | J11: =MAX(J23+J34,J45) -> 8.26368 | K11: =MAX(K23+K34,K45) -> 5.334633
B12: [7] | C12: Netherland Antilles | D12: =MAX(D24+D35,D46) -> 28.4249 | E12: =MAX(E24+E35,E46) -> 27.45845 | F12: =MAX(F24+F35,F46) -> 36.72894 | G12: =MAX(G24+G35,G46) -> 41.71873 | H12: =MAX(H24+H35,H46) -> 65.196541 | I12: =MAX(I24+I35,I46) -> 80.240605 | J12: =MAX(J24+J35,J46) -> 122.41903 | K12: =MAX(K24+K35,K46) -> 62.859991
B13: [8] | C13: BVI | D13: =MAX(D25+D36,D47) -> 43.15079 | E13: =MAX(E25+E36,E47) -> 42.32963 | F13: =MAX(F25+F36,F47) -> 65.48502 | G13: =MAX(G25+G36,G47) -> 66.99917 | H13: =MAX(H25+H36,H47) -> 93.39655 | I13: =MAX(I25+I36,I47) -> 199.8759 | J13: =MAX(J25+J36,J47) -> 203.996 | K13: =MAX(K25+K36,K47) -> 110.2087
B14: [9] | C14: Liechtenstein | D14: =MAX(D26+D37,D48) -> 8.78096 | E14: =MAX(E26+E37,E48) -> 7.5196421 | F14: =MAX(F26+F37,F48) -> 14.8618 | G14: =MAX(G26+G37,G48) -> 17.688393 | H14: =MAX(H26+H37,H48) -> 27.13958 | I14: =MAX(I26+I37,I48) -> 32.69998 | J14: =MAX(J26+J37,J48) -> 34.524475 | K14: =MAX(K26+K37,K48) -> 28.296591
B15: [10] | C15: Total | D15: =SUM(D6:D14) -> 702.73129 | E15: =SUM(E6:E14) -> 745.33431 | F15: =SUM(F6:F14) -> 1054.8723 | G15: =SUM(G6:G14) -> 1409.4489 | H15: =SUM(H6:H14) -> 1613.7314 | I15: =SUM(I6:I14) -> 2183.3617 | J15: =SUM(J6:J14) -> 2973.456 | K15: =SUM(K6:K14) -> 1853.5331
C17: Memo: investment funds foreign liabilities
B18: [11] | C18: Bahamas
B19: [12] | C19: Bermuda | D19: 55.99 | E19: 68.1 | F19: 115.84 | G19: 158.18 | H19: 187.53 | I19: 211.52 | J19: 249.17 | K19: 171.19
B20: [13] | C20: Cayman Islands | D20: 288.61553 | E20: 359.31339 | F20: 520.9752 | G20: 722.86348 | H20: 768.08373 | I20: 1065.6128 | J20: 1485.2546 | K20: 1045.3088
B21: [14] | C21: Jersey | D21: 63.349121 | E21: 40.814 | F21: 48.302906 | G21: 55.33461 | H21: 76.319774 | I21: 89.72873 | J21: 143.58167 | K21: 78.645394
B22: [15] | C22: Guernsey | D22: 29.126703 | E22: 35.243296 | F22: 48.562003 | G22: 72.203336 | H22: 95.772881 | I22: 134.22931 | J22: 183.98904 | K22: 114.19784
B23: [16] | C23: Isle of Man
B24: [17] | C24: Netherland Antilles | D24: 14.0389 | E24: 12.537283 | F24: 0 | G24: 11.639413 | H24: 20.001541 | I24: 24.204605 | J24: 34.744032 | K24: 25.925991
B25: [18] | C25: BVI
B26: [19] | C26: Liechtenstein | D26: 8.72196 | E26: 7.48872 | F26: 14.8428 | G26: 17.65296 | H26: 27.07458 | I26: 32.45998 | J26: 34.271475 | K26: 28.113591
C28: Memo: non-fund equity liabilities / U.S.
B29: [20] | C29: Bahamas | D29: 1.137 | E29: 1.1527799 | F29: 1.786 | G29: 1.7285957 | H29: 2.264 | I29: 0.938 | J29: 1.178 | K29: 0.556
B30: [21] | C30: Bermuda | D30: 118.407 | E30: 89.39677 | F30: 107.283 | G30: 152.33993 | H30: 172.517 | I30: 188.826 | J30: 252.397 | K30: 141.015
B31: [22] | C31: Cayman Islands | D31: 30.497 | E31: 26.963148 | F31: 40.217 | G31: 60.898792 | H31: 88.445 | I31: 129.432 | J31: 184.141 | K31: 60.593
B32: [23] | C32: Jersey | D32: 0.017 | E32: 0.33320791 | F32: 0.835 | G32: 0.41561809 | H32: 0.824 | I32: 2.835 | J32: 5.308 | K32: 10.565
B33: [24] | C33: Guernsey | D33: 4.219 | E33: 3.2564813 | F33: 4.202 | G33: 5.1159864 | H33: 5.502 | I33: 11.338 | J33: 10.628 | K33: 4.998
B34: [25] | C34: Isle of Man | D34: 0 | E34: -0.0001035626 | F34: 0 | G34: 0 | H34: 0.036 | I34: 0.541 | J34: 1.142 | K34: 0.345
B35: [26] | C35: Netherland Antilles | D35: 14.386 | E35: 14.921167 | F35: 23.307 | G35: 28.669084 | H35: 45.195 | I35: 56.036 | J35: 87.675 | K35: 36.934
B36: [27] | C36: BVI | D36: 0.859 | E36: 0.80579641 | F36: 1.59 | G36: 3.0661304 | H36: 4.791 | I36: 4.335 | J36: 4.663 | K36: 3.297
B37: [28] | C37: Liechtenstein | D37: 0.059 | E37: 0.030922117 | F37: 0.019 | G37: 0.035432622 | H37: 0.065 | I37: 0.24 | J37: 0.253 | K37: 0.183
C39: Memo: creditor-derived equity liabilities
B40: [29] | C40: Bahamas | D40: 10.327 | E40: 15.74009 | F40: 20.92782 | G40: 22.10284 | H40: 29.89134 | I40: 27.51256 | J40: 34.99853 | K40: 20.32008
B41: [30] | C41: Bermuda | D41: 195.3582 | E41: 184.1298 | F41: 250.8066 | G41: 335.102 | H41: 351.7418 | I41: 404.2096 | J41: 556.3519 | K41: 302.6788
B42: [31] | C42: Cayman Islands | D42: 116.6535 | E42: 134.3438 | F42: 214.687 | G42: 307.1049 | H42: 393.6525 | I42: 635.7456 | J42: 871.5224 | K42: 506.3736
B43: [32] | C43: Jersey | D43: 8.132004 | E43: 8.992595 | F43: 17.19676 | G43: 31.61894 | H43: 37.38396 | I43: 40.52367 | J43: 59.14199 | K43: 53.13895
B44: [33] | C44: Guernsey | D44: 12.32556 | E44: 14.46972 | F44: 17.28162 | G44: 23.06247 | H44: 32.75499 | I44: 54.42866 | J44: 68.16507 | K44: 49.94255
B45: [34] | C45: Isle of Man | D45: 0.8650818 | E45: 2.233183 | F45: 2.968001 | G45: 9.00592 | H45: 3.113042 | I45: 5.647154 | J45: 8.26368 | K45: 5.334633
B46: [35] | C46: Netherland Antilles | D46: 23.5709 | E46: 25.83884 | F46: 36.72894 | G46: 41.71873 | H46: 62.51339 | I46: 78.19817 | J46: 120.4834 | K46: 56.04607
B47: [36] | C47: BVI | D47: 43.15079 | E47: 42.32963 | F47: 65.48502 | G47: 66.99917 | H47: 93.39655 | I47: 199.8759 | J47: 203.996 | K47: 110.2087
B48: [37] | C48: Liechtenstein | D48: 3.61812 | E48: 5.972981 | F48: 2.843957 | G48: 1.629372 | H48: 4.541052 | I48: 5.859768 | J48: 12.29867 | K48: 7.584249

Sheet Table A11
B2: Table A11: Cross-Border Portfolio Debt Liabilities of Small Offshore Financial Centers (bn of USD)
D4: 2001 | E4: 2002 | F4: 2003 | G4: 2004 | H4: 2005 | I4: 2006 | J4: 2007 | K4: 2008
C5: Portfolio debt liabilities
B6: [1] | C6: Bahamas | D6: =MAX(D18,D29) -> 4.057066 | E6: =MAX(E18,E29) -> 5.443681 | F6: =MAX(F18,F29) -> 5.932163 | G6: =MAX(G18,G29) -> 10.20059 | H6: =MAX(H18,H29) -> 9.760697 | I6: =MAX(I18,I29) -> 8.10108 | J6: =MAX(J18,J29) -> 16.75984 | K6: =MAX(K18,K29) -> 9.608322
B7: [2] | C7: Bermuda | D7: =MAX(D19,D30) -> 24.051 | E7: =MAX(E19,E30) -> 22.998 | F7: =MAX(F19,F30) -> 26.869 | G7: =MAX(G19,G30) -> 28.1 | H7: =MAX(H19,H30) -> 33.42652 | I7: =MAX(I19,I30) -> 38.31988 | J7: =MAX(J19,J30) -> 44.178 | K7: =MAX(K19,K30) -> 53.196
B8: [3] | C8: Cayman Islands | D8: =MAX(D20,D31) -> 389.262 | E8: =MAX(E20,E31) -> 451.832 | F8: =MAX(F20,F31) -> 529.0553 | G8: =MAX(G20,G31) -> 672.9417 | H8: =MAX(H20,H31) -> 735.4636 | I8: =MAX(I20,I31) -> 946.7028 | J8: =MAX(J20,J31) -> 1177.133 | K8: =MAX(K20,K31) -> 1135.314
B9: [4] | C9: Jersey | D9: =MAX(D21,D32) -> 41.22736 | E9: =MAX(E21,E32) -> 61.19316 | F9: =MAX(F21,F32) -> 108.8469 | G9: =MAX(G21,G32) -> 134.2276 | H9: =MAX(H21,H32) -> 161.825 | I9: =MAX(I21,I32) -> 207.6378 | J9: =MAX(J21,J32) -> 292.2805 | K9: =MAX(K21,K32) -> 224.7821
B10: [5] | C10: Guernsey | D10: =MAX(D22,D33) -> 17.31997 | E10: =MAX(E22,E33) -> 14.06212 | F10: =MAX(F22,F33) -> 19.82731 | G10: =MAX(G22,G33) -> 21.60915 | H10: =MAX(H22,H33) -> 22.27729 | I10: =MAX(I22,I33) -> 27.13796 | J10: =MAX(J22,J33) -> 32.45052 | K10: =MAX(K22,K33) -> 26.83772
B11: [6] | C11: Isle of Man | D11: =MAX(D23,D34) -> 1.410246 | E11: =MAX(E23,E34) -> 0.96217 | F11: =MAX(F23,F34) -> 1.683225 | G11: =MAX(G23,G34) -> 4.068824 | H11: =MAX(H23,H34) -> 1.679273 | I11: =MAX(I23,I34) -> 2.616786 | J11: =MAX(J23,J34) -> 4.052321 | K11: =MAX(K23,K34) -> 3.676497
B12: [7] | C12: Netherland Antilles | D12: =MAX(D24,D35) -> 81.033 | E12: =MAX(E24,E35) -> 91.051 | F12: =MAX(F24,F35) -> 101.54 | G12: =MAX(G24,G35) -> 103.738 | H12: =MAX(H24,H35) -> 102.82 | I12: =MAX(I24,I35) -> 112.233 | J12: =MAX(J24,J35) -> 128.287 | K12: =MAX(K24,K35) -> 118.3
B13: [8] | C13: BVI | D13: =MAX(D25,D36) -> 9.958 | E13: =MAX(E25,E36) -> 9.817 | F13: =MAX(F25,F36) -> 21.052 | G13: =MAX(G25,G36) -> 23.386 | H13: =MAX(H25,H36) -> 24.39247 | I13: =MAX(I25,I36) -> 39.27305 | J13: =MAX(J25,J36) -> 32.03242 | K13: =MAX(K25,K36) -> 28.96137
B14: [9] | C14: Liechtenstein | D14: =MAX(D26,D37) -> 0.3864779 | E14: =MAX(E26,E37) -> 0.5545123 | F14: =MAX(F26,F37) -> 0.8507135 | G14: =MAX(G26,G37) -> 1.70009 | H14: =MAX(H26,H37) -> 5.878691 | I14: =MAX(I26,I37) -> 7.174844 | J14: =MAX(J26,J37) -> 13.05204 | K14: =MAX(K26,K37) -> 13.65779
B15: [10] | C15: Total | D15: =SUM(D6:D14) -> 568.70512 | E15: =SUM(E6:E14) -> 657.91364 | F15: =SUM(F6:F14) -> 815.65661 | G15: =SUM(G6:G14) -> 999.97195 | H15: =SUM(H6:H14) -> 1097.5235 | I15: =SUM(I6:I14) -> 1389.1972 | J15: =SUM(J6:J14) -> 1740.2256 | K15: =SUM(K6:K14) -> 1614.3338
C17: Memo: International debt issued (BIS)
B18: [11] | C18: Bahamas | D18: 2.488 | E18: 2.346 | F18: 3.276 | G18: 4.177 | H18: 5.846 | I18: 5.486 | J18: 8.786 | K18: 9.193
B19: [12] | C19: Bermuda | D19: 24.051 | E19: 22.998 | F19: 26.869 | G19: 28.1 | H19: 31.82 | I19: 35.439 | J19: 44.178 | K19: 53.196
B20: [13] | C20: Cayman Islands | D20: 389.262 | E20: 451.832 | F20: 493.026 | G20: 520.792 | H20: 535.516 | I20: 869.233 | J20: 1177.133 | K20: 1135.314
B21: [14] | C21: Jersey
B22: [15] | C22: Guernsey
B23: [16] | C23: Isle of Man
B24: [17] | C24: Netherland Antilles | D24: 81.033 | E24: 91.051 | F24: 101.54 | G24: 103.738 | H24: 102.82 | I24: 112.233 | J24: 128.287 | K24: 118.3
B25: [18] | C25: BVI | D25: 9.958 | E25: 9.817 | F25: 21.052 | G25: 23.386 | H25: 22.638 | I25: 24.639 | J25: 30.779 | K25: 28.832
B26: [19] | C26: Liechtenstein | D26: 0 | E26: 0.11 | F26: 0.157 | G26: 0.175 | H26: 0.167 | I26: 0.406 | J26: 0.615 | K26: 0.945
C28: Memo: Creditor-derived debt liabilities
B29: [20] | C29: Bahamas | D29: 4.057066 | E29: 5.443681 | F29: 5.932163 | G29: 10.20059 | H29: 9.760697 | I29: 8.10108 | J29: 16.75984 | K29: 9.608322
B30: [21] | C30: Bermuda | D30: 14.69438 | E30: 15.54264 | F30: 20.18822 | G30: 25.95319 | H30: 33.42652 | I30: 38.31988 | J30: 40.01679 | K30: 42.01599
B31: [22] | C31: Cayman Islands | D31: 327.0328 | E31: 429.8192 | F31: 529.0553 | G31: 672.9417 | H31: 735.4636 | I31: 946.7028 | J31: 1118.502 | K31: 894.1449
B32: [23] | C32: Jersey | D32: 41.22736 | E32: 61.19316 | F32: 108.8469 | G32: 134.2276 | H32: 161.825 | I32: 207.6378 | J32: 292.2805 | K32: 224.7821
B33: [24] | C33: Guernsey | D33: 17.31997 | E33: 14.06212 | F33: 19.82731 | G33: 21.60915 | H33: 22.27729 | I33: 27.13796 | J33: 32.45052 | K33: 26.83772
B34: [25] | C34: Isle of Man | D34: 1.410246 | E34: 0.96217 | F34: 1.683225 | G34: 4.068824 | H34: 1.679273 | I34: 2.616786 | J34: 4.052321 | K34: 3.676497
B35: [26] | C35: Netherland Antilles | D35: 44.82663 | E35: 51.39697 | F35: 58.35395 | G35: 65.71054 | H35: 75.2698 | I35: 98.8825 | J35: 123.3901 | K35: 91.18295
B36: [27] | C36: BVI | D36: 7.452287 | E36: 8.44799 | F36: 12.82863 | G36: 14.29949 | H36: 24.39247 | I36: 39.27305 | J36: 32.03242 | K36: 28.96137
B37: [28] | C37: Liechtenstein | D37: 0.3864779 | E37: 0.5545123 | F37: 0.8507135 | G37: 1.70009 | H37: 5.878691 | I37: 7.174844 | J37: 13.05204 | K37: 13.65779

Sheet Table A12
B2: Table A12: Raw CPIS-derived liabilities > reported liabilities (bn of USD)
C4: [1] | D4: [2] | E4: [3] | F4: [4] | G4: [5] | H4: [6] | I4: [7] | J4: [8] | K4: [9] | L4: [10] | M4: [11] | N4: [12] | O4: [13]
C5: Panel A: Equities
C7: Belgium | D7: Germany | E7: U.K. | F7: Cyprus | G7: Panama | H7: Canada | I7: Egypt | J7: India | K7: China | L7: Other | M7: Total | N7: Of which: Rich World | O7: Of which: Euro area
B8: 2001 | C8: 19.93652 | D8: 0 | E8: 0 | F8: 0 | G8: 0 | H8: 0 | I8: 0 | J8: 0 | K8: 0 | L8: 14.145179 | M8: 34.081699 | N8: =O8+E8+H8 -> 19.93652 | O8: =C8+D8+F8 -> 19.93652
B9: 2002 | C9: 15.52766 | D9: 0 | E9: 0 | F9: 0 | G9: 0 | H9: 0 | I9: 0 | J9: 0 | K9: 0 | L9: 24.122526 | M9: 39.650186 | N9: =O9+E9+H9 -> 15.52766 | O9: =C9+D9+F9 -> 15.52766
B10: 2003 | C10: 20.13062 | D10: 0 | E10: 0 | F10: 0 | G10: 16.49296 | H10: 20.554 | I10: 0 | J10: 0 | K10: 0 | L10: 5.6132812 | M10: 62.790861 | N10: =O10+E10+H10 -> 40.68462 | O10: =C10+D10+F10 -> 20.13062
B11: 2004 | C11: 34.64236 | D11: 24.2365 | E11: 0 | F11: 0 | G11: 21.58846 | H11: 0 | I11: 0 | J11: 0 | K11: 0 | L11: 14.407981 | M11: 94.875301 | N11: =O11+E11+H11 -> 58.87886 | O11: =C11+D11+F11 -> 58.87886
B12: 2005 | C12: 45.00219 | D12: 66.33559 | E12: 82.265 | F12: 0 | G12: 25.45514 | H12: 62.99203 | I12: 0 | J12: 0 | K12: 0 | L12: 18.461912 | M12: 300.51186 | N12: =O12+E12+H12 -> 256.59481 | O12: =C12+D12+F12 -> 111.33778
B13: 2006 | C13: 70.95083 | D13: 65.73525 | E13: 0 | F13: 0 | G13: 26.30678 | H13: 65.143 | I13: 0 | J13: 0 | K13: 0 | L13: 32.684489 | M13: 260.82035 | N13: =O13+E13+H13 -> 201.82908 | O13: =C13+D13+F13 -> 136.68608
B14: 2007 | C14: 67.29045 | D14: 147.2856 | E14: 13.11263 | F14: 11.50091 | G14: 32.07109 | H14: 127.7608 | I14: 16.39268 | J14: 25.52028 | K14: 0 | L14: 28.894973 | M14: 469.82941 | N14: =O14+E14+H14 -> 366.95039 | O14: =C14+D14+F14 -> 226.07696
B15: 2008 | C15: 11.50274 | D15: 45.32325 | E15: 35.346 | F15: 0 | G15: 15.13581 | H15: 160.121 | I15: 0 | J15: 97.90277 | K15: 67.30361 | L15: 39.671178 | M15: 472.30636 | N15: =O15+E15+H15 -> 252.29299 | O15: =C15+D15+F15 -> 56.82599
C16: Panel B: Debt
C18: Belgium | D18: Germany | E18: Luxembourg | F18: Greece | G18: Ireland | H18: Malaysia | I18: Singapore | L18: Other | M18: Total | N18: Of which: Rich World | O18: Of which: Euro area
B19: 2001 | C19: 0 | D19: 123.9289 | E19: 46.93855 | F19: 0 | G19: 0 | H19: 0 | I19: 0 | L19: 37.358723 | M19: 208.22617 | N19: =O19 -> 170.86745 | O19: =C19+D19+E19+F19+G19 -> 170.86745
B20: 2002 | C20: 11.37041 | D20: 73.57763 | E20: 55.12181 | F20: 0 | G20: 0 | H20: 0 | I20: 0 | L20: 18.698834 | M20: 158.76868 | N20: =O20 -> 140.06985 | O20: =C20+D20+E20+F20+G20 -> 140.06985
B21: 2003 | C21: 0 | D21: 132.4364 | E21: 30.07688 | F21: 12.94115 | G21: 0 | H21: 17.13618 | I21: 0 | L21: 13.230088 | M21: 205.8207 | N21: =O21 -> 175.45443 | O21: =C21+D21+E21+F21+G21 -> 175.45443
B22: 2004 | C22: 0 | D22: 0 | E22: 66.18622 | F22: 22.04655 | G22: 0 | H22: 0 | I22: 0 | L22: 42.024828 | M22: 130.2576 | N22: =O22 -> 88.23277 | O22: =C22+D22+E22+F22+G22 -> 88.23277
B23: 2005 | C23: 0 | D23: 0 | E23: 77.37536 | F23: 14.14266 | G23: 0 | H23: 10.25085 | I23: 13.71738 | L23: 40.200649 | M23: 155.6869 | N23: =O23 -> 91.51802 | O23: =C23+D23+E23+F23+G23 -> 91.51802
B24: 2006 | C24: 15.20425 | D24: 0 | E24: 89.46538 | F24: 0 | G24: 0 | H24: 0 | I24: 13.13329 | L24: 51.218784 | M24: 169.0217 | N24: =O24 -> 104.66963 | O24: =C24+D24+E24+F24+G24 -> 104.66963
B25: 2007 | C25: 0 | D25: 0 | E25: 78.78425 | F25: 0 | G25: 0 | H25: 12.74471 | I25: 23.62964 | L25: 34.207104 | M25: 149.3657 | N25: =O25 -> 78.78425 | O25: =C25+D25+E25+F25+G25 -> 78.78425
B26: 2008 | C26: 0 | D26: 0 | E26: 0 | F26: 0 | G26: 12.26825 | H26: 0 | I26: 11.40514 | L26: 27.352173 | M26: 51.025563 | N26: =O26 -> 12.26825 | O26: =C26+D26+E26+F26+G26 -> 12.26825

Sheet Table A13
A2: Table A13: Reported equity liabilities minus creditor-derived liabilities (bn of USD)
B4: 2001 | C4: 2002 | D4: 2003 | E4: 2004 | F4: 2005 | G4: 2006 | H4: 2007 | I4: 2008
A5: Afghanistan, Islamic State of | B5: 0 | C5: 0 | D5: 0 | E5: 0 | F5: 0 | G5: 0 | H5: 0 | I5: 0
A6: Albania | B6: -0.23362 | C6: -0.29975 | D6: -0.15646 | E6: -0.12749 | F6: -0.33009 | G6: -0.53888 | H6: -0.40151 | I6: -0.18624
A7: Algeria | B7: -0.24459 | C7: -0.21814 | D7: -0.21066 | E7: -0.16094 | F7: -0.4418 | G7: -0.32199 | H7: -0.73152 | I7: -0.55507
A8: American Samoa | B8: 0 | C8: 0 | D8: 0 | E8: 0 | F8: 0 | G8: 0 | H8: 0 | I8: 0
A9: Andorra | B9: 0 | C9: 0 | D9: 0 | E9: 0 | F9: 0 | G9: 0 | H9: 0 | I9: 0
A10: Angola | B10: -0.11798 | C10: -0.33934 | D10: -0.09684 | E10: -0.09695 | F10: -0.17773 | G10: -0.44486 | H10: -0.98506 | I10: -0.48932
A11: Anguilla | B11: 0 | C11: 0 | D11: 0 | E11: 0 | F11: 0 | G11: 0 | H11: 0 | I11: 0
A12: Antigua and Barbuda | B12: -0.41265 | C12: -0.22813 | D12: -0.29676 | E12: -0.50727 | F12: -0.30658 | G12: -1.19522 | H12: -2.77587 | I12: -1.07804
A13: Argentina | B13: -0.38744 | C13: -0.35891 | D13: -0.51897 | E13: -0.51574 | F13: -0.47392 | G13: 0.07538 | H13: 0.42495 | I13: -0.3265
A14: Armenia | B14: -0.10992 | C14: -0.11263 | D14: -0.08618 | E14: -0.09787 | F14: -0.22199 | G14: -0.38829 | H14: -0.78584 | I14: -0.35807
A15: Aruba | B15: -0.23138 | C15: -0.17186 | D15: -0.17488 | E15: -0.21012 | F15: -0.29583 | G15: -0.48446 | H15: -0.89326 | I15: -0.23647
A16: Australia | B16: 19.58221 | C16: 11.87468 | D16: 24.63742 | E16: 12.77795 | F16: 9.15634 | G16: 8.73497 | H16: 24.12672 | I16: 3.75053
... A242: International Organizations | B242: 0 | C242: -4.41349 | D242: -1.27645 | E242: -8.08406 | F242: -0.39848 | G242: -0.60401 | H242: -0.02685 | I242: -1.01949

Sheet Table A14
A2: Table A14: Reported debt liabilities minus creditor-derived liabilities (bn of USD)
B4: 2001 | C4: 2002 | D4: 2003 | E4: 2004 | F4: 2005 | G4: 2006 | H4: 2007 | I4: 2008
A5: Afghanistan, Islamic State of | B5: 0 | C5: 0 | D5: 0 | E5: 0 | F5: 0 | G5: 0 | H5: 0 | I5: 0
A6: Albania | B6: 0 | C6: 0 | D6: 0 | E6: 0 | F6: 0 | G6: 0 | H6: -1.87732 | I6: -3.03461
A7: Algeria | B7: 0 | C7: 0 | D7: 0 | E7: 0 | F7: 0 | G7: 0 | H7: 0 | I7: 0
A8: American Samoa | B8: 0 | C8: 0 | D8: 0 | E8: 0 | F8: 0 | G8: 0 | H8: 0 | I8: 0
A9: Andorra | B9: 0 | C9: 0 | D9: 0 | E9: 0 | F9: 0 | G9: 0 | H9: 0 | I9: 0
A10: Angola | B10: 0 | C10: 0 | D10: -0.18196 | E10: -0.35524 | F10: -0.59494 | G10: -0.49727 | H10: -1.07833 | I10: -1.01054
A11: Anguilla | B11: 0 | C11: 0 | D11: 0 | E11: 0 | F11: 0 | G11: 0 | H11: 0 | I11: 0
A12: Antigua and Barbuda | B12: 0 | C12: 0 | D12: 0 | E12: 0 | F12: 0 | G12: 0 | H12: 0 | I12: 0
A13: Argentina | B13: 9.6968 | C13: 5.88431 | D13: 10.44334 | E13: 6.80362 | F13: 4.66083 | G13: 6.81267 | H13: 7.24602 | I13: -0.65161
A14: Armenia | B14: -0.05863 | C14: -0.07216 | D14: -0.12835 | E14: -0.28935 | F14: -0.49241 | G14: -0.70899 | H14: -0.8366 | I14: -0.76459
A15: Aruba | B15: -0.65804 | C15: -0.70565 | D15: -0.75742 | E15: -0.90549 | F15: -0.77942 | G15: -1.06112 | H15: -1.43652 | I15: -2.97103
A16: Australia | B16: 46.89416 | C16: 48.41453 | D16: 65.10995 | E16: 63.09316 | F16: 69.31869 | G16: 82.92847 | H16: 101.08178 | I16: 80.73641
... A242: International Organizations | B242: 81.64562 | C242: 90.35419 | D242: 101.10791 | E242: 66.24425 | F242: -8.05925 | G242: -84.83862 | H242: -95.98119 | I242: -77.915

Sheet Table A15
B2: Table A15: Allocation of SEFER-SSIO Holdings
C4: 2001 | D4: 2002 | E4: 2003 | F4: 2004 | G4: 2005 | H4: 2006 | I4: 2007 | J4: 2008
B5: United States | C5: 0.64706731 | D5: 0.58359191 | E5: 0.57897763 | F5: 0.54399621 | G5: 0.54302632 | H5: 0.53894447 | I5: 0.4664857 | J5: 0.50768111
B6: Japan | C6: 0.03816076 | D6: 0.058234281 | E6: 0.050027374 | F6: 0.046299323 | G6: 0.041578747 | H6: 0.040399582 | I6: 0.038999764 | J6: 0.03828258
B7: United Kingdom | C7: 0.036842896 | D7: 0.031719781 | E7: 0.031596444 | F7: 0.026370255 | G7: 0.030431539 | H7: 0.035594109 | I7: 0.042242428 | J7: 0.042278466
B9: Euro Area | C9: =SUM(C10:C16) -> 0.20456135 | D9: =SUM(D10:D16) -> 0.20473413 | E9: =SUM(E10:E16) -> 0.23179247 | F9: =SUM(F10:F16) -> 0.27240472 | G9: =SUM(G10:G16) -> 0.25471236 | H9: =SUM(H10:H16) -> 0.25258473 | I9: =SUM(I10:I16) -> 0.26498058 | J9: =SUM(J10:J16) -> 0.2706671
B10: Germany | C10: 0.15307969 | D10: 0.11376696 | E10: 0.12015451 | F10: 0.12577881 | G10: 0.127201 | H10: 0.12506595 | I10: 0.12893097 | J10: 0.14649784
B11: France | C11: 0.030672447 | D11: 0.043448005 | E11: 0.061244335 | F11: 0.096391643 | G11: 0.072024366 | H11: 0.070084414 | I11: 0.063428425 | J11: 0.055013767
B12: Spain | C12: 0.002400607 | D12: 0.0053286949 | E12: 0.0049153773 | F12: 0.0067530897 | G12: 0.0084190017 | H12: 0.0078191397 | I12: 0.012585959 | J12: 0.017303226
B13: Netherlands | C13: 0.0071958935 | D13: 0.013121998 | E13: 0.015527374 | F13: 0.016283985 | G13: 0.01712941 | H13: 0.019999647 | I13: 0.023745359 | J13: 0.019513052
B14: Italy | C14: 0.0071899661 | D14: 0.019696352 | E14: 0.021642315 | F14: 0.018642253 | G14: 0.020075596 | H14: 0.015529845 | I14: 0.015875724 | J14: 0.01220245
B15: Ireland | C15: 0.00043665361 | D15: 0.0023806557 | E15: 0.0027014105 | F15: 0.0020661186 | G15: 0.0025758935 | H15: 0.0059320188 | I15: 0.009865549 | J15: 0.008525871
B16: Belgium | C16: 0.0035860919 | D16: 0.0069914669 | E16: 0.0056071425 | F16: 0.0064888185 | G16: 0.0072870916 | H16: 0.0081537103 | I16: 0.010548597 | J16: 0.011610898
B19: International organizations | C19: 0.022399738 | D19: 0.071293172 | E19: 0.066360792 | F19: 0.057307936 | G19: 0.064355198 | H19: 0.08390157 | I19: 0.086258821 | J19: 0.085234244
B20: Confidential | C20: 0.0041136327 | D20: 0.012765584 | E20: 0.0087536144 | F20: 0.019516805 | G20: 0.027215729 | H20: 0.012506279 | I20: 0.061692568 | J20: 0.0075827547
B21: Other | C21: =1-C19-C9-C7-C6-C5-C20 -> 0.046854316 | D21: =1-D19-D9-D7-D6-D5-D20 -> 0.037661141 | E21: =1-E19-E9-E7-E6-E5-E20 -> 0.032491674 | F21: =1-F19-F9-F7-F6-F5-F20 -> 0.034104753 | G21: =1-G19-G9-G7-G6-G5-G20 -> 0.038680105 | H21: =1-H19-H9-H7-H6-H5-H20 -> 0.03606926 | I21: =1-I19-I9-I7-I6-I5-I20 -> 0.039340138 | J21: =1-J19-J9-J7-J6-J5-J20 -> 0.048273744
B23: Memo: SEFER+SSIO (bn USD) | C23: 1281.8058 | D23: 1429.1011 | E23: 1849.7833 | F23: 2145.013 | G23: 2221.1363 | H23: 2558.3584 | I23: 3109.3694 | J23: 3643.0773

Sheet Table A16
A2: Table A16: Actual and Predicted Shares of Each Developed Country in the Aggregate Portfolio of CPIS-Participating Countries
B5: Equity | E5: Debt | I5: Equity | L5: Debt | P5: Equity | S5: Debt
B6: Actual | C6: Predicted | E6: Actual | F6: Predicted | I6: Actual | J6: Predicted | L6: Actual | M6: Predicted | P6: Actual | Q6: Predicted | S6: Actual | T6: Predicted
A8: Austria | H8: Italy | O8: Switzerland
A9: 2001 | B9: 0.0063066 | C9: 0.0038253 | E9: 0.0151238 | F9: 0.0153624 | H9: 2001 | I9: 0.018598 | J9: 0.0108503 | L9: 0.0393106 | M9: 0.0222747 | O9: 2001 | P9: 0.0246145 | Q9: 0.0218238 | S9: 0.0050266 | T9: 0.004279
A10: 2002 | B10: 0.0059226 | C10: 0.0035035 | E10: 0.0166696 | F10: 0.0148016 | H10: 2002 | I10: 0.024595 | J10: 0.0105557 | L10: 0.0406434 | M10: 0.0217722 | O10: 2002 | P10: 0.0213535 | Q10: 0.0204004 | S10: 0.0055185 | T10: 0.0041454
A11: 2003 | B11: 0.0123679 | C11: 0.0033667 | E11: 0.0162547 | F11: 0.0142451 | H11: 2003 | I11: 0.0205366 | J11: 0.0100189 | L11: 0.0392207 | M11: 0.0208876 | O11: 2003 | P11: 0.0198072 | Q11: 0.0203962 | S11: 0.0039779 | T11: 0.0041934
A12: 2004 | B12: 0.0167293 | C12: 0.0033463 | E12: 0.0174069 | F12: 0.0141051 | H12: 2004 | I12: 0.0161141 | J12: 0.0104122 | L12: 0.0372722 | M12: 0.0211015 | O12: 2004 | P12: 0.0188268 | Q12: 0.0207719 | S12: 0.0048944 | T12: 0.0042729
A13: 2005 | B13: 0.0291035 | C13: 0.0038094 | E13: 0.0220902 | F13: 0.0147891 | H13: 2005 | I13: 0.0131735 | J13: 0.0104886 | L13: 0.0393283 | M13: 0.0210632 | O13: 2005 | P13: 0.0202763 | Q13: 0.0219254 | S13: 0.0045483 | T13: 0.0044218
A14: 2006 | B14: 0.0336982 | C14: 0.0039187 | E14: 0.0251 | F14: 0.0147813 | H14: 2006 | I14: 0.0115961 | J14: 0.0109602 | L14: 0.0302737 | M14: 0.0214084 | O14: 2006 | P14: 0.0232793 | Q14: 0.0232887 | S14: 0.0047153 | T14: 0.0047417
A15: 2007 | B15: 0.023933 | C15: 0.0036881 | E15: 0.0212518 | F15: 0.0141692 | H15: 2007 | I15: 0.010077 | J15: 0.0109273 | L15: 0.0315307 | M15: 0.0211444 | O15: 2007 | P15: 0.0175216 | Q15: 0.023663 | S15: 0.0062589 | T15: 0.0046958
A16: 2008 | B16: 0.0162261 | C16: 0.0035794 | E16: 0.0231502 | F16: 0.0138927 | H16: 2008 | I16: 0.0096785 | J16: 0.0112655 | L16: 0.0310338 | M16: 0.0214054 | O16: 2008 | P16: 0.0238004 | Q16: 0.0220175 | S16: 0.0069349 | T16: 0.004468
A18: Belgium | H18: Luxembourg | O18: United Kingdom
A19: 2001 | B19: 0.0091012 | C19: 0.0055981 | E19: 0.0126078 | F19: 0.007865 | H19: 2001 | I19: 0.1129169 | J19: 0.1050903 | L19: 0.0444405 | M19: 0.024532 | O19: 2001 | P19: 0.1021856 | Q19: 0.0955821 | S19: 0.0842783 | T19: 0.1149682
A20: 2002 | B20: 0.0076728 | C20: 0.0057483 | E20: 0.0108712 | F20: 0.0080227 | H20: 2002 | I20: 0.1135312 | J20: 0.1008823 | L20: 0.0419255 | M20: 0.0238186 | O20: 2002 | P20: 0.1050508 | Q20: 0.0904251 | S20: 0.085496 | T20: 0.1104192
A21: 2003 | B21: 0.0082171 | C21: 0.0057604 | E21: 0.0113698 | F21: 0.0079028 | H21: 2003 | I21: 0.1391615 | J21: 0.0927526 | L21: 0.0410617 | M21: 0.0225681 | O21: 2003 | P21: 0.1020945 | Q21: 0.0905991 | S21: 0.0865131 | T21: 0.1107743
A22: 2004 | B22: 0.0067079 | C22: 0.0053664 | E22: 0.0098163 | F22: 0.0076854 | H22: 2004 | I22: 0.1418892 | J22: 0.0881834 | L22: 0.0288994 | M22: 0.0218311 | O22: 2004 | P22: 0.1071338 | Q22: 0.0900119 | S22: 0.1095883 | T22: 0.1098532
A23: 2005 | B23: 0.0095999 | C23: 0.0056243 | E23: 0.0116137 | F23: 0.0077923 | H23: 2005 | I23: 0.1427832 | J23: 0.086923 | L23: 0.0230211 | M23: 0.0215788 | O23: 2005 | P23: 0.1040852 | Q23: 0.0936568 | S23: 0.0959526 | T23: 0.1123368
A24: 2006 | B24: 0.0102631 | C24: 0.0056586 | E24: 0.0099957 | F24: 0.007797 | H24: 2006 | I24: 0.143093 | J24: 0.0854277 | L24: 0.0300165 | M24: 0.0215664 | O24: 2006 | P24: 0.1018001 | Q24: 0.0900881 | S24: 0.0995259 | T24: 0.1099846
A25: 2007 | B25: 0.0082202 | C25: 0.0057628 | E25: 0.010599 | F25: 0.0079287 | H25: 2007 | I25: 0.1432947 | J25: 0.080019 | L25: 0.0287499 | M25: 0.0202586 | O25: 2007 | P25: 0.0932833 | Q25: 0.0890353 | S25: 0.1220845 | T25: 0.1079859
A26: 2008 | B26: 0.0090523 | C26: 0.0056948 | E26: 0.0082463 | F26: 0.0077656 | H26: 2008 | I26: 0.1413221 | J26: 0.0785496 | L26: 0.0262818 | M26: 0.0199518 | O26: 2008 | P26: 0.0988262 | Q26: 0.0909687 | S26: 0.1217766 | T26: 0.110625
A28: Denmark | H28: Netherlands | O28: United States
A29: 2001 | B29: 0.0025162 | C29: 0.0030209 | E29: 0.0067312 | F29: 0.006755 | H29: 2001 | I29: 0.0297118 | J29: 0.023529 | L29: 0.0478194 | M29: 0.0606836 | O29: 2001 | P29: 0.3116954 | Q29: 0.2165713 | S29: 0.3563828 | T29: 0.3201067
A30: 2002 | B30: 0.0032993 | C30: 0.0029006 | E30: 0.0081444 | F30: 0.0066413 | H30: 2002 | I30: 0.0381449 | J30: 0.0224181 | L30: 0.0625437 | M30: 0.0584456 | O30: 2002 | P30: 0.2933526 | Q30: 0.214324 | S30: 0.3554937 | T30: 0.3178246
A31: 2003 | B31: 0.0031138 | C31: 0.0030779 | E31: 0.0079771 | F31: 0.0067783 | H31: 2003 | I31: 0.0315564 | J31: 0.0214402 | L31: 0.0578258 | M31: 0.0564167 | O31: 2003 | P31: 0.282063 | Q31: 0.22621 | S31: 0.3514379 | T31: 0.3295322
A32: 2004 | B32: 0.0022024 | C32: 0.0035461 | E32: 0.0076987 | F32: 0.0071362 | H32: 2004 | I32: 0.0355319 | J32: 0.0213794 | L32: 0.0618169 | M32: 0.0563912 | O32: 2004 | P32: 0.262556 | Q32: 0.2336277 | S32: 0.3021644 | T32: 0.3355941
A33: 2005 | B33: 0.0093277 | C33: 0.0029064 | E33: 0.0118564 | F33: 0.0065303 | H33: 2005 | I33: 0.0292311 | J33: 0.021556 | L33: 0.051359 | M33: 0.056353 | O33: 2005 | P33: 0.2473815 | Q33: 0.2304989 | S33: 0.3136097 | T33: 0.3322821
A34: 2006 | B34: 0.0076402 | C34: 0.0030867 | E34: 0.0077398 | F34: 0.0067397 | H34: 2006 | I34: 0.0227053 | J34: 0.0220298 | L34: 0.0559321 | M34: 0.0568625 | O34: 2006 | P34: 0.2316323 | Q34: 0.2298455 | S34: 0.3085695 | T34: 0.3307263
A35: 2007 | B35: 0.0052719 | C35: 0.0030728 | E35: 0.0104365 | F35: 0.0066024 | H35: 2007 | I35: 0.0226158 | J35: 0.0215899 | L35: 0.0668646 | M35: 0.0555837 | O35: 2007 | P35: 0.2323252 | Q35: 0.2427509 | S35: 0.2846866 | T35: 0.3400038
A36: 2008 | B36: 0.005497 | C36: 0.0029546 | E36: 0.0094058 | F36: 0.0064283 | H36: 2008 | I36: 0.02189 | J36: 0.0217921 | L36: 0.0551024 | M36: 0.0552517 | O36: 2008 | P36: 0.2516514 | Q36: 0.2459448 | S36: 0.288612 | T36: 0.3441198
A38: France | H38: Norway
A39: 2001 | B39: 0.0464595 | C39: 0.0422437 | E39: 0.0380165 | F39: 0.0496244 | H39: 2001 | I39: 0.0014403 | J39: 0.0034344 | L39: 0.0064112 | M39: 0.0059686
A40: 2002 | B40: 0.0484111 | C40: 0.0448078 | E40: 0.0457591 | F40: 0.0513155 | H40: 2002 | I40: 0.0016613 | J40: 0.0033228 | L40: 0.0093842 | M40: 0.0059159
A41: 2003 | B41: 0.0536907 | C41: 0.0421407 | E41: 0.0518562 | F41: 0.0486822 | H41: 2003 | I41: 0.0015418 | J41: 0.0032061 | L41: 0.005169 | M41: 0.005747
A42: 2004 | B42: 0.0467828 | C42: 0.0381463 | E42: 0.0582907 | F42: 0.0463171 | H42: 2004 | I42: 0.0022346 | J42: 0.0031958 | L42: 0.0049916 | M42: 0.0057171
A43: 2005 | B43: 0.0383557 | C43: 0.0399957 | E43: 0.0525258 | F43: 0.0470148 | H43: 2005 | I43: 0.0042573 | J43: 0.0031662 | L43: 0.0055343 | M43: 0.0055582
A44: 2006 | B44: 0.0396874 | C44: 0.0391267 | E44: 0.0520226 | F44: 0.0464383 | H44: 2006 | I44: 0.0050318 | J44: 0.0031001 | L44: 0.0061108 | M44: 0.0054603
A45: 2007 | B45: 0.037628 | C45: 0.0389589 | E45: 0.0502058 | F45: 0.0468587 | H45: 2007 | I45: 0.0063156 | J45: 0.0030631 | L45: 0.0077062 | M45: 0.0053766
A46: 2008 | B46: 0.0374312 | C46: 0.0383809 | E46: 0.0537724 | F46: 0.0457266 | H46: 2008 | I46: 0.0052595 | J46: 0.0029216 | L46: 0.0087091 | M46: 0.0051904
A48: Germany | H48: Sweden
A49: 2001 | B49: 0.0486657 | C49: 0.035043 | E49: 0.0960818 | F49: 0.1015086 | H49: 2001 | I49: 0.0155783 | J49: 0.0081223 | L49: 0.019545 | M49: 0.0107998
A50: 2002 | B50: 0.0499321 | C50: 0.0382157 | E50: 0.1010471 | F50: 0.1045862 | H50: 2002 | I50: 0.015586 | J50: 0.0077006 | L50: 0.0141901 | M50: 0.0104786
A51: 2003 | B51: 0.0419142 | C51: 0.0326888 | E51: 0.1056794 | F51: 0.0965163 | H51: 2003 | I51: 0.0164397 | J51: 0.0073139 | L51: 0.0131064 | M51: 0.0101003
A52: 2004 | B52: 0.0347176 | C52: 0.0314114 | E52: 0.1129912 | F52: 0.0938 | H52: 2004 | I52: 0.0139 | J52: 0.0076538 | L52: 0.0111164 | M52: 0.0104264
A53: 2005 | B53: 0.0342783 | C53: 0.0324893 | E53: 0.104872 | F53: 0.0952195 | H53: 2005 | I53: 0.0158436 | J53: 0.0073752 | L53: 0.0129225 | M53: 0.0101332
A54: 2006 | B54: 0.0305966 | C54: 0.0332619 | E54: 0.0917466 | F54: 0.0957526 | H54: 2006 | I54: 0.0177974 | J54: 0.0078938 | L54: 0.0154408 | M54: 0.0104683
A55: 2007 | B55: 0.0401642 | C55: 0.0331221 | E55: 0.0823058 | F55: 0.0948023 | H55: 2007 | I55: 0.0136342 | J55: 0.0076059 | L55: 0.0138656 | M55: 0.010099
A56: 2008 | B56: 0.036472 | C56: 0.0323973 | E56: 0.0761058 | F56: 0.0940918 | H56: 2008 | I56: 0.0092787 | J56: 0.0083523 | L56: 0.0171095 | M56: 0.0106007

Sheet Table A17
A2: Table A17: Reported and Predicted Shares of Each Foreign Country in the U.S., Japanese, and French Portfolios (2001-2008 averages)
B4: USA | G4: Japan | L4: France
B5: Equity recorded | C5: Equity predicted | D5: Debt recorded | E5: Debt predicted | G5: Equity recorded | H5: Equity predicted | I5: Debt recorded | J5: Debt predicted | L5: Equity recorded | M5: Equity predicted | N5: Debt recorded | O5: Debt predicted
A6: United States | G6: 0.4702864 | H6: 0.5058329 | I6: 0.320735 | J6: 0.5504819 | L6: 0.1445149 | M6: 0.1886544 | N6: 0.0989174 | O6: 0.2026257
A7: United Kingdom | B7: 0.1757134 | C7: 0.2516887 | D7: 0.2231005 | E7: 0.1913188 | G7: 0.1096542 | H7: 0.1097769 | I7: 0.0550371 | J7: 0.0876098 | L7: 0.1101073 | M7: 0.2986018 | N7: 0.0888179 | O7: 0.268288
A8: Austria | B8: 0.0025977 | C8: 0.0054335 | D8: 0.0047607 | E8: 0.0196228 | G8: 0.0015047 | H8: 0.0039506 | I8: 0.0069764 | J8: 0.0102114 | L8: 0.0027308 | M8: 0.0039922 | N8: 0.0213943 | O8: 0.0116527
A9: Belgium | B9: 0.0059095 | C9: 0.0082252 | D9: 0.004866 | E9: 0.0121632 | G9: 0.0037969 | H9: 0.0053011 | I9: 0.0090401 | J9: 0.0055834 | L9: 0.0264949 | M9: 0.0272802 | N9: 0.0382158 | O9: 0.0223453
A10: Denmark | B10: 0.0054082 | C10: 0.0042329 | D10: 0.0080475 | E10: 0.0094894 | G10: 0.0027231 | H10: 0.0024527 | I10: 0.0050185 | J10: 0.0041253 | L10: 0.0018329 | M10: 0.0019849 | N10: 0.0049187 | O10: 0.0039343
A11: France | B11: 0.0673533 | C11: 0.081895 | D11: 0.0482149 | E11: 0.0888717 | G11: 0.043686 | H11: 0.0602876 | I11: 0.0586616 | J11: 0.0439492
A12: Germany | B12: 0.0504262 | C12: 0.0690148 | D12: 0.063515 | E12: 0.1854494 | G12: 0.0308837 | H12: 0.0591952 | I12: 0.0905028 | J12: 0.1037389 | L12: 0.109504 | M12: 0.1442539 | N12: 0.1307912 | O12: 0.2781637
A13: San Marino | B13: 0 | C13: 0.0001184 | D13: 0 | E13: 7.44e-05 | G13: 0 | H13: 5.14e-05 | I13: 0 | J13: 2.52e-05 | L13: 0 | M13: 5.35e-05 | N13: 0 | O13: 3.25e-05
A14: Italy | B14: 0.0199666 | C14: 0.0206249 | D14: 0.015866 | E14: 0.0388075 | G14: 0.0150204 | H14: 0.0218827 | I14: 0.033098 | J14: 0.0255981 | L14: 0.0564201 | M14: 0.0212474 | N14: 0.1398223 | O14: 0.028216
A15: Luxembourg | B15: 0.0037596 | C15: 0.1016158 | D15: 0.0227455 | E15: 0.0293909 | G15: 0.0211046 | H15: 0.0570279 | I15: 0.0390203 | J15: 0.0121273 | L15: 0.1364835 | M15: 0.1414549 | N15: 0.015155 | O15: 0.0274087
A16: Netherlands | B16: 0.0472612 | C16: 0.0403801 | D16: 0.0525883 | E16: 0.1001508 | G16: 0.0196011 | H16: 0.0281185 | I16: 0.0360883 | J16: 0.0476196 | L16: 0.0822031 | M16: 0.0352352 | N16: 0.1169143 | O16: 0.081433
A17: Vatican City State | B17: 0 | C17: 0 | D17: 0 | E17: 0 | G17: 0 | H17: 0 | I17: 0 | J17: 0 | L17: 0 | M17: 0 | N17: 0 | O17: 0
A18: Norway | B18: 0.0063691 | C18: 0.0052089 | D18: 0.0101374 | E18: 0.0081952 | G18: 0.0023803 | H18: 0.002886 | I18: 0.0087946 | J18: 0.0034342 | L18: 0.0024688 | M18: 0.0021506 | N18: 0.0031137 | O18: 0.0028433
A19: Sweden | B19: 0.0128448 | C19: 0.0166277 | D19: 0.0221843 | E19: 0.0211156 | G19: 0.0081274 | H19: 0.0067539 | I19: 0.012622 | J19: 0.0075 | L19: 0.0059307 | M19: 0.0050782 | N19: 0.0111848 | O19: 0.0059849
A20: Switzerland | B20: 0.0581049 | C20: 0.0387405 | D20: 0.0030405 | E20: 0.0065938 | G20: 0.0295682 | H20: 0.0160529 | I20: 0.001156 | J20: 0.0021948 | L20: 0.0445708 | M20: 0.0332159 | N20: 0.0011832 | O20: 0.0039181
A21: Canada | B21: 0.0675434 | C21: 0.0630222 | D21: 0.1384178 | E21: 0.0851939 | G21: 0.0218746 | H21: 0.0097802 | I21: 0.017337 | J21: 0.0097312 | L21: 0.0043392 | M21: 0.0102698 | N21: 0.0101564 | O21: 0.0053484
A22: Japan | B22: 0.1214474 | C22: 0.0842138 | D22: 0.0317521 | E22: 0.0215077 | L22: 0.0474143 | M22: 0.0227034 | N22: 0.0268615 | O22: 0.0038546
A23: Finland | B23: 0.0177989 | C23: 0.0104977 | D23: 0.0039827 | E23: 0.0074768 | G23: 0.0064374 | H23: 0.0080611 | I23: 0.0032375 | J23: 0.0041809 | L23: 0.0164124 | M23: 0.0053685 | N23: 0.0103859 | O23: 0.0028767
A24: Greece | B24: 0.0027002 | C24: 0.0024565 | D24: 0.0013664 | E24: 0.0083902 | G24: 0.0017787 | H24: 0.0019213 | I24: 0.0028991 | J24: 0.0047444 | L24: 0.0026929 | M24: 0.0012645 | N24: 0.0255885 | O24: 0.0033058
A25: Iceland | B25: 7.26e-06 | C25: 0.0003436 | D25: 0.0016382 | E25: 0.0053149 | G25: 0 | H25: 0.0001671 | I25: 0.0003716 | J25: 0.0018732 | L25: 1.49e-05 | M25: 8.72e-05 | N25: 0.0012196 | O25: 0.0010646
A26: Ireland | B26: 0.0115618 | C26: 0.0620954 | D26: 0.0238968 | E26: 0.0306154 | G26: 0.0137088 | H26: 0.0216607 | I26: 0.0203744 | J26: 0.0116172 | L26: 0.0432492 | M26: 0.0201377 | N26: 0.0356233 | O26: 0.0136311
A27: Malta | B27: 4.15e-06 | C27: 0.0002903 | D27: 5.55e-05 | E27: 0.0001061 | G27: 4.99e-07 | H27: 0.0001191 | I27: 3.64e-06 | J27: 4.88e-05 | L27: 5.22e-06 | M27: 9.34e-05 | N27: 3.13e-05 | O27: 4.28e-05
A28: Portugal | B28: 0.0017608 | C28: 0.0027192 | D28: 0.0008289 | E28: 0.0058273 | G28: 0.0010378 | H28: 0.0015802 | I28: 0.0009739 | J28: 0.0023025 | L28: 0.0027676 | M28: 0.0013581 | N28: 0.0235111 | O28: 0.002237
A29: Spain | B29: 0.0210457 | C29: 0.0188478 | D29: 0.0116508 | E29: 0.0258985 | G29: 0.0140485 | H29: 0.0135869 | I29: 0.0119006 | J29: 0.0121878 | L29: 0.0505098 | M29: 0.013384 | N29: 0.0906827 | O29: 0.0141158
A30: Turkey | B30: 0.0024504 | C30: 0.0017717 | D30: 0.0023815 | E30: 0.0017486 | G30: 0.0004389 | H30: 0.00133 | I30: 0.0007124 | J30: 0.0009784 | L30: 0.0004613 | M30: 0.0008633 | N30: 0.000376 | O30: 0.00065
A31: Australia | B31: 0.0241792 | C31: 0.0206814 | D31: 0.0384658 | E31: 0.0193743 | G31: 0.0242402 | H31: 0.015303 | I31: 0.0201298 | J31: 0.0183546 | L31: 0.0028063 | M31: 0.0042904 | N31: 0.0090721 | O31: 0.0037581
A32: New Zealand | B32: 0.0013086 | C32: 0.0016201 | D32: 0.0049118 | E32: 0.002173 | G32: 0.0006608 | H32: 0.0011012 | I32: 0.0019229 | J32: 0.0017849 | L32: 0.0002338 | M32: 0.0002567 | N32: 0.0006247 | O32: 0.0003263
A33: South Africa | B33: 0.008207 | C33: 0.0041676 | D33: 0.002174 | E33: 0.0013545 | G33: 0.0009117 | H33: 0.001913 | I33: 0.0008528 | J33: 0.0007156 | L33: 0.0014845 | M33: 0.0008063 | N33: 0.0002471 | O33: 0.0002714
A34: Argentina | B34: 0.0003719 | C34: 0.0002269 | D34: 0.0040403 | E34: 0.0008701 | G34: 3.61e-05 | H34: 0.0001193 | I34: 0.0010102 | J34: 0.0003227 | L34: 8.85e-05 | M34: 5.15e-05 | N34: 0.0004173 | O34: 0.0001265
... A243: International Organizations | B243: 0.0001027 | C243: 0 | D243: 0.0158025 | E243: 0 | G243: 0 | H243: 0 | I243: 0.0535094 | J243: 0 | L243: 0.0007818 | M243: 0 | N243: 0.017892 | O243: 0

Sheet Table A18
B2: Table A18a: Unidentified Investments in U.S. Equities through Irish, Luxembourgish and Caymanian Funds, bn U.S.D., 2008
D4: [1] | E4: [2] | F4: [3] | G4: [4] | H4: [5] | I4: [6] | J4: [7]
D5: Creditor-derived equity liabilities | E5: Reported equity liabilities | F5: Discrepancy | G5: Discrepancy, % of equity liabilities | H5: Share of fund assets invested in U.S. equities | I5: U.S. equities with no identifiable owner | J5: As a % of U.S. foreign equity liabilities
F6: [2]-[1] | G6: ([2]-[1])/[2] | I6: [3]x[5]
B7: Ireland | D7: 253 | E7: 889 | F7: =E7-D7 -> 636 | G7: =F7/E7 -> 0.71541057 | H7: 0.055066411 | I7: =H7*F7 -> 35.022237 | J7: 0.016590826
B8: Luxembourg | D8: 1151 | E8: 2081 | F8: =E8-D8 -> 930 | G8: =F8/E8 -> 0.44690053 | H8: 0.065905112 | I8: =H8*F8 -> 61.291754 | J8: 0.02903529
B9: Cayman Islands | D9: 506 | E9: 1106 | F9: =E9-D9 -> 600 | G9: =F9/E9 -> 0.54249548 | H9: 0.16987066 | I9: =H9*F9 -> 101.9224 | J9: 0.048282944
B10: Total | D10: =SUM(D7:D9) -> 1910 | E10: =SUM(E7:E9) -> 4076 | F10: =SUM(F7:F9) -> 2166 | G10: =F10/E10 -> 0.53140334 | H10: =I10/F10 -> 0.091521879 | I10: =SUM(I7:I9) -> 198.23639 | J10: 0.09390906
B14: Table A18b: Unidentified Investments in U.S. Equities through Switzerland, bn U.S.D.
C16: 2001 | D16: 2002 | E16: 2003 | F16: 2004 | G16: 2005 | H16: 2006 | I16: 2007 | J16: 2008
B17: U.S. equity assets of Switzerland | C17: 47.215861 | D17: 39.986762 | E17: 52.079282 | F17: 54.901576 | G17: 55.518405 | H17: 63.356068 | I17: 66.872457 | J17: 46.539438
B18: U.S. equity liabilities "vis-à-vis Switzerland" | C18: 121.658 | D18: 96.528 | E18: 123.498 | F18: 134.546 | G18: 142.574 | H18: 166.745 | I18: 178.501 | J18: 119.709
B19: U.S. equities in Swiss banks with unidentifiable owner | C19: =C18-C17 -> 74.442139 | D19: =D18-D17 -> 56.541238 | E19: =E18-E17 -> 71.418718 | F19: =F18-F17 -> 79.644424 | G19: =G18-G17 -> 87.055595 | H19: =H18-H17 -> 103.38893 | I19: =I18-I17 -> 111.62854 | J19: =J18-J17 -> 73.169562
B20: As a fraction of U.S. equity liab. "vis-à-vis Switzerland" | C20: =C19/C18 -> 0.61189678 | D20: =D19/D18 -> 0.58574961 | E20: =E19/E18 -> 0.57829858 | F20: =F19/F18 -> 0.5919494 | G20: =G19/G18 -> 0.61059937 | H20: =H19/H18 -> 0.62004217 | I20: =I19/I18 -> 0.62536649 | J20: =J19/J18 -> 0.61122858
B21: As a fraction of all U.S. equity liabilities | C21: 0.047322568 | D21: 0.042551529 | E21: 0.038838182 | F21: 0.037491056 | G21: 0.037703804 | H21: 0.037092289 | I21: 0.034540116 | J21: 0.034662076

Sheet Table A19
L2: Table A19 – The World Current Account: Credits
M3: [1] | N3: [2] | O3: [3] | P3: [4] | Q3: [5] | R3: [6] | S3: [7] | T3: [8] | U3: [9] | V3: [10] | W3: [11]
N4: Billions of current USD
M5: Memo: number of countries used for estimation | N5: Current account | O5: Trade | P5: Income | U5: Current Transfers | V5: World GDP | W5: World exports / world GDP
Q6: Compensation of employees | R6: Investment income
S7: FDI income | T7: Portfolio and other income
L8: 1970 | M8: 14 | N8: 184.61704 | O8: 159.38301 | P8: 21.633674 | Q8: 0.86045711 | R8: 20.773215 | S8: 13.198476 | U8: 3.600356 | V8: 2873.8165 | W8: =O8/V8 -> 0.055460398
L9: =L8+1 -> 1971 | M9: 20 | N9: 257.5061 | O9: 225.68699 | P9: 25.922381 | Q9: 1.1980906 | R9: 24.724289 | S9: 14.475921 | U9: 5.8967275 | V9: 3177.5316 | W9: =O9/V9 -> 0.071025885
L10: =L9+1 -> 1972 | M10: 23 | N10: 309.59936 | O10: 268.20754 | P10: 33.790629 | Q10: 1.4102299 | R10: 32.380403 | S10: 16.445797 | U10: 7.6011935 | V10: 3671.982 | W10: =O10/V10 -> 0.073041627
L11: =L10+1 -> 1973 | M11: 23 | N11: 424.89523 | O11: 364.33757 | P11: 49.740275 | Q11: 1.5681824 | R11: 48.172093 | S11: 25.941071 | U11: 10.817388 | V11: 4488.1506 | W11: =O11/V11 -> 0.081177661
L12: =L11+1 -> 1974 | M12: 37 | N12: 597.04969 | O12: 519.32204 | P12: 64.215332 | Q12: 1.4988018 | R12: 62.71653 | S12: 29.040371 | U12: 13.51232 | V12: 5183.3353 | W12: =O12/V12 -> 0.10019071
L13: =L12+1 -> 1975 | M13: 62 | N13: 898.55987 | O13: 784.55356 | P13: 78.415371 | Q13: 2.9247489 | R13: =P13-Q13 -> 75.490622 | S13: 24.961506 | T13: =R13-S13 -> 50.529116 | U13: =N13-O13-P13 -> 35.590943 | V13: 5785.9511 | W13: =O13/V13 -> 0.1355963
L14: =L13+1 -> 1976 | M14: 89 | N14: 1090.8695 | O14: 958.0077 | P14: 86.248114 | Q14: 3.0341769 | R14: =P14-Q14 -> 83.213937 | S14: 28.869481 | T14: =R14-S14 -> 54.344456 | U14: =N14-O14-P14 -> 46.613677 | V14: 6295.5027 | W14: =O14/V14 -> 0.15217334
L15: =L14+1 -> 1977 | M15: 118 | N15: 1435.13 | O15: 1263.9509 | P15: 108.22494 | Q15: 5.6543464 | R15: =P15-Q15 -> 102.57059 | S15: 30.452915 | T15: =R15-S15 -> 72.117679 | U15: =N15-O15-P15 -> 62.954182 | V15: 7120.4338 | W15: =O15/V15 -> 0.17751037
L16: =L15+1 -> 1978 | M16: 124 | N16: 1694.0813 | O16: 1470.4501 | P16: 146.33718 | Q16: 7.7868048 | R16: =P16-Q16 -> 138.55038 | S16: 37.789532 | T16: =R16-S16 -> 100.76085 | U16: =N16-O16-P16 -> 77.293986 | V16: 8396.4382 | W16: =O16/V16 -> 0.17512784
L17: =L16+1 -> 1979 | M17: 129 | N17: 2192.7641 | O17: 1869.1494 | P17: 224.66832 | Q17: 9.6827846 | R17: =P17-Q17 -> 214.98553 | S17: 61.805326 | T17: =R17-S17 -> 153.18021 | U17: =N17-O17-P17 -> 98.946439 | V17: 9749.5601 | W17: =O17/V17 -> 0.19171628
L18: =L17+1 -> 1980 | M18: 135 | N18: 2683.1741 | O18: 2266.77 | P18: 299.452 | Q18: 11.414181 | R18: =P18-Q18 -> 288.03782 | S18: 61.890906 | T18: =R18-S18 -> 226.14692 | U18: =N18-O18-P18 -> 116.95216 | V18: 10964.04 | W18: =O18/V18 -> 0.20674586
L19: =L18+1 -> 1981 | M19: 138 | N19: 2790.0646 | O19: 2303.6569 | P19: 369.53561 | Q19: 10.510244 | R19: =P19-Q19 -> 359.02537 | S19: 54.825778 | T19: =R19-S19 -> 304.19959 | U19: =N19-O19-P19 -> 116.87204 | V19: 11242.462 | W19: =O19/V19 -> 0.20490681
L20: =L19+1 -> 1982 | M20: 142 | N20: 2679.1367 | O20: 2189.3576 | P20: 373.91626 | Q20: 11.18435 | R20: =P20-Q20 -> 362.73191 | S20: 45.960961 | T20: =R20-S20 -> 316.77095 | U20: =N20-O20-P20 -> 115.86285 | V20: 11135.678 | W20: =O20/V20 -> 0.19660748
L21: =L20+1 -> 1983 | M21: 142 | N21: 2580.063 | O21: 2131.9609 | P21: 331.51981 | Q21: 11.203719 | R21: =P21-Q21 -> 320.3161 | S21: 49.9386 | T21: =R21-S21 -> 270.3775 | U21: =N21-O21-P21 -> 116.58231 | V21: 11377.33 | W21: =O21/V21 -> 0.18738675
L22: =L21+1 -> 1984 | M22: 144 | N22: 2732.1549 | O22: 2245.2681 | P22: 367.69291 | Q22: 10.556571 | R22: =P22-Q22 -> 357.13634 | S22: 58.757277 | T22: =R22-S22 -> 298.37906 | U22: =N22-O22-P22 -> 119.1939 | V22: 11813.138 | W22: =O22/V22 -> 0.19006534
L23: =L22+1 -> 1985 | M23: 146 | N23: 2751.8428 | O23: 2272.5873 | P23: 356.65333 | Q23: 10.549771 | R23: =P23-Q23 -> 346.10356 | S23: 53.413411 | T23: =R23-S23 -> 292.69015 | U23: =N23-O23-P23 -> 122.60215 | V23: 12415.312 | W23: =O23/V23 -> 0.18304714
L24: =L23+1 -> 1986 | M24: 148 | N24: 3055.8242 | O24: 2518.7052 | P24: 392.35798 | Q24: 14.237312 | R24: =P24-Q24 -> 378.12066 | S24: 63.783548 | T24: =R24-S24 -> 314.33712 | U24: =N24-O24-P24 -> 144.761 | V24: 14670.89 | W24: =O24/V24 -> 0.17168047
... L31: =L30+1 -> 1993 | M31: 156 | N31: 5832.2967 | O31: 4640.1299 | P31: 908.99288 | Q31: 28.374545 | R31: =P31-Q31 -> 880.61834 | S31: 133.5952 | T31: =R31-S31 -> 747.02313 | U31: =N31-O31-P31 -> 283.17393 | V31: 24860.857 | W31: =O31/V31 -> 0.18664401
L32: =L31+1 -> 1994 | M32: All | N32: 6519.02 | O32: 5311.91 | P32: 914.123 | Q32: 29.2147 | R32: 884.909 | S32: 170.1839 | T32: 714.725 | U32: 292.991 | V32: 26706.552 | W32: =O32/V32 -> 0.19889913
L33: =L32+1 -> 1995 | M33: All | N33: 7745 | O33: 6328.7 | P33: 1093.54 | Q33: 35.6625 | R33: 1057.87 | S33: 208.7098 | T33: 849.165 | U33: 322.77 | V33: 29640.43 | W33: =O33/V33 -> 0.21351579
L34: =L33+1 -> 1996 | M34: All | N34: 8090.18 | O34: 6673.82 | P34: 1049.62 | Q34: 34.4561 | R34: 1015.16 | S34: 241.002 | T34: 774.163 | U34: 366.743 | V34: 30272.947 | W34: =O34/V34 -> 0.22045491
L35: =L34+1 -> 1997 | M35: All | N35: 8388.44 | O35: 6926.87 | P35: 1107.38 | Q35: 42.4945 | R35: 1064.88 | S35: 271.522 | T35: 793.359 | U35: 354.193 | V35: 30169.983 | W35: =O35/V35 -> 0.22959476
L36: =L35+1 -> 1998 | M36: All | N36: 8419.3 | O36: 6842.27 | P36: 1207.09 | Q36: 43.3024 | R36: 1163.79 | S36: 278.2591 | T36: 885.532 | U36: 369.946 | V36: 30012.323 | W36: =O36/V36 -> 0.22798202
L37: =L36+1 -> 1999 | M37: All | N37: 8715.65 | O37: 7076.27 | P37: 1259.25 | Q37: 41.3429 | R37: 1217.91 | S37: 340.711 | T37: 877.198 | U37: 380.128 | V37: 31098.996 | W37: =O37/V37 -> 0.22754014
L38: =L37+1 -> 2000 | M38: All | N38: 9666.59 | O38: 7869.88 | P38: 1431.46 | Q38: 41.2816 | R38: 1390.18 | S38: 390.452 | T38: 999.73 | U38: 365.249 | V38: 32048.357 | W38: =O38/V38 -> 0.24556267
L39: =L38+1 -> 2001 | M39: All | N39: 9335.08 | O39: 7614.77 | P39: 1331.17 | Q39: 43.5182 | R39: 1287.66 | S39: 347.359 | T39: 940.298 | U39: 389.137 | V39: 31825.716 | W39: =O39/V39 -> 0.23926469
L40: =L39+1 -> 2002 | M40: All | N40: 9747.96 | O40: 8033.43 | P40: 1278.73 | Q40: 49.475 | R40: 1229.25 | S40: 385.526 | T40: 843.727 | U40: 435.801 | V40: 33086.986 | W40: =O40/V40 -> 0.24279727
L41: =L40+1 -> 2003 | M41: All | N41: 11366.8 | O41: 9356.29 | P41: 1498.93 | Q41: 60.0838 | R41: 1438.85 | S41: 525.052 | T41: 913.794 | U41: 511.592 | V41: 37234.777 | W41: =O41/V41 -> 0.25127826
L42: =L41+1 -> 2004 | M42: All | N42: 13850.8 | O42: 11354.73 | P42: 1890.57 | Q42: 71.6642 | R42: 1818.9 | S42: 733.042 | T42: 1085.86 | U42: 605.52 | V42: 42167.192 | W42: =O42/V42 -> 0.26927878
L43: =L42+1 -> 2005 | M43: All | N43: 16049.3 | O43: 12924.79 | P43: 2431.75 | Q43: 78.592 | R43: 2353.16 | S43: 951.561 | T43: 1401.6 | U43: 692.7 | V43: 45602.844 | W43: =O43/V43 -> 0.2834207
... L46: =L45+1 -> 2008 | M46: All | N46: 24896 | O46: 19873.28 | P46: 4047.72 | Q46: 120.267 | R46: 3927.46 | S46: 1297.362 | T46: 2630.09 | U46: 974.996 | V46: 61305.355 | W46: =O46/V46 -> 0.32416874

Sheet Table A20
L2: Table A20 – The World Current Account: Debits
M3: [1] | N3: [2] | O3: [3] | P3: [4] | Q3: [5] | R3: [6] | S3: [7] | T3: [8] | U3: [9]
N4: Billions of current USD
M5: Memo: number of countries used for estimation | N5: Current account | O5: Trade | P5: Income | U5: Current Transfers
Q6: Compensation of employees | R6: Investment income
S7: FDI income | T7: Portfolio and other income
L8: 1970 | M8: 14 | N8: 184.61704 | O8: 159.38301 | P8: 21.633674 | Q8: 0.86045711 | R8: 20.773215 | S8: 13.198476 | U8: 3.600356
L9: =L8+1 -> 1971 | M9: 20 | N9: 257.5061 | O9: 225.68699 | P9: 25.922381 | Q9: 1.1980906 | R9: 24.724289 | S9: 14.475921 | U9: 5.8967275
L10: =L9+1 -> 1972 | M10: 23 | N10: 309.59936 | O10: 268.20754 | P10: 33.790629 | Q10: 1.4102299 | R10: 32.380403 | S10: 16.445797 | U10: 7.6011935
L11: =L10+1 -> 1973 | M11: 23 | N11: 424.89523 | O11: 364.33757 | P11: 49.740275 | Q11: 1.5681824 | R11: 48.172093 | S11: 25.941071 | U11: 10.817388
L12: =L11+1 -> 1974 | M12: 37 | N12: 597.04969 | O12: 519.32204 | P12: 64.215332 | Q12: 1.4988018 | R12: 62.71653 | S12: 29.040371 | U12: 13.51232
L13: =L12+1 -> 1975 | M13: 62 | N13: ='Table A19'!N13-'Table A21'!N13 -> 893.2555 | O13: ='Table A19'!O13-'Table A21'!O13 -> 769.24633 | P13: ='Table A19'!P13-'Table A21'!P13 -> 76.458057 | Q13: ='Table A19'!Q13-'Table A21'!Q13 -> 3.2501645 | R13: ='Table A19'!R13-'Table A21'!R13 -> 73.207892 | S13: ='Table A19'!S13-'Table A21'!S13 -> 18.077074 | T13: ='Table A19'!T13-'Table A21'!T13 -> 55.130818 | U13: ='Table A19'!U13-'Table A21'!U13 -> 47.551116
L14: =L13+1 -> 1976 | M14: 89 | N14: ='Table A19'!N14-'Table A21'!N14 -> 1099.8669 | O14: ='Table A19'!O14-'Table A21'!O14 -> 960.37558 | P14: ='Table A19'!P14-'Table A21'!P14 -> 85.119862 | Q14: ='Table A19'!Q14-'Table A21'!Q14 -> 3.4805167 | R14: ='Table A19'!R14-'Table A21'!R14 -> 81.639345 | S14: ='Table A19'!S14-'Table A21'!S14 -> 21.922445 | T14: ='Table A19'!T14-'Table A21'!T14 -> 59.716901 | U14: ='Table A19'!U14-'Table A21'!U14 -> 54.371405
L15: =L14+1 -> 1977 | M15: 118 | N15: ='Table A19'!N15-'Table A21'!N15 -> 1458.3806 | O15: ='Table A19'!O15-'Table A21'!O15 -> 1275.8832 | P15: ='Table A19'!P15-'Table A21'!P15 -> 112.81179 | Q15: ='Table A19'!Q15-'Table A21'!Q15 -> 6.0529341 | R15: ='Table A19'!R15-'Table A21'!R15 -> 106.75886 | S15: ='Table A19'!S15-'Table A21'!S15 -> 31.209464 | T15: ='Table A19'!T15-'Table A21'!T15 -> 75.549392 | U15: ='Table A19'!U15-'Table A21'!U15 -> 69.685539
L16: =L15+1 -> 1978 | M16: 124 | N16: ='Table A19'!N16-'Table A21'!N16 -> 1719.4037 | O16: ='Table A19'!O16-'Table A21'!O16 -> 1482.892 | P16: ='Table A19'!P16-'Table A21'!P16 -> 149.22755 | Q16: ='Table A19'!Q16-'Table A21'!Q16 -> 7.5104678 | R16: ='Table A19'!R16-'Table A21'!R16 -> 141.71708 | S16: ='Table A19'!S16-'Table A21'!S16 -> 36.147958 | T16: ='Table A19'!T16-'Table A21'!T16 -> 105.56913 | U16: ='Table A19'!U16-'Table A21'!U16 -> 87.28416
L17: =L16+1 -> 1979 | M17: 129 | N17: ='Table A19'!N17-'Table A21'!N17 -> 2223.4038 | O17: ='Table A19'!O17-'Table A21'!O17 -> 1895.7203 | P17: ='Table A19'!P17-'Table A21'!P17 -> 220.62228 | Q17: ='Table A19'!Q17-'Table A21'!Q17 -> 8.1463782 | R17: ='Table A19'!R17-'Table A21'!R17 -> 212.47591 | S17: ='Table A19'!S17-'Table A21'!S17 -> 46.783891 | T17: ='Table A19'!T17-'Table A21'!T17 -> 165.69202 | U17: ='Table A19'!U17-'Table A21'!U17 -> 107.06117
L18: =L17+1 -> 1980 | M18: 135 | N18: ='Table A19'!N18-'Table A21'!N18 -> 2741.6036 | O18: ='Table A19'!O18-'Table A21'!O18 -> 2304.1126 | P18: ='Table A19'!P18-'Table A21'!P18 -> 312.62192 | Q18: ='Table A19'!Q18-'Table A21'!Q18 -> 10.720258 | R18: ='Table A19'!R18-'Table A21'!R18 -> 301.90166 | S18: ='Table A19'!S18-'Table A21'!S18 -> 58.498225 | T18: ='Table A19'!T18-'Table A21'!T18 -> 243.40344 | U18: ='Table A19'!U18-'Table A21'!U18 -> 124.86914
L19: =L18+1 -> 1981 | M19: 138 | N19: ='Table A19'!N19-'Table A21'!N19 -> 2866.5699 | O19: ='Table A19'!O19-'Table A21'!O19 -> 2339.2238 | P19: ='Table A19'!P19-'Table A21'!P19 -> 401.66768 | Q19: ='Table A19'!Q19-'Table A21'!Q19 -> 11.956351 | R19: ='Table A19'!R19-'Table A21'!R19 -> 389.71133 | S19: ='Table A19'!S19-'Table A21'!S19 -> 59.735271 | T19: ='Table A19'!T19-'Table A21'!T19 -> 329.97606 | U19: ='Table A19'!U19-'Table A21'!U19 -> 125.67835
L20: =L19+1 -> 1982 | M20: 142 | N20: ='Table A19'!N20-'Table A21'!N20 -> 2767.5604 | O20: ='Table A19'!O20-'Table A21'!O20 -> 2226.887 | P20: ='Table A19'!P20-'Table A21'!P20 -> 412.59901 | Q20: ='Table A19'!Q20-'Table A21'!Q20 -> 13.194694 | R20: ='Table A19'!R20-'Table A21'!R20 -> 399.40432 | S20: ='Table A19'!S20-'Table A21'!S20 -> 45.994008 | T20: ='Table A19'!T20-'Table A21'!T20 -> 353.41031 | U20: ='Table A19'!U20-'Table A21'!U20 -> 128.07447
L21: =L20+1 -> 1983 | M21: 142 | N21: ='Table A19'!N21-'Table A21'!N21 -> 2656.1395 | O21: ='Table A19'!O21-'Table A21'!O21 -> 2169.5703 | P21: ='Table A19'!P21-'Table A21'!P21 -> 360.65672 | Q21: ='Table A19'!Q21-'Table A21'!Q21 -> 12.380694 | R21: ='Table A19'!R21-'Table A21'!R21 -> 348.27603 | S21: ='Table A19'!S21-'Table A21'!S21 -> 44.89753 | T21: ='Table A19'!T21-'Table A21'!T21 -> 303.3785 | U21: ='Table A19'!U21-'Table A21'!U21 -> 125.91255
L22: =L21+1 -> 1984 | M22: 144 | N22: ='Table A19'!N22-'Table A21'!N22 -> 2815.3323 | O22: ='Table A19'!O22-'Table A21'!O22 -> 2284.0415 | P22: ='Table A19'!P22-'Table A21'!P22 -> 403.06418 | Q22: ='Table A19'!Q22-'Table A21'!Q22 -> 12.550119 | R22: ='Table A19'!R22-'Table A21'!R22 -> 390.51406 | S22: ='Table A19'!S22-'Table A21'!S22 -> 51.335457 | T22: ='Table A19'!T22-'Table A21'!T22 -> 339.1786 | U22: ='Table A19'!U22-'Table A21'!U22 -> 128.22668
L23: =L22+1 -> 1985 | M23: 146 | N23: ='Table A19'!N23-'Table A21'!N23 -> 2838.9711 | O23: ='Table A19'!O23-'Table A21'!O23 -> 2304.2269 | P23: ='Table A19'!P23-'Table A21'!P23 -> 403.66919 | Q23: ='Table A19'!Q23-'Table A21'!Q23 -> 13.757351 | R23: ='Table A19'!R23-'Table A21'!R23 -> 389.91184 | S23: ='Table A19'!S23-'Table A21'!S23 -> 49.428545 | T23: ='Table A19'!T23-'Table A21'!T23 -> 340.4833 | U23: ='Table A19'!U23-'Table A21'!U23 -> 131.07502
L24: =L23+1 -> 1986 | M24: 148 | N24: ='Table A19'!N24-'Table A21'!N24 -> 3133.7803 | O24: ='Table A19'!O24-'Table A21'!O24 -> 2539.6519 | P24: ='Table A19'!P24-'Table A21'!P24 -> 436.7887 | Q24: ='Table A19'!Q24-'Table A21'!Q24 -> 17.758705 | R24: ='Table A19'!R24-'Table A21'!R24 -> 419.02999 | S24: ='Table A19'!S24-'Table A21'!S24 -> 50.246811 | T24: ='Table A19'!T24-'Table A21'!T24 -> 368.78318 | U24: ='Table A19'!U24-'Table A21'!U24 -> 157.33968
... L31: =L30+1 -> 1993 | M31: 156 | N31: ='Table A19'!N31-'Table A21'!N31 -> 5907.4475 | O31: ='Table A19'!O31-'Table A21'!O31 -> 4606.9556 | P31: ='Table A19'!P31-'Table A21'!P31 -> 972.45441 | Q31: ='Table A19'!Q31-'Table A21'!Q31 -> 36.628136 | R31: ='Table A19'!R31-'Table A21'!R31 -> 935.82628 | S31: ='Table A19'!S31-'Table A21'!S31 -> 85.442478 | T31: ='Table A19'!T31-'Table A21'!T31 -> 850.3838 | U31: ='Table A19'!U31-'Table A21'!U31 -> 328.03746
L32: =L31+1 -> 1994 | M32: All | N32: ='Table A19'!N32-'Table A21'!N32 -> 6577.5118 | O32: ='Table A19'!O32-'Table A21'!O32 -> 5237.2652 | P32: ='Table A19'!P32-'Table A21'!P32 -> 993.3479 | Q32: ='Table A19'!Q32-'Table A21'!Q32 -> 37.09327 | R32: ='Table A19'!R32-'Table A21'!R32 -> 956.25506 | S32: ='Table A19'!S32-'Table A21'!S32 -> 120.93796 | T32: ='Table A19'!T32-'Table A21'!T32 -> 835.317 | U32: ='Table A19'!U32-'Table A21'!U32 -> 346.9028
L33: =L32+1 -> 1995 | M33: All | N33: ='Table A19'!N33-'Table A21'!N33 -> 7800.4846 | O33: ='Table A19'!O33-'Table A21'!O33 -> 6244.9587 | P33: ='Table A19'!P33-'Table A21'!P33 -> 1180.2927 | Q33: ='Table A19'!Q33-'Table A21'!Q33 -> 43.13566 | R33: ='Table A19'!R33-'Table A21'!R33 -> 1137.1491 | S33: ='Table A19'!S33-'Table A21'!S33 -> 169.9239 | T33: ='Table A19'!T33-'Table A21'!T33 -> 967.23 | U33: ='Table A19'!U33-'Table A21'!U33 -> 375.2435
L34: =L33+1 -> 1996 | M34: All | N34: ='Table A19'!N34-'Table A21'!N34 -> 8127.7673 | O34: ='Table A19'!O34-'Table A21'!O34 -> 6588.5653 | P34: ='Table A19'!P34-'Table A21'!P34 -> 1139.1562 | Q34: ='Table A19'!Q34-'Table A21'!Q34 -> 42.50481 | R34: ='Table A19'!R34-'Table A21'!R34 -> 1096.6471 | S34: ='Table A19'!S34-'Table A21'!S34 -> 190.1331 | T34: ='Table A19'!T34-'Table A21'!T34 -> 906.519 | U34: ='Table A19'!U34-'Table A21'!U34 -> 400.0492
L35: =L34+1 -> 1997 | M35: All | N35: ='Table A19'!N35-'Table A21'!N35 -> 8379.1577 | O35: ='Table A19'!O35-'Table A21'!O35 -> 6816.5439 | P35: ='Table A19'!P35-'Table A21'!P35 -> 1178.8432 | Q35: ='Table A19'!Q35-'Table A21'!Q35 -> 41.33447 | R35: ='Table A19'!R35-'Table A21'!R35 -> 1137.5028 | S35: ='Table A19'!S35-'Table A21'!S35 -> 216.10781 | T35: ='Table A19'!T35-'Table A21'!T35 -> 921.396 | U35: ='Table A19'!U35-'Table A21'!U35 -> 383.7732
L36: =L35+1 -> 1998 | M36: All | N36: ='Table A19'!N36-'Table A21'!N36 -> 8487.5808 | O36: ='Table A19'!O36-'Table A21'!O36 -> 6778.7067 | P36: ='Table A19'!P36-'Table A21'!P36 -> 1305.4816 | Q36: ='Table A19'!Q36-'Table A21'!Q36 -> 43.742919 | R36: ='Table A19'!R36-'Table A21'!R36 -> 1261.7408 | S36: ='Table A19'!S36-'Table A21'!S36 -> 244.39386 | T36: ='Table A19'!T36-'Table A21'!T36 -> 1017.348 | U36: ='Table A19'!U36-'Table A21'!U36 -> 403.3985
L37: =L36+1 -> 1999 | M37: All | N37: ='Table A19'!N37-'Table A21'!N37 -> 8817.394 | O37: ='Table A19'!O37-'Table A21'!O37 -> 7059.7048 | P37: ='Table A19'!P37-'Table A21'!P37 -> 1350.8056 | Q37: ='Table A19'!Q37-'Table A21'!Q37 -> 47.37546 | R37: ='Table A19'!R37-'Table A21'!R37 -> 1303.4328 | S37: ='Table A19'!S37-'Table A21'!S37 -> 298.2528 | T37: ='Table A19'!T37-'Table A21'!T37 -> 1005.179 | U37: ='Table A19'!U37-'Table A21'!U37 -> 406.8811
L38: =L37+1 -> 2000 | M38: All | N38: ='Table A19'!N38-'Table A21'!N38 -> 9816.356 | O38: ='Table A19'!O38-'Table A21'!O38 -> 7892.3643 | P38: ='Table A19'!P38-'Table A21'!P38 -> 1522.3815 | Q38: ='Table A19'!Q38-'Table A21'!Q38 -> 47.71008 | R38: ='Table A19'!R38-'Table A21'!R38 -> 1474.6735 | S38: ='Table A19'!S38-'Table A21'!S38 -> 362.1815 | T38: ='Table A19'!T38-'Table A21'!T38 -> 1112.494 | U38: ='Table A19'!U38-'Table A21'!U38 -> 401.6091
L39: =L38+1 -> 2001 | M39: All | N39: ='Table A19'!N39-'Table A21'!N39 -> 9483.726 | O39: ='Table A19'!O39-'Table A21'!O39 -> 7658.4949 | P39: ='Table A19'!P39-'Table A21'!P39 -> 1404.7582 | Q39: ='Table A19'!Q39-'Table A21'!Q39 -> 51.02999 | R39: ='Table A19'!R39-'Table A21'!R39 -> 1353.7362 | S39: ='Table A19'!S39-'Table A21'!S39 -> 287.8162 | T39: ='Table A19'!T39-'Table A21'!T39 -> 1065.917 | U39: ='Table A19'!U39-'Table A21'!U39 -> 420.4698
L40: =L39+1 -> 2002 | M40: All | N40: ='Table A19'!N40-'Table A21'!N40 -> 9845.7534 | O40: ='Table A19'!O40-'Table A21'!O40 -> 8018.8221 | P40: ='Table A19'!P40-'Table A21'!P40 -> 1373.4082 | Q40: ='Table A19'!Q40-'Table A21'!Q40 -> 57.31226 | R40: ='Table A19'!R40-'Table A21'!R40 -> 1316.0913 | S40: ='Table A19'!S40-'Table A21'!S40 -> 348.2923 | T40: ='Table A19'!T40-'Table A21'!T40 -> 967.802 | U40: ='Table A19'!U40-'Table A21'!U40 -> 453.5241
L41: =L40+1 -> 2003 | M41: All | N41: ='Table A19'!N41-'Table A21'!N41 -> 11386.845 | O41: ='Table A19'!O41-'Table A21'!O41 -> 9290.2949 | P41: ='Table A19'!P41-'Table A21'!P41 -> 1575.5708 | Q41: ='Table A19'!Q41-'Table A21'!Q41 -> 67.92641 | R41: ='Table A19'!R41-'Table A21'!R41 -> 1507.6478 | S41: ='Table A19'!S41-'Table A21'!S41 -> 475.6338 | T41: ='Table A19'!T41-'Table A21'!T41 -> 1032.01 | U41: ='Table A19'!U41-'Table A21'!U41 -> 520.99075
L42: =L41+1 -> 2004 | M42: All | N42: ='Table A19'!N42-'Table A21'!N42 -> 13795.841 | O42: ='Table A19'!O42-'Table A21'!O42 -> 11265.294 | P42: ='Table A19'!P42-'Table A21'!P42 -> 1906.7845 | Q42: ='Table A19'!Q42-'Table A21'!Q42 -> 77.67943 | R42: ='Table A19'!R42-'Table A21'!R42 -> 1829.0996 | S42: ='Table A19'!S42-'Table A21'!S42 -> 622.4866 | T42: ='Table A19'!T42-'Table A21'!T42 -> 1206.615 | U42: ='Table A19'!U42-'Table A21'!U42 -> 623.782
L43: =L42+1 -> 2005 | M43: All | N43: ='Table A19'!N43-'Table A21'!N43 -> 15945.893 | O43: ='Table A19'!O43-'Table A21'!O43 -> 12787.476 | P43: ='Table A19'!P43-'Table A21'!P43 -> 2444.1585 | Q43: ='Table A19'!Q43-'Table A21'!Q43 -> 86.64588 | R43: ='Table A19'!R43-'Table A21'!R43 -> 2357.5149 | S43: ='Table A19'!S43-'Table A21'!S43 -> 828.0869 | T43: ='Table A19'!T43-'Table A21'!T43 -> 1529.429 | U43: ='Table A19'!U43-'Table A21'!U43 -> 714.1986
... L46: =L45+1 -> 2008 | M46: All | N46: ='Table A19'!N46-'Table A21'!N46 -> 24597.877 | O46: ='Table A19'!O46-'Table A21'!O46 -> 19506.94 | P46: ='Table A19'!P46-'Table A21'!P46 -> 4147.0393 | Q46: ='Table A19'!Q46-'Table A21'!Q46 -> 136.4549 | R46: ='Table A19'!R46-'Table A21'!R46 -> 4010.592 | S46: ='Table A19'!S46-'Table A21'!S46 -> 1224.685 | T46: ='Table A19'!T46-'Table A21'!T46 -> 2785.899 | U46: ='Table A19'!U46-'Table A21'!U46 -> 943.8941

Sheet Table A21
L2: Table A21 – The World Current Account: Discrepancies
M3: [1] | N3: [2] | O3: [3] | P3: [4] | Q3: [5] | R3: [6] | S3: [7] | T3: [8] | U3: [9] | V3: [10] | W3: [11] | X3: [12] | Y3: [13] | Z3: [14] | AA3: [15] | AB3: [16] | AC3: [17] | AD3: [18]
N4: Billions of current USD | V4: Memo: Portfolio & other income balance / debits | W4: Billions of 2008 USD
M5: Memo: number of countries used for estimation | N5: Current account | O5: Trade | P5: Income | U5: Current Transfers | W5: Cumulative current account balance | X5: Cumulative investment income balance (ex-FDI) | Y5: Cumulative C.A. minus non-DI inv income balance | Z5: Cumulative trade | AA5: Cumulateive FDI income | AB5: Cumulative trade + FDI income | AC5: Cumulative transfers + employee income | AD5: U.S. CPI-U (annual average)
Q6: Compensation of employees | R6: Investment income
S7: FDI income | T7: Portfolio and other income
L8: 1970 | M8: 14 | N8: 2.4126398 | O8: 0.3445089 | P8: 5.6149883 | Q8: 0.36207013 | R8: 5.2529185 | S8: 8.1139128 | T8: =R8-S8 -> -2.8609943 | U8: =N8-O8-P8 -> -3.5468574 | AD8: 38.8
L9: =L8+1 -> 1971 | M9: 20 | N9: 0.62123575 | O9: 2.5751309 | P9: 4.9126059 | Q9: 0.14082795 | R9: 4.7717785 | S9: 6.3092801 | T9: =R9-S9 -> -1.5375016 | U9: =N9-O9-P9 -> -6.8665011 | AD9: 40.5
L10: =L9+1 -> 1972 | M10: 23 | N10: -0.83427636 | O10: 1.0661059 | P10: 5.9119252 | Q10: 0.17956505 | R10: 5.7323595 | S10: 7.7857475 | T10: =R10-S10 -> -2.0533879 | U10: =N10-O10-P10 -> -7.8123075 | AD10: 41.8
L11: =L10+1 -> 1973 | M11: 23 | N11: 11.181555 | O11: 12.094018 | P11: 8.4966202 | Q11: -0.18150002 | R11: 8.6781173 | S11: 11.903126 | T11: =R11-S11 -> -3.2250084 | U11: =N11-O11-P11 -> -9.409083 | AD11: 44.4
L12: =L11+1 -> 1974 | M12: 37 | N12: 10.017001 | O12: 13.730894 | P12: 8.9314641 | Q12: -0.44591926 | R12: 9.3773847 | S12: 12.143801 | T12: =R12-S12 -> -2.766416 | U12: =N12-O12-P12 -> -12.645357 | AD12: 49.3
L13: =L12+1 -> 1975 | M13: 62 | N13: 5.3043715 | O13: 15.30723 | P13: 1.9573139 | Q13: =P13-R13 -> -0.32541566 | R13: 2.2827296 | S13: 6.8844323 | T13: =R13-S13 -> -4.6017027 | U13: =N13-O13-P13 -> -11.960172 | V13: =T13/'Table A20'!T13 -> -0.083468789 | W13: =SUM($N$13:N13)/(AD13/AD$46) -> 21.227641 | X13: =SUM($T$13:T13)/(AD13/$AD$46) -> -18.415621 | Y13: =(SUM($N$13:N13)-SUM($T$13:T13))/(AD13/$AD$46) -> 39.643262 | Z13: =SUM($O$13:O13)/(AD13/$AD$46) -> 61.258225 | AA13: =SUM($S$13:S13)/(AD13/$AD$46) -> 27.550909 | AB13: =Z13+AA13 -> 88.809135 | AC13: =(SUM($Q$13:Q13)+SUM($U$13:U13))/(AD13/$AD$46) -> -49.165873 | AD13: 53.8
L14: =L13+1 -> 1976 | M14: 89 | N14: -8.9973614 | O14: -2.3678855 | P14: 1.1282519 | Q14: =P14-R14 -> -0.44633982 | R14: 1.5745917 | S14: 6.9470363 | T14: =R14-S14 -> -5.3724446 | U14: =N14-O14-P14 -> -7.7577278 | V14: =T14/'Table A20'!T14 -> -0.089965229 | W14: =SUM($N$13:N14)/(AD14/AD$46) -> -13.973846 | X14: =SUM($T$13:T14)/(AD14/$AD$46) -> -37.741016 | Y14: =(SUM($N$13:N14)-SUM($T$13:T14))/(AD14/$AD$46) -> 23.767171 | Z14: =SUM($O$13:O14)/(AD14/$AD$46) -> 48.960978 | AA14: =SUM($S$13:S14)/(AD14/$AD$46) -> 52.336673 | AB14: =Z14+AA14 -> 101.29765 | AC14: =(SUM($Q$13:Q14)+SUM($U$13:U14))/(AD14/$AD$46) -> -77.530481 | AD14: 56.9
L15: =L14+1 -> 1977 | M15: 118 | N15: -23.250558 | O15: -11.932351 | P15: -4.5868503 | Q15: =P15-R15 -> -0.39858771 | R15: -4.1882626 | S15: -0.75654938 | T15: =R15-S15 -> -3.4317132 | U15: =N15-O15-P15 -> -6.7313573 | V15: =T15/'Table A20'!T15 -> -0.045423439 | W15: =SUM($N$13:N15)/(AD15/AD$46) -> -95.726514 | X15: =SUM($T$13:T15)/(AD15/$AD$46) -> -47.629076 | Y15: =(SUM($N$13:N15)-SUM($T$13:T15))/(AD15/$AD$46) -> -48.097438 | Z15: =SUM($O$13:O15)/(AD15/$AD$46) -> 3.5777031 | AA15: =SUM($S$13:S15)/(AD15/$AD$46) -> 46.453289 | AB15: =Z15+AA15 -> 50.030992 | AC15: =(SUM($Q$13:Q15)+SUM($U$13:U15))/(AD15/$AD$46) -> -98.12843 | AD15: 60.6
L16: =L15+1 -> 1978 | M16: 124 | N16: -25.322395 | O16: -12.441852 | P16: -2.8903696 | Q16: =P16-R16 -> 0.27633698 | R16: -3.1667066 | S16: 1.6415736 | T16: =R16-S16 -> -4.8082801 | U16: =N16-O16-P16 -> -9.9901739 | V16: =T16/'Table A20'!T16 -> -0.045546272 | W16: =SUM($N$13:N16)/(AD16/AD$46) -> -172.59225 | X16: =SUM($T$13:T16)/(AD16/$AD$46) -> -60.146612 | Y16: =(SUM($N$13:N16)-SUM($T$13:T16))/(AD16/$AD$46) -> -112.44563 | Z16: =SUM($O$13:O16)/(AD16/$AD$46) -> -37.760111 | AA16: =SUM($S$13:S16)/(AD16/$AD$46) -> 48.596703 | AB16: =Z16+AA16 -> 10.836592 | AC16: =(SUM($Q$13:Q16)+SUM($U$13:U16))/(AD16/$AD$46) -> -123.28223 | AD16: 65.2
L17: =L16+1 -> 1979 | M17: 129 | N17: -30.639624 | O17: -26.570926 | P17: 4.0460346 | Q17: =P17-R17 -> 1.5364064 | R17: 2.5096282 | S17: 15.021435 | T17: =R17-S17 -> -12.511807 | U17: =N17-O17-P17 -> -8.1147325 | V17: =T17/'Table A20'!T17 -> -0.07551243 | W17: =SUM($N$13:N17)/(AD17/AD$46) -> -245.86525 | X17: =SUM($T$13:T17)/(AD17/$AD$46) -> -91.121056 | Y17: =(SUM($N$13:N17)-SUM($T$13:T17))/(AD17/$AD$46) -> -154.7442 | Z17: =SUM($O$13:O17)/(AD17/$AD$46) -> -112.71018 | AA17: =SUM($S$13:S17)/(AD17/$AD$46) -> 88.190979 | AB17: =Z17+AA17 -> -24.519205 | AC17: =(SUM($Q$13:Q17)+SUM($U$13:U17))/(AD17/$AD$46) -> -130.22499 | AD17: 72.6
L18: =L17+1 -> 1980 | M18: 135 | N18: -58.429491 | O18: -37.342594 | P18: -13.169918 | Q18: =P18-R18 -> 0.69392313 | R18: -13.863841 | S18: 3.3926813 | T18: =R18-S18 -> -17.256523 | U18: =N18-O18-P18 -> -7.9169791 | V18: =T18/'Table A20'!T18 -> -0.07089679 | W18: =SUM($N$13:N18)/(AD18/AD$46) -> -369.29444 | X18: =SUM($T$13:T18)/(AD18/$AD$46) -> -125.37342 | Y18: =(SUM($N$13:N18)-SUM($T$13:T18))/(AD18/$AD$46) -> -243.92102 | Z18: =SUM($O$13:O18)/(AD18/$AD$46) -> -196.87781 | AA18: =SUM($S$13:S18)/(AD18/$AD$46) -> 86.566984 | AB18: =Z18+AA18 -> -110.31083 | AC18: =(SUM($Q$13:Q18)+SUM($U$13:U18))/(AD18/$AD$46) -> -133.61019 | AD18: 82.4
L19: =L18+1 -> 1981 | M19: 138 | N19: -76.505287 | O19: -35.566912 | P19: -32.132067 | Q19: =P19-R19 -> -1.4461074 | R19: -30.685959 | S19: -4.9094938 | T19: =R19-S19 -> -25.776466 | U19: =N19-O19-P19 -> -8.806308 | V19: =T19/'Table A20'!T19 -> -0.07811617 | W19: =SUM($N$13:N19)/(AD19/AD$46) -> -515.97007 | X19: =SUM($T$13:T19)/(AD19/$AD$46) -> -174.70319 | Y19: =(SUM($N$13:N19)-SUM($T$13:T19))/(AD19/$AD$46) -> -341.26688 | Z19: =SUM($O$13:O19)/(AD19/$AD$46) -> -262.71061 | AA19: =SUM($S$13:S19)/(AD19/$AD$46) -> 66.843683 | AB19: =Z19+AA19 -> -195.86693 | AC19: =(SUM($Q$13:Q19)+SUM($U$13:U19))/(AD19/$AD$46) -> -145.39995 | AD19: 90.9
L20: =L19+1 -> 1982 | M20: 142 | N20: -88.423736 | O20: -37.529357 | P20: -38.682756 | Q20: =P20-R20 -> -2.0103435 | R20: -36.672413 | S20: -0.033047249 | T20: =R20-S20 -> -36.639366 | U20: =N20-O20-P20 -> -12.211622 | V20: =T20/'Table A20'!T20 -> -0.10367373 | W20: =SUM($N$13:N20)/(AD20/AD$46) -> -683.31166 | X20: =SUM($T$13:T20)/(AD20/$AD$46) -> -246.31177 | Y20: =(SUM($N$13:N20)-SUM($T$13:T20))/(AD20/$AD$46) -> -436.9999 | Z20: =SUM($O$13:O20)/(AD20/$AD$46) -> -331.1977 | AA20: =SUM($S$13:S20)/(AD20/$AD$46) -> 62.890939 | AB20: =Z20+AA20 -> -268.30676 | AC20: =(SUM($Q$13:Q20)+SUM($U$13:U20))/(AD20/$AD$46) -> -168.69314 | AD20: 96.5
L21: =L20+1 -> 1983 | M21: 142 | N21: -76.076535 | O21: -37.60939 | P21: -29.136905 | Q21: =P21-R21 -> -1.1769745 | R21: -27.95993 | S21: 5.0410695 | T21: =R21-S21 -> -33.001 | U21: =N21-O21-P21 -> -9.3302403 | V21: =T21/'Table A20'!T21 -> -0.10877831 | W21: =SUM($N$13:N21)/(AD21/AD$46) -> -826.4968 | X21: =SUM($T$13:T21)/(AD21/$AD$46) -> -309.98293 | Y21: =(SUM($N$13:N21)-SUM($T$13:T21))/(AD21/$AD$46) -> -516.51387 | Z21: =SUM($O$13:O21)/(AD21/$AD$46) -> -402.18868 | AA21: =SUM($S$13:S21)/(AD21/$AD$46) -> 71.830652 | AB21: =Z21+AA21 -> -330.35802 | AC21: =(SUM($Q$13:Q21)+SUM($U$13:U21))/(AD21/$AD$46) -> -186.15585 | AD21: 99.6
L22: =L21+1 -> 1984 | M22: 144 | N22: -83.177399 | O22: -38.773358 | P22: -35.371267 | Q22: =P22-R22 -> -1.9935475 | R22: -33.377719 | S22: 7.4218194 | T22: =R22-S22 -> -40.799539 | U22: =N22-O22-P22 -> -9.032774 | V22: =T22/'Table A20'!T22 -> -0.12028925 | W22: =SUM($N$13:N22)/(AD22/AD$46) -> -964.65279 | X22: =SUM($T$13:T22)/(AD22/$AD$46) -> -381.69935 | Y22: =(SUM($N$13:N22)-SUM($T$13:T22))/(AD22/$AD$46) -> -582.95344 | Z22: =SUM($O$13:O22)/(AD22/$AD$46) -> -465.8904 | AA22: =SUM($S$13:S22)/(AD22/$AD$46) -> 84.237468 | AB22: =Z22+AA22 -> -381.65293 | AC22: =(SUM($Q$13:Q22)+SUM($U$13:U22))/(AD22/$AD$46) -> -201.30051 | AD22: 103.9
L23: =L22+1 -> 1985 | M23: 146 | N23: -87.128292 | O23: -31.639557 | P23: -47.015864 | Q23: =P23-R23 -> -3.2075803 | R23: -43.808284 | S23: 3.9848661 | T23: =R23-S23 -> -47.79315 | U23: =N23-O23-P23 -> -8.472871 | V23: =T23/'Table A20'!T23 -> -0.14036856 | W23: =SUM($N$13:N23)/(AD23/AD$46) -> -1105.8216 | X23: =SUM($T$13:T23)/(AD23/$AD$46) -> -464.20605 | Y23: =(SUM($N$13:N23)-SUM($T$13:T23))/(AD23/$AD$46) -> -641.61558 | Z23: =SUM($O$13:O23)/(AD23/$AD$46) -> -513.17941 | AA23: =SUM($S$13:S23)/(AD23/$AD$46) -> 89.314373 | AB23: =Z23+AA23 -> -423.86503 | AC23: =(SUM($Q$13:Q23)+SUM($U$13:U23))/(AD23/$AD$46) -> -217.75055 | AD23: 107.6
L24: =L23+1 -> 1986 | M24: 148 | N24: -77.956102 | O24: -20.946701 | P24: -44.430725 | Q24: =P24-R24 -> -3.5213934 | R24: -40.909331 | S24: 13.536737 | T24: =R24-S24 -> -54.446069 | U24: =N24-O24-P24 -> -12.578676 | V24: =T24/'Table A20'!T24 -> -0.14763707 | W24: =SUM($N$13:N24)/(AD24/AD$46) -> -1238.7828 | X24: =SUM($T$13:T24)/(AD24/$AD$46) -> -562.69136 | Y24: =(SUM($N$13:N24)-SUM($T$13:T24))/(AD24/$AD$46) -> -676.0914 | Z24: =SUM($O$13:O24)/(AD24/$AD$46) -> -544.96343 | AA24: =SUM($S$13:S24)/(AD24/$AD$46) -> 114.2767 | AB24: =Z24+AA24 -> -430.68672 | AC24: =(SUM($Q$13:Q24)+SUM($U$13:U24))/(AD24/$AD$46) -> -245.40467 | AD24: 109.6
... L31: =L30+1 -> 1993 | M31: 156 | N31: -75.150768 | O31: 33.174297 | P31: -63.46153 | Q31: =P31-R31 -> -8.2535907 | R31: -55.207939 | S31: 48.152726 | T31: =R31-S31 -> -103.36067 | U31: =N31-O31-P31 -> -44.863535 | V31: =T31/'Table A20'!T31 -> -0.1215459 | W31: =SUM($N$13:N31)/(AD31/AD$46) -> -1899.9203 | X31: =SUM($T$13:T31)/(AD31/$AD$46) -> -1401.2341 | Y31: =(SUM($N$13:N31)-SUM($T$13:T31))/(AD31/$AD$46) -> -498.68627 | Z31: =SUM($O$13:O31)/(AD31/$AD$46) -> -492.04403 | AA31: =SUM($S$13:S31)/(AD31/$AD$46) -> 516.66338 | AB31: =Z31+AA31 -> 24.619353 | AC31: =(SUM($Q$13:Q31)+SUM($U$13:U31))/(AD31/$AD$46) -> -523.30562 | AD31: 144.5
L32: =L31+1 -> 1994 | M32: All | N32: -58.4918 | O32: 74.6448 | P32: -79.2249 | Q32: -7.87857 | R32: -71.34606 | S32: 49.24594 | T32: -120.592 | U32: -53.9118 | V32: =T32/'Table A20'!T32 -> -0.14436675 | W32: =SUM($N$13:N32)/(AD32/AD$46) -> -1937.4625 | X32: =SUM($T$13:T32)/(AD32/$AD$46) -> -1541.445 | Y32: =(SUM($N$13:N32)-SUM($T$13:T32))/(AD32/$AD$46) -> -396.01759 | Z32: =SUM($O$13:O32)/(AD32/$AD$46) -> -371.31655 | AA32: =SUM($S$13:S32)/(AD32/$AD$46) -> 575.30808 | AB32: =Z32+AA32 -> 203.99153 | AC32: =(SUM($Q$13:Q32)+SUM($U$13:U32))/(AD32/$AD$46) -> -600.00887 | AD32: 148.2
L33: =L32+1 -> 1995 | M33: All | N33: -55.4846 | O33: 83.7413 | P33: -86.7527 | Q33: -7.47316 | R33: -79.2791 | S33: 38.7859 | T33: -118.065 | U33: -52.4735 | V33: =T33/'Table A20'!T33 -> -0.12206507 | W33: =SUM($N$13:N33)/(AD33/AD$46) -> -1962.4537 | X33: =SUM($T$13:T33)/(AD33/$AD$46) -> -1665.7604 | Y33: =(SUM($N$13:N33)-SUM($T$13:T33))/(AD33/$AD$46) -> -296.6933 | Z33: =SUM($O$13:O33)/(AD33/$AD$46) -> -242.77795 | AA33: =SUM($S$13:S33)/(AD33/$AD$46) -> 614.24789 | AB33: =Z33+AA33 -> 371.46994 | AC33: =(SUM($Q$13:Q33)+SUM($U$13:U33))/(AD33/$AD$46) -> -668.1628 | AD33: 152.4
L34: =L33+1 -> 1996 | M34: All | N34: -37.5873 | O34: 85.2547 | P34: -89.5362 | Q34: -8.04871 | R34: -81.4871 | S34: 50.8689 | T34: -132.356 | U34: -33.3062 | V34: =T34/'Table A20'!T34 -> -0.14600466 | W34: =SUM($N$13:N34)/(AD34/AD$46) -> -1957.7477 | X34: =SUM($T$13:T34)/(AD34/$AD$46) -> -1799.6083 | Y34: =(SUM($N$13:N34)-SUM($T$13:T34))/(AD34/$AD$46) -> -158.13941 | Z34: =SUM($O$13:O34)/(AD34/$AD$46) -> -118.8258 | AA34: =SUM($S$13:S34)/(AD34/$AD$46) -> 666.4347 | AB34: =Z34+AA34 -> 547.60891 | AC34: =(SUM($Q$13:Q34)+SUM($U$13:U34))/(AD34/$AD$46) -> -705.7479 | AD34: 156.9
L35: =L34+1 -> 1997 | M35: All | N35: 9.28227 | O35: 110.32611 | P35: -71.4632 | Q35: 1.16003 | R35: -72.622812 | S35: 55.414188 | T35: -128.037 | U35: -29.5802 | V35: =T35/'Table A20'!T35 -> -0.1389598 | W35: =SUM($N$13:N35)/(AD35/AD$46) -> -1901.3838 | X35: =SUM($T$13:T35)/(AD35/$AD$46) -> -1930.9987 | Y35: =(SUM($N$13:N35)-SUM($T$13:T35))/(AD35/$AD$46) -> 29.614815 | Z35: =SUM($O$13:O35)/(AD35/$AD$46) -> 31.836606 | AA35: =SUM($S$13:S35)/(AD35/$AD$46) -> 725.82209 | AB35: =Z35+AA35 -> 757.6587 | AC35: =(SUM($Q$13:Q35)+SUM($U$13:U35))/(AD35/$AD$46) -> -728.04233 | AD35: 160.5
L36: =L35+1 -> 1998 | M36: All | N36: -68.2808 | O36: 63.56326 | P36: -98.3916 | Q36: -0.440519 | R36: -97.95076 | S36: 33.86524 | T36: -131.816 | U36: -33.4525 | V36: =T36/'Table A20'!T36 -> -0.12956825 | W36: =SUM($N$13:N36)/(AD36/AD$46) -> -1962.4121 | X36: =SUM($T$13:T36)/(AD36/$AD$46) -> -2075.4949 | Y36: =(SUM($N$13:N36)-SUM($T$13:T36))/(AD36/$AD$46) -> 113.0828 | Z36: =SUM($O$13:O36)/(AD36/$AD$46) -> 115.30758 | AA36: =SUM($S$13:S36)/(AD36/$AD$46) -> 759.42168 | AB36: =Z36+AA36 -> 874.72926 | AC36: =(SUM($Q$13:Q36)+SUM($U$13:U36))/(AD36/$AD$46) -> -761.64456 | AD36: 163
L37: =L36+1 -> 1999 | M37: All | N37: -101.744 | O37: 16.56524 | P37: -91.5556 | Q37: -6.03256 | R37: -85.5228 | S37: 42.4582 | T37: -127.981 | U37: -26.7531 | V37: =T37/'Table A20'!T37 -> -0.1273216 | W37: =SUM($N$13:N37)/(AD37/AD$46) -> -2051.4943 | X37: =SUM($T$13:T37)/(AD37/$AD$46) -> -2196.0406 | Y37: =(SUM($N$13:N37)-SUM($T$13:T37))/(AD37/$AD$46) -> 144.54623 | Z37: =SUM($O$13:O37)/(AD37/$AD$46) -> 134.22378 | AA37: =SUM($S$13:S37)/(AD37/$AD$46) -> 797.88182 | AB37: =Z37+AA37 -> 932.1056 | AC37: =(SUM($Q$13:Q37)+SUM($U$13:U37))/(AD37/$AD$46) -> -787.5565 | AD37: 166.6
L38: =L37+1 -> 2000 | M38: All | N38: -149.766 | O38: -22.48435 | P38: -90.9215 | Q38: -6.42848 | R38: -84.4935 | S38: 28.2705 | T38: -112.764 | U38: -36.3601 | V38: =T38/'Table A20'!T38 -> -0.10136145 | W38: =SUM($N$13:N38)/(AD38/AD$46) -> -2172.0327 | X38: =SUM($T$13:T38)/(AD38/$AD$46) -> -2265.6143 | Y38: =(SUM($N$13:N38)-SUM($T$13:T38))/(AD38/$AD$46) -> 93.58165 | Z38: =SUM($O$13:O38)/(AD38/$AD$46) -> 101.74642 | AA38: =SUM($S$13:S38)/(AD38/$AD$46) -> 807.28127 | AB38: =Z38+AA38 -> 909.02769 | AC38: =(SUM($Q$13:Q38)+SUM($U$13:U38))/(AD38/$AD$46) -> -815.44381 | AD38: 172.2
L39: =L38+1 -> 2001 | M39: All | N39: -148.646 | O39: -43.7249 | P39: -73.5882 | Q39: -7.51179 | R39: -66.0762 | S39: 59.5428 | T39: -125.619 | U39: -31.3328 | V39: =T39/'Table A20'!T39 -> -0.11785064 | W39: =SUM($N$13:N39)/(AD39/AD$46) -> -2292.648 | X39: =SUM($T$13:T39)/(AD39/$AD$46) -> -2355.6462 | Y39: =(SUM($N$13:N39)-SUM($T$13:T39))/(AD39/$AD$46) -> 62.998182 | Z39: =SUM($O$13:O39)/(AD39/$AD$46) -> 45.774317 | AA39: =SUM($S$13:S39)/(AD39/$AD$46) -> 857.33246 | AB39: =Z39+AA39 -> 903.10678 | AC39: =(SUM($Q$13:Q39)+SUM($U$13:U39))/(AD39/$AD$46) -> -840.10604 | AD39: 177.1
L40: =L39+1 -> 2002 | M40: All | N40: -97.7934 | O40: 14.60795 | P40: -94.6782 | Q40: -7.83726 | R40: -86.8413 | S40: 37.2337 | T40: -124.075 | U40: -17.7231 | V40: =T40/'Table A20'!T40 -> -0.12820288 | W40: =SUM($N$13:N40)/(AD40/AD$46) -> -2374.0032 | X40: =SUM($T$13:T40)/(AD40/$AD$46) -> -2467.4745 | Y40: =(SUM($N$13:N40)-SUM($T$13:T40))/(AD40/$AD$46) -> 93.471291 | Z40: =SUM($O$13:O40)/(AD40/$AD$46) -> 62.544563 | AA40: =SUM($S$13:S40)/(AD40/$AD$46) -> 888.54978 | AB40: =Z40+AA40 -> 951.09435 | AC40: =(SUM($Q$13:Q40)+SUM($U$13:U40))/(AD40/$AD$46) -> -857.62091 | AD40: 179.9
L41: =L40+1 -> 2003 | M41: All | N41: -20.0445 | O41: 65.9951 | P41: -76.6408 | Q41: -7.84261 | R41: -68.7978 | S41: 49.4182 | T41: -118.216 | U41: -9.39875 | V41: =T41/'Table A20'!T41 -> -0.11454928 | W41: =SUM($N$13:N41)/(AD41/AD$46) -> -2344.5587 | X41: =SUM($T$13:T41)/(AD41/$AD$46) -> -2550.8202 | Y41: =(SUM($N$13:N41)-SUM($T$13:T41))/(AD41/$AD$46) -> 206.26143 | Z41: =SUM($O$13:O41)/(AD41/$AD$46) -> 138.37342 | AA41: =SUM($S$13:S41)/(AD41/$AD$46) -> 926.57605 | AB41: =Z41+AA41 -> 1064.9495 | AC41: =(SUM($Q$13:Q41)+SUM($U$13:U41))/(AD41/$AD$46) -> -858.68543 | AD41: 184
L42: =L41+1 -> 2004 | M42: All | N42: 54.9592 | O42: 89.4356 | P42: -16.2145 | Q42: -6.01523 | R42: -10.1996 | S42: 110.5554 | T42: -120.755 | U42: -18.262 | V42: =T42/'Table A20'!T42 -> -0.10007749 | W42: =SUM($N$13:N42)/(AD42/AD$46) -> -2221.1007 | X42: =SUM($T$13:T42)/(AD42/$AD$46) -> -2622.286 | Y42: =(SUM($N$13:N42)-SUM($T$13:T42))/(AD42/$AD$46) -> 401.18527 | Z42: =SUM($O$13:O42)/(AD42/$AD$46) -> 236.72029 | AA42: =SUM($S$13:S42)/(AD42/$AD$46) -> 1028.549 | AB42: =Z42+AA42 -> 1265.2693 | AC42: =(SUM($Q$13:Q42)+SUM($U$13:U42))/(AD42/$AD$46) -> -864.08194 | AD42: 188.9
L43: =L42+1 -> 2005 | M43: All | N43: 103.407 | O43: 137.3142 | P43: -12.4085 | Q43: -8.05388 | R43: -4.3549 | S43: 123.4741 | T43: -127.829 | U43: -21.4986 | V43: =T43/'Table A20'!T43 -> -0.083579558 | W43: =SUM($N$13:N43)/(AD43/AD$46) -> -2034.3169 | X43: =SUM($T$13:T43)/(AD43/$AD$46) -> -2677.2749 | Y43: =(SUM($N$13:N43)-SUM($T$13:T43))/(AD43/$AD$46) -> 642.95803 | Z43: =SUM($O$13:O43)/(AD43/$AD$46) -> 380.34113 | AA43: =SUM($S$13:S43)/(AD43/$AD$46) -> 1130.9639 | AB43: =Z43+AA43 -> 1511.305 | AC43: =(SUM($Q$13:Q43)+SUM($U$13:U43))/(AD43/$AD$46) -> -868.3452 | AD43: 195.3
... L46: =L45+1 -> 2008 | M46: All | N46: 298.123 | O46: 366.34 | P46: -99.3193 | Q46: -16.1879 | R46: -83.132 | S46: 72.677 | T46: -155.809 | U46: 31.1019 | V46: =T46/'Table A20'!T46 -> -0.055927727 | W46: =SUM($N$13:N46)/(AD46/AD$46) -> -890.3301 | X46: =SUM($T$13:T46)/(AD46/$AD$46) -> -2810.6923 | Y46: =(SUM($N$13:N46)-SUM($T$13:T46))/(AD46/$AD$46) -> 1920.3622 | Z46: =SUM($O$13:O46)/(AD46/$AD$46) -> 1376.922 | AA46: =SUM($S$13:S46)/(AD46/$AD$46) -> 1300.2669 | AB46: =Z46+AA46 -> 2677.189 | AC46: =(SUM($Q$13:Q46)+SUM($U$13:U46))/(AD46/$AD$46) -> -756.82465 | AD46: 215.303

Sheet Table A22
L2: Table A22 – Yield on Global Cross-Border Bank Deposits and Portfolio Claims
M3: [1] | N3: [2] | O3: [3] | P3: [4] | Q3: [5] | R3: [6] | S3: [7] | T3: [8] | U3: [9] | V3: [10] | W3: [11]
M4: Billions of current USD
M5: Liabilities and debits | T5: Missing flows and stocks
M6: Memo: Cross-Border Bank Liabilities | N6: Cross-Border Bank Accounts | O6: Cross Border Portfolios | P6: Memo: EWNII debt + equity | Q6: Deposits & portfolio, stocks | R6: Deposits & portfolio, income | S6: Yield | T6: Missing deposits & portfolio income | W6: Memo: Capitalized missing wealth
U7: Missing portfolio wealth | V7: Yield
L8: 1970 | M8: 2.4126398 | O8: 0.3445089 | Q8: 5.6149883
L9: =L8+1 -> 1971 | M9: 0.62123575 | O9: 2.5751309 | Q9: 4.9126059
L10: =L9+1 -> 1972 | M10: -0.83427636 | O10: 1.0661059 | Q10: 5.9119252
L11: =L10+1 -> 1973 | M11: 11.181555 | O11: 12.094018 | Q11: 8.4966202
L12: =L11+1 -> 1974 | M12: 10.017001 | O12: 13.730894 | Q12: 8.9314641
L13: =L12+1 -> 1975 | P13: 1055.381 | Q13: =Q14*P13/P14 -> 1038.3581 | R13: ='Table A20'!T13 -> 55.130818 | S13: =R13/Q13 -> 0.053094224 | T13: ='Table A21'!T13 -> -4.6017027 | W13: =-T13/S13 -> 86.670495
L14: =L13+1 -> 1976 | P14: 1288.65 | Q14: =Q15*P14/P15 -> 1267.8646 | R14: ='Table A20'!T14 -> 59.716901 | S14: =R14/Q14 -> 0.047100378 | T14: ='Table A21'!T14 -> -5.3724446 | W14: =-T14/S14 -> 114.06373
L15: =L14+1 -> 1977 | M15: 671.534 | N15: =N16*M15/M16 -> 640.32978 | P15: 1576.044 | Q15: =Q16*P15/P16 -> 1550.623 | R15: ='Table A20'!T15 -> 75.549392 | S15: =R15/Q15 -> 0.048721959 | T15: ='Table A21'!T15 -> -3.4317132 | W15: =-T15/S15 -> 70.434631
L16: =L15+1 -> 1978 | M16: 856.903 | N16: =N17*M16/M17 -> 817.08522 | P16: 1977.934 | Q16: =Q17*P16/P17 -> 1946.0307 | R16: ='Table A20'!T16 -> 105.56913 | S16: =R16/Q16 -> 0.054248438 | T16: ='Table A21'!T16 -> -4.8082801 | W16: =-T16/S16 -> 88.634444
L17: =L16+1 -> 1979 | M17: 1119.763 | N17: =N18*M17/M18 -> 1067.7309 | P17: 2410.884 | Q17: =Q18*P17/P18 -> 2371.9974 | R17: ='Table A20'!T17 -> 165.69202 | S17: =R17/Q17 -> 0.069853372 | T17: ='Table A21'!T17 -> -12.511807 | W17: =-T17/S17 -> 179.11529
L18: =L17+1 -> 1980 | M18: 1334.859 | N18: =N19*M18/M19 -> 1272.832 | P18: 2862.22 | Q18: =Q19*P18/P19 -> 2816.0535 | R18: ='Table A20'!T18 -> 243.40344 | S18: =R18/Q18 -> 0.086434238 | T18: ='Table A21'!T18 -> -17.256523 | W18: =-T18/S18 -> 199.64916
L19: =L18+1 -> 1981 | M19: 1531.963 | N19: =N20*M19/M20 -> 1460.7772 | P19: 3257.877 | Q19: =Q20*P19/P20 -> 3205.3287 | R19: ='Table A20'!T19 -> 329.97606 | S19: =R19/Q19 -> 0.10294609 | T19: ='Table A21'!T19 -> -25.776466 | W19: =-T19/S19 -> 250.388
L20: =L19+1 -> 1982 | M20: 1627.393 | N20: =N21*M20/M21 -> 1551.7728 | P20: 3548.793 | Q20: =Q21*P20/P21 -> 3491.5524 | R20: ='Table A20'!T20 -> 353.41031 | S20: =R20/Q20 -> 0.10121868 | T20: ='Table A21'!T20 -> -36.639366 | W20: =-T20/S20 -> 361.98226
L21: =L20+1 -> 1983 | M21: 2038.161 | N21: =N22*M21/M22 -> 1943.4536 | P21: 3841.708 | Q21: =Q22*P21/P22 -> 3779.7428 | R21: ='Table A20'!T21 -> 303.3785 | S21: =R21/Q21 -> 0.080264323 | T21: ='Table A21'!T21 -> -33.001 | W21: =-T21/S21 -> 411.15402
L22: =L21+1 -> 1984 | M22: 2124.932 | N22: =N23*M22/M23 -> 2026.1926 | P22: 4044.502 | Q22: =Q23*P22/P23 -> 3979.2658 | R22: ='Table A20'!T22 -> 339.1786 | S22: =R22/Q22 -> 0.085236479 | T22: ='Table A21'!T22 -> -40.799539 | W22: =-T22/S22 -> 478.66288
L23: =L22+1 -> 1985 | M23: 2536.403 | N23: =N24*M23/M24 -> 2418.5438 | P23: 4803.509 | Q23: =Q24*P23/P24 -> 4726.0303 | R23: ='Table A20'!T23 -> 340.4833 | S23: =R23/Q23 -> 0.072044247 | T23: ='Table A21'!T23 -> -47.79315 | W23: =-T23/S23 -> 663.38606
L24: =L23+1 -> 1986 | M24: 3233.994 | N24: =N25*M24/M25 -> 3083.7198 | P24: 6024.131 | Q24: =Q25*P24/P25 -> 5926.9641 | R24: ='Table A20'!T24 -> 368.78318 | S24: =R24/Q24 -> 0.062221261 | T24: ='Table A21'!T24 -> -54.446069 | W24: =-T24/S24 -> 875.03962
L25: =L24+1 -> 1987 | M25: 4232.103 | N25: =N26*M25/M26 -> 4035.4496 | P25: 7452.076 | Q25: =Q26*P25/P26 -> 7331.8769 | R25: ='Table A20'!T25 -> 429.12316 | S25: =R25/Q25 -> 0.058528418 | T25: ='Table A21'!T25 -> -69.692318 | W25: =-T25/S25 -> 1190.7432
L26: =L25+1 -> 1988 | M26: 4623.436 | N26: =N27*M26/M27 -> 4408.5985 | P26: 8196.904 | Q26: =Q27*P26/P27 -> 8064.6912 | R26: ='Table A20'!T26 -> 528.43418 | S26: =R26/Q26 -> 0.065524417 | T26: ='Table A21'!T26 -> -75.104586 | W26: =-T26/S26 -> 1146.2076
... L32: =L31+1 -> 1994 | M32: 7150.433 | N32: =N33*M32/M33 -> 6818.1733 | P32: 15545.414 | Q32: =Q33*P32/P33 -> 15294.673 | R32: ='Table A20'!T32 -> 835.317 | S32: =R32/Q32 -> 0.054614899 | T32: ='Table A21'!T32 -> -120.592 | W32: =-T32/S32 -> 2208.0422
L33: =L32+1 -> 1995 | M33: 7831.33 | N33: 7467.431 | P33: 17807.912 | Q33: =Q34*P33/P34 -> 17520.677 | R33: ='Table A20'!T33 -> 967.23 | S33: =R33/Q33 -> 0.055205057 | T33: ='Table A21'!T33 -> -118.065 | W33: =-T33/S33 -> 2138.6628
L34: =L33+1 -> 1996 | M34: 8100.069 | N34: 7673.182 | P34: 19391.369 | Q34: =Q35*P34/P35 -> 19078.594 | R34: ='Table A20'!T34 -> 906.519 | S34: =R34/Q34 -> 0.04751498 | T34: ='Table A21'!T34 -> -132.356 | W34: =-T34/S34 -> 2785.5636
L35: =L34+1 -> 1997 | M35: 9117.98 | N35: 8453.866 | P35: 21239.597 | Q35: =Q36*P35/P36 -> 20897.011 | R35: ='Table A20'!T35 -> 921.396 | S35: =R35/Q35 -> 0.04409224 | T35: ='Table A21'!T35 -> -128.037 | W35: =-T35/S35 -> 2903.8443
L36: =L35+1 -> 1998 | M36: 9695.323 | N36: 8942.734 | P36: 24053.639 | Q36: =Q37*P36/P37 -> 23665.663 | R36: ='Table A20'!T36 -> 1017.348 | S36: =R36/Q36 -> 0.042988358 | T36: ='Table A21'!T36 -> -131.816 | W36: =-T36/S36 -> 3066.3186
L37: =L36+1 -> 1999 | M37: 9611.207 | N37: 8835.568 | P37: 26663.87 | Q37: =Q38*P37/P38 -> 26233.792 | R37: ='Table A20'!T37 -> 1005.179 | S37: =R37/Q37 -> 0.038316191 | T37: ='Table A21'!T37 -> -127.981 | W37: =-T37/S37 -> 3340.1284
L38: =L37+1 -> 2000 | M38: 10420.68 | N38: 9454.574 | P38: 27474.536 | Q38: =Q39*P38/P39 -> 27031.383 | R38: ='Table A20'!T38 -> 1112.494 | S38: =R38/Q38 -> 0.041155646 | T38: ='Table A21'!T38 -> -112.764 | W38: =-T38/S38 -> 2739.94
L39: =L38+1 -> 2001 | M39: 11187.486 | N39: 10020.57 | O39: ='Table A3'!D10 -> 16272.541 | P39: 27910.208 | Q39: =O39+M39 -> 27460.027 | R39: ='Table A20'!T39 -> 1065.917 | S39: =R39/Q39 -> 0.038817041 | T39: ='Table A21'!T39 -> -125.619 | U39: ='Table A3'!E10 -> 2531.9709 | V39: =-T39/U39 -> 0.04961313 | W39: =-T39/S39 -> 3236.1818
L40: =L39+1 -> 2002 | M40: 12802.834 | N40: 11388.513 | O40: ='Table A3'!D11 -> 17754.004 | P40: 31092.233 | Q40: =O40+M40 -> 30556.838 | R40: ='Table A20'!T40 -> 967.802 | S40: =R40/Q40 -> 0.031672191 | T40: ='Table A21'!T40 -> -124.075 | U40: ='Table A3'!E11 -> 2392.014 | V40: =-T40/U40 -> 0.051870517 | W40: =-T40/S40 -> 3917.4745
L41: =L40+1 -> 2003 | M41: 15464.34 | N41: 13488.304 | O41: ='Table A3'!D12 -> 23637.533 | P41: 38552.547 | Q41: =O41+M41 -> 39101.873 | R41: ='Table A20'!T41 -> 1032.01 | S41: =R41/Q41 -> 0.026392853 | T41: ='Table A21'!T41 -> -118.216 | U41: ='Table A3'!E12 -> 2857.6815 | V41: =-T41/U41 -> 0.041367801 | W41: =-T41/S41 -> 4479.0913
L42: =L41+1 -> 2004 | M42: 18243.925 | N42: 15855.659 | O42: ='Table A3'!D13 -> 28950.123 | P42: 46573.294 | Q42: =O42+M42 -> 47194.048 | R42: ='Table A20'!T42 -> 1206.615 | S42: =R42/Q42 -> 0.025567101 | T42: ='Table A21'!T42 -> -120.755 | U42: ='Table A3'!E13 -> 3316.0255 | V42: =-T42/U42 -> 0.036415582 | W42: =-T42/S42 -> 4723.0618
L43: =L42+1 -> 2005 | M43: 20052.006 | N43: 17222.544 | O43: ='Table A3'!D14 -> 32398.632 | P43: 50699.404 | Q43: =O43+M43 -> 52450.638 | R43: ='Table A20'!T43 -> 1529.429 | S43: =R43/Q43 -> 0.029159398 | T43: ='Table A21'!T43 -> -127.829 | U43: ='Table A3'!E14 -> 3675.6375 | V43: =-T43/U43 -> 0.034777368 | W43: =-T43/S43 -> 4383.8011
L44: =L43+1 -> 2006 | M44: 24602.105 | N44: 21289.071 | O44: ='Table A3'!D15 -> 40731.592 | P44: 63057.153 | Q44: =O44+M44 -> 65333.697 | R44: ='Table A20'!T44 -> 2039.224 | S44: =R44/Q44 -> 0.031212438 | T44: ='Table A21'!T44 -> -120.674 | U44: ='Table A3'!E15 -> 3760.0032 | V44: =-T44/U44 -> 0.032094122 | W44: =-T44/S44 -> 3866.2151
L45: =L44+1 -> 2007 | M45: 31418.053 | N45: 27131.069 | O45: ='Table A3'!D16 -> 49301.442 | P45: 77301.468 | Q45: =O45+M45 -> 80719.495 | R45: ='Table A20'!T45 -> 2691.68 | S45: =R45/Q45 -> 0.033346096 | T45: ='Table A21'!T45 -> -105.67 | U45: ='Table A3'!E16 -> 5131.3254 | V45: =-T45/U45 -> 0.02059312 | W45: =-T45/S45 -> 3168.8867
L46: =L45+1 -> 2008 | M46: 29067.436 | N46: 24342.457 | O46: ='Table A3'!D17 -> 40097.279 | P46: n.a. | Q46: =O46+M46 -> 69164.715 | R46: ='Table A20'!T46 -> 2785.899 | S46: =R46/Q46 -> 0.040279194 | T46: ='Table A21'!T46 -> -155.809 | U46: ='Table A3'!E17 -> 4489.9776 | V46: =-T46/U46 -> 0.03470151 | W46: =-T46/S46 -> 3868.2253

Sheet Table A23
B2: Table A23: Securities in Custody in Swiss Banks, bn of USD
C4: [1] | D4: [2] | E4: [3] | F4: [4] | G4: [5] | H4: [6] | I4: [7] | J4: [8] | K4: [9] | L4: [10] | M4: [11] | N4: [12]
C5: All securities | D5: Swiss owned | E5: Foreign owned | K5: Asset allocation of Swiss offshore portfolio | N5: Swiss offshore portfolio / Global offshore portfolio
F6: Swiss securities | G6: Foreign securities (= offshore)
H7: Equities | I7: Mutual fund shares | J7: Bonds | K7: Equities | L7: Mutual fund shares | M7: Bonds
B8: 1998 | C8: 2139.0828 | D8: 987.02116 | E8: 1152.0617 | F8: =E8-G8 -> 361.33762 | G8: 790.72407 | H8: 310.84154 | I8: 161.36903 | J8: 479.88252 | K8: =H8/G8 -> 0.39311 | L8: =I8/G8 -> 0.20407756 | M8: =J8/G8 -> 0.60688999
B9: 1999 | C9: 2144.6431 | D9: 983.75228 | E9: 1160.8909 | F9: =E9-G9 -> 360.61992 | G9: 800.27094 | H9: 398.14405 | I9: 175.34816 | J9: 402.12689 | K9: =H9/G9 -> 0.49751157 | L9: =I9/G9 -> 0.21911099 | M9: =J9/G9 -> 0.50248843
B10: 2000 | C10: 2247.1467 | D10: 1015.0448 | E10: 1232.1018 | F10: =E10-G10 -> 438.50856 | G10: 793.59328 | H10: 404.61584 | I10: 184.06807 | J10: 388.97744 | K10: =H10/G10 -> 0.50985291 | L10: =I10/G10 -> 0.23194257 | M10: =J10/G10 -> 0.49014709
B11: 2001 | C11: 2011.7445 | D11: 883.48551 | E11: 1128.259 | F11: =E11-G11 -> 339.6182 | G11: 788.64081 | H11: 402.03678 | I11: 205.91459 | J11: 386.60404 | K11: =H11/G11 -> 0.5097844 | L11: =I11/G11 -> 0.2611006 | M11: =J11/G11 -> 0.49021561 | N11: =G11/'Table A3'!E10 -> 0.3114731
B12: 2002 | C12: 2114.001 | D12: 917.77202 | E12: 1196.229 | F12: =E12-G12 -> 337.61942 | G12: 858.60959 | H12: 392.27303 | I12: 224.2474 | J12: 466.33655 | K12: =H12/G12 -> 0.45687008 | L12: =I12/G12 -> 0.26117505 | M12: =J12/G12 -> 0.54312992 | N12: =G12/'Table A3'!E11 -> 0.3589484
B13: 2003 | C13: 2651.8934 | D13: 1134.298 | E13: 1517.5953 | F13: =E13-G13 -> 438.39612 | G13: 1079.1992 | H13: 548.7872 | I13: 305.95553 | J13: 530.41203 | K13: =H13/G13 -> 0.50851333 | L13: =I13/G13 -> 0.28350236 | M13: =J13/G13 -> 0.49148666 | N13: =G13/'Table A3'!E12 -> 0.37764853
B14: 2004 | C14: 3121.246 | D14: 1351.4172 | E14: 1769.8289 | F14: =E14-G14 -> 508.46244 | G14: 1261.3664 | H14: 683.87 | I14: 381.97446 | J14: 577.49644 | K14: =H14/G14 -> 0.54216601 | L14: =I14/G14 -> 0.30282593 | M14: =J14/G14 -> 0.457834 | N14: =G14/'Table A3'!E13 -> 0.38038502
B15: 2005 | C15: 3357.4509 | D15: 1377.9428 | E15: 1979.5081 | F15: =E15-G15 -> 608.61807 | G15: 1370.89 | H15: 892.48252 | I15: 606.11103 | J15: 478.4075 | K15: =H15/G15 -> 0.65102416 | L15: =I15/G15 -> 0.44212959 | M15: =J15/G15 -> 0.34897584 | N15: =G15/'Table A3'!E14 -> 0.3729666
B16: 2006 | C16: 4111.6385 | D16: 1705.4703 | E16: 2406.1682 | F16: =E16-G16 -> 772.36998 | G16: 1633.7982 | H16: 1148.8709 | I16: 782.21165 | J16: 484.92729 | K16: =H16/G16 -> 0.70319022 | L16: =I16/G16 -> 0.47876882 | M16: =J16/G16 -> 0.29680978 | N16: =G16/'Table A3'!E15 -> 0.43452044
B17: 2007 | C17: 4799.9392 | D17: 2017.4627 | E17: 2782.4765 | F17: =E17-G17 -> 790.2952 | G17: 1992.1813 | H17: 1465.2015 | I17: 1035.6303 | J17: 526.9798 | K17: =H17/G17 -> 0.73547599 | L17: =I17/G17 -> 0.51984743 | M17: =J17/G17 -> 0.26452401 | N17: =G17/'Table A3'!E16 -> 0.38823914
B18: 2008 | C18: 3772.0035 | D18: 1664.9621 | E18: 2107.0414 | F18: =E18-G18 -> 562.35421 | G18: 1544.6872 | H18: 1005.0196 | I18: 767.43369 | J18: 539.66757 | K18: =H18/G18 -> 0.65062987 | L18: =I18/G18 -> 0.49682142 | M18: =J18/G18 -> 0.34937013 | N18: =G18/'Table A3'!E17 -> 0.34403005
B19: 2009 | C19: 4374.7379 | D19: 1962.7702 | E19: 2411.9677 | F19: =E19-G19 -> 686.2627 | G19: 1725.705 | H19: 1102.0711 | I19: 754.82691 | J19: 623.63394 | K19: =H19/G19 -> 0.63862077 | L19: =I19/G19 -> 0.43740205 | M19: =J19/G19 -> 0.36137922
B20: 2010 | C20: 4825.5438 | D20: 2207.1286 | E20: 2618.4152 | F20: =E20-G20 -> 769.30318 | G20: 1849.112 | H20: 1221.4983 | I20: 823.03915 | J20: 627.61375 | K20: =H20/G20 -> 0.66058642 | L20: =I20/G20 -> 0.44509967 | M20: =J20/G20 -> 0.33941358

Sheet Table A24
A2: Table A24: Fiduciary Deposits in Swiss Banks, 1976-2008, mn of USD
B4: [1] | C4: [2] | D4: [3] | E4: [4] | F4: [5] | G4: [6] | H4: [7] | I4: [8] | J4: [9] | K4: [10] | L4: [11] | M4: [12] | N4: [13] | O4: [14]
B5: Tax havens | C5: Europe | D5: Middle East | E5: Latin and South America | F5: Asia | G5: Africa | H5: North America | I5: Caribbean | J5: Total ex-tax havens | K5: Total | L5: Rich countries | M5: Of which: Euro area 16 | N5: Developing countries | O5: Excl. Middle East | Q5: Memo: Japan
A6: 1976 | B6: 7536 | C6: 9190 | D6: 3440 | E6: 1266 | F6: 775 | G6: 1076 | H6: 695 | I6: 0 | J6: =SUM(C6:I6) -> 16442 | K6: =J6+B6 -> 23978 | L6: 9039 | M6: 7666 | N6: 7404 | O6: =N6-D6 -> 3964 | Q6: 29
A7: 1977 | B7: 9620 | C7: 11642 | D7: 3421 | E7: 1498 | F7: 954 | G7: 1337 | H7: 620 | I7: 0 | J7: =SUM(C7:I7) -> 19472 | K7: =J7+B7 -> 29092 | L7: 11259 | M7: 8970 | N7: 8213 | O7: =N7-D7 -> 4792 | Q7: 35
A8: 1978 | B8: 12004 | C8: 12487 | D8: 4931 | E8: 1843 | F8: 948 | G8: 1925 | H8: 817 | I8: 0 | J8: =SUM(C8:I8) -> 22951 | K8: =J8+B8 -> 34955 | L8: 12108 | M8: 10235 | N8: 10844 | O8: =N8-D8 -> 5913 | Q8: 47
A9: 1979 | B9: 15744 | C9: 19535 | D9: 7096 | E9: 2730 | F9: 1350 | G9: 2795 | H9: 1328 | I9: 0 | J9: =SUM(C9:I9) -> 34834 | K9: =J9+B9 -> 50578 | L9: 18915 | M9: 15666 | N9: 15918 | O9: =N9-D9 -> 8822 | Q9: 89
A10: 1980 | B10: 19219 | C10: 29102 | D10: 10121 | E10: 4055 | F10: 2043 | G10: 3484 | H10: 1808 | I10: 0 | J10: =SUM(C10:I10) -> 50613 | K10: =J10+B10 -> 69832 | L10: 28107 | M10: 22344 | N10: 22506 | O10: =N10-D10 -> 12385 | Q10: 160
A11: 1981 | B11: 22997 | C11: 39495 | D11: 11481 | E11: 6454 | F11: 2476 | G11: 3941 | H11: 2342 | I11: 0 | J11: =SUM(C11:I11) -> 66189 | K11: =J11+B11 -> 89186 | L11: 38335 | M11: 29529 | N11: 27854 | O11: =N11-D11 -> 16373 | Q11: 150
A12: 1982 | B12: 23622 | C12: 34564 | D12: 15066 | E12: 5790 | F12: 2725 | G12: 3912 | H12: 2337 | I12: 0 | J12: =SUM(C12:I12) -> 64394 | K12: =J12+B12 -> 88016 | L12: 33062 | M12: 25652 | N12: 31333 | O12: =N12-D12 -> 16267 | Q12: 168
A13: 1983 | B13: 26083 | C13: 31940 | D13: 16740 | E13: 5619 | F13: 3157 | G13: 3868 | H13: 2545 | I13: 0 | J13: =SUM(C13:I13) -> 63869 | K13: =J13+B13 -> 89952 | L13: 30183 | M13: 22525 | N13: 33685 | O13: =N13-D13 -> 16945 | Q13: 212
A14: 1984 | B14: 31287 | C14: 30573 | D14: 20519 | E14: 6290 | F14: 4408 | G14: 3156 | H14: 3221 | I14: 27 | J14: =SUM(C14:I14) -> 68194 | K14: =J14+B14 -> 99481 | L14: 34132 | M14: 24513 | N14: 34061 | O14: =N14-D14 -> 13542 | Q14: 248
A15: 1985 | B15: 36054 | C15: 34110 | D15: 22954 | E15: 6773 | F15: 5396 | G15: 3437 | H15: 3527 | I15: 23 | J15: =SUM(C15:I15) -> 76220 | K15: =J15+B15 -> 112274 | L15: 38048 | M15: 27244 | N15: 38173 | O15: =N15-D15 -> 15219 | Q15: 273
A16: 1986 | B16: 41891 | C16: 37954 | D16: 22495 | E16: 7698 | F16: 6088 | G16: 3756 | H16: 4169 | I16: 27 | J16: =SUM(C16:I16) -> 82187 | K16: =J16+B16 -> 124078 | L16: 42638 | M16: 30521 | N16: 39549 | O16: =N16-D16 -> 17054 | Q16: 327
A17: 1987 | B17: 54532 | C17: 49199 | D17: 26023 | E17: 9840 | F17: 7323 | G17: 4647 | H17: 5709 | I17: 31 | J17: =SUM(C17:I17) -> 102772 | K17: =J17+B17 -> 157304 | L17: 55549 | M17: 38484 | N17: 47224 | O17: =N17-D17 -> 21201 | Q17: 415
... A38: 2008 | B38: 293305 | C38: 74898 | D38: 37434 | E38: 21732 | F38: 29824 | G38: 8338 | H38: 11949 | I38: 203 | J38: =SUM(C38:I38) -> 184378 | K38: =J38+B38 -> 477683 | L38: 87146 | M38: 61707 | N38: 97231 | O38: =N38-D38 -> 59797 | Q38: 1545

Sheet Table A25
A2: Table A25: Distribution of Fiduciary Deposits in Swiss Banks by Country of Owner, 1976-2008, Uncorrected Shares (% of Total)
B4: [1] | C4: [2] | D4: [3] | E4: [4] | F4: [5] | G4: [6] | H4: [7] | I4: [8] | J4: [9] | K4: [10] | L4: [11] | M4: [12] | N4: [13] | O4: [14]
B5: Tax havens | C5: Europe | D5: Middle East | E5: Latin and South America | F5: Asia | G5: Africa | H5: North America | I5: Caribbean | J5: Total ex-tax havens | K5: Total | L5: Rich countries | M5: Of which: Euro area 16 | N5: Developing countries | O5: Excl. Middle East
A6: 1976 | B6: ='Table A24'!B6/'Table A24'!$K6 -> 0.3142881 | C6: ='Table A24'!C6/'Table A24'!$K6 -> 0.383268 | D6: ='Table A24'!D6/'Table A24'!$K6 -> 0.14346484 | E6: ='Table A24'!E6/'Table A24'!$K6 -> 0.052798399 | F6: ='Table A24'!F6/'Table A24'!$K6 -> 0.032321295 | G6: ='Table A24'!G6/'Table A24'!$K6 -> 0.044874468 | H6: ='Table A24'!H6/'Table A24'!$K6 -> 0.028984903 | I6: ='Table A24'!I6/'Table A24'!$K6 -> 0 | ... N6: ='Table A24'!N6/'Table A24'!$K6 -> 0.30878305 | O6: =N6-D6 -> 0.16531821
A7: 1977 | B7: ='Table A24'!B7/'Table A24'!$K7 -> 0.3306751 | C7: ='Table A24'!C7/'Table A24'!$K7 -> 0.40017874 | D7: ='Table A24'!D7/'Table A24'!$K7 -> 0.11759247 | E7: ='Table A24'!E7/'Table A24'!$K7 -> 0.051491819 | F7: ='Table A24'!F7/'Table A24'!$K7 -> 0.03279252 | G7: ='Table A24'!G7/'Table A24'!$K7 -> 0.045957652 | H7: ='Table A24'!H7/'Table A24'!$K7 -> 0.021311701 | I7: ='Table A24'!I7/'Table A24'!$K7 -> 0 | ... N7: ='Table A24'!N7/'Table A24'!$K7 -> 0.28231129 | O7: =N7-D7 -> 0.16471882
A8: 1978 | B8: ='Table A24'!B8/'Table A24'!$K8 -> 0.34341296 | C8: ='Table A24'!C8/'Table A24'!$K8 -> 0.35723073 | D8: ='Table A24'!D8/'Table A24'!$K8 -> 0.14106709 | E8: ='Table A24'!E8/'Table A24'!$K8 -> 0.052724932 | F8: ='Table A24'!F8/'Table A24'!$K8 -> 0.027120584 | G8: ='Table A24'!G8/'Table A24'!$K8 -> 0.055070805 | H8: ='Table A24'!H8/'Table A24'!$K8 -> 0.023372908 | I8: ='Table A24'!I8/'Table A24'!$K8 -> 0 | ... N8: ='Table A24'!N8/'Table A24'!$K8 -> 0.31022744 | O8: =N8-D8 -> 0.16916035
A9: 1979 | B9: ='Table A24'!B9/'Table A24'!$K9 -> 0.31128158 | C9: ='Table A24'!C9/'Table A24'!$K9 -> 0.38623512 | D9: ='Table A24'!D9/'Table A24'!$K9 -> 0.14029815 | E9: ='Table A24'!E9/'Table A24'!$K9 -> 0.053976037 | F9: ='Table A24'!F9/'Table A24'!$K9 -> 0.026691447 | G9: ='Table A24'!G9/'Table A24'!$K9 -> 0.055261181 | H9: ='Table A24'!H9/'Table A24'!$K9 -> 0.026256475 | I9: ='Table A24'!I9/'Table A24'!$K9 -> 0 | ... N9: ='Table A24'!N9/'Table A24'!$K9 -> 0.31472182 | O9: =N9-D9 -> 0.17442366
A10: 1980 | B10: ='Table A24'!B10/'Table A24'!$K10 -> 0.27521767 | C10: ='Table A24'!C10/'Table A24'!$K10 -> 0.41674304 | D10: ='Table A24'!D10/'Table A24'!$K10 -> 0.14493355 | E10: ='Table A24'!E10/'Table A24'!$K10 -> 0.058067934 | F10: ='Table A24'!F10/'Table A24'!$K10 -> 0.029255929 | G10: ='Table A24'!G10/'Table A24'!$K10 -> 0.049891167 | H10: ='Table A24'!H10/'Table A24'!$K10 -> 0.025890709 | I10: ='Table A24'!I10/'Table A24'!$K10 -> 0 | ... N10: ='Table A24'!N10/'Table A24'!$K10 -> 0.32228778 | O10: =N10-D10 -> 0.17735422
A11: 1981 | B11: ='Table A24'!B11/'Table A24'!$K11 -> 0.25785437 | C11: ='Table A24'!C11/'Table A24'!$K11 -> 0.44283856 | D11: ='Table A24'!D11/'Table A24'!$K11 -> 0.12873097 | E11: ='Table A24'!E11/'Table A24'!$K11 -> 0.072365618 | F11: ='Table A24'!F11/'Table A24'!$K11 -> 0.027762205 | G11: ='Table A24'!G11/'Table A24'!$K11 -> 0.04418855 | H11: ='Table A24'!H11/'Table A24'!$K11 -> 0.026259727 | I11: ='Table A24'!I11/'Table A24'!$K11 -> 0 | ... N11: ='Table A24'!N11/'Table A24'!$K11 -> 0.31231359 | O11: =N11-D11 -> 0.18358263
A12: 1982 | B12: ='Table A24'!B12/'Table A24'!$K12 -> 0.26838302 | C12: ='Table A24'!C12/'Table A24'!$K12 -> 0.39270133 | D12: ='Table A24'!D12/'Table A24'!$K12 -> 0.17117342 | E12: ='Table A24'!E12/'Table A24'!$K12 -> 0.065783494 | F12: ='Table A24'!F12/'Table A24'!$K12 -> 0.03096028 | G12: ='Table A24'!G12/'Table A24'!$K12 -> 0.044446464 | H12: ='Table A24'!H12/'Table A24'!$K12 -> 0.026551991 | I12: ='Table A24'!I12/'Table A24'!$K12 -> 0 | ... N12: ='Table A24'!N12/'Table A24'!$K12 -> 0.35599209 | O12: =N12-D12 -> 0.18481867
A13: 1983 | B13: ='Table A24'!B13/'Table A24'!$K13 -> 0.28996576 | C13: ='Table A24'!C13/'Table A24'!$K13 -> 0.35507826 | D13: ='Table A24'!D13/'Table A24'!$K13 -> 0.18609925 | E13: ='Table A24'!E13/'Table A24'!$K13 -> 0.062466649 | F13: ='Table A24'!F13/'Table A24'!$K13 -> 0.035096496 | G13: ='Table A24'!G13/'Table A24'!$K13 -> 0.043000711 | H13: ='Table A24'!H13/'Table A24'!$K13 -> 0.028292867 | I13: ='Table A24'!I13/'Table A24'!$K13 -> 0 | ... N13: ='Table A24'!N13/'Table A24'!$K13 -> 0.3744775 | O13: =N13-D13 -> 0.18837825
A14: 1984 | B14: ='Table A24'!B14/'Table A24'!$K14 -> 0.31450227 | C14: ='Table A24'!C14/'Table A24'!$K14 -> 0.30732502 | D14: ='Table A24'!D14/'Table A24'!$K14 -> 0.20626049 | E14: ='Table A24'!E14/'Table A24'!$K14 -> 0.063228154 | F14: ='Table A24'!F14/'Table A24'!$K14 -> 0.044309969 | G14: ='Table A24'!G14/'Table A24'!$K14 -> 0.031724651 | H14: ='Table A24'!H14/'Table A24'!$K14 -> 0.032378042 | I14: ='Table A24'!I14/'Table A24'!$K14 -> 0.00027140861 | ... N14: ='Table A24'!N14/'Table A24'!$K14 -> 0.34238699 | O14: =N14-D14 -> 0.1361265
A15: 1985 | B15: ='Table A24'!B15/'Table A24'!$K15 -> 0.3211251 | C15: ='Table A24'!C15/'Table A24'!$K15 -> 0.30381032 | D15: ='Table A24'!D15/'Table A24'!$K15 -> 0.20444627 | E15: ='Table A24'!E15/'Table A24'!$K15 -> 0.060325632 | F15: ='Table A24'!F15/'Table A24'!$K15 -> 0.048060994 | G15: ='Table A24'!G15/'Table A24'!$K15 -> 0.030612608 | H15: ='Table A24'!H15/'Table A24'!$K15 -> 0.031414219 | I15: ='Table A24'!I15/'Table A24'!$K15 -> 0.00020485598 | ... N15: ='Table A24'!N15/'Table A24'!$K15 -> 0.33999857 | O15: =N15-D15 -> 0.13555231
A16: 1986 | B16: ='Table A24'!B16/'Table A24'!$K16 -> 0.33761827 | C16: ='Table A24'!C16/'Table A24'!$K16 -> 0.30588823 | D16: ='Table A24'!D16/'Table A24'!$K16 -> 0.18129725 | E16: ='Table A24'!E16/'Table A24'!$K16 -> 0.062041619 | F16: ='Table A24'!F16/'Table A24'!$K16 -> 0.04906591 | G16: ='Table A24'!G16/'Table A24'!$K16 -> 0.030271281 | H16: ='Table A24'!H16/'Table A24'!$K16 -> 0.033599832 | I16: ='Table A24'!I16/'Table A24'!$K16 -> 0.00021760505 | ... N16: ='Table A24'!N16/'Table A24'!$K16 -> 0.31874305 | O16: =N16-D16 -> 0.1374458
A17: 1987 | B17: ='Table A24'!B17/'Table A24'!$K17 -> 0.34666633 | C17: ='Table A24'!C17/'Table A24'!$K17 -> 0.31276382 | D17: ='Table A24'!D17/'Table A24'!$K17 -> 0.16543127 | E17: ='Table A24'!E17/'Table A24'!$K17 -> 0.062554035 | F17: ='Table A24'!F17/'Table A24'!$K17 -> 0.046553171 | G17: ='Table A24'!G17/'Table A24'!$K17 -> 0.029541525 | H17: ='Table A24'!H17/'Table A24'!$K17 -> 0.036292783 | I17: ='Table A24'!I17/'Table A24'!$K17 -> 0.00019707064 | ... N17: ='Table A24'!N17/'Table A24'!$K17 -> 0.30020851 | O17: =N17-D17 -> 0.13477725
... A38: 2008 | B38: ='Table A24'!B38/'Table A24'!$K38 -> 0.61401599 | C38: ='Table A24'!C38/'Table A24'!$K38 -> 0.15679436 | D38: ='Table A24'!D38/'Table A24'!$K38 -> 0.078365778 | E38: ='Table A24'!E38/'Table A24'!$K38 -> 0.045494606 | F38: ='Table A24'!F38/'Table A24'!$K38 -> 0.062434711 | G38: ='Table A24'!G38/'Table A24'!$K38 -> 0.017455091 | H38: ='Table A24'!H38/'Table A24'!$K38 -> 0.025014497 | I38: ='Table A24'!I38/'Table A24'!$K38 -> 0.00042496802 | ... N38: ='Table A24'!N38/'Table A24'!$K38 -> 0.20354712 | O38: =N38-D38 -> 0.12518134

Sheet Table A26
A3: Table A26: Distribution of Fiduciary Deposits in Swiss Banks by Country of Owner, 1976-2004, Corrected Shares (% of Total)
B5: [1] | C5: [2] | D5: [3] | E5: [4] | F5: [5] | G5: [6] | H5: [7] | I5: [8] | J5: [9] | K5: [10] | L5: [11] | M5: [12] | N5: [13]
B6: Tax havens | C6: Europe | D6: Middle East | E6: Latin and South America | F6: Asia | G6: Africa | H6: North America | I6: Caribbean | J6: Total | K6: Rich countries | L6: Of which: Euro area 16 | M6: Developing countries | N6: Excl. Middle East
A7: 1976 | B7: 0 | C7: ='Table A25'!C6+'Table A25'!$B6*'Table A24'!C6/('Table A24'!$J6-'Table A24'!$D6) -> 0.60541133 | D7: ='Table A24'!D6/'Table A24'!$K6 -> 0.14346484 | E7: ='Table A25'!E6+'Table A25'!$B6*'Table A24'!E6/('Table A24'!$J6-'Table A24'!$D6) -> 0.083400516 | F7: ='Table A25'!F6+'Table A25'!$B6*'Table A24'!F6/('Table A24'!$J6-'Table A24'!$D6) -> 0.051054818 | G7: ='Table A25'!G6+'Table A25'!$B6*'Table A24'!G6/('Table A24'!$J6-'Table A24'!$D6) -> 0.070883851 | H7: ='Table A25'!H6+'Table A25'!$B6*'Table A24'!H6/('Table A24'!$J6-'Table A24'!$D6) -> 0.045784643 | I7: ='Table A25'!I6+'Table A25'!$B6*'Table A24'!I6/('Table A24'!$J6-'Table A24'!$D6) -> 0 | J7: =SUM(B7:I7) -> 1 | K7: ='Table A25'!L6+('Table A25'!L6/('Table A25'!L6+'Table A25'!O6)*'Table A25'!B6) -> 0.59544707 | L7: ='Table A25'!M6+'Table A25'!M6/('Table A25'!L6+'Table A25'!O6)*'Table A25'!B6 -> 0.50500025 | M7: =N7+D7 -> 0.40459463 | N7: ='Table A25'!O6+'Table A25'!O6/('Table A25'!O6+'Table A25'!L6)*'Table A25'!B6 -> 0.26112979
A8: 1977 | B8: 0 | C8: ='Table A25'!C7+'Table A25'!$B7*'Table A24'!C7/('Table A24'!$J7-'Table A24'!$D7) -> 0.64002171 | D8: ='Table A24'!D7/'Table A24'!$K7 -> 0.11759247 | E8: ='Table A25'!E7+'Table A25'!$B7*'Table A24'!E7/('Table A24'!$J7-'Table A24'!$D7) -> 0.082352906 | F8: ='Table A25'!F7+'Table A25'!$B7*'Table A24'!F7/('Table A24'!$J7-'Table A24'!$D7) -> 0.052446376 | G8: ='Table A25'!G7+'Table A25'!$B7*'Table A24'!G7/('Table A24'!$J7-'Table A24'!$D7) -> 0.073501892 | H8: ='Table A25'!H7+'Table A25'!$B7*'Table A24'!H7/('Table A24'!$J7-'Table A24'!$D7) -> 0.034084647 | I8: ='Table A25'!I7+'Table A25'!$B7*'Table A24'!I7/('Table A24'!$J7-'Table A24'!$D7) -> 0 | J8: =SUM(B8:I8) -> 1 | K8: ='Table A25'!L7+('Table A25'!L7/('Table A25'!L7+'Table A25'!O7)*'Table A25'!B7) -> 0.6189662 | L8: ='Table A25'!M7+'Table A25'!M7/('Table A25'!L7+'Table A25'!O7)*'Table A25'!B7 -> 0.49312788 | M8: =N8+D8 -> 0.3810338 | N8: ='Table A25'!O7+'Table A25'!O7/('Table A25'!O7+'Table A25'!L7)*'Table A25'!B7 -> 0.26344134
A9: 1978 | B9: 0 | C9: ='Table A25'!C8+'Table A25'!$B8*'Table A24'!C8/('Table A24'!$J8-'Table A24'!$D8) -> 0.59519952 | D9: ='Table A24'!D8/'Table A24'!$K8 -> 0.14106709 | E9: ='Table A25'!E8+'Table A25'!$B8*'Table A24'!E8/('Table A24'!$J8-'Table A24'!$D8) -> 0.087847578 | F9: ='Table A25'!F8+'Table A25'!$B8*'Table A24'!F8/('Table A24'!$J8-'Table A24'!$D8) -> 0.045186926 | G9: ='Table A25'!G8+'Table A25'!$B8*'Table A24'!G8/('Table A24'!$J8-'Table A24'!$D8) -> 0.091756152 | H9: ='Table A25'!H8+'Table A25'!$B8*'Table A24'!H8/('Table A24'!$J8-'Table A24'!$D8) -> 0.038942741 | I9: ='Table A25'!I8+'Table A25'!$B8*'Table A24'!I8/('Table A24'!$J8-'Table A24'!$D8) -> 0 | J9: =SUM(B9:I9) -> 1 | K9: ='Table A25'!L8+('Table A25'!L8/('Table A25'!L8+'Table A25'!O8)*'Table A25'!B8) -> 0.57712148 | L9: ='Table A25'!M8+'Table A25'!M8/('Table A25'!L8+'Table A25'!O8)*'Table A25'!B8 -> 0.48784591 | M9: =N9+D9 -> 0.42290713 | N9: ='Table A25'!O8+'Table A25'!O8/('Table A25'!O8+'Table A25'!L8)*'Table A25'!B8 -> 0.28184005
A10: 1979 | B10: 0 | C10: ='Table A25'!C9+'Table A25'!$B9*'Table A24'!C9/('Table A24'!$J9-'Table A24'!$D9) -> 0.60546094 | D10: ='Table A24'!D9/'Table A24'!$K9 -> 0.14029815 | E10: ='Table A25'!E9+'Table A25'!$B9*'Table A24'!E9/('Table A24'!$J9-'Table A24'!$D9) -> 0.084612663 | F10: ='Table A25'!F9+'Table A25'!$B9*'Table A24'!F9/('Table A24'!$J9-'Table A24'!$D9) -> 0.041841427 | G10: ='Table A25'!G9+'Table A25'!$B9*'Table A24'!G9/('Table A24'!$J9-'Table A24'!$D9) -> 0.08662725 | H10: ='Table A25'!H9+'Table A25'!$B9*'Table A24'!H9/('Table A24'!$J9-'Table A24'!$D9) -> 0.041159566 | I10: ='Table A25'!I9+'Table A25'!$B9*'Table A24'!I9/('Table A24'!$J9-'Table A24'!$D9) -> 0 | J10: =SUM(B10:I10) -> 1 | K10: ='Table A25'!L9+('Table A25'!L9/('Table A25'!L9+'Table A25'!O9)*'Table A25'!B9) -> 0.58625253 | L10: ='Table A25'!M9+'Table A25'!M9/('Table A25'!L9+'Table A25'!O9)*'Table A25'!B9 -> 0.48555285 | M10: =N10+D10 -> 0.4137277 | N10: ='Table A25'!O9+'Table A25'!O9/('Table A25'!O9+'Table A25'!L9)*'Table A25'!B9 -> 0.27342954
A11: 1980 | B11: 0 | C11: ='Table A25'!C10+'Table A25'!$B10*'Table A24'!C10/('Table A24'!$J10-'Table A24'!$D10) -> 0.61454469 | D11: ='Table A24'!D10/'Table A24'!$K10 -> 0.14493355 | E11: ='Table A25'!E10+'Table A25'!$B10*'Table A24'!E10/('Table A24'!$J10-'Table A24'!$D10) -> 0.085629123 | F11: ='Table A25'!F10+'Table A25'!$B10*'Table A24'!F10/('Table A24'!$J10-'Table A24'!$D10) -> 0.043141874 | G11: ='Table A25'!G10+'Table A25'!$B10*'Table A24'!G10/('Table A24'!$J10-'Table A24'!$D10) -> 0.07357136 | H11: ='Table A25'!H10+'Table A25'!$B10*'Table A24'!H10/('Table A24'!$J10-'Table A24'!$D10) -> 0.038179397 | I11: ='Table A25'!I10+'Table A25'!$B10*'Table A24'!I10/('Table A24'!$J10-'Table A24'!$D10) -> 0 | J11: =SUM(B11:I11) -> 1 | K11: ='Table A25'!L10+('Table A25'!L10/('Table A25'!L10+'Table A25'!O10)*'Table A25'!B10) -> 0.59353335 | L11: ='Table A25'!M10+'Table A25'!M10/('Table A25'!L10+'Table A25'!O10)*'Table A25'!B10 -> 0.47183653 | M11: =N11+D11 -> 0.40646665 | N11: ='Table A25'!O10+'Table A25'!O10/('Table A25'!O10+'Table A25'!L10)*'Table A25'!B10 -> 0.26153309
A12: 1981 | B12: 0 | C12: ='Table A25'!C11+'Table A25'!$B11*'Table A24'!C11/('Table A24'!$J11-'Table A24'!$D11) -> 0.62898974 | D12: ='Table A24'!D11/'Table A24'!$K11 -> 0.12873097 | E12: ='Table A25'!E11+'Table A25'!$B11*'Table A24'!E11/('Table A24'!$J11-'Table A24'!$D11) -> 0.10278516 | F12: ='Table A25'!F11+'Table A25'!$B11*'Table A24'!F11/('Table A24'!$J11-'Table A24'!$D11) -> 0.039432297 | G12: ='Table A25'!G11+'Table A25'!$B11*'Table A24'!G11/('Table A24'!$J11-'Table A24'!$D11) -> 0.062763604 | H12: ='Table A25'!H11+'Table A25'!$B11*'Table A24'!H11/('Table A24'!$J11-'Table A24'!$D11) -> 0.037298239 | I12: ='Table A25'!I11+'Table A25'!$B11*'Table A24'!I11/('Table A24'!$J11-'Table A24'!$D11) -> 0 | J12: =SUM(B12:I12) -> 1 | K12: ='Table A25'!L11+('Table A25'!L11/('Table A25'!L11+'Table A25'!O11)*'Table A25'!B11) -> 0.6105158 | L12: ='Table A25'!M11+'Table A25'!M11/('Table A25'!L11+'Table A25'!O11)*'Table A25'!B11 -> 0.47027315 | M12: =N12+D12 -> 0.3894842 | N12: ='Table A25'!O11+'Table A25'!O11/('Table A25'!O11+'Table A25'!L11)*'Table A25'!B11 -> 0.26075323
A13: 1982 | B13: 0 | C13: ='Table A25'!C12+'Table A25'!$B12*'Table A24'!C12/('Table A24'!$J12-'Table A24'!$D12) -> 0.5807566 | D13: ='Table A24'!D12/'Table A24'!$K12 -> 0.17117342 | E13: ='Table A25'!E12+'Table A25'!$B12*'Table A24'!E12/('Table A24'!$J12-'Table A24'!$D12) -> 0.097285637 | F13: ='Table A25'!F12+'Table A25'!$B12*'Table A24'!F12/('Table A24'!$J12-'Table A24'!$D12) -> 0.045786418 | G13: ='Table A25'!G12+'Table A25'!$B12*'Table A24'!G12/('Table A24'!$J12-'Table A24'!$D12) -> 0.065730814 | H13: ='Table A25'!H12+'Table A25'!$B12*'Table A24'!H12/('Table A24'!$J12-'Table A24'!$D12) -> 0.039267104 | I13: ='Table A25'!I12+'Table A25'!$B12*'Table A24'!I12/('Table A24'!$J12-'Table A24'!$D12) -> 0 | J13: =SUM(B13:I13) -> 1 | K13: ='Table A25'!L12+('Table A25'!L12/('Table A25'!L12+'Table A25'!O12)*'Table A25'!B12) -> 0.55551582 | L13: ='Table A25'!M12+'Table A25'!M12/('Table A25'!L12+'Table A25'!O12)*'Table A25'!B12 -> 0.43101119 | M13: =N13+D13 -> 0.44449554 | N13: ='Table A25'!O12+'Table A25'!O12/('Table A25'!O12+'Table A25'!L12)*'Table A25'!B12 -> 0.27332212
A14: 1983 | B14: 0 | C14: ='Table A25'!C13+'Table A25'!$B13*'Table A24'!C13/('Table A24'!$J13-'Table A24'!$D13) -> 0.55159222 | D14: ='Table A24'!D13/'Table A24'!$K13 -> 0.18609925 | E14: ='Table A25'!E13+'Table A25'!$B13*'Table A24'!E13/('Table A24'!$J13-'Table A24'!$D13) -> 0.097038093 | F14: ='Table A25'!F13+'Table A25'!$B13*'Table A24'!F13/('Table A24'!$J13-'Table A24'!$D13) -> 0.054520246 | G14: ='Table A25'!G13+'Table A25'!$B13*'Table A24'!G13/('Table A24'!$J13-'Table A24'!$D13) -> 0.066798958 | H14: ='Table A25'!H13+'Table A25'!$B13*'Table A24'!H13/('Table A24'!$J13-'Table A24'!$D13) -> 0.043951228 | I14: ='Table A25'!I13+'Table A25'!$B13*'Table A24'!I13/('Table A24'!$J13-'Table A24'!$D13) -> 0 | J14: =SUM(B14:I14) -> 1 | K14: ='Table A25'!L13+('Table A25'!L13/('Table A25'!L13+'Table A25'!O13)*'Table A25'!B13) -> 0.52125341 | L14: ='Table A25'!M13+'Table A25'!M13/('Table A25'!L13+'Table A25'!O13)*'Table A25'!B13 -> 0.38900153 | M14: =N14+D14 -> 0.47873547 | N14: ='Table A25'!O13+'Table A25'!O13/('Table A25'!O13+'Table A25'!L13)*'Table A25'!B13 -> 0.29263622
A15: 1984 | B15: 0 | C15: ='Table A25'!C14+'Table A25'!$B14*'Table A24'!C14/('Table A24'!$J14-'Table A24'!$D14) -> 0.50900887 | D15: ='Table A24'!D14/'Table A24'!$K14 -> 0.20626049 | E15: ='Table A25'!E14+'Table A25'!$B14*'Table A24'!E14/('Table A24'!$J14-'Table A24'!$D14) -> 0.104722 | F15: ='Table A25'!F14+'Table A25'!$B14*'Table A24'!F14/('Table A24'!$J14-'Table A24'!$D14) -> 0.073388647 | G15: ='Table A25'!G14+'Table A25'!$B14*'Table A24'!G14/('Table A24'!$J14-'Table A24'!$D14) -> 0.05254414 | H15: ='Table A25'!H14+'Table A25'!$B14*'Table A24'!H14/('Table A24'!$J14-'Table A24'!$D14) -> 0.053626323 | I15: ='Table A25'!I14+'Table A25'!$B14*'Table A24'!I14/('Table A24'!$J14-'Table A24'!$D14) -> 0.00044952211 | J15: =SUM(B15:I15) -> 1 | K15: ='Table A25'!L14+('Table A25'!L14/('Table A25'!L14+'Table A25'!O14)*'Table A25'!B14) -> 0.56826727 | L15: ='Table A25'!M14+'Table A25'!M14/('Table A25'!L14+'Table A25'!O14)*'Table A25'!B14 -> 0.40811952 | M15: =N15+D15 -> 0.43172268 | N15: ='Table A25'!O14+'Table A25'!O14/('Table A25'!O14+'Table A25'!L14)*'Table A25'!B14 -> 0.22546219
A16: 1985 | B16: 0 | C16: ='Table A25'!C15+'Table A25'!$B15*'Table A24'!C15/('Table A24'!$J15-'Table A24'!$D15) -> 0.50944952 | D16: ='Table A24'!D15/'Table A24'!$K15 -> 0.20444627 | E16: ='Table A25'!E15+'Table A25'!$B15*'Table A24'!E15/('Table A24'!$J15-'Table A24'!$D15) -> 0.10115806 | F16: ='Table A25'!F15+'Table A25'!$B15*'Table A24'!F15/('Table A24'!$J15-'Table A24'!$D15) -> 0.080591896 | G16: ='Table A25'!G15+'Table A25'!$B15*'Table A24'!G15/('Table A24'!$J15-'Table A24'!$D15) -> 0.051333274 | H16: ='Table A25'!H15+'Table A25'!$B15*'Table A24'!H15/('Table A24'!$J15-'Table A24'!$D15) -> 0.052677468 | I16: ='Table A25'!I15+'Table A25'!$B15*'Table A24'!I15/('Table A24'!$J15-'Table A24'!$D15) -> 0.00034351624 | J16: =SUM(B16:I16) -> 1 | K16: ='Table A25'!L15+('Table A25'!L15/('Table A25'!L15+'Table A25'!O15)*'Table A25'!B15) -> 0.56826116 | L16: ='Table A25'!M15+'Table A25'!M15/('Table A25'!L15+'Table A25'!O15)*'Table A25'!B15 -> 0.40689937 | M16: =N16+D16 -> 0.43174774 | N16: ='Table A25'!O15+'Table A25'!O15/('Table A25'!O15+'Table A25'!L15)*'Table A25'!B15 -> 0.22730148
A17: 1986 | B17: 0 | C17: ='Table A25'!C16+'Table A25'!$B16*'Table A24'!C16/('Table A24'!$J16-'Table A24'!$D16) -> 0.52055626 | D17: ='Table A24'!D16/'Table A24'!$K16 -> 0.18129725 | E17: ='Table A25'!E16+'Table A25'!$B16*'Table A24'!E16/('Table A24'!$J16-'Table A24'!$D16) -> 0.10558155 | F17: ='Table A25'!F16+'Table A25'!$B16*'Table A24'!F16/('Table A24'!$J16-'Table A24'!$D16) -> 0.083499671 | G17: ='Table A25'!G16+'Table A25'!$B16*'Table A24'!G16/('Table A24'!$J16-'Table A24'!$D16) -> 0.051515237 | H17: ='Table A25'!H16+'Table A25'!$B16*'Table A24'!H16/('Table A24'!$J16-'Table A24'!$D16) -> 0.057179719 | I17: ='Table A25'!I16+'Table A25'!$B16*'Table A24'!I16/('Table A24'!$J16-'Table A24'!$D16) -> 0.0003703172 | J17: =SUM(B17:I17) -> 1 | K17: ='Table A25'!L16+('Table A25'!L16/('Table A25'!L16+'Table A25'!O16)*'Table A25'!B16) -> 0.58479944 | L17: ='Table A25'!M16+'Table A25'!M16/('Table A25'!L16+'Table A25'!O16)*'Table A25'!B16 -> 0.41860931 | M17: =N17+D17 -> 0.41520056 | N17: ='Table A25'!O16+'Table A25'!O16/('Table A25'!O16+'Table A25'!L16)*'Table A25'!B16 -> 0.23390332
A18: 1987 | B18: 0 | C18: ='Table A25'!C17+'Table A25'!$B17*'Table A24'!C17/('Table A24'!$J17-'Table A24'!$D17) -> 0.53498999 | D18: ='Table A24'!D17/'Table A24'!$K17 -> 0.16543127 | E18: ='Table A25'!E17+'Table A25'!$B17*'Table A24'!E17/('Table A24'!$J17-'Table A24'!$D17) -> 0.10700017 | F18: ='Table A25'!F17+'Table A25'!$B17*'Table A24'!F17/('Table A24'!$J17-'Table A24'!$D17) -> 0.079630312 | G18: ='Table A25'!G17+'Table A25'!$B17*'Table A24'!G17/('Table A24'!$J17-'Table A24'!$D17) -> 0.050531484 | H18: ='Table A25'!H17+'Table A25'!$B17*'Table A24'!H17/('Table A24'!$J17-'Table A24'!$D17) -> 0.062079674 | I18: ='Table A25'!I17+'Table A25'!$B17*'Table A24'!I17/('Table A24'!$J17-'Table A24'!$D17) -> 0.00033709404 | J18: =SUM(B18:I18) -> 1 | K18: ='Table A25'!L17+('Table A25'!L17/('Table A25'!L17+'Table A25'!O17)*'Table A25'!B17) -> 0.60403663 | L18: ='Table A25'!M17+'Table A25'!M17/('Table A25'!L17+'Table A25'!O17)*'Table A25'!B17 -> 0.4184728 | M18: =N18+D18 -> 0.39596972 | N18: ='Table A25'!O17+'Table A25'!O17/('Table A25'!O17+'Table A25'!L17)*'Table A25'!B17 -> 0.23053846
... A35: 2004 | B35: 0 | C35: ='Table A25'!C34+'Table A25'!$B34*'Table A24'!C34/('Table A24'!$J34-'Table A24'!$D34) -> 0.55566514 | D35: ='Table A24'!D34/'Table A24'!$K34 -> 0.098234901 | E35: ='Table A25'!E34+'Table A25'!$B34*'Table A24'!E34/('Table A24'!$J34-'Table A24'!$D34) -> 0.11617636 | F35: ='Table A25'!F34+'Table A25'!$B34*'Table A24'!F34/('Table A24'!$J34-'Table A24'!$D34) -> 0.12960802 | G35: ='Table A25'!G34+'Table A25'!$B34*'Table A24'!G34/('Table A24'!$J34-'Table A24'!$D34) -> 0.045425407 | H35: ='Table A25'!H34+'Table A25'!$B34*'Table A24'!H34/('Table A24'!$J34-'Table A24'!$D34) -> 0.054413868 | I35: ='Table A25'!I34+'Table A25'!$B34*'Table A24'!I34/('Table A24'!$J34-'Table A24'!$D34) -> 0.00047629996 | J35: =SUM(B35:I35) -> 1 | K35: ='Table A25'!L34+('Table A25'!L34/('Table A25'!L34+'Table A25'!O34)*'Table A25'!B34) -> 0.61727794 | L35: ='Table A25'!M34+'Table A25'!M34/('Table A25'!L34+'Table A25'!O34)*'Table A25'!B34 -> 0.43609344 | M35: =N35+D35 -> 0.38272206 | N35: ='Table A25'!O34+'Table A25'!O34/('Table A25'!O34+'Table A25'!L34)*'Table A25'!B34 -> 0.28448716

Sheet Table A27
B2: Table A27: Net Foreign Asset Positions of Rich Countries, As Officially Reported
C4: Net foreign asset position / World GDP | J4: Net foreign asset position / Country or region GDP | R4: Memo: unrecorded offshore assets/World GDP
C5: Rich countries | D5: USA | E5: Japan | F5: Other rich countries | G5: Euro area 16 | H5: Other Europe | I5: Canada, Australia, NZ | J5: Rich countries | K5: USA | L5: Japan | M5: Other rich countries | N5: Euro area 16 | O5: Other Europe | P5: Canada, Australia, NZ
